Workbook

Sheet FINANCIAL STATEMENTS
A2: FINANCIAL STATEMENTS OF PIDILITE
A4: INCOME STATEMENT
A6: PARTICULARS(AMOUNT IN CRORES OF INR) | B6: 43921 | C6: 44286 | D6: 44651 | E6: 45016 | F6: 45382 | G6: 45747
A7: INCOME
A9: REVENUE FROM OPERATIONS | B9: 6332.59 | C9: 6216.33 | D9: 8895.62 | E9: 10597.07 | F9: 11166.97 | G9: 12072.7
A10: OTHER INCOME | B10: 151.86 | C10: 73.49 | D10: 39.96 | E10: 63.04 | F10: 165.55 | G10: 294.34
A11: TOTAL INCOME | B11: =SUM(B9:B10) -> 6484.45 | C11: =SUM(C9:C10) -> 6289.82 | D11: =SUM(D9:D10) -> 8935.58 | E11: =SUM(E9:E10) -> 10660.11 | F11: =SUM(F9:F10) -> 11332.52 | G11: =SUM(G9:G10) -> 12367.04
A13: EXPENSES
A15: COST OF MATERIALS CONSUMED | B15: 2520.7 | C15: 2469.53 | D15: 4523.17 | E15: 5345.97 | F15: 4520.2 | G15: 4850.1
A16: PURCHASES OF STOCK IN TRADE | B16: 387.71 | C16: 453.99 | D16: 607.84 | E16: 858.96 | F16: 837.67 | G16: 825.67
A17: CHANGES IN INVENTORIES OF FINISHED GOODS, WORK IN PROGRESS, AND STOCK IN TRADE | B17: 27.98 | C17: -89.77 | D17: -225.52 | E17: -61.02 | F17: 57.65 | G17: -124.69
A18: EMPLOYEE BENEFITS EXPENSE | B18: 736.89 | C18: 787.75 | D18: 926.76 | E18: 1044.83 | F18: 1254.32 | G18: 1545.47
A19: OTHER EXPENSE | B19: 1175.75 | C19: 1047.15 | D19: 1290.97 | E19: 1553.15 | F19: 1947.45 | G19: 2141.32
A20: TOTAL EXPENSE BEFORE DEPRECIATION AND AMMORTISATION | B20: =SUM(B15:B19) -> 4849.03 | C20: =SUM(C15:C19) -> 4668.65 | D20: =SUM(D15:D19) -> 7123.22 | E20: =SUM(E15:E19) -> 8741.89 | F20: =SUM(F15:F19) -> 8617.29 | G20: =SUM(G15:G19) -> 9237.87
A22: EBITDA | B22: =B11-B20 -> 1635.42 | C22: =C11-C20 -> 1621.17 | D22: =D11-D20 -> 1812.36 | E22: =E11-E20 -> 1918.22 | F22: =F11-F20 -> 2715.23 | G22: =G11-G20 -> 3129.17
A23: DEPRECIATION, AMORTISATION AND IMPAIRMENT EXPENSE | B23: 125.79 | C23: 147.1 | D23: 194.38 | E23: 221.97 | F23: 289.11 | G23: 308.41
A24: EBIT | B24: =B22-B23 -> 1509.63 | C24: =C22-C23 -> 1474.07 | D24: =D22-D23 -> 1617.98 | E24: =E22-E23 -> 1696.25 | F24: =F22-F23 -> 2426.12 | G24: =G22-G23 -> 2820.76
A25: FINANCE COSTS | B25: 13.4 | C25: 16.99 | D25: 27.24 | E25: 28.53 | F25: 29.46 | G25: 34.72
A26: EXCEPTIONAL ITEMS | B26: 59.28 | C26: 0.45 | D26: 0 | E26: 0 | F26: -7.15 | G26: 20.16
A27: PROFIT BEFORE TAX | B27: =B24-SUM(B25:B26) -> 1436.95 | C27: =C24-SUM(C25:C26) -> 1456.63 | D27: =D24-SUM(D25:D26) -> 1590.74 | E27: =E24-SUM(E25:E26) -> 1667.72 | F27: =F24-SUM(F25:F26) -> 2403.81 | G27: =G24-SUM(G25:G26) -> 2765.88
A29: TAX EXPENSE
A31: CURRENT TAX | B31: 368.65 | C31: 375.05 | D31: 397.53 | E31: 423.05 | F31: 604.74 | G31: 676.08
A32: DEFERRED TAX | B32: -33.32 | C32: 0.12 | D32: 1.8 | E32: -12.51 | F32: -0.4 | G32: 15.97
A33: NET TAX EXPENSE | B33: =B31+B32 -> 335.33 | C33: =C31+C32 -> 375.17 | D33: =D31+D32 -> 399.33 | E33: =E31+E32 -> 410.54 | F33: =F31+F32 -> 604.34 | G33: =G31+G32 -> 692.05
A34: TAX RATE | B34: =B33/B27 -> 0.23336233 | C34: =C33/C27 -> 0.25756026 | D34: =D33/D27 -> 0.25103411 | E34: =E33/E27 -> 0.24616842 | F34: =F33/F27 -> 0.25140922 | G34: =G33/G27 -> 0.2502097
A36: TOTAL PROFIT FOR THE YEAR ( PROFIT AFTER TAX) | B36: =B27-B33 -> 1101.62 | C36: =C27-C33 -> 1081.46 | D36: =D27-D33 -> 1191.41 | E36: =E27-E33 -> 1257.18 | F36: =F27-F33 -> 1799.47 | G36: =G27-G33 -> 2073.83
A38: OTHER COMPREHENSIVE INCOME
A39: ITEMS THAT WILL NOT BE RECLASSIFIED TO INCOME STATEMENT
A41: REMEASUREMENT OF DEFINED BENEFIT PLAN | B41: -14.88 | C41: -0.95 | D41: -12.11 | E41: 1.94 | F41: -26.78 | G41: -15.24
A42: INCOME TAX RELATING TO ITEMS THAT WILL NOT RECLASSIFIED TO PROFIT OR LOSS | B42: 3.08 | C42: 0.24 | D42: 3.05 | E42: -0.49 | F42: 6.74 | G42: 3.84
A43: TOTAL OTHER COMPREHENSIVE LOSS | B43: =B42+B41 -> -11.8 | C43: =C42+C41 -> -0.71 | D43: =D42+D41 -> -9.06 | E43: =E42+E41 -> 1.45 | F43: =F42+F41 -> -20.04 | G43: =G42+G41 -> -11.4
A45: TOTAL COMPREHENSIVE INCOME FOR THE YEAR | B45: =B36+B43 -> 1089.82 | C45: =C36+C43 -> 1080.75 | D45: =D36+D43 -> 1182.35 | E45: =E36+E43 -> 1258.63 | F45: =F36+F43 -> 1779.43 | G45: =G36+G43 -> 2062.43
A47: EARNINGS PER EQUITY SHARE
A49: BASIC | B49: 21.69 | C49: 21.28 | D49: 23.45 | E49: 24.73 | F49: 35.39 | G49: 40.77
A50: DILUTED | B50: 21.68 | C50: 21.27 | D50: 23.43 | E50: 24.72 | F50: 35.35 | G50: 40.68
A53: BALANCE SHEET
A55: PARTICULARS(AMOUNT IN CRORES OF INR) | B55: 43921 | C55: 44286 | D55: 44651 | E55: 45016 | F55: 45382 | G55: 45747
A56: ASSETS
A58: NON CURRENT ASSETS
A60: PROPERTY , PLANT AND EQUIPMENT | B60: 861.24 | C60: 1023.38 | D60: 1322.77 | E60: 1443.37 | F60: 1897.08 | G60: 2096.07
A61: RIGHT OF USE ASSETS | B61: 109.15 | C61: 118.67 | D61: 170.95 | E61: 272.95 | F61: 313.65 | G61: 397.42
A62: CAPITAL WORK IN PROGRESS | B62: 247.64 | C62: 281.5 | D62: 207.34 | E62: 351 | F62: 135.46 | G62: 105.82
A63: GOODWILL | B63: 86.11 | C63: 86.34 | D63: 1184.85 | E63: 1184.85 | F63: 1184.85 | G63: 1184.85
A64: OTHER INTANGIBLE ASSETS | B64: 192.99 | C64: 194.17 | D64: 1556.88 | E64: 1536.24 | F64: 1539.05 | G64: 1523.17
A65: INVESTMENTS | B65: 1108.34 | C65: 3312.26 | D65: 914.46 | E65: 1003.91 | F65: 1053.85 | G65: 1136.1
A66: LOANS | B66: 4.04 | C66: 4.82 | D66: 5.05 | E66: 6.2 | F66: 7.75 | G66: 7.37
A67: OTHER FINANCIAL ASSETS | B67: 13.12 | C67: 15.15 | D67: 19.45 | E67: 34.95 | F67: 39.51 | G67: 45.04
A68: INCOME TAX ASSETS (NET) | B68: 105.8 | C68: 86.98 | D68: 129.92 | E68: 137.21 | F68: 129.58 | G68: 158.07
A69: OTHER NON CURRENT ASSETS | B69: 64.57 | C69: 79.37 | D69: 42.2 | E69: 47.76 | F69: 52.32 | G69: 45.55
A71: TOTAL NON CURRENT ASSETS | B71: =SUM(B60:B69) -> 2793 | C71: =SUM(C60:C69) -> 5202.64 | D71: =SUM(D60:D69) -> 5553.87 | E71: =SUM(E60:E69) -> 6018.44 | F71: =SUM(F60:F69) -> 6353.1 | G71: =SUM(G60:G69) -> 6699.46
A73: CURRENT ASSETS
A75: INVENTORIES | B75: 730.49 | C75: 975.94 | D75: 1441.92 | E75: 1561.24 | F75: 1257.22 | G75: 1490.37
A76: INVESTMENTS | B76: 715.18 | C76: 169.35 | D76: 170.31 | E76: 442.71 | F76: 1759.39 | G76: 3036.92
A77: TRADE RECEIVABLES | B77: 806.63 | C77: 999.09 | D77: 1211.93 | E77: 1305.12 | F77: 1405.53 | G77: 1555.91
A78: CASH AND CASH EQUIVALENTS | B78: 564.17 | C78: 109.81 | D78: 147.7 | E78: 153.3 | F78: 379.87 | G78: 212.06
A79: BANK BALANCES OTHER THAN CASH AND CASH EQUIVALENTS | B79: 4.67 | C79: 2.56 | D79: 2.87 | E79: 2.75 | F79: 2.3 | G79: 2.58
A80: LOANS | B80: 25.38 | C80: 16.25 | D80: 17.81 | E80: 23.96 | F80: 29.61 | G80: 22.75
A81: OTHER FINANCIAL ASSETS | B81: 8.23 | C81: 7.34 | D81: 11.4 | E81: 7.7 | F81: 5.82 | G81: 7.52
A82: OTHER CURRENT ASSETS | B82: 171.31 | C82: 140.43 | D82: 180.56 | E82: 164.91 | F82: 174.51 | G82: 243.56
A83: ASSETS HELD FOR SALE | B83: 0 | C83: 0 | D83: 0 | E83: 0 | F83: 3.41 | G83: 0
A85: TOTAL CURRENT ASSETS | B85: =SUM(B75:B83) -> 3026.06 | C85: =SUM(C75:C83) -> 2420.77 | D85: =SUM(D75:D83) -> 3184.5 | E85: =SUM(E75:E83) -> 3661.69 | F85: =SUM(F75:F83) -> 5017.66 | G85: =SUM(G75:G83) -> 6571.67
A87: TOTAL ASSETS | B87: =B71+B85 -> 5819.06 | C87: =C71+C85 -> 7623.41 | D87: =D71+D85 -> 8738.37 | E87: =E71+E85 -> 9680.13 | F87: =F71+F85 -> 11370.76 | G87: =G71+G85 -> 13271.13
A89: EQUITIES AND LIABILITES
A91: EQUITY
A93: EQUITY SHARE CAPITAL | B93: 50.81 | C93: 50.82 | D93: 50.83 | E93: 50.83 | F93: 50.86 | G93: 50.86
A94: EQUITY | B94: 4414.01 | C94: 5510.4 | D94: 6292.87 | E94: 7057.33 | F94: 8286.53 | G94: 9625.54
A95: TOTAL EQUITY | B95: =SUM(B93,B94) -> 4464.82 | C95: =SUM(C93,C94) -> 5561.22 | D95: =SUM(D93,D94) -> 6343.7 | E95: =SUM(E93,E94) -> 7108.16 | F95: =SUM(F93,F94) -> 8337.39 | G95: =SUM(G93,G94) -> 9676.4
A97: LIABILITIES
A99: NON CURRENT LIABILITIES
A101: LEASE LIABILITIES | B101: 51.3 | C101: 48.79 | D101: 66.94 | E101: 143.15 | F101: 162.33 | G101: 212.79
A102: OTHER FINANCIAL LIABILITIES | B102: 7.26 | C102: 13.63 | D102: 19.94 | E102: 14.45 | F102: 4.41 | G102: 3.87
A103: PROVISIONS | B103: 40.89 | C103: 45.02 | D103: 56.22 | E103: 64.62 | F103: 79.54 | G103: 112.62
A104: DEFERRED TAX LIABILITIES(NET) | B104: 75.97 | C104: 75.86 | D104: 388.53 | E104: 376.51 | F104: 376.11 | G104: 392.08
A105: TOTAL NON CURRENT LIABILITIES | B105: =SUM(B101:B104) -> 175.42 | C105: =SUM(C101:C104) -> 183.3 | D105: =SUM(D101:D104) -> 531.63 | E105: =SUM(E101:E104) -> 598.73 | F105: =SUM(F101:F104) -> 622.39 | G105: =SUM(G101:G104) -> 721.36
A107: CURRENT LIABILITIES
A109: BORROWINGS | B109: 0 | C109: 55 | D109: 105 | E109: 0 | F109: 0 | G109: 0
A110: TOTAL OUTSTANDING DUES OF MICRO ENTERPRISES AND SMALL ENTERPRISES | B110: 9.3 | C110: 67.04 | D110: 68.15 | E110: 52.82 | F110: 68.95 | G110: 33.78
A111: TOTAL OUTSTANDING DUES OF CREDITORS OTHER THAN MICRO ENTERPRISES AND SMALL ENTERPRISES | B111: 485.51 | C111: 726.78 | D111: 877.69 | E111: 886.14 | F111: 972.76 | G111: 1235.18
A112: LEASE LIABILTIES | B112: 22.04 | C112: 18.54 | D112: 26.48 | E112: 43.47 | F112: 49.36 | G112: 59.48
A113: OTHER FINANCIAL LIABILITIES | B113: 552.42 | C113: 900.44 | D113: 659.62 | E113: 834.38 | F113: 1007.84 | G113: 1191.57
A114: OTHER CURRENT LIABILITIES | B114: 90.03 | C114: 72.66 | D114: 82.1 | E114: 87.94 | F114: 98.64 | G114: 88.62
A115: PROVISIONS | B115: 11.78 | C115: 16.48 | D115: 34.94 | E115: 30.24 | F115: 190.32 | G115: 244.28
A116: CURRENT TAX LIABILITIES(NET) | B116: 7.74 | C116: 21.95 | D116: 9.06 | E116: 38.25 | F116: 23.11 | G116: 20.46
A117: TOTAL CURRENT LIABILTIES | B117: =SUM(B109:B116) -> 1178.82 | C117: =SUM(C109:C116) -> 1878.89 | D117: =SUM(D109:D116) -> 1863.04 | E117: =SUM(E109:E116) -> 1973.24 | F117: =SUM(F109:F116) -> 2410.98 | G117: =SUM(G109:G116) -> 2873.37
A119: TOTAL LIABILITIES | B119: =SUM(B105,B117) -> 1354.24 | C119: =SUM(C105,C117) -> 2062.19 | D119: =SUM(D105,D117) -> 2394.67 | E119: =SUM(E105,E117) -> 2571.97 | F119: =SUM(F105,F117) -> 3033.37 | G119: =SUM(G105,G117) -> 3594.73
A121: TOTAL EQUITY AND LIABILITIES | B121: =SUM(B119,B95) -> 5819.06 | C121: =SUM(C119,C95) -> 7623.41 | D121: =SUM(D119,D95) -> 8738.37 | E121: =SUM(E119,E95) -> 9680.13 | F121: =SUM(F119,F95) -> 11370.76 | G121: =SUM(G119,G95) -> 13271.13
A123: AVERAGE RECEIVABLES | B123: =B77 -> 806.63 | C123: =AVERAGE(C77,B77) -> 902.86 | D123: =AVERAGE(D77,C77) -> 1105.51 | E123: =AVERAGE(E77,D77) -> 1258.525 | F123: =AVERAGE(F77,E77) -> 1355.325 | G123: =AVERAGE(G77,F77) -> 1480.72
A124: AVERAGE INVENTORY | B124: =B75 -> 730.49 | C124: =AVERAGE(C75,B75) -> 853.215 | D124: =AVERAGE(D75,C75) -> 1208.93 | E124: =AVERAGE(E75,D75) -> 1501.58 | F124: =AVERAGE(F75,E75) -> 1409.23 | G124: =AVERAGE(G75,F75) -> 1373.795
A125: AVERAGE PAYABLES | B125: =B111+B110 -> 494.81 | C125: =AVERAGE((C111+C110),(B111+B110)) -> 644.315 | D125: =AVERAGE((D111+D110),(C111+C110)) -> 869.83 | E125: =AVERAGE((E111+E110),(D111+D110)) -> 942.4 | F125: =AVERAGE((F111+F110),(E111+E110)) -> 990.335 | G125: =AVERAGE((G111+G110),(F111+F110)) -> 1155.335
A126: AVERAGE TOTAL ASSETS | B126: =B87 -> 5819.06 | C126: =AVERAGE(C87,B87) -> 6721.235 | D126: =AVERAGE(D87,C87) -> 8180.89 | E126: =AVERAGE(E87,D87) -> 9209.25 | F126: =AVERAGE(F87,E87) -> 10525.445 | G126: =AVERAGE(G87,F87) -> 12320.945
A127: WORKING CAPITAL ( CURRENT ASSETS - CURRENT LIABILITIES) | B127: =B85-B117 -> 1847.24 | C127: =C85-C117 -> 541.88 | D127: =D85-D117 -> 1321.46 | E127: =E85-E117 -> 1688.45 | F127: =F85-F117 -> 2606.68 | G127: =G85-G117 -> 3698.3
A128: AVERAGE WORKING CAPITAL | B128: =B127 -> 1847.24 | C128: =AVERAGE(C127,B127) -> 1194.56 | D128: =AVERAGE(D127,C127) -> 931.67 | E128: =AVERAGE(E127,D127) -> 1504.955 | F128: =AVERAGE(F127,E127) -> 2147.565 | G128: =AVERAGE(G127,F127) -> 3152.49
A129: AVERAGE SHAREHOLDER'S EQUITY | B129: =B95 -> 4464.82 | C129: =AVERAGE(C95,B95) -> 5013.02 | D129: =AVERAGE(D95,C95) -> 5952.46 | E129: =AVERAGE(E95,D95) -> 6725.93 | F129: =AVERAGE(F95,E95) -> 7722.775 | G129: =AVERAGE(G95,F95) -> 9006.895
A131: RATIOS
A132: LIQUIDITY MEASURES | B132: 43921 | C132: 44286 | D132: 44651 | E132: 45016 | F132: 45382 | G132: 45747
A133: CURRENT RATIO (CA/CL) | B133: =B85/B117 -> 2.5670247 | C133: =C85/C117 -> 1.2884043 | D133: =D85/D117 -> 1.7093031 | E133: =E85/E117 -> 1.8556739 | F133: =F85/F117 -> 2.0811703 | G133: =G85/G117 -> 2.2870949
A134: QUICK RATIO (CA - INVENTORY / CL) | B134: =(B85-B75)/B119 -> 1.6950984 | C134: =(C85-C75)/C119 -> 0.70062894 | D134: =(D85-D75)/D119 -> 0.72769108 | E134: =(E85-E75)/E119 -> 0.81666971 | F134: =(F85-F75)/F119 -> 1.2396905 | G134: =(G85-G75)/G119 -> 1.4135415
A135: CASH RATIO (CASH AND EQUIVALENTS / CL) | B135: =B78/B117 -> 0.47858876 | C135: =C78/C117 -> 0.058444081 | D135: =D78/D117 -> 0.079279028 | E135: =E78/E117 -> 0.077689485 | F135: =F78/F117 -> 0.15755834 | G135: =G78/G117 -> 0.073801842
A137: LEVERAGE MEASURES | B137: 43921 | C137: 44286 | D137: 44651 | E137: 45016 | F137: 45382 | G137: 45747
A138: TOTAL DEBT TO TOTAL ASSETS [(CL + NCL) / AVG. TA] | B138: =(B117+B105)/B126 -> 0.23272487 | C138: =(C117+C105)/C126 -> 0.30681713 | D138: =(D117+D105)/D126 -> 0.2927151 | E138: =(E117+E105)/E126 -> 0.27928116 | F138: =(F117+F105)/F126 -> 0.28819399 | G138: =(G117+G105)/G126 -> 0.29175765
...

Sheet SHAREHOLDERS
A1: SHAREHOLDERS | B1: HOLDING
A2: UTI,MUTUAL FUNDS,BANKS,INSURANCE COMPANIES | B2: 0.0904
A3: FII'S AND FPI'S | B3: 0.116
A4: BODIES CORPORATE AND INDIAN PUBLIC | B4: 0.0986
A5: PROMOTER AND PROMOTER GROUP | B5: 0.695

Sheet TREND ANALYSIS
A2: TREND ANALYSIS
A4: INCOME STATEMENT
A6: PARTICULARS(AMOUNT IN CRORES OF INR) | B6: 43921 | C6: 44286 | D6: 44651 | E6: 45016 | F6: 45382 | G6: 45747
A7: INCOME
A9: REVENUE FROM OPERATIONS | B9: ='FINANCIAL STATEMENTS'!B9/'FINANCIAL STATEMENTS'!$B9 -> 1 | C9: ='FINANCIAL STATEMENTS'!C9/'FINANCIAL STATEMENTS'!$B9 -> 0.981641 | D9: ='FINANCIAL STATEMENTS'!D9/'FINANCIAL STATEMENTS'!$B9 -> 1.4047365 | E9: ='FINANCIAL STATEMENTS'!E9/'FINANCIAL STATEMENTS'!$B9 -> 1.673418 | F9: ='FINANCIAL STATEMENTS'!F9/'FINANCIAL STATEMENTS'!$B9 -> 1.7634128 | G9: ='FINANCIAL STATEMENTS'!G9/'FINANCIAL STATEMENTS'!$B9 -> 1.9064395
A10: OTHER INCOME | B10: ='FINANCIAL STATEMENTS'!B10/'FINANCIAL STATEMENTS'!$B10 -> 1 | C10: ='FINANCIAL STATEMENTS'!C10/'FINANCIAL STATEMENTS'!$B10 -> 0.48393257 | D10: ='FINANCIAL STATEMENTS'!D10/'FINANCIAL STATEMENTS'!$B10 -> 0.2631371 | E10: ='FINANCIAL STATEMENTS'!E10/'FINANCIAL STATEMENTS'!$B10 -> 0.41511919 | F10: ='FINANCIAL STATEMENTS'!F10/'FINANCIAL STATEMENTS'!$B10 -> 1.0901488 | G10: ='FINANCIAL STATEMENTS'!G10/'FINANCIAL STATEMENTS'!$B10 -> 1.9382326
A11: TOTAL INCOME | B11: ='FINANCIAL STATEMENTS'!B11/'FINANCIAL STATEMENTS'!$B11 -> 1 | C11: ='FINANCIAL STATEMENTS'!C11/'FINANCIAL STATEMENTS'!$B11 -> 0.96998512 | D11: ='FINANCIAL STATEMENTS'!D11/'FINANCIAL STATEMENTS'!$B11 -> 1.3780012 | E11: ='FINANCIAL STATEMENTS'!E11/'FINANCIAL STATEMENTS'!$B11 -> 1.6439498 | F11: ='FINANCIAL STATEMENTS'!F11/'FINANCIAL STATEMENTS'!$B11 -> 1.7476455 | G11: ='FINANCIAL STATEMENTS'!G11/'FINANCIAL STATEMENTS'!$B11 -> 1.9071841
A13: EXPENSES
A15: COST OF MATERIALS CONSUMED | B15: ='FINANCIAL STATEMENTS'!B15/'FINANCIAL STATEMENTS'!$B15 -> 1 | C15: ='FINANCIAL STATEMENTS'!C15/'FINANCIAL STATEMENTS'!$B15 -> 0.97970008 | D15: ='FINANCIAL STATEMENTS'!D15/'FINANCIAL STATEMENTS'!$B15 -> 1.7944103 | E15: ='FINANCIAL STATEMENTS'!E15/'FINANCIAL STATEMENTS'!$B15 -> 2.1208275 | F15: ='FINANCIAL STATEMENTS'!F15/'FINANCIAL STATEMENTS'!$B15 -> 1.793232 | G15: ='FINANCIAL STATEMENTS'!G15/'FINANCIAL STATEMENTS'!$B15 -> 1.9241084
A16: PURCHASES OF STOCK IN TRADE | B16: ='FINANCIAL STATEMENTS'!B16/'FINANCIAL STATEMENTS'!$B16 -> 1 | C16: ='FINANCIAL STATEMENTS'!C16/'FINANCIAL STATEMENTS'!$B16 -> 1.1709525 | D16: ='FINANCIAL STATEMENTS'!D16/'FINANCIAL STATEMENTS'!$B16 -> 1.5677697 | E16: ='FINANCIAL STATEMENTS'!E16/'FINANCIAL STATEMENTS'!$B16 -> 2.2154703 | F16: ='FINANCIAL STATEMENTS'!F16/'FINANCIAL STATEMENTS'!$B16 -> 2.1605581 | G16: ='FINANCIAL STATEMENTS'!G16/'FINANCIAL STATEMENTS'!$B16 -> 2.1296072
A17: CHANGES IN INVENTORIES OF FINISHED GOODS, WORK IN PROGRESS, AND STOCK IN TRADE | B17: ='FINANCIAL STATEMENTS'!B17/'FINANCIAL STATEMENTS'!$B17 -> 1 | C17: ='FINANCIAL STATEMENTS'!C17/'FINANCIAL STATEMENTS'!$B17 -> -3.2083631 | D17: ='FINANCIAL STATEMENTS'!D17/'FINANCIAL STATEMENTS'!$B17 -> -8.0600429 | E17: ='FINANCIAL STATEMENTS'!E17/'FINANCIAL STATEMENTS'!$B17 -> -2.1808435 | F17: ='FINANCIAL STATEMENTS'!F17/'FINANCIAL STATEMENTS'!$B17 -> 2.0604003 | G17: ='FINANCIAL STATEMENTS'!G17/'FINANCIAL STATEMENTS'!$B17 -> -4.4563974
A18: EMPLOYEE BENEFITS EXPENSE | B18: ='FINANCIAL STATEMENTS'!B18/'FINANCIAL STATEMENTS'!$B18 -> 1 | C18: ='FINANCIAL STATEMENTS'!C18/'FINANCIAL STATEMENTS'!$B18 -> 1.0690198 | D18: ='FINANCIAL STATEMENTS'!D18/'FINANCIAL STATEMENTS'!$B18 -> 1.257664 | E18: ='FINANCIAL STATEMENTS'!E18/'FINANCIAL STATEMENTS'!$B18 -> 1.4178914 | F18: ='FINANCIAL STATEMENTS'!F18/'FINANCIAL STATEMENTS'!$B18 -> 1.7021808 | G18: ='FINANCIAL STATEMENTS'!G18/'FINANCIAL STATEMENTS'!$B18 -> 2.0972872
A19: OTHER EXPENSE | B19: ='FINANCIAL STATEMENTS'!B19/'FINANCIAL STATEMENTS'!$B19 -> 1 | C19: ='FINANCIAL STATEMENTS'!C19/'FINANCIAL STATEMENTS'!$B19 -> 0.89062301 | D19: ='FINANCIAL STATEMENTS'!D19/'FINANCIAL STATEMENTS'!$B19 -> 1.097997 | E19: ='FINANCIAL STATEMENTS'!E19/'FINANCIAL STATEMENTS'!$B19 -> 1.3209866 | F19: ='FINANCIAL STATEMENTS'!F19/'FINANCIAL STATEMENTS'!$B19 -> 1.656347 | G19: ='FINANCIAL STATEMENTS'!G19/'FINANCIAL STATEMENTS'!$B19 -> 1.8212375
A20: TOTAL EXPENSE BEFORE DEPRECIATION AND AMMORTISATION | B20: ='FINANCIAL STATEMENTS'!B20/'FINANCIAL STATEMENTS'!$B20 -> 1 | C20: ='FINANCIAL STATEMENTS'!C20/'FINANCIAL STATEMENTS'!$B20 -> 0.96280081 | D20: ='FINANCIAL STATEMENTS'!D20/'FINANCIAL STATEMENTS'!$B20 -> 1.468999 | E20: ='FINANCIAL STATEMENTS'!E20/'FINANCIAL STATEMENTS'!$B20 -> 1.8028121 | F20: ='FINANCIAL STATEMENTS'!F20/'FINANCIAL STATEMENTS'!$B20 -> 1.7771162 | G20: ='FINANCIAL STATEMENTS'!G20/'FINANCIAL STATEMENTS'!$B20 -> 1.9050965
A22: EBITDA | B22: ='FINANCIAL STATEMENTS'!B22/'FINANCIAL STATEMENTS'!$B22 -> 1 | C22: ='FINANCIAL STATEMENTS'!C22/'FINANCIAL STATEMENTS'!$B22 -> 0.99128664 | D22: ='FINANCIAL STATEMENTS'!D22/'FINANCIAL STATEMENTS'!$B22 -> 1.1081924 | E22: ='FINANCIAL STATEMENTS'!E22/'FINANCIAL STATEMENTS'!$B22 -> 1.1729219 | F22: ='FINANCIAL STATEMENTS'!F22/'FINANCIAL STATEMENTS'!$B22 -> 1.6602646 | G22: ='FINANCIAL STATEMENTS'!G22/'FINANCIAL STATEMENTS'!$B22 -> 1.9133739
A23: DEPRECIATION, AMORTISATION AND IMPAIRMENT EXPENSE | B23: ='FINANCIAL STATEMENTS'!B23/'FINANCIAL STATEMENTS'!$B23 -> 1 | C23: ='FINANCIAL STATEMENTS'!C23/'FINANCIAL STATEMENTS'!$B23 -> 1.1694093 | D23: ='FINANCIAL STATEMENTS'!D23/'FINANCIAL STATEMENTS'!$B23 -> 1.5452739 | E23: ='FINANCIAL STATEMENTS'!E23/'FINANCIAL STATEMENTS'!$B23 -> 1.7646077 | F23: ='FINANCIAL STATEMENTS'!F23/'FINANCIAL STATEMENTS'!$B23 -> 2.2983544 | G23: ='FINANCIAL STATEMENTS'!G23/'FINANCIAL STATEMENTS'!$B23 -> 2.4517847
A24: EBIT | B24: ='FINANCIAL STATEMENTS'!B24/'FINANCIAL STATEMENTS'!$B24 -> 1 | C24: ='FINANCIAL STATEMENTS'!C24/'FINANCIAL STATEMENTS'!$B24 -> 0.97644456 | D24: ='FINANCIAL STATEMENTS'!D24/'FINANCIAL STATEMENTS'!$B24 -> 1.0717726 | E24: ='FINANCIAL STATEMENTS'!E24/'FINANCIAL STATEMENTS'!$B24 -> 1.1236197 | F24: ='FINANCIAL STATEMENTS'!F24/'FINANCIAL STATEMENTS'!$B24 -> 1.6070958 | G24: ='FINANCIAL STATEMENTS'!G24/'FINANCIAL STATEMENTS'!$B24 -> 1.8685108
A25: FINANCE COSTS | B25: ='FINANCIAL STATEMENTS'!B25/'FINANCIAL STATEMENTS'!$B25 -> 1 | C25: ='FINANCIAL STATEMENTS'!C25/'FINANCIAL STATEMENTS'!$B25 -> 1.2679104 | D25: ='FINANCIAL STATEMENTS'!D25/'FINANCIAL STATEMENTS'!$B25 -> 2.0328358 | E25: ='FINANCIAL STATEMENTS'!E25/'FINANCIAL STATEMENTS'!$B25 -> 2.1291045 | F25: ='FINANCIAL STATEMENTS'!F25/'FINANCIAL STATEMENTS'!$B25 -> 2.1985075 | G25: ='FINANCIAL STATEMENTS'!G25/'FINANCIAL STATEMENTS'!$B25 -> 2.5910448
A26: EXCEPTIONAL ITEMS | B26: ='FINANCIAL STATEMENTS'!B26/'FINANCIAL STATEMENTS'!$B26 -> 1 | C26: ='FINANCIAL STATEMENTS'!C26/'FINANCIAL STATEMENTS'!$B26 -> 0.0075910931 | D26: ='FINANCIAL STATEMENTS'!D26/'FINANCIAL STATEMENTS'!$B26 -> 0 | E26: ='FINANCIAL STATEMENTS'!E26/'FINANCIAL STATEMENTS'!$B26 -> 0 | F26: ='FINANCIAL STATEMENTS'!F26/'FINANCIAL STATEMENTS'!$B26 -> -0.12061404 | G26: ='FINANCIAL STATEMENTS'!G26/'FINANCIAL STATEMENTS'!$B26 -> 0.34008097
A27: PROFIT BEFORE TAX | B27: ='FINANCIAL STATEMENTS'!B27/'FINANCIAL STATEMENTS'!$B27 -> 1 | C27: ='FINANCIAL STATEMENTS'!C27/'FINANCIAL STATEMENTS'!$B27 -> 1.0136957 | D27: ='FINANCIAL STATEMENTS'!D27/'FINANCIAL STATEMENTS'!$B27 -> 1.1070253 | E27: ='FINANCIAL STATEMENTS'!E27/'FINANCIAL STATEMENTS'!$B27 -> 1.1605971 | F27: ='FINANCIAL STATEMENTS'!F27/'FINANCIAL STATEMENTS'!$B27 -> 1.6728557 | G27: ='FINANCIAL STATEMENTS'!G27/'FINANCIAL STATEMENTS'!$B27 -> 1.9248269
A29: TAX EXPENSE
A31: CURRENT TAX | B31: ='FINANCIAL STATEMENTS'!B31/'FINANCIAL STATEMENTS'!$B31 -> 1 | C31: ='FINANCIAL STATEMENTS'!C31/'FINANCIAL STATEMENTS'!$B31 -> 1.0173606 | D31: ='FINANCIAL STATEMENTS'!D31/'FINANCIAL STATEMENTS'!$B31 -> 1.0783399 | E31: ='FINANCIAL STATEMENTS'!E31/'FINANCIAL STATEMENTS'!$B31 -> 1.1475654 | F31: ='FINANCIAL STATEMENTS'!F31/'FINANCIAL STATEMENTS'!$B31 -> 1.6404177 | G31: ='FINANCIAL STATEMENTS'!G31/'FINANCIAL STATEMENTS'!$B31 -> 1.8339346
A32: DEFERRED TAX | B32: ='FINANCIAL STATEMENTS'!B32/'FINANCIAL STATEMENTS'!$B32 -> 1 | C32: ='FINANCIAL STATEMENTS'!C32/'FINANCIAL STATEMENTS'!$B32 -> -0.0036014406 | D32: ='FINANCIAL STATEMENTS'!D32/'FINANCIAL STATEMENTS'!$B32 -> -0.054021609 | E32: ='FINANCIAL STATEMENTS'!E32/'FINANCIAL STATEMENTS'!$B32 -> 0.37545018 | F32: ='FINANCIAL STATEMENTS'!F32/'FINANCIAL STATEMENTS'!$B32 -> 0.012004802 | G32: ='FINANCIAL STATEMENTS'!G32/'FINANCIAL STATEMENTS'!$B32 -> -0.47929172
A33: NET TAX EXPENSE | B33: ='FINANCIAL STATEMENTS'!B33/'FINANCIAL STATEMENTS'!$B33 -> 1 | C33: ='FINANCIAL STATEMENTS'!C33/'FINANCIAL STATEMENTS'!$B33 -> 1.1188083 | D33: ='FINANCIAL STATEMENTS'!D33/'FINANCIAL STATEMENTS'!$B33 -> 1.1908568 | E33: ='FINANCIAL STATEMENTS'!E33/'FINANCIAL STATEMENTS'!$B33 -> 1.2242865 | F33: ='FINANCIAL STATEMENTS'!F33/'FINANCIAL STATEMENTS'!$B33 -> 1.8022247 | G33: ='FINANCIAL STATEMENTS'!G33/'FINANCIAL STATEMENTS'!$B33 -> 2.0637879
A34: TAX RATE | B34: ='FINANCIAL STATEMENTS'!B34/'FINANCIAL STATEMENTS'!$B34 -> 1 | C34: ='FINANCIAL STATEMENTS'!C34/'FINANCIAL STATEMENTS'!$B34 -> 1.1036925 | D34: ='FINANCIAL STATEMENTS'!D34/'FINANCIAL STATEMENTS'!$B34 -> 1.0757268 | E34: ='FINANCIAL STATEMENTS'!E34/'FINANCIAL STATEMENTS'!$B34 -> 1.0548764 | F34: ='FINANCIAL STATEMENTS'!F34/'FINANCIAL STATEMENTS'!$B34 -> 1.0773342 | G34: ='FINANCIAL STATEMENTS'!G34/'FINANCIAL STATEMENTS'!$B34 -> 1.072194
A36: TOTAL PROFIT FOR THE YEAR ( PROFIT AFTER TAX) | B36: ='FINANCIAL STATEMENTS'!B36/'FINANCIAL STATEMENTS'!$B36 -> 1 | C36: ='FINANCIAL STATEMENTS'!C36/'FINANCIAL STATEMENTS'!$B36 -> 0.98169968 | D36: ='FINANCIAL STATEMENTS'!D36/'FINANCIAL STATEMENTS'!$B36 -> 1.0815072 | E36: ='FINANCIAL STATEMENTS'!E36/'FINANCIAL STATEMENTS'!$B36 -> 1.1412102 | F36: ='FINANCIAL STATEMENTS'!F36/'FINANCIAL STATEMENTS'!$B36 -> 1.6334762 | G36: ='FINANCIAL STATEMENTS'!G36/'FINANCIAL STATEMENTS'!$B36 -> 1.8825276
A38: OTHER COMPREHENSIVE INCOME
A39: ITEMS THAT WILL NOT BE RECLASSIFIED TO INCOME STATEMENT
A41: REMEASUREMENT OF DEFINED BENEFIT PLAN | B41: ='FINANCIAL STATEMENTS'!B41/'FINANCIAL STATEMENTS'!$B41 -> 1 | C41: ='FINANCIAL STATEMENTS'!C41/'FINANCIAL STATEMENTS'!$B41 -> 0.063844086 | D41: ='FINANCIAL STATEMENTS'!D41/'FINANCIAL STATEMENTS'!$B41 -> 0.81384409 | E41: ='FINANCIAL STATEMENTS'!E41/'FINANCIAL STATEMENTS'!$B41 -> -0.13037634 | F41: ='FINANCIAL STATEMENTS'!F41/'FINANCIAL STATEMENTS'!$B41 -> 1.7997312 | G41: ='FINANCIAL STATEMENTS'!G41/'FINANCIAL STATEMENTS'!$B41 -> 1.0241935
A42: INCOME TAX RELATING TO ITEMS THAT WILL NOT RECLASSIFIED TO PROFIT OR LOSS | B42: ='FINANCIAL STATEMENTS'!B42/'FINANCIAL STATEMENTS'!$B42 -> 1 | C42: ='FINANCIAL STATEMENTS'!C42/'FINANCIAL STATEMENTS'!$B42 -> 0.077922078 | D42: ='FINANCIAL STATEMENTS'!D42/'FINANCIAL STATEMENTS'!$B42 -> 0.99025974 | E42: ='FINANCIAL STATEMENTS'!E42/'FINANCIAL STATEMENTS'!$B42 -> -0.15909091 | F42: ='FINANCIAL STATEMENTS'!F42/'FINANCIAL STATEMENTS'!$B42 -> 2.1883117 | G42: ='FINANCIAL STATEMENTS'!G42/'FINANCIAL STATEMENTS'!$B42 -> 1.2467532
A43: TOTAL OTHER COMPREHENSIVE LOSS | B43: ='FINANCIAL STATEMENTS'!B43/'FINANCIAL STATEMENTS'!$B43 -> 1 | C43: ='FINANCIAL STATEMENTS'!C43/'FINANCIAL STATEMENTS'!$B43 -> 0.060169492 | D43: ='FINANCIAL STATEMENTS'!D43/'FINANCIAL STATEMENTS'!$B43 -> 0.76779661 | E43: ='FINANCIAL STATEMENTS'!E43/'FINANCIAL STATEMENTS'!$B43 -> -0.12288136 | F43: ='FINANCIAL STATEMENTS'!F43/'FINANCIAL STATEMENTS'!$B43 -> 1.6983051 | G43: ='FINANCIAL STATEMENTS'!G43/'FINANCIAL STATEMENTS'!$B43 -> 0.96610169
A45: TOTAL COMPREHENSIVE INCOME FOR THE YEAR | B45: ='FINANCIAL STATEMENTS'!B45/'FINANCIAL STATEMENTS'!$B45 -> 1 | C45: ='FINANCIAL STATEMENTS'!C45/'FINANCIAL STATEMENTS'!$B45 -> 0.99167752 | D45: ='FINANCIAL STATEMENTS'!D45/'FINANCIAL STATEMENTS'!$B45 -> 1.0849039 | E45: ='FINANCIAL STATEMENTS'!E45/'FINANCIAL STATEMENTS'!$B45 -> 1.1548971 | F45: ='FINANCIAL STATEMENTS'!F45/'FINANCIAL STATEMENTS'!$B45 -> 1.6327742 | G45: ='FINANCIAL STATEMENTS'!G45/'FINANCIAL STATEMENTS'!$B45 -> 1.8924501
A47: EARNINGS PER EQUITY SHARE
A48: BASIC | B48: ='FINANCIAL STATEMENTS'!B49/'FINANCIAL STATEMENTS'!$B49 -> 1 | C48: ='FINANCIAL STATEMENTS'!C49/'FINANCIAL STATEMENTS'!$B49 -> 0.98109728 | D48: ='FINANCIAL STATEMENTS'!D49/'FINANCIAL STATEMENTS'!$B49 -> 1.0811434 | E48: ='FINANCIAL STATEMENTS'!E49/'FINANCIAL STATEMENTS'!$B49 -> 1.1401568 | F48: ='FINANCIAL STATEMENTS'!F49/'FINANCIAL STATEMENTS'!$B49 -> 1.6316275 | G48: ='FINANCIAL STATEMENTS'!G49/'FINANCIAL STATEMENTS'!$B49 -> 1.879668
A49: DILUTED | B49: ='FINANCIAL STATEMENTS'!B50/'FINANCIAL STATEMENTS'!$B50 -> 1 | C49: ='FINANCIAL STATEMENTS'!C50/'FINANCIAL STATEMENTS'!$B50 -> 0.98108856 | D49: ='FINANCIAL STATEMENTS'!D50/'FINANCIAL STATEMENTS'!$B50 -> 1.0807196 | E49: ='FINANCIAL STATEMENTS'!E50/'FINANCIAL STATEMENTS'!$B50 -> 1.1402214 | F49: ='FINANCIAL STATEMENTS'!F50/'FINANCIAL STATEMENTS'!$B50 -> 1.6305351 | G49: ='FINANCIAL STATEMENTS'!G50/'FINANCIAL STATEMENTS'!$B50 -> 1.8763838
A52: BALANCE SHEET
A54: PARTICULARS(AMOUNT IN CRORES OF INR) | B54: 43921 | C54: 44286 | D54: 44651 | E54: 45016 | F54: 45382 | G54: 45747 | O54: PARTICULARS(AMOUNT IN CRORES OF INR) | P54: 43921 | Q54: 44286 | R54: 44651 | S54: 45016 | T54: 45382 | U54: 45747
A55: ASSETS | O55: TOTAL ASSETS | P55: 1 | Q55: 1.3100759 | R55: 1.5016807 | S55: 1.6635213 | T55: 1.9540544 | U55: 2.2806312
O56: TOTAL EQUITY AND LIABILITIES | P56: 1 | Q56: 1.3100759 | R56: 1.5016807 | S56: 1.6635213 | T56: 1.9540544 | U56: 2.2806312
A57: NON CURRENT ASSETS
A58: PROPERTY , PLANT AND EQUIPMENT | B58: ='FINANCIAL STATEMENTS'!B60/'FINANCIAL STATEMENTS'!$B60 -> 1 | C58: ='FINANCIAL STATEMENTS'!C60/'FINANCIAL STATEMENTS'!$B60 -> 1.1882634 | D58: ='FINANCIAL STATEMENTS'!D60/'FINANCIAL STATEMENTS'!$B60 -> 1.5358901 | E58: ='FINANCIAL STATEMENTS'!E60/'FINANCIAL STATEMENTS'!$B60 -> 1.6759208 | F58: ='FINANCIAL STATEMENTS'!F60/'FINANCIAL STATEMENTS'!$B60 -> 2.2027309 | G58: ='FINANCIAL STATEMENTS'!G60/'FINANCIAL STATEMENTS'!$B60 -> 2.4337815
A59: RIGHT OF USE ASSETS | B59: ='FINANCIAL STATEMENTS'!B61/'FINANCIAL STATEMENTS'!$B61 -> 1 | C59: ='FINANCIAL STATEMENTS'!C61/'FINANCIAL STATEMENTS'!$B61 -> 1.0872194 | D59: ='FINANCIAL STATEMENTS'!D61/'FINANCIAL STATEMENTS'!$B61 -> 1.5661933 | E59: ='FINANCIAL STATEMENTS'!E61/'FINANCIAL STATEMENTS'!$B61 -> 2.5006871 | F59: ='FINANCIAL STATEMENTS'!F61/'FINANCIAL STATEMENTS'!$B61 -> 2.8735685 | G59: ='FINANCIAL STATEMENTS'!G61/'FINANCIAL STATEMENTS'!$B61 -> 3.6410444
A60: CAPITAL WORK IN PROGRESS | B60: ='FINANCIAL STATEMENTS'!B62/'FINANCIAL STATEMENTS'!$B62 -> 1 | C60: ='FINANCIAL STATEMENTS'!C62/'FINANCIAL STATEMENTS'!$B62 -> 1.1367307 | D60: ='FINANCIAL STATEMENTS'!D62/'FINANCIAL STATEMENTS'!$B62 -> 0.83726377 | E60: ='FINANCIAL STATEMENTS'!E62/'FINANCIAL STATEMENTS'!$B62 -> 1.4173801 | F60: ='FINANCIAL STATEMENTS'!F62/'FINANCIAL STATEMENTS'!$B62 -> 0.54700372 | G60: ='FINANCIAL STATEMENTS'!G62/'FINANCIAL STATEMENTS'!$B62 -> 0.42731384
A61: GOODWILL | B61: ='FINANCIAL STATEMENTS'!B63/'FINANCIAL STATEMENTS'!$B63 -> 1 | C61: ='FINANCIAL STATEMENTS'!C63/'FINANCIAL STATEMENTS'!$B63 -> 1.002671 | D61: ='FINANCIAL STATEMENTS'!D63/'FINANCIAL STATEMENTS'!$B63 -> 13.759726 | E61: ='FINANCIAL STATEMENTS'!E63/'FINANCIAL STATEMENTS'!$B63 -> 13.759726 | F61: ='FINANCIAL STATEMENTS'!F63/'FINANCIAL STATEMENTS'!$B63 -> 13.759726 | G61: ='FINANCIAL STATEMENTS'!G63/'FINANCIAL STATEMENTS'!$B63 -> 13.759726
A62: OTHER INTANGIBLE ASSETS | B62: ='FINANCIAL STATEMENTS'!B64/'FINANCIAL STATEMENTS'!$B64 -> 1 | C62: ='FINANCIAL STATEMENTS'!C64/'FINANCIAL STATEMENTS'!$B64 -> 1.0061143 | D62: ='FINANCIAL STATEMENTS'!D64/'FINANCIAL STATEMENTS'!$B64 -> 8.0671537 | E62: ='FINANCIAL STATEMENTS'!E64/'FINANCIAL STATEMENTS'!$B64 -> 7.9602052 | F62: ='FINANCIAL STATEMENTS'!F64/'FINANCIAL STATEMENTS'!$B64 -> 7.9747655 | G62: ='FINANCIAL STATEMENTS'!G64/'FINANCIAL STATEMENTS'!$B64 -> 7.8924815
A63: INVESTMENTS | B63: ='FINANCIAL STATEMENTS'!B65/'FINANCIAL STATEMENTS'!$B65 -> 1 | C63: ='FINANCIAL STATEMENTS'!C65/'FINANCIAL STATEMENTS'!$B65 -> 2.9884873 | D63: ='FINANCIAL STATEMENTS'!D65/'FINANCIAL STATEMENTS'!$B65 -> 0.82507173 | E63: ='FINANCIAL STATEMENTS'!E65/'FINANCIAL STATEMENTS'!$B65 -> 0.90577801 | F63: ='FINANCIAL STATEMENTS'!F65/'FINANCIAL STATEMENTS'!$B65 -> 0.95083639 | G63: ='FINANCIAL STATEMENTS'!G65/'FINANCIAL STATEMENTS'!$B65 -> 1.0250465
A64: LOANS | B64: ='FINANCIAL STATEMENTS'!B66/'FINANCIAL STATEMENTS'!$B66 -> 1 | C64: ='FINANCIAL STATEMENTS'!C66/'FINANCIAL STATEMENTS'!$B66 -> 1.1930693 | D64: ='FINANCIAL STATEMENTS'!D66/'FINANCIAL STATEMENTS'!$B66 -> 1.25 | E64: ='FINANCIAL STATEMENTS'!E66/'FINANCIAL STATEMENTS'!$B66 -> 1.5346535 | F64: ='FINANCIAL STATEMENTS'!F66/'FINANCIAL STATEMENTS'!$B66 -> 1.9183168 | G64: ='FINANCIAL STATEMENTS'!G66/'FINANCIAL STATEMENTS'!$B66 -> 1.8242574
A65: OTHER FINANCIAL ASSETS | B65: ='FINANCIAL STATEMENTS'!B67/'FINANCIAL STATEMENTS'!$B67 -> 1 | C65: ='FINANCIAL STATEMENTS'!C67/'FINANCIAL STATEMENTS'!$B67 -> 1.1547256 | D65: ='FINANCIAL STATEMENTS'!D67/'FINANCIAL STATEMENTS'!$B67 -> 1.4824695 | E65: ='FINANCIAL STATEMENTS'!E67/'FINANCIAL STATEMENTS'!$B67 -> 2.663872 | F65: ='FINANCIAL STATEMENTS'!F67/'FINANCIAL STATEMENTS'!$B67 -> 3.0114329 | G65: ='FINANCIAL STATEMENTS'!G67/'FINANCIAL STATEMENTS'!$B67 -> 3.4329268
A66: INCOME TAX ASSETS (NET) | B66: ='FINANCIAL STATEMENTS'!B68/'FINANCIAL STATEMENTS'!$B68 -> 1 | C66: ='FINANCIAL STATEMENTS'!C68/'FINANCIAL STATEMENTS'!$B68 -> 0.8221172 | D66: ='FINANCIAL STATEMENTS'!D68/'FINANCIAL STATEMENTS'!$B68 -> 1.2279773 | E66: ='FINANCIAL STATEMENTS'!E68/'FINANCIAL STATEMENTS'!$B68 -> 1.2968809 | F66: ='FINANCIAL STATEMENTS'!F68/'FINANCIAL STATEMENTS'!$B68 -> 1.2247637 | G66: ='FINANCIAL STATEMENTS'!G68/'FINANCIAL STATEMENTS'!$B68 -> 1.4940454
A67: OTHER NON CURRENT ASSETS | B67: ='FINANCIAL STATEMENTS'!B69/'FINANCIAL STATEMENTS'!$B69 -> 1 | C67: ='FINANCIAL STATEMENTS'!C69/'FINANCIAL STATEMENTS'!$B69 -> 1.2292086 | D67: ='FINANCIAL STATEMENTS'!D69/'FINANCIAL STATEMENTS'!$B69 -> 0.65355428 | E67: ='FINANCIAL STATEMENTS'!E69/'FINANCIAL STATEMENTS'!$B69 -> 0.73966238 | F67: ='FINANCIAL STATEMENTS'!F69/'FINANCIAL STATEMENTS'!$B69 -> 0.81028341 | G67: ='FINANCIAL STATEMENTS'!G69/'FINANCIAL STATEMENTS'!$B69 -> 0.70543596
A68: TOTAL NON CURRENT ASSETS | B68: ='FINANCIAL STATEMENTS'!B71/'FINANCIAL STATEMENTS'!$B71 -> 1 | C68: ='FINANCIAL STATEMENTS'!C71/'FINANCIAL STATEMENTS'!$B71 -> 1.8627426 | D68: ='FINANCIAL STATEMENTS'!D71/'FINANCIAL STATEMENTS'!$B71 -> 1.9884962 | E68: ='FINANCIAL STATEMENTS'!E71/'FINANCIAL STATEMENTS'!$B71 -> 2.1548299 | F68: ='FINANCIAL STATEMENTS'!F71/'FINANCIAL STATEMENTS'!$B71 -> 2.2746509 | G68: ='FINANCIAL STATEMENTS'!G71/'FINANCIAL STATEMENTS'!$B71 -> 2.3986609
A70: CURRENT ASSETS
A71: INVENTORIES | B71: ='FINANCIAL STATEMENTS'!B75/'FINANCIAL STATEMENTS'!$B75 -> 1 | C71: ='FINANCIAL STATEMENTS'!C75/'FINANCIAL STATEMENTS'!$B75 -> 1.3360073 | D71: ='FINANCIAL STATEMENTS'!D75/'FINANCIAL STATEMENTS'!$B75 -> 1.9739079 | E71: ='FINANCIAL STATEMENTS'!E75/'FINANCIAL STATEMENTS'!$B75 -> 2.1372503 | F71: ='FINANCIAL STATEMENTS'!F75/'FINANCIAL STATEMENTS'!$B75 -> 1.7210639 | G71: ='FINANCIAL STATEMENTS'!G75/'FINANCIAL STATEMENTS'!$B75 -> 2.0402333
A72: INVESTMENTS | B72: ='FINANCIAL STATEMENTS'!B76/'FINANCIAL STATEMENTS'!$B76 -> 1 | C72: ='FINANCIAL STATEMENTS'!C76/'FINANCIAL STATEMENTS'!$B76 -> 0.23679353 | D72: ='FINANCIAL STATEMENTS'!D76/'FINANCIAL STATEMENTS'!$B76 -> 0.23813585 | E72: ='FINANCIAL STATEMENTS'!E76/'FINANCIAL STATEMENTS'!$B76 -> 0.61901899 | F72: ='FINANCIAL STATEMENTS'!F76/'FINANCIAL STATEMENTS'!$B76 -> 2.460066 | G72: ='FINANCIAL STATEMENTS'!G76/'FINANCIAL STATEMENTS'!$B76 -> 4.2463715
A73: TRADE RECEIVABLES | B73: ='FINANCIAL STATEMENTS'!B77/'FINANCIAL STATEMENTS'!$B77 -> 1 | C73: ='FINANCIAL STATEMENTS'!C77/'FINANCIAL STATEMENTS'!$B77 -> 1.2385976 | D73: ='FINANCIAL STATEMENTS'!D77/'FINANCIAL STATEMENTS'!$B77 -> 1.5024609 | E73: ='FINANCIAL STATEMENTS'!E77/'FINANCIAL STATEMENTS'!$B77 -> 1.6179909 | F73: ='FINANCIAL STATEMENTS'!F77/'FINANCIAL STATEMENTS'!$B77 -> 1.7424718 | G73: ='FINANCIAL STATEMENTS'!G77/'FINANCIAL STATEMENTS'!$B77 -> 1.9289017
A74: CASH AND CASH EQUIVALENTS | B74: ='FINANCIAL STATEMENTS'!B78/'FINANCIAL STATEMENTS'!$B78 -> 1 | C74: ='FINANCIAL STATEMENTS'!C78/'FINANCIAL STATEMENTS'!$B78 -> 0.19463991 | D74: ='FINANCIAL STATEMENTS'!D78/'FINANCIAL STATEMENTS'!$B78 -> 0.26180052 | E74: ='FINANCIAL STATEMENTS'!E78/'FINANCIAL STATEMENTS'!$B78 -> 0.27172661 | F74: ='FINANCIAL STATEMENTS'!F78/'FINANCIAL STATEMENTS'!$B78 -> 0.67332542 | G74: ='FINANCIAL STATEMENTS'!G78/'FINANCIAL STATEMENTS'!$B78 -> 0.37587961
A75: BANK BALANCES OTHER THAN CASH AND CASH EQUIVALENTS | B75: ='FINANCIAL STATEMENTS'!B79/'FINANCIAL STATEMENTS'!$B79 -> 1 | C75: ='FINANCIAL STATEMENTS'!C79/'FINANCIAL STATEMENTS'!$B79 -> 0.54817987 | D75: ='FINANCIAL STATEMENTS'!D79/'FINANCIAL STATEMENTS'!$B79 -> 0.61456103 | E75: ='FINANCIAL STATEMENTS'!E79/'FINANCIAL STATEMENTS'!$B79 -> 0.5888651 | F75: ='FINANCIAL STATEMENTS'!F79/'FINANCIAL STATEMENTS'!$B79 -> 0.49250535 | G75: ='FINANCIAL STATEMENTS'!G79/'FINANCIAL STATEMENTS'!$B79 -> 0.55246253
A76: LOANS | B76: ='FINANCIAL STATEMENTS'!B80/'FINANCIAL STATEMENTS'!$B80 -> 1 | C76: ='FINANCIAL STATEMENTS'!C80/'FINANCIAL STATEMENTS'!$B80 -> 0.64026793 | D76: ='FINANCIAL STATEMENTS'!D80/'FINANCIAL STATEMENTS'!$B80 -> 0.70173365 | E76: ='FINANCIAL STATEMENTS'!E80/'FINANCIAL STATEMENTS'!$B80 -> 0.94405043 | F76: ='FINANCIAL STATEMENTS'!F80/'FINANCIAL STATEMENTS'!$B80 -> 1.1666667 | G76: ='FINANCIAL STATEMENTS'!G80/'FINANCIAL STATEMENTS'!$B80 -> 0.8963751
A77: OTHER FINANCIAL ASSETS | B77: ='FINANCIAL STATEMENTS'!B81/'FINANCIAL STATEMENTS'!$B81 -> 1 | C77: ='FINANCIAL STATEMENTS'!C81/'FINANCIAL STATEMENTS'!$B81 -> 0.89185905 | D77: ='FINANCIAL STATEMENTS'!D81/'FINANCIAL STATEMENTS'!$B81 -> 1.3851762 | E77: ='FINANCIAL STATEMENTS'!E81/'FINANCIAL STATEMENTS'!$B81 -> 0.93560146 | F77: ='FINANCIAL STATEMENTS'!F81/'FINANCIAL STATEMENTS'!$B81 -> 0.70716889 | G77: ='FINANCIAL STATEMENTS'!G81/'FINANCIAL STATEMENTS'!$B81 -> 0.91373026 | K77: LIQUIDITY MEASURES | L77: 43921 | M77: 44286 | N77: 44651 | O77: 45016 | P77: 45382 | Q77: 45747
A78: OTHER CURRENT ASSETS | B78: ='FINANCIAL STATEMENTS'!B82/'FINANCIAL STATEMENTS'!$B82 -> 1 | C78: ='FINANCIAL STATEMENTS'!C82/'FINANCIAL STATEMENTS'!$B82 -> 0.81974199 | D78: ='FINANCIAL STATEMENTS'!D82/'FINANCIAL STATEMENTS'!$B82 -> 1.0539957 | E78: ='FINANCIAL STATEMENTS'!E82/'FINANCIAL STATEMENTS'!$B82 -> 0.96264083 | F78: ='FINANCIAL STATEMENTS'!F82/'FINANCIAL STATEMENTS'!$B82 -> 1.0186796 | G78: ='FINANCIAL STATEMENTS'!G82/'FINANCIAL STATEMENTS'!$B82 -> 1.42175 | K78: CASH RATIO (CASH AND EQUIVALENTS / CL) | L78: 1 | M78: 0.12211754 | N78: 0.16565167 | O78: 0.16233036 | P78: 0.32921446 | Q78: 0.15420722
A79: ASSETS HELD FOR SALE | K79: TOTAL DEBT TO EQUITY RATIO [(CL + NCL) / AVG. SE] | L79: 1 | M79: 1.3562431 | N79: 1.3263481 | O79: 1.2607294 | P79: 1.2949718 | Q79: 1.3158291
A80: TOTAL CURRENT ASSETS | B80: ='FINANCIAL STATEMENTS'!B85/'FINANCIAL STATEMENTS'!$B85 -> 1 | C80: ='FINANCIAL STATEMENTS'!C85/'FINANCIAL STATEMENTS'!$B85 -> 0.79997422 | D80: ='FINANCIAL STATEMENTS'!D85/'FINANCIAL STATEMENTS'!$B85 -> 1.0523585 | E80: ='FINANCIAL STATEMENTS'!E85/'FINANCIAL STATEMENTS'!$B85 -> 1.210052 | F80: ='FINANCIAL STATEMENTS'!F85/'FINANCIAL STATEMENTS'!$B85 -> 1.6581495 | G80: ='FINANCIAL STATEMENTS'!G85/'FINANCIAL STATEMENTS'!$B85 -> 2.1716919
A81: TOTAL ASSETS | B81: ='FINANCIAL STATEMENTS'!B87/'FINANCIAL STATEMENTS'!$B87 -> 1 | C81: ='FINANCIAL STATEMENTS'!C87/'FINANCIAL STATEMENTS'!$B87 -> 1.3100759 | D81: ='FINANCIAL STATEMENTS'!D87/'FINANCIAL STATEMENTS'!$B87 -> 1.5016807 | E81: ='FINANCIAL STATEMENTS'!E87/'FINANCIAL STATEMENTS'!$B87 -> 1.6635213 | F81: ='FINANCIAL STATEMENTS'!F87/'FINANCIAL STATEMENTS'!$B87 -> 1.9540544 | G81: ='FINANCIAL STATEMENTS'!G87/'FINANCIAL STATEMENTS'!$B87 -> 2.2806312
A83: EQUITIES AND LIABILITES
A85: EQUITY
A86: EQUITY SHARE CAPITAL | B86: ='FINANCIAL STATEMENTS'!B93/'FINANCIAL STATEMENTS'!$B93 -> 1 | C86: ='FINANCIAL STATEMENTS'!C93/'FINANCIAL STATEMENTS'!$B93 -> 1.0001968 | D86: ='FINANCIAL STATEMENTS'!D93/'FINANCIAL STATEMENTS'!$B93 -> 1.0003936 | E86: ='FINANCIAL STATEMENTS'!E93/'FINANCIAL STATEMENTS'!$B93 -> 1.0003936 | F86: ='FINANCIAL STATEMENTS'!F93/'FINANCIAL STATEMENTS'!$B93 -> 1.0009841 | G86: ='FINANCIAL STATEMENTS'!G93/'FINANCIAL STATEMENTS'!$B93 -> 1.0009841
A87: EQUITY | B87: ='FINANCIAL STATEMENTS'!B94/'FINANCIAL STATEMENTS'!$B94 -> 1 | C87: ='FINANCIAL STATEMENTS'!C94/'FINANCIAL STATEMENTS'!$B94 -> 1.2483887 | D87: ='FINANCIAL STATEMENTS'!D94/'FINANCIAL STATEMENTS'!$B94 -> 1.4256583 | E87: ='FINANCIAL STATEMENTS'!E94/'FINANCIAL STATEMENTS'!$B94 -> 1.5988478 | F87: ='FINANCIAL STATEMENTS'!F94/'FINANCIAL STATEMENTS'!$B94 -> 1.8773247 | G87: ='FINANCIAL STATEMENTS'!G94/'FINANCIAL STATEMENTS'!$B94 -> 2.1806792
A88: TOTAL EQUITY | B88: ='FINANCIAL STATEMENTS'!B95/'FINANCIAL STATEMENTS'!$B95 -> 1 | C88: ='FINANCIAL STATEMENTS'!C95/'FINANCIAL STATEMENTS'!$B95 -> 1.2455642 | D88: ='FINANCIAL STATEMENTS'!D95/'FINANCIAL STATEMENTS'!$B95 -> 1.4208188 | E88: ='FINANCIAL STATEMENTS'!E95/'FINANCIAL STATEMENTS'!$B95 -> 1.5920373 | F88: ='FINANCIAL STATEMENTS'!F95/'FINANCIAL STATEMENTS'!$B95 -> 1.8673519 | G88: ='FINANCIAL STATEMENTS'!G95/'FINANCIAL STATEMENTS'!$B95 -> 2.1672542
A90: LIABILITIES
A91: NON CURRENT LIABILITIES
A92: LEASE LIABILITIES | B92: ='FINANCIAL STATEMENTS'!B101/'FINANCIAL STATEMENTS'!$B101 -> 1 | C92: ='FINANCIAL STATEMENTS'!C101/'FINANCIAL STATEMENTS'!$B101 -> 0.95107212 | D92: ='FINANCIAL STATEMENTS'!D101/'FINANCIAL STATEMENTS'!$B101 -> 1.3048733 | E92: ='FINANCIAL STATEMENTS'!E101/'FINANCIAL STATEMENTS'!$B101 -> 2.7904483 | F92: ='FINANCIAL STATEMENTS'!F101/'FINANCIAL STATEMENTS'!$B101 -> 3.1643275 | G92: ='FINANCIAL STATEMENTS'!G101/'FINANCIAL STATEMENTS'!$B101 -> 4.1479532
A93: OTHER FINANCIAL LIABILITIES | B93: ='FINANCIAL STATEMENTS'!B102/'FINANCIAL STATEMENTS'!$B102 -> 1 | C93: ='FINANCIAL STATEMENTS'!C102/'FINANCIAL STATEMENTS'!$B102 -> 1.8774105 | D93: ='FINANCIAL STATEMENTS'!D102/'FINANCIAL STATEMENTS'!$B102 -> 2.7465565 | E93: ='FINANCIAL STATEMENTS'!E102/'FINANCIAL STATEMENTS'!$B102 -> 1.9903581 | F93: ='FINANCIAL STATEMENTS'!F102/'FINANCIAL STATEMENTS'!$B102 -> 0.60743802 | G93: ='FINANCIAL STATEMENTS'!G102/'FINANCIAL STATEMENTS'!$B102 -> 0.53305785
A94: PROVISIONS | B94: ='FINANCIAL STATEMENTS'!B103/'FINANCIAL STATEMENTS'!$B103 -> 1 | C94: ='FINANCIAL STATEMENTS'!C103/'FINANCIAL STATEMENTS'!$B103 -> 1.1010027 | D94: ='FINANCIAL STATEMENTS'!D103/'FINANCIAL STATEMENTS'!$B103 -> 1.3749083 | E94: ='FINANCIAL STATEMENTS'!E103/'FINANCIAL STATEMENTS'!$B103 -> 1.5803375 | F94: ='FINANCIAL STATEMENTS'!F103/'FINANCIAL STATEMENTS'!$B103 -> 1.9452189 | G94: ='FINANCIAL STATEMENTS'!G103/'FINANCIAL STATEMENTS'!$B103 -> 2.7542186
A95: DEFERRED TAX LIABILITIES(NET) | B95: ='FINANCIAL STATEMENTS'!B104/'FINANCIAL STATEMENTS'!$B104 -> 1 | C95: ='FINANCIAL STATEMENTS'!C104/'FINANCIAL STATEMENTS'!$B104 -> 0.99855206 | D95: ='FINANCIAL STATEMENTS'!D104/'FINANCIAL STATEMENTS'!$B104 -> 5.1142556 | E95: ='FINANCIAL STATEMENTS'!E104/'FINANCIAL STATEMENTS'!$B104 -> 4.9560353 | F95: ='FINANCIAL STATEMENTS'!F104/'FINANCIAL STATEMENTS'!$B104 -> 4.95077 | G95: ='FINANCIAL STATEMENTS'!G104/'FINANCIAL STATEMENTS'!$B104 -> 5.1609846
A96: TOTAL NON CURRENT LIABILITIES | B96: ='FINANCIAL STATEMENTS'!B105/'FINANCIAL STATEMENTS'!$B105 -> 1 | C96: ='FINANCIAL STATEMENTS'!C105/'FINANCIAL STATEMENTS'!$B105 -> 1.0449208 | D96: ='FINANCIAL STATEMENTS'!D105/'FINANCIAL STATEMENTS'!$B105 -> 3.0306122 | E96: ='FINANCIAL STATEMENTS'!E105/'FINANCIAL STATEMENTS'!$B105 -> 3.4131228 | F96: ='FINANCIAL STATEMENTS'!F105/'FINANCIAL STATEMENTS'!$B105 -> 3.5479991 | G96: ='FINANCIAL STATEMENTS'!G105/'FINANCIAL STATEMENTS'!$B105 -> 4.1121879
A98: CURRENT LIABILITIES
A99: BORROWINGS
A100: TOTAL OUTSTANDING DUES OF MICRO ENTERPRISES AND SMALL ENTERPRISES | B100: ='FINANCIAL STATEMENTS'!B110/'FINANCIAL STATEMENTS'!$B110 -> 1 | C100: ='FINANCIAL STATEMENTS'!C110/'FINANCIAL STATEMENTS'!$B110 -> 7.2086022 | D100: ='FINANCIAL STATEMENTS'!D110/'FINANCIAL STATEMENTS'!$B110 -> 7.327957 | E100: ='FINANCIAL STATEMENTS'!E110/'FINANCIAL STATEMENTS'!$B110 -> 5.6795699 | F100: ='FINANCIAL STATEMENTS'!F110/'FINANCIAL STATEMENTS'!$B110 -> 7.4139785 | G100: ='FINANCIAL STATEMENTS'!G110/'FINANCIAL STATEMENTS'!$B110 -> 3.6322581
A101: TOTAL OUTSTANDING DUES OF CREDITORS OTHER THAN MICRO ENTERPRISES AND SMALL ENTERPRISES | B101: ='FINANCIAL STATEMENTS'!B111/'FINANCIAL STATEMENTS'!$B111 -> 1 | C101: ='FINANCIAL STATEMENTS'!C111/'FINANCIAL STATEMENTS'!$B111 -> 1.4969414 | D101: ='FINANCIAL STATEMENTS'!D111/'FINANCIAL STATEMENTS'!$B111 -> 1.8077691 | E101: ='FINANCIAL STATEMENTS'!E111/'FINANCIAL STATEMENTS'!$B111 -> 1.8251735 | F101: ='FINANCIAL STATEMENTS'!F111/'FINANCIAL STATEMENTS'!$B111 -> 2.0035839 | G101: ='FINANCIAL STATEMENTS'!G111/'FINANCIAL STATEMENTS'!$B111 -> 2.5440877
A102: LEASE LIABILTIES | B102: ='FINANCIAL STATEMENTS'!B112/'FINANCIAL STATEMENTS'!$B112 -> 1 | C102: ='FINANCIAL STATEMENTS'!C112/'FINANCIAL STATEMENTS'!$B112 -> 0.84119782 | D102: ='FINANCIAL STATEMENTS'!D112/'FINANCIAL STATEMENTS'!$B112 -> 1.2014519 | E102: ='FINANCIAL STATEMENTS'!E112/'FINANCIAL STATEMENTS'!$B112 -> 1.972323 | F102: ='FINANCIAL STATEMENTS'!F112/'FINANCIAL STATEMENTS'!$B112 -> 2.2395644 | G102: ='FINANCIAL STATEMENTS'!G112/'FINANCIAL STATEMENTS'!$B112 -> 2.6987296
A103: OTHER FINANCIAL LIABILITIES | B103: ='FINANCIAL STATEMENTS'!B113/'FINANCIAL STATEMENTS'!$B113 -> 1 | C103: ='FINANCIAL STATEMENTS'!C113/'FINANCIAL STATEMENTS'!$B113 -> 1.6299917 | D103: ='FINANCIAL STATEMENTS'!D113/'FINANCIAL STATEMENTS'!$B113 -> 1.1940552 | E103: ='FINANCIAL STATEMENTS'!E113/'FINANCIAL STATEMENTS'!$B113 -> 1.5104087 | F103: ='FINANCIAL STATEMENTS'!F113/'FINANCIAL STATEMENTS'!$B113 -> 1.824409 | G103: ='FINANCIAL STATEMENTS'!G113/'FINANCIAL STATEMENTS'!$B113 -> 2.1570001
A104: OTHER CURRENT LIABILITIES | B104: ='FINANCIAL STATEMENTS'!B114/'FINANCIAL STATEMENTS'!$B114 -> 1 | C104: ='FINANCIAL STATEMENTS'!C114/'FINANCIAL STATEMENTS'!$B114 -> 0.80706431 | D104: ='FINANCIAL STATEMENTS'!D114/'FINANCIAL STATEMENTS'!$B114 -> 0.91191825 | E104: ='FINANCIAL STATEMENTS'!E114/'FINANCIAL STATEMENTS'!$B114 -> 0.97678552 | F104: ='FINANCIAL STATEMENTS'!F114/'FINANCIAL STATEMENTS'!$B114 -> 1.0956348 | G104: ='FINANCIAL STATEMENTS'!G114/'FINANCIAL STATEMENTS'!$B114 -> 0.98433855
A105: PROVISIONS | B105: ='FINANCIAL STATEMENTS'!B115/'FINANCIAL STATEMENTS'!$B115 -> 1 | C105: ='FINANCIAL STATEMENTS'!C115/'FINANCIAL STATEMENTS'!$B115 -> 1.3989813 | D105: ='FINANCIAL STATEMENTS'!D115/'FINANCIAL STATEMENTS'!$B115 -> 2.9660441 | E105: ='FINANCIAL STATEMENTS'!E115/'FINANCIAL STATEMENTS'!$B115 -> 2.5670628 | F105: ='FINANCIAL STATEMENTS'!F115/'FINANCIAL STATEMENTS'!$B115 -> 16.156197 | G105: ='FINANCIAL STATEMENTS'!G115/'FINANCIAL STATEMENTS'!$B115 -> 20.736842
A106: CURRENT TAX LIABILITIES(NET) | B106: ='FINANCIAL STATEMENTS'!B116/'FINANCIAL STATEMENTS'!$B116 -> 1 | C106: ='FINANCIAL STATEMENTS'!C116/'FINANCIAL STATEMENTS'!$B116 -> 2.8359173 | D106: ='FINANCIAL STATEMENTS'!D116/'FINANCIAL STATEMENTS'!$B116 -> 1.1705426 | E106: ='FINANCIAL STATEMENTS'!E116/'FINANCIAL STATEMENTS'!$B116 -> 4.9418605 | F106: ='FINANCIAL STATEMENTS'!F116/'FINANCIAL STATEMENTS'!$B116 -> 2.9857881 | G106: ='FINANCIAL STATEMENTS'!G116/'FINANCIAL STATEMENTS'!$B116 -> 2.6434109
A107: TOTAL CURRENT LIABILTIES | B107: ='FINANCIAL STATEMENTS'!B117/'FINANCIAL STATEMENTS'!$B117 -> 1 | C107: ='FINANCIAL STATEMENTS'!C117/'FINANCIAL STATEMENTS'!$B117 -> 1.5938735 | D107: ='FINANCIAL STATEMENTS'!D117/'FINANCIAL STATEMENTS'!$B117 -> 1.5804279 | E107: ='FINANCIAL STATEMENTS'!E117/'FINANCIAL STATEMENTS'!$B117 -> 1.6739112 | F107: ='FINANCIAL STATEMENTS'!F117/'FINANCIAL STATEMENTS'!$B117 -> 2.0452486 | G107: ='FINANCIAL STATEMENTS'!G117/'FINANCIAL STATEMENTS'!$B117 -> 2.4374968
A108: TOTAL LIABILITIES | B108: ='FINANCIAL STATEMENTS'!B119/'FINANCIAL STATEMENTS'!$B119 -> 1 | C108: ='FINANCIAL STATEMENTS'!C119/'FINANCIAL STATEMENTS'!$B119 -> 1.5227655 | D108: ='FINANCIAL STATEMENTS'!D119/'FINANCIAL STATEMENTS'!$B119 -> 1.7682759 | E108: ='FINANCIAL STATEMENTS'!E119/'FINANCIAL STATEMENTS'!$B119 -> 1.8991981 | F108: ='FINANCIAL STATEMENTS'!F119/'FINANCIAL STATEMENTS'!$B119 -> 2.2399058 | G108: ='FINANCIAL STATEMENTS'!G119/'FINANCIAL STATEMENTS'!$B119 -> 2.6544261
A109: TOTAL EQUITY AND LIABILITIES | B109: ='FINANCIAL STATEMENTS'!B121/'FINANCIAL STATEMENTS'!$B121 -> 1 | C109: ='FINANCIAL STATEMENTS'!C121/'FINANCIAL STATEMENTS'!$B121 -> 1.3100759 | D109: ='FINANCIAL STATEMENTS'!D121/'FINANCIAL STATEMENTS'!$B121 -> 1.5016807 | E109: ='FINANCIAL STATEMENTS'!E121/'FINANCIAL STATEMENTS'!$B121 -> 1.6635213 | F109: ='FINANCIAL STATEMENTS'!F121/'FINANCIAL STATEMENTS'!$B121 -> 1.9540544 | G109: ='FINANCIAL STATEMENTS'!G121/'FINANCIAL STATEMENTS'!$B121 -> 2.2806312
A111: AVERAGE RECEIVABLES | B111: ='FINANCIAL STATEMENTS'!B123/'FINANCIAL STATEMENTS'!$B123 -> 1 | C111: ='FINANCIAL STATEMENTS'!C123/'FINANCIAL STATEMENTS'!$B123 -> 1.1192988 | D111: ='FINANCIAL STATEMENTS'!D123/'FINANCIAL STATEMENTS'!$B123 -> 1.3705292 | E111: ='FINANCIAL STATEMENTS'!E123/'FINANCIAL STATEMENTS'!$B123 -> 1.5602259 | F111: ='FINANCIAL STATEMENTS'!F123/'FINANCIAL STATEMENTS'!$B123 -> 1.6802313 | G111: ='FINANCIAL STATEMENTS'!G123/'FINANCIAL STATEMENTS'!$B123 -> 1.8356867
A112: AVERAGE INVENTORY | B112: ='FINANCIAL STATEMENTS'!B124/'FINANCIAL STATEMENTS'!$B124 -> 1 | C112: ='FINANCIAL STATEMENTS'!C124/'FINANCIAL STATEMENTS'!$B124 -> 1.1680037 | D112: ='FINANCIAL STATEMENTS'!D124/'FINANCIAL STATEMENTS'!$B124 -> 1.6549576 | E112: ='FINANCIAL STATEMENTS'!E124/'FINANCIAL STATEMENTS'!$B124 -> 2.0555791 | F112: ='FINANCIAL STATEMENTS'!F124/'FINANCIAL STATEMENTS'!$B124 -> 1.9291571 | G112: ='FINANCIAL STATEMENTS'!G124/'FINANCIAL STATEMENTS'!$B124 -> 1.8806486
A113: AVERAGE PAYABLES | B113: ='FINANCIAL STATEMENTS'!B125/'FINANCIAL STATEMENTS'!$B125 -> 1 | C113: ='FINANCIAL STATEMENTS'!C125/'FINANCIAL STATEMENTS'!$B125 -> 1.3021463 | D113: ='FINANCIAL STATEMENTS'!D125/'FINANCIAL STATEMENTS'!$B125 -> 1.7579071 | E113: ='FINANCIAL STATEMENTS'!E125/'FINANCIAL STATEMENTS'!$B125 -> 1.9045694 | F113: ='FINANCIAL STATEMENTS'!F125/'FINANCIAL STATEMENTS'!$B125 -> 2.001445 | G113: ='FINANCIAL STATEMENTS'!G125/'FINANCIAL STATEMENTS'!$B125 -> 2.3349063
A114: AVERAGE TOTAL ASSETS | B114: ='FINANCIAL STATEMENTS'!B126/'FINANCIAL STATEMENTS'!$B126 -> 1 | C114: ='FINANCIAL STATEMENTS'!C126/'FINANCIAL STATEMENTS'!$B126 -> 1.1550379 | D114: ='FINANCIAL STATEMENTS'!D126/'FINANCIAL STATEMENTS'!$B126 -> 1.4058783 | E114: ='FINANCIAL STATEMENTS'!E126/'FINANCIAL STATEMENTS'!$B126 -> 1.582601 | F114: ='FINANCIAL STATEMENTS'!F126/'FINANCIAL STATEMENTS'!$B126 -> 1.8087878 | G114: ='FINANCIAL STATEMENTS'!G126/'FINANCIAL STATEMENTS'!$B126 -> 2.1173428
A115: WORKING CAPITAL ( CURRENT ASSETS - CURRENT LIABILITIES) | B115: ='FINANCIAL STATEMENTS'!B127/'FINANCIAL STATEMENTS'!$B127 -> 1 | C115: ='FINANCIAL STATEMENTS'!C127/'FINANCIAL STATEMENTS'!$B127 -> 0.29334575 | D115: ='FINANCIAL STATEMENTS'!D127/'FINANCIAL STATEMENTS'!$B127 -> 0.71536996 | E115: ='FINANCIAL STATEMENTS'!E127/'FINANCIAL STATEMENTS'!$B127 -> 0.91403932 | F115: ='FINANCIAL STATEMENTS'!F127/'FINANCIAL STATEMENTS'!$B127 -> 1.4111215 | G115: ='FINANCIAL STATEMENTS'!G127/'FINANCIAL STATEMENTS'!$B127 -> 2.002068
A116: AVERAGE WORKING CAPITAL | B116: ='FINANCIAL STATEMENTS'!B128/'FINANCIAL STATEMENTS'!$B128 -> 1 | C116: ='FINANCIAL STATEMENTS'!C128/'FINANCIAL STATEMENTS'!$B128 -> 0.64667287 | D116: ='FINANCIAL STATEMENTS'!D128/'FINANCIAL STATEMENTS'!$B128 -> 0.50435785 | E116: ='FINANCIAL STATEMENTS'!E128/'FINANCIAL STATEMENTS'!$B128 -> 0.81470464 | F116: ='FINANCIAL STATEMENTS'!F128/'FINANCIAL STATEMENTS'!$B128 -> 1.1625804 | G116: ='FINANCIAL STATEMENTS'!G128/'FINANCIAL STATEMENTS'!$B128 -> 1.7065947
A117: AVERAGE SHAREHOLDER'S EQUITY | B117: ='FINANCIAL STATEMENTS'!B129/'FINANCIAL STATEMENTS'!$B129 -> 1 | C117: ='FINANCIAL STATEMENTS'!C129/'FINANCIAL STATEMENTS'!$B129 -> 1.1227821 | D117: ='FINANCIAL STATEMENTS'!D129/'FINANCIAL STATEMENTS'!$B129 -> 1.3331915 | E117: ='FINANCIAL STATEMENTS'!E129/'FINANCIAL STATEMENTS'!$B129 -> 1.506428 | F117: ='FINANCIAL STATEMENTS'!F129/'FINANCIAL STATEMENTS'!$B129 -> 1.7296946 | G117: ='FINANCIAL STATEMENTS'!G129/'FINANCIAL STATEMENTS'!$B129 -> 2.017303
A119: RATIOS
A120: LIQUIDITY MEASURES | B120: 43921 | C120: 44286 | D120: 44651 | E120: 45016 | F120: 45382 | G120: 45747
A121: CURRENT RATIO (CA/CL) | B121: ='FINANCIAL STATEMENTS'!B133/'FINANCIAL STATEMENTS'!$B133 -> 1 | C121: ='FINANCIAL STATEMENTS'!C133/'FINANCIAL STATEMENTS'!$B133 -> 0.50190571 | D121: ='FINANCIAL STATEMENTS'!D133/'FINANCIAL STATEMENTS'!$B133 -> 0.66586936 | E121: ='FINANCIAL STATEMENTS'!E133/'FINANCIAL STATEMENTS'!$B133 -> 0.72288901 | F121: ='FINANCIAL STATEMENTS'!F133/'FINANCIAL STATEMENTS'!$B133 -> 0.8107325 | G121: ='FINANCIAL STATEMENTS'!G133/'FINANCIAL STATEMENTS'!$B133 -> 0.89095169
A122: QUICK RATIO (CA - INVENTORY / CL) | B122: ='FINANCIAL STATEMENTS'!B134/'FINANCIAL STATEMENTS'!$B134 -> 1 | C122: ='FINANCIAL STATEMENTS'!C134/'FINANCIAL STATEMENTS'!$B134 -> 0.41332642 | D122: ='FINANCIAL STATEMENTS'!D134/'FINANCIAL STATEMENTS'!$B134 -> 0.42929136 | E122: ='FINANCIAL STATEMENTS'!E134/'FINANCIAL STATEMENTS'!$B134 -> 0.48178308 | F122: ='FINANCIAL STATEMENTS'!F134/'FINANCIAL STATEMENTS'!$B134 -> 0.73133839 | G122: ='FINANCIAL STATEMENTS'!G134/'FINANCIAL STATEMENTS'!$B134 -> 0.83389939
A123: CASH RATIO (CASH AND EQUIVALENTS / CL) | B123: ='FINANCIAL STATEMENTS'!B135/'FINANCIAL STATEMENTS'!$B135 -> 1 | C123: ='FINANCIAL STATEMENTS'!C135/'FINANCIAL STATEMENTS'!$B135 -> 0.12211754 | D123: ='FINANCIAL STATEMENTS'!D135/'FINANCIAL STATEMENTS'!$B135 -> 0.16565167 | E123: ='FINANCIAL STATEMENTS'!E135/'FINANCIAL STATEMENTS'!$B135 -> 0.16233036 | F123: ='FINANCIAL STATEMENTS'!F135/'FINANCIAL STATEMENTS'!$B135 -> 0.32921446 | G123: ='FINANCIAL STATEMENTS'!G135/'FINANCIAL STATEMENTS'!$B135 -> 0.15420722
A125: LEVERAGE MEASURES | B125: 43921 | C125: 44286 | D125: 44651 | E125: 45016 | F125: 45382 | G125: 45747
...

Sheet CASH FLOW STATEMENT
A2: CASH FLOW STATEMENT
A5: CASH FLOW | B5: 43921 | C5: 44286 | D5: 44651 | E5: 45016 | F5: 45382 | G5: 45747
A6: OPERATING ACTIVITIES
A7: PROFIT BEFORE TAX | B7: 1436.95 | C7: 1456.63 | D7: 1590.74 | E7: 1667.72 | F7: 2403.81 | G7: 2765.88
A9: ADJUSTMENTS FOR :
A11: FINANCE COSTS | B11: 13.4 | C11: 16.99 | D11: 27.24 | E11: 28.53 | F11: 29.46 | G11: 34.72
A12: INTEREST INCOME | B12: -5.93 | C12: -12.78 | D12: -2.41 | E12: -4.9 | F12: -7.59 | G12: -5.63
A13: DIVIDEND INCOME | B13: -13.38 | C13: -2.78 | D13: -4.01 | E13: -17.46 | F13: -39.97 | G13: -54.82
A14: LOSS/(PROFIT) ON DISPOSAL OF PROPERTY , PLANT AND EQUIPMENT | B14: -2.67 | C14: 5.85 | D14: 8.2 | E14: -1.96 | F14: 8.88 | G14: 1.36
A15: NET GAIN ARISING ON ASSETS DESIGNATED AS FVTPL | B15: -110.39 | C15: -39.99 | D15: -11.37 | E15: -16.78 | F15: -84.94 | G15: -214.23
A16: ALLOWANCE FOR DOUBTFUL DEBTS | B16: 0 | C16: 3.73 | D16: -2.57 | E16: 4.64 | F16: 4 | G16: 6.87
A17: PROVISION IN RESPECT OF WRITE DOWN OF INVENTORIES | B17: 0 | C17: 0 | D17: 0 | E17: 0 | F17: 0 | G17: 5.34
A18: LIABILITIES NO LONGER REQUIRED WRITTEN BACK | B18: 0 | C18: 0 | D18: 0 | E18: 0 | F18: -3.77 | G18: -2.25
A19: ALLOWANCE FOR DOUBTFUL DEBTS WRITTEN BACK | B19: -5.8 | C19: 0 | D19: 0 | E19: 0 | F19: 0 | G19: 0
A20: EXCEPTIONAL ITEM - IMPAIRMENT IN VALUE OF ASSETS AND INVESTMENTS LOSS/(GAIN) | B20: 59.28 | C20: 0.45 | D20: 194.38 | E20: 0 | F20: -7.15 | G20: 20.16
A21: DEPRECIATION , AMMORTISATION AND IMPAIRMENT EXPENSE | B21: 125.79 | C21: 147.1 | D21: 3.75 | E21: 221.97 | F21: 289.11 | G21: 308.41
A22: UNREALISED FOREIGN EXCHANGE NET LOSS/(GAIN) | B22: -0.15 | C22: -1.88 | D22: 15.79 | E22: 4.73 | F22: -6.73 | G22: 0.57
... A26: OTHER PROVISIONS | B26: 0 | C26: 0 | D26: 0 | E26: 0 | F26: 48.02 | G26: 57.37
A28: OPERATING PROFITS BEFORE WORKING CAPITAL CHANGES | B28: =B7+SUM(B11:B26) -> 1500.05 | C28: =C7+SUM(C11:C26) -> 1598.49 | D28: =D7+SUM(D11:D26) -> 1846.72 | E28: =E7+SUM(E11:E26) -> 1906.26 | F28: =F7+SUM(F11:F26) -> 2656.77 | G28: =G7+SUM(G11:G26) -> 3024.83
A30: MOVEMENTS IN WORKING CAPITAL
A31: (INCREASE)/DECREASE IN OPERATING ASSETS
A33: TRADE RECEIVABLES | B33: -17.94 | C33: -200.06 | D33: -122.46 | E33: -99.3 | F33: -104.06 | G33: -157.35
A34: INVENTORIES | B34: 3.81 | C34: -240.47 | D34: -415.73 | E34: -119.32 | F34: 304.02 | G34: -238.49
A35: NON-CURRENT LOANS | B35: -1.1 | C35: -0.78 | D35: -0.2 | E35: -1.15 | F35: -1.93 | G35: -0.24
A36: CURRENT LOANS | B36: -10 | C36: -7.87 | D36: -1.36 | E36: -6.15 | F36: 2.35 | G36: -0.18
A37: OTHER NON-CURRENT FINANCIAL ASSETS | B37: 5.39 | C37: 0.02 | D37: -3.64 | E37: -15.5 | F37: -4.56 | G37: -3.11
A38: OTHER CURRENT FINANCIAL ASSETS | B38: 1.02 | C38: 0.89 | D38: -2.9 | E38: 3.7 | F38: 1.88 | G38: -1.71
A39: OTHER NON CURRENT NON FINANCIAL ASSETS | B39: 2.83 | C39: -27.8 | D39: -21.06 | E39: -17.32 | F39: -0.14 | G39: -4.92
A40: OTHER CURRENT NON FINANCIAL ASSETS | B40: -25.7 | C40: 13.39 | D40: -15.39 | E40: 15.59 | F40: -10.27 | G40: -69.05
A42: INCREASE/(DECREASE) IN OPERATING LIABILITIES
A44: TRADE PAYABLES | B44: 37.89 | C44: 296.34 | D44: -1.91 | E44: -10.05 | F44: 109.72 | G44: 229.09
A45: OTHER CURRENT FINANCIAL LIABILITIES | B45: 113.99 | C45: 121.42 | D45: 35.02 | E45: 173.36 | F45: 226.72 | G45: 163.24
A46: OTHER NON CURRENT FINANCIAL LIABILITIES | B46: -38.75 | C46: 6.37 | D46: 6.31 | E46: -5.49 | F46: 0 | G46: 0
A47: OTHER CURRENT NON FINANCIAL LIABILITIES | B47: 32.6 | C47: -17.4 | D47: 2.48 | E47: 6.3 | F47: 10.91 | G47: -10.02
A49: CASH GENERATED FROM OPERATIONS | B49: =SUM(B33:B40)+SUM(B44:B47)+B28 -> 1604.09 | C49: =SUM(C33:C40)+SUM(C44:C47)+C28 -> 1542.54 | D49: =SUM(D33:D40)+SUM(D44:D47)+D28 -> 1305.88 | E49: =SUM(E33:E40)+SUM(E44:E47)+E28 -> 1830.93 | F49: =SUM(F33:F40)+SUM(F44:F47)+F28 -> 3191.41 | G49: =SUM(G33:G40)+SUM(G44:G47)+G28 -> 2932.09
A51: TAXES PAID (NET OF REFUNDS) | B51: -375.92 | C51: -342.02 | D51: -448.96 | E51: -398.57 | F51: -605.51 | G51: -703.38
A53: NET CASH GENERATED FROM OPERATING ACTIVITIES [A] | B53: =B49+B51 -> 1228.17 | C53: =C49+C51 -> 1200.52 | D53: =D49+D51 -> 856.92 | E53: =E49+E51 -> 1432.36 | F53: =F49+F51 -> 2585.9 | G53: =G49+G51 -> 2228.71
A55: INVESTING ACTIVITIES
A57: PAYMENTS FOR PURCHASE OF PROPERT,PLANT AND EQUIPMENT, OTHER INTANGIBLE ASSETS AND CAPITAL WORK-IN-PROGRESS | B57: -398.86 | C57: -323.97 | D57: -322.57 | E57: -435.6 | F57: -510.07 | G57: -433.46
A58: PROCEEDS FROM DISPOSAL OF PROPERTY ,PLANT AND EQUIPMENT AND OTHER INTANGIBLE ASSETS | B58: 5.03 | C58: 1.76 | D58: 0.77 | E58: 7 | F58: 5.76 | G58: 4.27
A59: NET CASH OUTFLOW ON ACQUISITION/INVESTMENT INSUBSIDIARIES | B59: -127.44 | C59: -2109.95 | D59: -359.95 | E59: -78.95 | F59: -170.6 | G59: -68.31
A60: PAYMENTS TO PURCHASE INVESTMENTS | B60: -1305.53 | C60: -2898.47 | D60: 11.28 | E60: 0 | F60: 126.95 | G60: 11.54
A61: PROCEEDS ON SALE OF INVESTMENTS | B61: 1907.3 | C61: 3634.27 | D61: -49 | E61: -1713.68 | F61: -2544.85 | G61: -4444.22
A62: PAYMENT TOWARDS SHARE APPLICATION MONEY | B62: -18.74 | C62: 0 | D62: 170.24 | E62: 1447.81 | F62: 1315.25 | G62: 3364.87
A63: LOANS GIVEN TO ASSOCIATE | B63: 0 | C63: 0 | D63: 0 | E63: 0 | F63: -7.5 | G63: -7.66
A64: LOANS GIVEN TO SUBSIDIARY | B64: 0 | C64: 0 | D64: 0 | E64: 0 | F64: 0 | G64: -2
A65: DECREASE/(INCREASE) IN BANK DEPOSITS | B65: 53.67 | C65: 1.42 | D65: 3.01 | E65: 0.12 | F65: 0.15 | G65: -0.1
A66: (INCREASE)/DECREASE IN OTHER BANK BALANCES | B66: -1.4 | C66: 0.69 | D66: -0.08 | E66: 0 | F66: 0.45 | G66: -0.39
A67: INTEREST RECEIVED | B67: 5.93 | C67: 12.78 | D67: 2.41 | E67: 2.32 | F67: 7.59 | G67: 5.63
A68: DIVIDEND RECEIVED | B68: 13.38 | C68: 2.78 | D68: 4.01 | E68: 17.46 | F68: 39.97 | G68: 54.82
A70: NET CASH (USED IN ) / GENERATED FROM INVESTING ACTIVITIES [B] | B70: =SUM(B57:B68) -> 133.34 | C70: =SUM(C57:C68) -> -1678.69 | D70: =SUM(D57:D68) -> -539.88 | E70: =SUM(E57:E68) -> -753.52 | F70: =SUM(F57:F68) -> -1736.9 | G70: =SUM(G57:G68) -> -1515.01
A72: FINANCING ACTIVITES
A74: NET INCREASE IN CURRENT BORROWINGS | B74: 0 | C74: 55 | D74: 50 | E74: -105 | F74: 0 | G74: 0
A75: PROCEEDS FROM ISSUE OF EQUITY SHARES OF THE COMPANY | B75: 0.01 | C75: 0.01 | D75: 0 | E75: 0 | F75: 0.03 | G75: 1.59
A76: PAYMENT OF LEASE LIABILITES (PRINCIPAL PLUS INTEREST) | B76: -25.05 | C76: -24.08 | D76: -33.63 | E76: -41.8 | F76: =-47.93-14.91 -> -62.84 | G76: =-49.52-18.82 -> -68.34
A77: DIVIDEND PAID ON EQUITY SHARES( INCLUDING TAX THEREON) | B77: -825.36 | C77: -0.69 | D77: -431.85 | E77: -508.3 | F77: -559.75 | G77: -813.38
A78: INTEREST PAID OTHER THAN LEASE LIABILITIES | B78: -7.32 | C78: -11.53 | D78: -20.12 | E78: -17.59 | F78: -0.35 | G78: -1.38
A80: NET CASH (USED IN ) / GENERATED FROM FINANCING ACTIVITIES [C] | B80: =SUM(B74:B78) -> -857.72 | C80: =SUM(C74:C78) -> 18.71 | D80: =SUM(D74:D78) -> -435.6 | E80: =SUM(E74:E78) -> -672.69 | F80: =SUM(F74:F78) -> -622.91 | G80: =SUM(G74:G78) -> -881.51
A82: NET INCREASE/(DECREASE) IN CASH AND CASH EQUIVALENTS [A+B+C] | B82: =SUM(B53,B70,B80) -> 503.79 | C82: =SUM(C53,C70,C80) -> -459.46 | D82: =SUM(D53,D70,D80) -> -118.56 | E82: =SUM(E53,E70,E80) -> 6.15 | F82: =SUM(F53,F70,F80) -> 226.09 | G82: =SUM(G53,G70,G80) -> -167.81
A84: CASH AND CASH EQUIVALENTS AT THE BEGINNING OF THE YEAR | B84: 60.24 | C84: 564.17 | D84: 109.81 | E84: 147.7 | F84: 153.3 | G84: 379.87
A85: BANK UNREALISED GAIN | B85: 0.33 | C85: 0.18 | D85: 0 | E85: 0 | F85: 0.5 | G85: 0.02
A86: ACQUISITION UNDER BUSINESS COMBINATION | B86: 0 | C86: 0 | D86: 156.45 | E86: 0 | F86: 0 | G86: 0
A87: UNREALISED GAIN ON FOREIGN CURRENCY CASH AND CASH EQUIVALENTS | B87: 0 | C87: 0 | D87: -0.05 | E87: -0.05 | F87: 0 | G87: 0
A89: CASH AND CASH EQUIVALENTS AT THE BEGINNING OF THE YEAR | B89: =SUM(B84:B87) -> 60.57 | C89: =SUM(C84:C87) -> 564.35 | D89: =SUM(D84:D87) -> 266.21 | E89: =SUM(E84:E87) -> 147.65 | F89: =SUM(F84:F87) -> 153.8 | G89: =SUM(G84:G87) -> 379.89
A91: CASH AND CASH EQUIVALENTS AT THE END OF THE YEAR | B91: 564.17 | C91: 109.81 | D91: 147.7 | E91: 153.3 | F91: 379.87 | G91: 212.06
A92: BANK UNREALISED GAIN | B92: 0.18 | C92: -0.05 | D92: -0.05 | E92: 0 | F92: 0.02 | G92: 0.02
A93: ACQUISTION UNDER BUSINESS COMBINATION | B93: 0 | C93: -4.87 | D93: 0 | E93: 0 | F93: 0 | G93: 0
A94: UNREALISED LOSS/(GAIN) ON FOREIGN CURRENCY CASH AND CASH EQUIVALENTS | B94: 0 | C94: 0 | D94: 0 | E94: 0.5 | F94: 0 | G94: 0
A96: CASH AND CASH EQUIVALENTS AT THE END OF THE YEAR | B96: =SUM(B91:B94) -> 564.35 | C96: =SUM(C91:C94) -> 104.89 | D96: =SUM(D91:D94) -> 147.65 | E96: =SUM(E91:E94) -> 153.8 | F96: =SUM(F91:F94) -> 379.89 | G96: =SUM(G91:G94) -> 212.08
A98: NET (DECREASE)/INCREASE IN CASH AND CASH EQUIVALENTS | B98: =B96-B89 -> 503.78 | C98: =C96-C89 -> -459.46 | D98: =D96-D89 -> -118.56 | E98: =E96-E89 -> 6.15 | F98: =F96-F89 -> 226.09 | G98: =G96-G89 -> -167.81

Sheet COMMON SIZE FINANCIAL STATMENT
A2: COMMON SIZE FINANCIAL STATEMENT
A4: INCOME STATEMENT
A6: PARTICULARS(AMOUNT IN CRORES OF INR) | B6: 43921 | C6: 44286 | D6: 44651 | E6: 45016 | F6: 45382 | G6: 45747
A7: INCOME
A9: REVENUE FROM OPERATIONS | B9: ='FINANCIAL STATEMENTS'!B9/'FINANCIAL STATEMENTS'!B$9 -> 1 | C9: ='FINANCIAL STATEMENTS'!C9/'FINANCIAL STATEMENTS'!C$9 -> 1 | D9: ='FINANCIAL STATEMENTS'!D9/'FINANCIAL STATEMENTS'!D$9 -> 1 | E9: ='FINANCIAL STATEMENTS'!E9/'FINANCIAL STATEMENTS'!E$9 -> 1 | F9: ='FINANCIAL STATEMENTS'!F9/'FINANCIAL STATEMENTS'!F$9 -> 1 | G9: ='FINANCIAL STATEMENTS'!G9/'FINANCIAL STATEMENTS'!G$9 -> 1
A10: OTHER INCOME | B10: ='FINANCIAL STATEMENTS'!B10/'FINANCIAL STATEMENTS'!B$9 -> 0.023980709 | C10: ='FINANCIAL STATEMENTS'!C10/'FINANCIAL STATEMENTS'!C$9 -> 0.011822088 | D10: ='FINANCIAL STATEMENTS'!D10/'FINANCIAL STATEMENTS'!D$9 -> 0.0044920984 | E10: ='FINANCIAL STATEMENTS'!E10/'FINANCIAL STATEMENTS'!E$9 -> 0.0059488142 | F10: ='FINANCIAL STATEMENTS'!F10/'FINANCIAL STATEMENTS'!F$9 -> 0.01482497 | G10: ='FINANCIAL STATEMENTS'!G10/'FINANCIAL STATEMENTS'!G$9 -> 0.024380627
A11: TOTAL INCOME | B11: ='FINANCIAL STATEMENTS'!B11/'FINANCIAL STATEMENTS'!B$9 -> 1.0239807 | C11: ='FINANCIAL STATEMENTS'!C11/'FINANCIAL STATEMENTS'!C$9 -> 1.0118221 | D11: ='FINANCIAL STATEMENTS'!D11/'FINANCIAL STATEMENTS'!D$9 -> 1.0044921 | E11: ='FINANCIAL STATEMENTS'!E11/'FINANCIAL STATEMENTS'!E$9 -> 1.0059488 | F11: ='FINANCIAL STATEMENTS'!F11/'FINANCIAL STATEMENTS'!F$9 -> 1.014825 | G11: ='FINANCIAL STATEMENTS'!G11/'FINANCIAL STATEMENTS'!G$9 -> 1.0243806
A13: EXPENSES
A15: COST OF MATERIALS CONSUMED | B15: ='FINANCIAL STATEMENTS'!B15/'FINANCIAL STATEMENTS'!B$9 -> 0.39805198 | C15: ='FINANCIAL STATEMENTS'!C15/'FINANCIAL STATEMENTS'!C$9 -> 0.39726495 | D15: ='FINANCIAL STATEMENTS'!D15/'FINANCIAL STATEMENTS'!D$9 -> 0.50847158 | E15: ='FINANCIAL STATEMENTS'!E15/'FINANCIAL STATEMENTS'!E$9 -> 0.50447624 | F15: ='FINANCIAL STATEMENTS'!F15/'FINANCIAL STATEMENTS'!F$9 -> 0.40478303 | G15: ='FINANCIAL STATEMENTS'!G15/'FINANCIAL STATEMENTS'!G$9 -> 0.40174112
A16: PURCHASES OF STOCK IN TRADE | B16: ='FINANCIAL STATEMENTS'!B16/'FINANCIAL STATEMENTS'!B$9 -> 0.061224554 | C16: ='FINANCIAL STATEMENTS'!C16/'FINANCIAL STATEMENTS'!C$9 -> 0.073031837 | D16: ='FINANCIAL STATEMENTS'!D16/'FINANCIAL STATEMENTS'!D$9 -> 0.068330257 | E16: ='FINANCIAL STATEMENTS'!E16/'FINANCIAL STATEMENTS'!E$9 -> 0.081056367 | F16: ='FINANCIAL STATEMENTS'!F16/'FINANCIAL STATEMENTS'!F$9 -> 0.075013186 | G16: ='FINANCIAL STATEMENTS'!G16/'FINANCIAL STATEMENTS'!G$9 -> 0.068391495
A17: CHANGES IN INVENTORIES OF FINISHED GOODS, WORK IN PROGRESS, AND STOCK IN TRADE | B17: ='FINANCIAL STATEMENTS'!B17/'FINANCIAL STATEMENTS'!B$9 -> 0.0044184133 | C17: ='FINANCIAL STATEMENTS'!C17/'FINANCIAL STATEMENTS'!C$9 -> -0.014440997 | D17: ='FINANCIAL STATEMENTS'!D17/'FINANCIAL STATEMENTS'!D$9 -> -0.025351802 | E17: ='FINANCIAL STATEMENTS'!E17/'FINANCIAL STATEMENTS'!E$9 -> -0.0057581954 | F17: ='FINANCIAL STATEMENTS'!F17/'FINANCIAL STATEMENTS'!F$9 -> 0.0051625463 | G17: ='FINANCIAL STATEMENTS'!G17/'FINANCIAL STATEMENTS'!G$9 -> -0.010328261
A18: EMPLOYEE BENEFITS EXPENSE | B18: ='FINANCIAL STATEMENTS'!B18/'FINANCIAL STATEMENTS'!B$9 -> 0.11636471 | C18: ='FINANCIAL STATEMENTS'!C18/'FINANCIAL STATEMENTS'!C$9 -> 0.12672268 | D18: ='FINANCIAL STATEMENTS'!D18/'FINANCIAL STATEMENTS'!D$9 -> 0.10418161 | E18: ='FINANCIAL STATEMENTS'!E18/'FINANCIAL STATEMENTS'!E$9 -> 0.098596121 | F18: ='FINANCIAL STATEMENTS'!F18/'FINANCIAL STATEMENTS'!F$9 -> 0.11232411 | G18: ='FINANCIAL STATEMENTS'!G18/'FINANCIAL STATEMENTS'!G$9 -> 0.12801362
A19: OTHER EXPENSE | B19: ='FINANCIAL STATEMENTS'!B19/'FINANCIAL STATEMENTS'!B$9 -> 0.18566653 | C19: ='FINANCIAL STATEMENTS'!C19/'FINANCIAL STATEMENTS'!C$9 -> 0.16845148 | D19: ='FINANCIAL STATEMENTS'!D19/'FINANCIAL STATEMENTS'!D$9 -> 0.14512423 | E19: ='FINANCIAL STATEMENTS'!E19/'FINANCIAL STATEMENTS'!E$9 -> 0.1465641 | F19: ='FINANCIAL STATEMENTS'!F19/'FINANCIAL STATEMENTS'!F$9 -> 0.17439377 | G19: ='FINANCIAL STATEMENTS'!G19/'FINANCIAL STATEMENTS'!G$9 -> 0.17736877
A20: TOTAL EXPENSE BEFORE DEPRECIATION AND AMMORTISATION | B20: ='FINANCIAL STATEMENTS'!B20/'FINANCIAL STATEMENTS'!B$9 -> 0.76572619 | C20: ='FINANCIAL STATEMENTS'!C20/'FINANCIAL STATEMENTS'!C$9 -> 0.75102995 | D20: ='FINANCIAL STATEMENTS'!D20/'FINANCIAL STATEMENTS'!D$9 -> 0.80075588 | E20: ='FINANCIAL STATEMENTS'!E20/'FINANCIAL STATEMENTS'!E$9 -> 0.82493463 | F20: ='FINANCIAL STATEMENTS'!F20/'FINANCIAL STATEMENTS'!F$9 -> 0.77167665 | G20: ='FINANCIAL STATEMENTS'!G20/'FINANCIAL STATEMENTS'!G$9 -> 0.76518674
A22: EBITDA | B22: ='FINANCIAL STATEMENTS'!B22/'FINANCIAL STATEMENTS'!B$9 -> 0.25825452 | C22: ='FINANCIAL STATEMENTS'!C22/'FINANCIAL STATEMENTS'!C$9 -> 0.26079214 | D22: ='FINANCIAL STATEMENTS'!D22/'FINANCIAL STATEMENTS'!D$9 -> 0.20373622 | E22: ='FINANCIAL STATEMENTS'!E22/'FINANCIAL STATEMENTS'!E$9 -> 0.18101419 | F22: ='FINANCIAL STATEMENTS'!F22/'FINANCIAL STATEMENTS'!F$9 -> 0.24314832 | G22: ='FINANCIAL STATEMENTS'!G22/'FINANCIAL STATEMENTS'!G$9 -> 0.25919388
A23: DEPRECIATION, AMORTISATION AND IMPAIRMENT EXPENSE | B23: ='FINANCIAL STATEMENTS'!B23/'FINANCIAL STATEMENTS'!B$9 -> 0.01986391 | C23: ='FINANCIAL STATEMENTS'!C23/'FINANCIAL STATEMENTS'!C$9 -> 0.02366348 | D23: ='FINANCIAL STATEMENTS'!D23/'FINANCIAL STATEMENTS'!D$9 -> 0.021851203 | E23: ='FINANCIAL STATEMENTS'!E23/'FINANCIAL STATEMENTS'!E$9 -> 0.020946356 | F23: ='FINANCIAL STATEMENTS'!F23/'FINANCIAL STATEMENTS'!F$9 -> 0.025889744 | G23: ='FINANCIAL STATEMENTS'!G23/'FINANCIAL STATEMENTS'!G$9 -> 0.025546067
A24: EBIT | B24: ='FINANCIAL STATEMENTS'!B24/'FINANCIAL STATEMENTS'!B$9 -> 0.23839061 | C24: ='FINANCIAL STATEMENTS'!C24/'FINANCIAL STATEMENTS'!C$9 -> 0.23712866 | D24: ='FINANCIAL STATEMENTS'!D24/'FINANCIAL STATEMENTS'!D$9 -> 0.18188502 | E24: ='FINANCIAL STATEMENTS'!E24/'FINANCIAL STATEMENTS'!E$9 -> 0.16006783 | F24: ='FINANCIAL STATEMENTS'!F24/'FINANCIAL STATEMENTS'!F$9 -> 0.21725858 | G24: ='FINANCIAL STATEMENTS'!G24/'FINANCIAL STATEMENTS'!G$9 -> 0.23364782
A25: FINANCE COSTS | B25: ='FINANCIAL STATEMENTS'!B25/'FINANCIAL STATEMENTS'!B$9 -> 0.0021160378 | C25: ='FINANCIAL STATEMENTS'!C25/'FINANCIAL STATEMENTS'!C$9 -> 0.0027331239 | D25: ='FINANCIAL STATEMENTS'!D25/'FINANCIAL STATEMENTS'!D$9 -> 0.0030621812 | E25: ='FINANCIAL STATEMENTS'!E25/'FINANCIAL STATEMENTS'!E$9 -> 0.0026922536 | F25: ='FINANCIAL STATEMENTS'!F25/'FINANCIAL STATEMENTS'!F$9 -> 0.0026381373 | G25: ='FINANCIAL STATEMENTS'!G25/'FINANCIAL STATEMENTS'!G$9 -> 0.0028759101
A26: EXCEPTIONAL ITEMS | B26: ='FINANCIAL STATEMENTS'!B26/'FINANCIAL STATEMENTS'!B$9 -> 0.0093610987 | C26: ='FINANCIAL STATEMENTS'!C26/'FINANCIAL STATEMENTS'!C$9 -> 7.2389979e-05 | D26: ='FINANCIAL STATEMENTS'!D26/'FINANCIAL STATEMENTS'!D$9 -> 0 | E26: ='FINANCIAL STATEMENTS'!E26/'FINANCIAL STATEMENTS'!E$9 -> 0 | F26: ='FINANCIAL STATEMENTS'!F26/'FINANCIAL STATEMENTS'!F$9 -> -0.00064028111 | G26: ='FINANCIAL STATEMENTS'!G26/'FINANCIAL STATEMENTS'!G$9 -> 0.0016698833
A27: PROFIT BEFORE TAX | B27: ='FINANCIAL STATEMENTS'!B27/'FINANCIAL STATEMENTS'!B$9 -> 0.22691347 | C27: ='FINANCIAL STATEMENTS'!C27/'FINANCIAL STATEMENTS'!C$9 -> 0.23432315 | D27: ='FINANCIAL STATEMENTS'!D27/'FINANCIAL STATEMENTS'!D$9 -> 0.17882284 | E27: ='FINANCIAL STATEMENTS'!E27/'FINANCIAL STATEMENTS'!E$9 -> 0.15737558 | F27: ='FINANCIAL STATEMENTS'!F27/'FINANCIAL STATEMENTS'!F$9 -> 0.21526072 | G27: ='FINANCIAL STATEMENTS'!G27/'FINANCIAL STATEMENTS'!G$9 -> 0.22910202
A29: TAX EXPENSE
A31: CURRENT TAX | B31: ='FINANCIAL STATEMENTS'!B31/'FINANCIAL STATEMENTS'!B$9 -> 0.058214727 | C31: ='FINANCIAL STATEMENTS'!C31/'FINANCIAL STATEMENTS'!C$9 -> 0.060333026 | D31: ='FINANCIAL STATEMENTS'!D31/'FINANCIAL STATEMENTS'!D$9 -> 0.044688285 | E31: ='FINANCIAL STATEMENTS'!E31/'FINANCIAL STATEMENTS'!E$9 -> 0.039921412 | F31: ='FINANCIAL STATEMENTS'!F31/'FINANCIAL STATEMENTS'!F$9 -> 0.05415435 | G31: ='FINANCIAL STATEMENTS'!G31/'FINANCIAL STATEMENTS'!G$9 -> 0.056000729
A32: DEFERRED TAX | B32: ='FINANCIAL STATEMENTS'!B32/'FINANCIAL STATEMENTS'!B$9 -> -0.0052616702 | C32: ='FINANCIAL STATEMENTS'!C32/'FINANCIAL STATEMENTS'!C$9 -> 1.9303994e-05 | D32: ='FINANCIAL STATEMENTS'!D32/'FINANCIAL STATEMENTS'!D$9 -> 0.00020234677 | E32: ='FINANCIAL STATEMENTS'!E32/'FINANCIAL STATEMENTS'!E$9 -> -0.001180515 | F32: ='FINANCIAL STATEMENTS'!F32/'FINANCIAL STATEMENTS'!F$9 -> -3.5819923e-05 | G32: ='FINANCIAL STATEMENTS'!G32/'FINANCIAL STATEMENTS'!G$9 -> 0.0013228193
A33: NET TAX EXPENSE | B33: ='FINANCIAL STATEMENTS'!B33/'FINANCIAL STATEMENTS'!B$9 -> 0.052953057 | C33: ='FINANCIAL STATEMENTS'!C33/'FINANCIAL STATEMENTS'!C$9 -> 0.06035233 | D33: ='FINANCIAL STATEMENTS'!D33/'FINANCIAL STATEMENTS'!D$9 -> 0.044890632 | E33: ='FINANCIAL STATEMENTS'!E33/'FINANCIAL STATEMENTS'!E$9 -> 0.038740897 | F33: ='FINANCIAL STATEMENTS'!F33/'FINANCIAL STATEMENTS'!F$9 -> 0.05411853 | G33: ='FINANCIAL STATEMENTS'!G33/'FINANCIAL STATEMENTS'!G$9 -> 0.057323548
A35: TOTAL PROFIT FOR THE YEAR ( PROFIT AFTER TAX) | B35: ='FINANCIAL STATEMENTS'!B36/'FINANCIAL STATEMENTS'!B$9 -> 0.17396042 | C35: ='FINANCIAL STATEMENTS'!C36/'FINANCIAL STATEMENTS'!C$9 -> 0.17397082 | D35: ='FINANCIAL STATEMENTS'!D36/'FINANCIAL STATEMENTS'!D$9 -> 0.1339322 | E35: ='FINANCIAL STATEMENTS'!E36/'FINANCIAL STATEMENTS'!E$9 -> 0.11863468 | F35: ='FINANCIAL STATEMENTS'!F36/'FINANCIAL STATEMENTS'!F$9 -> 0.16114219 | G35: ='FINANCIAL STATEMENTS'!G36/'FINANCIAL STATEMENTS'!G$9 -> 0.17177848
A37: OTHER COMPREHENSIVE INCOME
A38: ITEMS THAT WILL NOT BE RECLASSIFIED TO INCOME STATEMENT
A40: REMEASUREMENT OF DEFINED BENEFIT PLAN | B40: ='FINANCIAL STATEMENTS'!B41/'FINANCIAL STATEMENTS'!B$9 -> -0.0023497495 | C40: ='FINANCIAL STATEMENTS'!C41/'FINANCIAL STATEMENTS'!C$9 -> -0.00015282329 | D40: ='FINANCIAL STATEMENTS'!D41/'FINANCIAL STATEMENTS'!D$9 -> -0.0013613441 | E40: ='FINANCIAL STATEMENTS'!E41/'FINANCIAL STATEMENTS'!E$9 -> 0.00018306947 | F40: ='FINANCIAL STATEMENTS'!F41/'FINANCIAL STATEMENTS'!F$9 -> -0.0023981438 | G40: ='FINANCIAL STATEMENTS'!G41/'FINANCIAL STATEMENTS'!G$9 -> -0.0012623522
A41: INCOME TAX RELATING TO ITEMS THAT WILL NOT RECLASSIFIED TO PROFIT OR LOSS | B41: ='FINANCIAL STATEMENTS'!B42/'FINANCIAL STATEMENTS'!B$9 -> 0.00048637287 | C41: ='FINANCIAL STATEMENTS'!C42/'FINANCIAL STATEMENTS'!C$9 -> 3.8607989e-05 | D41: ='FINANCIAL STATEMENTS'!D42/'FINANCIAL STATEMENTS'!D$9 -> 0.00034286537 | E41: ='FINANCIAL STATEMENTS'!E42/'FINANCIAL STATEMENTS'!E$9 -> -4.6239196e-05 | F41: ='FINANCIAL STATEMENTS'!F42/'FINANCIAL STATEMENTS'!F$9 -> 0.00060356569 | G41: ='FINANCIAL STATEMENTS'!G42/'FINANCIAL STATEMENTS'!G$9 -> 0.00031807301
A42: TOTAL OTHER COMPREHENSIVE LOSS | B42: ='FINANCIAL STATEMENTS'!B43/'FINANCIAL STATEMENTS'!B$9 -> -0.0018633766 | C42: ='FINANCIAL STATEMENTS'!C43/'FINANCIAL STATEMENTS'!C$9 -> -0.0001142153 | D42: ='FINANCIAL STATEMENTS'!D43/'FINANCIAL STATEMENTS'!D$9 -> -0.0010184788 | E42: ='FINANCIAL STATEMENTS'!E43/'FINANCIAL STATEMENTS'!E$9 -> 0.00013683027 | F42: ='FINANCIAL STATEMENTS'!F43/'FINANCIAL STATEMENTS'!F$9 -> -0.0017945781 | G42: ='FINANCIAL STATEMENTS'!G43/'FINANCIAL STATEMENTS'!G$9 -> -0.00094427924
A44: TOTAL COMPREHENSIVE INCOME FOR THE YEAR | B44: ='FINANCIAL STATEMENTS'!B45/'FINANCIAL STATEMENTS'!B$9 -> 0.17209704 | C44: ='FINANCIAL STATEMENTS'!C45/'FINANCIAL STATEMENTS'!C$9 -> 0.1738566 | D44: ='FINANCIAL STATEMENTS'!D45/'FINANCIAL STATEMENTS'!D$9 -> 0.13291373 | E44: ='FINANCIAL STATEMENTS'!E45/'FINANCIAL STATEMENTS'!E$9 -> 0.11877151 | F44: ='FINANCIAL STATEMENTS'!F45/'FINANCIAL STATEMENTS'!F$9 -> 0.15934761 | G44: ='FINANCIAL STATEMENTS'!G45/'FINANCIAL STATEMENTS'!G$9 -> 0.1708342
A46: EARNINGS PER EQUITY SHARE
A47: BASIC | B47: ='FINANCIAL STATEMENTS'!B49/'FINANCIAL STATEMENTS'!B$9 -> 0.0034251388 | C47: ='FINANCIAL STATEMENTS'!C49/'FINANCIAL STATEMENTS'!C$9 -> 0.0034232417 | D47: ='FINANCIAL STATEMENTS'!D49/'FINANCIAL STATEMENTS'!D$9 -> 0.0026361288 | E47: ='FINANCIAL STATEMENTS'!E49/'FINANCIAL STATEMENTS'!E$9 -> 0.0023336639 | F47: ='FINANCIAL STATEMENTS'!F49/'FINANCIAL STATEMENTS'!F$9 -> 0.0031691676 | G47: ='FINANCIAL STATEMENTS'!G49/'FINANCIAL STATEMENTS'!G$9 -> 0.0033770408
A48: DILUTED | B48: ='FINANCIAL STATEMENTS'!B50/'FINANCIAL STATEMENTS'!B$9 -> 0.0034235597 | C48: ='FINANCIAL STATEMENTS'!C50/'FINANCIAL STATEMENTS'!C$9 -> 0.003421633 | D48: ='FINANCIAL STATEMENTS'!D50/'FINANCIAL STATEMENTS'!D$9 -> 0.0026338805 | E48: ='FINANCIAL STATEMENTS'!E50/'FINANCIAL STATEMENTS'!E$9 -> 0.0023327203 | F48: ='FINANCIAL STATEMENTS'!F50/'FINANCIAL STATEMENTS'!F$9 -> 0.0031655857 | G48: ='FINANCIAL STATEMENTS'!G50/'FINANCIAL STATEMENTS'!G$9 -> 0.0033695859
A51: BALANCE SHEET
A53: PARTICULARS(AMOUNT IN CRORES OF INR) | B53: 43921 | C53: 44286 | D53: 44651 | E53: 45016 | F53: 45382 | G53: 45747
A54: ASSETS
A56: NON CURRENT ASSETS
A57: PROPERTY , PLANT AND EQUIPMENT | B57: ='FINANCIAL STATEMENTS'!B60/'FINANCIAL STATEMENTS'!B$87 -> 0.14800329 | C57: ='FINANCIAL STATEMENTS'!C60/'FINANCIAL STATEMENTS'!C$87 -> 0.13424176 | D57: ='FINANCIAL STATEMENTS'!D60/'FINANCIAL STATEMENTS'!D$87 -> 0.15137491 | E57: ='FINANCIAL STATEMENTS'!E60/'FINANCIAL STATEMENTS'!E$87 -> 0.14910647 | F57: ='FINANCIAL STATEMENTS'!F60/'FINANCIAL STATEMENTS'!F$87 -> 0.16683845 | G57: ='FINANCIAL STATEMENTS'!G60/'FINANCIAL STATEMENTS'!G$87 -> 0.15794209
A58: RIGHT OF USE ASSETS | B58: ='FINANCIAL STATEMENTS'!B61/'FINANCIAL STATEMENTS'!B$87 -> 0.018757325 | C58: ='FINANCIAL STATEMENTS'!C61/'FINANCIAL STATEMENTS'!C$87 -> 0.015566525 | D58: ='FINANCIAL STATEMENTS'!D61/'FINANCIAL STATEMENTS'!D$87 -> 0.019563145 | E58: ='FINANCIAL STATEMENTS'!E61/'FINANCIAL STATEMENTS'!E$87 -> 0.028196935 | F58: ='FINANCIAL STATEMENTS'!F61/'FINANCIAL STATEMENTS'!F$87 -> 0.027583908 | G58: ='FINANCIAL STATEMENTS'!G61/'FINANCIAL STATEMENTS'!G$87 -> 0.029946207
A59: CAPITAL WORK IN PROGRESS | B59: ='FINANCIAL STATEMENTS'!B62/'FINANCIAL STATEMENTS'!B$87 -> 0.042556702 | C59: ='FINANCIAL STATEMENTS'!C62/'FINANCIAL STATEMENTS'!C$87 -> 0.036925733 | D59: ='FINANCIAL STATEMENTS'!D62/'FINANCIAL STATEMENTS'!D$87 -> 0.023727537 | E59: ='FINANCIAL STATEMENTS'!E62/'FINANCIAL STATEMENTS'!E$87 -> 0.036259844 | F59: ='FINANCIAL STATEMENTS'!F62/'FINANCIAL STATEMENTS'!F$87 -> 0.011913012 | G59: ='FINANCIAL STATEMENTS'!G62/'FINANCIAL STATEMENTS'!G$87 -> 0.0079736993
A60: GOODWILL | B60: ='FINANCIAL STATEMENTS'!B63/'FINANCIAL STATEMENTS'!B$87 -> 0.014797923 | C60: ='FINANCIAL STATEMENTS'!C63/'FINANCIAL STATEMENTS'!C$87 -> 0.01132564 | D60: ='FINANCIAL STATEMENTS'!D63/'FINANCIAL STATEMENTS'!D$87 -> 0.13559165 | E60: ='FINANCIAL STATEMENTS'!E63/'FINANCIAL STATEMENTS'!E$87 -> 0.12240022 | F60: ='FINANCIAL STATEMENTS'!F63/'FINANCIAL STATEMENTS'!F$87 -> 0.10420148 | G60: ='FINANCIAL STATEMENTS'!G63/'FINANCIAL STATEMENTS'!G$87 -> 0.089280265
A61: OTHER INTANGIBLE ASSETS | B61: ='FINANCIAL STATEMENTS'!B64/'FINANCIAL STATEMENTS'!B$87 -> 0.03316515 | C61: ='FINANCIAL STATEMENTS'!C64/'FINANCIAL STATEMENTS'!C$87 -> 0.025470229 | D61: ='FINANCIAL STATEMENTS'!D64/'FINANCIAL STATEMENTS'!D$87 -> 0.17816595 | E61: ='FINANCIAL STATEMENTS'!E64/'FINANCIAL STATEMENTS'!E$87 -> 0.15870035 | F61: ='FINANCIAL STATEMENTS'!F64/'FINANCIAL STATEMENTS'!F$87 -> 0.13535155 | G61: ='FINANCIAL STATEMENTS'!G64/'FINANCIAL STATEMENTS'!G$87 -> 0.1147732
A62: INVESTMENTS | B62: ='FINANCIAL STATEMENTS'!B65/'FINANCIAL STATEMENTS'!B$87 -> 0.19046719 | C62: ='FINANCIAL STATEMENTS'!C65/'FINANCIAL STATEMENTS'!C$87 -> 0.43448535 | D62: ='FINANCIAL STATEMENTS'!D65/'FINANCIAL STATEMENTS'!D$87 -> 0.10464881 | E62: ='FINANCIAL STATEMENTS'!E65/'FINANCIAL STATEMENTS'!E$87 -> 0.10370832 | F62: ='FINANCIAL STATEMENTS'!F65/'FINANCIAL STATEMENTS'!F$87 -> 0.0926807 | G62: ='FINANCIAL STATEMENTS'!G65/'FINANCIAL STATEMENTS'!G$87 -> 0.085606877
A63: LOANS | B63: ='FINANCIAL STATEMENTS'!B66/'FINANCIAL STATEMENTS'!B$87 -> 0.00069427021 | C63: ='FINANCIAL STATEMENTS'!C66/'FINANCIAL STATEMENTS'!C$87 -> 0.00063226299 | D63: ='FINANCIAL STATEMENTS'!D66/'FINANCIAL STATEMENTS'!D$87 -> 0.00057791098 | E63: ='FINANCIAL STATEMENTS'!E66/'FINANCIAL STATEMENTS'!E$87 -> 0.00064048727 | F63: ='FINANCIAL STATEMENTS'!F66/'FINANCIAL STATEMENTS'!F$87 -> 0.00068157274 | G63: ='FINANCIAL STATEMENTS'!G66/'FINANCIAL STATEMENTS'!G$87 -> 0.0005553408
A64: OTHER FINANCIAL ASSETS | B64: ='FINANCIAL STATEMENTS'!B67/'FINANCIAL STATEMENTS'!B$87 -> 0.0022546597 | C64: ='FINANCIAL STATEMENTS'!C67/'FINANCIAL STATEMENTS'!C$87 -> 0.0019872996 | D64: ='FINANCIAL STATEMENTS'!D67/'FINANCIAL STATEMENTS'!D$87 -> 0.0022258156 | E64: ='FINANCIAL STATEMENTS'!E67/'FINANCIAL STATEMENTS'!E$87 -> 0.0036104887 | F64: ='FINANCIAL STATEMENTS'!F67/'FINANCIAL STATEMENTS'!F$87 -> 0.0034747018 | G64: ='FINANCIAL STATEMENTS'!G67/'FINANCIAL STATEMENTS'!G$87 -> 0.0033938331
A65: INCOME TAX ASSETS (NET) | B65: ='FINANCIAL STATEMENTS'!B68/'FINANCIAL STATEMENTS'!B$87 -> 0.018181631 | C65: ='FINANCIAL STATEMENTS'!C68/'FINANCIAL STATEMENTS'!C$87 -> 0.011409592 | D65: ='FINANCIAL STATEMENTS'!D68/'FINANCIAL STATEMENTS'!D$87 -> 0.014867761 | E65: ='FINANCIAL STATEMENTS'!E68/'FINANCIAL STATEMENTS'!E$87 -> 0.014174396 | F65: ='FINANCIAL STATEMENTS'!F68/'FINANCIAL STATEMENTS'!F$87 -> 0.011395896 | G65: ='FINANCIAL STATEMENTS'!G68/'FINANCIAL STATEMENTS'!G$87 -> 0.011910817
A66: OTHER NON CURRENT ASSETS | B66: ='FINANCIAL STATEMENTS'!B69/'FINANCIAL STATEMENTS'!B$87 -> 0.011096294 | C66: ='FINANCIAL STATEMENTS'!C69/'FINANCIAL STATEMENTS'!C$87 -> 0.010411351 | D66: ='FINANCIAL STATEMENTS'!D69/'FINANCIAL STATEMENTS'!D$87 -> 0.0048292759 | E66: ='FINANCIAL STATEMENTS'!E69/'FINANCIAL STATEMENTS'!E$87 -> 0.004933818 | F66: ='FINANCIAL STATEMENTS'!F69/'FINANCIAL STATEMENTS'!F$87 -> 0.0046012756 | G66: ='FINANCIAL STATEMENTS'!G69/'FINANCIAL STATEMENTS'!G$87 -> 0.0034322624
A67: TOTAL NON CURRENT ASSETS | B67: ='FINANCIAL STATEMENTS'!B71/'FINANCIAL STATEMENTS'!B$87 -> 0.47997443 | C67: ='FINANCIAL STATEMENTS'!C71/'FINANCIAL STATEMENTS'!C$87 -> 0.68245575 | D67: ='FINANCIAL STATEMENTS'!D71/'FINANCIAL STATEMENTS'!D$87 -> 0.63557277 | E67: ='FINANCIAL STATEMENTS'!E71/'FINANCIAL STATEMENTS'!E$87 -> 0.62173132 | F67: ='FINANCIAL STATEMENTS'!F71/'FINANCIAL STATEMENTS'!F$87 -> 0.55872255 | G67: ='FINANCIAL STATEMENTS'!G71/'FINANCIAL STATEMENTS'!G$87 -> 0.50481459
A69: CURRENT ASSETS
A70: INVENTORIES | B70: ='FINANCIAL STATEMENTS'!B75/'FINANCIAL STATEMENTS'!B$87 -> 0.12553402 | C70: ='FINANCIAL STATEMENTS'!C75/'FINANCIAL STATEMENTS'!C$87 -> 0.12801883 | D70: ='FINANCIAL STATEMENTS'!D75/'FINANCIAL STATEMENTS'!D$87 -> 0.16501018 | E70: ='FINANCIAL STATEMENTS'!E75/'FINANCIAL STATEMENTS'!E$87 -> 0.16128296 | F70: ='FINANCIAL STATEMENTS'!F75/'FINANCIAL STATEMENTS'!F$87 -> 0.11056605 | G70: ='FINANCIAL STATEMENTS'!G75/'FINANCIAL STATEMENTS'!G$87 -> 0.11230167
A71: INVESTMENTS | B71: ='FINANCIAL STATEMENTS'!B76/'FINANCIAL STATEMENTS'!B$87 -> 0.12290301 | C71: ='FINANCIAL STATEMENTS'!C76/'FINANCIAL STATEMENTS'!C$87 -> 0.022214468 | D71: ='FINANCIAL STATEMENTS'!D76/'FINANCIAL STATEMENTS'!D$87 -> 0.019489905 | E71: ='FINANCIAL STATEMENTS'!E76/'FINANCIAL STATEMENTS'!E$87 -> 0.04573389 | F71: ='FINANCIAL STATEMENTS'!F76/'FINANCIAL STATEMENTS'!F$87 -> 0.15472932 | G71: ='FINANCIAL STATEMENTS'!G76/'FINANCIAL STATEMENTS'!G$87 -> 0.22883658
A72: TRADE RECEIVABLES | B72: ='FINANCIAL STATEMENTS'!B77/'FINANCIAL STATEMENTS'!B$87 -> 0.13861861 | C72: ='FINANCIAL STATEMENTS'!C77/'FINANCIAL STATEMENTS'!C$87 -> 0.13105553 | D72: ='FINANCIAL STATEMENTS'!D77/'FINANCIAL STATEMENTS'!D$87 -> 0.13869063 | E72: ='FINANCIAL STATEMENTS'!E77/'FINANCIAL STATEMENTS'!E$87 -> 0.13482464 | F72: ='FINANCIAL STATEMENTS'!F77/'FINANCIAL STATEMENTS'!F$87 -> 0.12360915 | G72: ='FINANCIAL STATEMENTS'!G77/'FINANCIAL STATEMENTS'!G$87 -> 0.1172402
A73: CASH AND CASH EQUIVALENTS | B73: ='FINANCIAL STATEMENTS'!B78/'FINANCIAL STATEMENTS'!B$87 -> 0.096952085 | C73: ='FINANCIAL STATEMENTS'!C78/'FINANCIAL STATEMENTS'!C$87 -> 0.014404315 | D73: ='FINANCIAL STATEMENTS'!D78/'FINANCIAL STATEMENTS'!D$87 -> 0.016902466 | E73: ='FINANCIAL STATEMENTS'!E78/'FINANCIAL STATEMENTS'!E$87 -> 0.015836564 | F73: ='FINANCIAL STATEMENTS'!F78/'FINANCIAL STATEMENTS'!F$87 -> 0.033407617 | G73: ='FINANCIAL STATEMENTS'!G78/'FINANCIAL STATEMENTS'!G$87 -> 0.015979046
A74: BANK BALANCES OTHER THAN CASH AND CASH EQUIVALENTS | B74: ='FINANCIAL STATEMENTS'!B79/'FINANCIAL STATEMENTS'!B$87 -> 0.00080253512 | C74: ='FINANCIAL STATEMENTS'!C79/'FINANCIAL STATEMENTS'!C$87 -> 0.00033580773 | D74: ='FINANCIAL STATEMENTS'!D79/'FINANCIAL STATEMENTS'!D$87 -> 0.00032843654 | E74: ='FINANCIAL STATEMENTS'!E79/'FINANCIAL STATEMENTS'!E$87 -> 0.00028408709 | F74: ='FINANCIAL STATEMENTS'!F79/'FINANCIAL STATEMENTS'!F$87 -> 0.0002022732 | G74: ='FINANCIAL STATEMENTS'!G79/'FINANCIAL STATEMENTS'!G$87 -> 0.00019440696
A75: LOANS | B75: ='FINANCIAL STATEMENTS'!B80/'FINANCIAL STATEMENTS'!B$87 -> 0.0043615292 | C75: ='FINANCIAL STATEMENTS'!C80/'FINANCIAL STATEMENTS'!C$87 -> 0.002131592 | D75: ='FINANCIAL STATEMENTS'!D80/'FINANCIAL STATEMENTS'!D$87 -> 0.0020381375 | E75: ='FINANCIAL STATEMENTS'!E80/'FINANCIAL STATEMENTS'!E$87 -> 0.0024751734 | F75: ='FINANCIAL STATEMENTS'!F80/'FINANCIAL STATEMENTS'!F$87 -> 0.0026040476 | G75: ='FINANCIAL STATEMENTS'!G80/'FINANCIAL STATEMENTS'!G$87 -> 0.0017142474
A76: OTHER FINANCIAL ASSETS | B76: ='FINANCIAL STATEMENTS'!B81/'FINANCIAL STATEMENTS'!B$87 -> 0.0014143178 | C76: ='FINANCIAL STATEMENTS'!C81/'FINANCIAL STATEMENTS'!C$87 -> 0.00096282372 | D76: ='FINANCIAL STATEMENTS'!D81/'FINANCIAL STATEMENTS'!D$87 -> 0.0013045911 | E76: ='FINANCIAL STATEMENTS'!E81/'FINANCIAL STATEMENTS'!E$87 -> 0.00079544386 | F76: ='FINANCIAL STATEMENTS'!F81/'FINANCIAL STATEMENTS'!F$87 -> 0.00051183914 | G76: ='FINANCIAL STATEMENTS'!G81/'FINANCIAL STATEMENTS'!G$87 -> 0.00056664353
A77: OTHER CURRENT ASSETS | B77: ='FINANCIAL STATEMENTS'!B82/'FINANCIAL STATEMENTS'!B$87 -> 0.029439463 | C77: ='FINANCIAL STATEMENTS'!C82/'FINANCIAL STATEMENTS'!C$87 -> 0.01842089 | D77: ='FINANCIAL STATEMENTS'!D82/'FINANCIAL STATEMENTS'!D$87 -> 0.020662893 | E77: ='FINANCIAL STATEMENTS'!E82/'FINANCIAL STATEMENTS'!E$87 -> 0.017035928 | F77: ='FINANCIAL STATEMENTS'!F82/'FINANCIAL STATEMENTS'!F$87 -> 0.015347259 | G77: ='FINANCIAL STATEMENTS'!G82/'FINANCIAL STATEMENTS'!G$87 -> 0.01835262
A78: ASSETS HELD FOR SALE
A79: TOTAL CURRENT ASSETS | B79: ='FINANCIAL STATEMENTS'!B85/'FINANCIAL STATEMENTS'!B$87 -> 0.52002557 | C79: ='FINANCIAL STATEMENTS'!C85/'FINANCIAL STATEMENTS'!C$87 -> 0.31754425 | D79: ='FINANCIAL STATEMENTS'!D85/'FINANCIAL STATEMENTS'!D$87 -> 0.36442723 | E79: ='FINANCIAL STATEMENTS'!E85/'FINANCIAL STATEMENTS'!E$87 -> 0.37826868 | F79: ='FINANCIAL STATEMENTS'!F85/'FINANCIAL STATEMENTS'!F$87 -> 0.44127745 | G79: ='FINANCIAL STATEMENTS'!G85/'FINANCIAL STATEMENTS'!G$87 -> 0.49518541
A80: TOTAL ASSETS | B80: ='FINANCIAL STATEMENTS'!B87/'FINANCIAL STATEMENTS'!B$87 -> 1 | C80: ='FINANCIAL STATEMENTS'!C87/'FINANCIAL STATEMENTS'!C$87 -> 1 | D80: ='FINANCIAL STATEMENTS'!D87/'FINANCIAL STATEMENTS'!D$87 -> 1 | E80: ='FINANCIAL STATEMENTS'!E87/'FINANCIAL STATEMENTS'!E$87 -> 1 | F80: ='FINANCIAL STATEMENTS'!F87/'FINANCIAL STATEMENTS'!F$87 -> 1 | G80: ='FINANCIAL STATEMENTS'!G87/'FINANCIAL STATEMENTS'!G$87 -> 1
A82: EQUITIES AND LIABILITES
A84: EQUITY
A85: EQUITY SHARE CAPITAL | B85: ='FINANCIAL STATEMENTS'!B93/'FINANCIAL STATEMENTS'!B$121 -> 0.0087316508 | C85: ='FINANCIAL STATEMENTS'!C93/'FINANCIAL STATEMENTS'!C$121 -> 0.0066663081 | D85: ='FINANCIAL STATEMENTS'!D93/'FINANCIAL STATEMENTS'!D$121 -> 0.0058168743 | E85: ='FINANCIAL STATEMENTS'!E93/'FINANCIAL STATEMENTS'!E$121 -> 0.0052509625 | F85: ='FINANCIAL STATEMENTS'!F93/'FINANCIAL STATEMENTS'!F$121 -> 0.004472876 | G85: ='FINANCIAL STATEMENTS'!G93/'FINANCIAL STATEMENTS'!G$121 -> 0.003832379
A86: EQUITY | B86: ='FINANCIAL STATEMENTS'!B94/'FINANCIAL STATEMENTS'!B$121 -> 0.75854348 | C86: ='FINANCIAL STATEMENTS'!C94/'FINANCIAL STATEMENTS'!C$121 -> 0.72282614 | D86: ='FINANCIAL STATEMENTS'!D94/'FINANCIAL STATEMENTS'!D$121 -> 0.72014231 | E86: ='FINANCIAL STATEMENTS'!E94/'FINANCIAL STATEMENTS'!E$121 -> 0.72905323 | F86: ='FINANCIAL STATEMENTS'!F94/'FINANCIAL STATEMENTS'!F$121 -> 0.7287578 | G86: ='FINANCIAL STATEMENTS'!G94/'FINANCIAL STATEMENTS'!G$121 -> 0.7252992
A87: TOTAL EQUITY | B87: ='FINANCIAL STATEMENTS'!B95/'FINANCIAL STATEMENTS'!B$121 -> 0.76727513 | C87: ='FINANCIAL STATEMENTS'!C95/'FINANCIAL STATEMENTS'!C$121 -> 0.72949244 | D87: ='FINANCIAL STATEMENTS'!D95/'FINANCIAL STATEMENTS'!D$121 -> 0.72595919 | E87: ='FINANCIAL STATEMENTS'!E95/'FINANCIAL STATEMENTS'!E$121 -> 0.73430419 | F87: ='FINANCIAL STATEMENTS'!F95/'FINANCIAL STATEMENTS'!F$121 -> 0.73323067 | G87: ='FINANCIAL STATEMENTS'!G95/'FINANCIAL STATEMENTS'!G$121 -> 0.72913158
A89: LIABILITIES
A90: NON CURRENT LIABILITIES
A91: LEASE LIABILITIES | B91: ='FINANCIAL STATEMENTS'!B101/'FINANCIAL STATEMENTS'!B$121 -> 0.0088158569 | C91: ='FINANCIAL STATEMENTS'!C101/'FINANCIAL STATEMENTS'!C$121 -> 0.0064000231 | D91: ='FINANCIAL STATEMENTS'!D101/'FINANCIAL STATEMENTS'!D$121 -> 0.0076604676 | E91: ='FINANCIAL STATEMENTS'!E101/'FINANCIAL STATEMENTS'!E$121 -> 0.014788025 | F91: ='FINANCIAL STATEMENTS'!F101/'FINANCIAL STATEMENTS'!F$121 -> 0.014276091 | G91: ='FINANCIAL STATEMENTS'!G101/'FINANCIAL STATEMENTS'!G$121 -> 0.016034053
A92: OTHER FINANCIAL LIABILITIES | B92: ='FINANCIAL STATEMENTS'!B102/'FINANCIAL STATEMENTS'!B$121 -> 0.0012476242 | C92: ='FINANCIAL STATEMENTS'!C102/'FINANCIAL STATEMENTS'!C$121 -> 0.0017879138 | D92: ='FINANCIAL STATEMENTS'!D102/'FINANCIAL STATEMENTS'!D$121 -> 0.0022818901 | E92: ='FINANCIAL STATEMENTS'!E102/'FINANCIAL STATEMENTS'!E$121 -> 0.0014927485 | F92: ='FINANCIAL STATEMENTS'!F102/'FINANCIAL STATEMENTS'!F$121 -> 0.00038783687 | G92: ='FINANCIAL STATEMENTS'!G102/'FINANCIAL STATEMENTS'!G$121 -> 0.00029161044
A93: PROVISIONS | B93: ='FINANCIAL STATEMENTS'!B103/'FINANCIAL STATEMENTS'!B$121 -> 0.0070269081 | C93: ='FINANCIAL STATEMENTS'!C103/'FINANCIAL STATEMENTS'!C$121 -> 0.0059054937 | D93: ='FINANCIAL STATEMENTS'!D103/'FINANCIAL STATEMENTS'!D$121 -> 0.0064336942 | E93: ='FINANCIAL STATEMENTS'!E103/'FINANCIAL STATEMENTS'!E$121 -> 0.0066755302 | F93: ='FINANCIAL STATEMENTS'!F103/'FINANCIAL STATEMENTS'!F$121 -> 0.0069951349 | G93: ='FINANCIAL STATEMENTS'!G103/'FINANCIAL STATEMENTS'!G$121 -> 0.0084860897
A94: DEFERRED TAX LIABILITIES(NET) | B94: ='FINANCIAL STATEMENTS'!B104/'FINANCIAL STATEMENTS'!B$121 -> 0.013055373 | C94: ='FINANCIAL STATEMENTS'!C104/'FINANCIAL STATEMENTS'!C$121 -> 0.0099509275 | D94: ='FINANCIAL STATEMENTS'!D104/'FINANCIAL STATEMENTS'!D$121 -> 0.044462526 | E94: ='FINANCIAL STATEMENTS'!E104/'FINANCIAL STATEMENTS'!E$121 -> 0.038895139 | F94: ='FINANCIAL STATEMENTS'!F104/'FINANCIAL STATEMENTS'!F$121 -> 0.033076945 | G94: ='FINANCIAL STATEMENTS'!G104/'FINANCIAL STATEMENTS'!G$121 -> 0.029543829
A95: TOTAL NON CURRENT LIABILITIES | B95: ='FINANCIAL STATEMENTS'!B105/'FINANCIAL STATEMENTS'!B$121 -> 0.030145762 | C95: ='FINANCIAL STATEMENTS'!C105/'FINANCIAL STATEMENTS'!C$121 -> 0.024044358 | D95: ='FINANCIAL STATEMENTS'!D105/'FINANCIAL STATEMENTS'!D$121 -> 0.060838577 | E95: ='FINANCIAL STATEMENTS'!E105/'FINANCIAL STATEMENTS'!E$121 -> 0.061851442 | F95: ='FINANCIAL STATEMENTS'!F105/'FINANCIAL STATEMENTS'!F$121 -> 0.054736007 | G95: ='FINANCIAL STATEMENTS'!G105/'FINANCIAL STATEMENTS'!G$121 -> 0.054355582
A97: CURRENT LIABILITIES
A98: BORROWINGS
A99: TOTAL OUTSTANDING DUES OF MICRO ENTERPRISES AND SMALL ENTERPRISES | B99: ='FINANCIAL STATEMENTS'!B110/'FINANCIAL STATEMENTS'!B$121 -> 0.0015981963 | C99: ='FINANCIAL STATEMENTS'!C110/'FINANCIAL STATEMENTS'!C$121 -> 0.0087939649 | D99: ='FINANCIAL STATEMENTS'!D110/'FINANCIAL STATEMENTS'!D$121 -> 0.0077989373 | E99: ='FINANCIAL STATEMENTS'!E110/'FINANCIAL STATEMENTS'!E$121 -> 0.0054565383 | F99: ='FINANCIAL STATEMENTS'!F110/'FINANCIAL STATEMENTS'!F$121 -> 0.0060637987 | G99: ='FINANCIAL STATEMENTS'!G110/'FINANCIAL STATEMENTS'!G$121 -> 0.0025453748
A100: TOTAL OUTSTANDING DUES OF CREDITORS OTHER THAN MICRO ENTERPRISES AND SMALL ENTERPRISES | B100: ='FINANCIAL STATEMENTS'!B111/'FINANCIAL STATEMENTS'!B$121 -> 0.083434438 | C100: ='FINANCIAL STATEMENTS'!C111/'FINANCIAL STATEMENTS'!C$121 -> 0.09533529 | D100: ='FINANCIAL STATEMENTS'!D111/'FINANCIAL STATEMENTS'!D$121 -> 0.10044093 | E100: ='FINANCIAL STATEMENTS'!E111/'FINANCIAL STATEMENTS'!E$121 -> 0.091542159 | F100: ='FINANCIAL STATEMENTS'!F111/'FINANCIAL STATEMENTS'!F$121 -> 0.085549251 | G100: ='FINANCIAL STATEMENTS'!G111/'FINANCIAL STATEMENTS'!G$121 -> 0.093072707
A101: LEASE LIABILTIES | B101: ='FINANCIAL STATEMENTS'!B112/'FINANCIAL STATEMENTS'!B$121 -> 0.0037875533 | C101: ='FINANCIAL STATEMENTS'!C112/'FINANCIAL STATEMENTS'!C$121 -> 0.0024319825 | D101: ='FINANCIAL STATEMENTS'!D112/'FINANCIAL STATEMENTS'!D$121 -> 0.0030303134 | E101: ='FINANCIAL STATEMENTS'!E112/'FINANCIAL STATEMENTS'!E$121 -> 0.0044906422 | F101: ='FINANCIAL STATEMENTS'!F112/'FINANCIAL STATEMENTS'!F$121 -> 0.0043409587 | G101: ='FINANCIAL STATEMENTS'!G112/'FINANCIAL STATEMENTS'!G$121 -> 0.0044819092
A102: OTHER FINANCIAL LIABILITIES | B102: ='FINANCIAL STATEMENTS'!B113/'FINANCIAL STATEMENTS'!B$121 -> 0.094932859 | C102: ='FINANCIAL STATEMENTS'!C113/'FINANCIAL STATEMENTS'!C$121 -> 0.11811512 | D102: ='FINANCIAL STATEMENTS'!D113/'FINANCIAL STATEMENTS'!D$121 -> 0.075485474 | E102: ='FINANCIAL STATEMENTS'!E113/'FINANCIAL STATEMENTS'!E$121 -> 0.086195123 | F102: ='FINANCIAL STATEMENTS'!F113/'FINANCIAL STATEMENTS'!F$121 -> 0.088634357 | G102: ='FINANCIAL STATEMENTS'!G113/'FINANCIAL STATEMENTS'!G$121 -> 0.089786627
A103: OTHER CURRENT LIABILITIES | B103: ='FINANCIAL STATEMENTS'!B114/'FINANCIAL STATEMENTS'!B$121 -> 0.015471571 | C103: ='FINANCIAL STATEMENTS'!C114/'FINANCIAL STATEMENTS'!C$121 -> 0.0095311678 | D103: ='FINANCIAL STATEMENTS'!D114/'FINANCIAL STATEMENTS'!D$121 -> 0.0093953449 | E103: ='FINANCIAL STATEMENTS'!E114/'FINANCIAL STATEMENTS'!E$121 -> 0.0090845887 | F103: ='FINANCIAL STATEMENTS'!F114/'FINANCIAL STATEMENTS'!F$121 -> 0.0086748819 | G103: ='FINANCIAL STATEMENTS'!G114/'FINANCIAL STATEMENTS'!G$121 -> 0.0066776529
A104: PROVISIONS | B104: ='FINANCIAL STATEMENTS'!B115/'FINANCIAL STATEMENTS'!B$121 -> 0.0020243819 | C104: ='FINANCIAL STATEMENTS'!C115/'FINANCIAL STATEMENTS'!C$121 -> 0.0021617623 | D104: ='FINANCIAL STATEMENTS'!D115/'FINANCIAL STATEMENTS'!D$121 -> 0.0039984574 | E104: ='FINANCIAL STATEMENTS'!E115/'FINANCIAL STATEMENTS'!E$121 -> 0.003123925 | F104: ='FINANCIAL STATEMENTS'!F115/'FINANCIAL STATEMENTS'!F$121 -> 0.016737667 | G104: ='FINANCIAL STATEMENTS'!G115/'FINANCIAL STATEMENTS'!G$121 -> 0.018406873
A105: CURRENT TAX LIABILITIES(NET) | B105: ='FINANCIAL STATEMENTS'!B116/'FINANCIAL STATEMENTS'!B$121 -> 0.0013301117 | C105: ='FINANCIAL STATEMENTS'!C116/'FINANCIAL STATEMENTS'!C$121 -> 0.0028792889 | D105: ='FINANCIAL STATEMENTS'!D116/'FINANCIAL STATEMENTS'!D$121 -> 0.0010368066 | E105: ='FINANCIAL STATEMENTS'!E116/'FINANCIAL STATEMENTS'!E$121 -> 0.0039513932 | F105: ='FINANCIAL STATEMENTS'!F116/'FINANCIAL STATEMENTS'!F$121 -> 0.0020324059 | G105: ='FINANCIAL STATEMENTS'!G116/'FINANCIAL STATEMENTS'!G$121 -> 0.0015416924
A106: TOTAL CURRENT LIABILTIES | B106: ='FINANCIAL STATEMENTS'!B117/'FINANCIAL STATEMENTS'!B$121 -> 0.20257911 | C106: ='FINANCIAL STATEMENTS'!C117/'FINANCIAL STATEMENTS'!C$121 -> 0.2464632 | D106: ='FINANCIAL STATEMENTS'!D117/'FINANCIAL STATEMENTS'!D$121 -> 0.21320223 | E106: ='FINANCIAL STATEMENTS'!E117/'FINANCIAL STATEMENTS'!E$121 -> 0.20384437 | F106: ='FINANCIAL STATEMENTS'!F117/'FINANCIAL STATEMENTS'!F$121 -> 0.21203332 | G106: ='FINANCIAL STATEMENTS'!G117/'FINANCIAL STATEMENTS'!G$121 -> 0.21651284
A107: TOTAL LIABILITIES | B107: ='FINANCIAL STATEMENTS'!B119/'FINANCIAL STATEMENTS'!B$121 -> 0.23272487 | C107: ='FINANCIAL STATEMENTS'!C119/'FINANCIAL STATEMENTS'!C$121 -> 0.27050756 | D107: ='FINANCIAL STATEMENTS'!D119/'FINANCIAL STATEMENTS'!D$121 -> 0.27404081 | E107: ='FINANCIAL STATEMENTS'!E119/'FINANCIAL STATEMENTS'!E$121 -> 0.26569581 | F107: ='FINANCIAL STATEMENTS'!F119/'FINANCIAL STATEMENTS'!F$121 -> 0.26676933 | G107: ='FINANCIAL STATEMENTS'!G119/'FINANCIAL STATEMENTS'!G$121 -> 0.27086842
A108: TOTAL EQUITY AND LIABILITIES | B108: ='FINANCIAL STATEMENTS'!B121/'FINANCIAL STATEMENTS'!B$121 -> 1 | C108: ='FINANCIAL STATEMENTS'!C121/'FINANCIAL STATEMENTS'!C$121 -> 1 | D108: ='FINANCIAL STATEMENTS'!D121/'FINANCIAL STATEMENTS'!D$121 -> 1 | E108: ='FINANCIAL STATEMENTS'!E121/'FINANCIAL STATEMENTS'!E$121 -> 1 | F108: ='FINANCIAL STATEMENTS'!F121/'FINANCIAL STATEMENTS'!F$121 -> 1 | G108: ='FINANCIAL STATEMENTS'!G121/'FINANCIAL STATEMENTS'!G$121 -> 1

Sheet COMPARATIVE FINANCIAL STATEMENT
A2: COMPARATIVE FINANCIAL STATEMENT (YEAR ON YEAR)
A4: INCOME STATEMENT
A6: PARTICULARS(AMOUNT IN CRORES OF INR) | B6: 44286 | C6: 44651 | D6: 45016 | E6: 45382 | F6: 45747
A7: INCOME
A9: REVENUE FROM OPERATIONS | B9: =('FINANCIAL STATEMENTS'!C9-'FINANCIAL STATEMENTS'!B9)/'FINANCIAL STATEMENTS'!B9 -> -0.018358997 | C9: =('FINANCIAL STATEMENTS'!D9-'FINANCIAL STATEMENTS'!C9)/'FINANCIAL STATEMENTS'!C9 -> 0.43100833 | D9: =('FINANCIAL STATEMENTS'!E9-'FINANCIAL STATEMENTS'!D9)/'FINANCIAL STATEMENTS'!D9 -> 0.19126829 | E9: =('FINANCIAL STATEMENTS'!F9-'FINANCIAL STATEMENTS'!E9)/'FINANCIAL STATEMENTS'!E9 -> 0.053779016 | F9: =('FINANCIAL STATEMENTS'!G9-'FINANCIAL STATEMENTS'!F9)/'FINANCIAL STATEMENTS'!F9 -> 0.081107946
A10: OTHER INCOME | B10: =('FINANCIAL STATEMENTS'!C10-'FINANCIAL STATEMENTS'!B10)/'FINANCIAL STATEMENTS'!B10 -> -0.51606743 | C10: =('FINANCIAL STATEMENTS'!D10-'FINANCIAL STATEMENTS'!C10)/'FINANCIAL STATEMENTS'!C10 -> -0.45625255 | D10: =('FINANCIAL STATEMENTS'!E10-'FINANCIAL STATEMENTS'!D10)/'FINANCIAL STATEMENTS'!D10 -> 0.57757758 | E10: =('FINANCIAL STATEMENTS'!F10-'FINANCIAL STATEMENTS'!E10)/'FINANCIAL STATEMENTS'!E10 -> 1.6261104 | F10: =('FINANCIAL STATEMENTS'!G10-'FINANCIAL STATEMENTS'!F10)/'FINANCIAL STATEMENTS'!F10 -> 0.77795228
A11: TOTAL INCOME | B11: =('FINANCIAL STATEMENTS'!C11-'FINANCIAL STATEMENTS'!B11)/'FINANCIAL STATEMENTS'!B11 -> -0.030014882 | C11: =('FINANCIAL STATEMENTS'!D11-'FINANCIAL STATEMENTS'!C11)/'FINANCIAL STATEMENTS'!C11 -> 0.42064161 | D11: =('FINANCIAL STATEMENTS'!E11-'FINANCIAL STATEMENTS'!D11)/'FINANCIAL STATEMENTS'!D11 -> 0.19299587 | E11: =('FINANCIAL STATEMENTS'!F11-'FINANCIAL STATEMENTS'!E11)/'FINANCIAL STATEMENTS'!E11 -> 0.06307721 | F11: =('FINANCIAL STATEMENTS'!G11-'FINANCIAL STATEMENTS'!F11)/'FINANCIAL STATEMENTS'!F11 -> 0.091287728
A13: EXPENSES
A15: COST OF MATERIALS CONSUMED | B15: =('FINANCIAL STATEMENTS'!C15-'FINANCIAL STATEMENTS'!B15)/'FINANCIAL STATEMENTS'!B15 -> -0.020299917 | C15: =('FINANCIAL STATEMENTS'!D15-'FINANCIAL STATEMENTS'!C15)/'FINANCIAL STATEMENTS'!C15 -> 0.83159144 | D15: =('FINANCIAL STATEMENTS'!E15-'FINANCIAL STATEMENTS'!D15)/'FINANCIAL STATEMENTS'!D15 -> 0.18190782 | E15: =('FINANCIAL STATEMENTS'!F15-'FINANCIAL STATEMENTS'!E15)/'FINANCIAL STATEMENTS'!E15 -> -0.15446589 | F15: =('FINANCIAL STATEMENTS'!G15-'FINANCIAL STATEMENTS'!F15)/'FINANCIAL STATEMENTS'!F15 -> 0.072983496
A16: PURCHASES OF STOCK IN TRADE | B16: =('FINANCIAL STATEMENTS'!C16-'FINANCIAL STATEMENTS'!B16)/'FINANCIAL STATEMENTS'!B16 -> 0.17095252 | C16: =('FINANCIAL STATEMENTS'!D16-'FINANCIAL STATEMENTS'!C16)/'FINANCIAL STATEMENTS'!C16 -> 0.33888412 | D16: =('FINANCIAL STATEMENTS'!E16-'FINANCIAL STATEMENTS'!D16)/'FINANCIAL STATEMENTS'!D16 -> 0.41313504 | E16: =('FINANCIAL STATEMENTS'!F16-'FINANCIAL STATEMENTS'!E16)/'FINANCIAL STATEMENTS'!E16 -> -0.024785787 | F16: =('FINANCIAL STATEMENTS'!G16-'FINANCIAL STATEMENTS'!F16)/'FINANCIAL STATEMENTS'!F16 -> -0.01432545
A17: CHANGES IN INVENTORIES OF FINISHED GOODS, WORK IN PROGRESS, AND STOCK IN TRADE | B17: =('FINANCIAL STATEMENTS'!C17-'FINANCIAL STATEMENTS'!B17)/'FINANCIAL STATEMENTS'!B17 -> -4.2083631 | C17: =('FINANCIAL STATEMENTS'!D17-'FINANCIAL STATEMENTS'!C17)/'FINANCIAL STATEMENTS'!C17 -> 1.5121978 | D17: =('FINANCIAL STATEMENTS'!E17-'FINANCIAL STATEMENTS'!D17)/'FINANCIAL STATEMENTS'!D17 -> -0.72942533 | E17: =('FINANCIAL STATEMENTS'!F17-'FINANCIAL STATEMENTS'!E17)/'FINANCIAL STATEMENTS'!E17 -> -1.9447722 | F17: =('FINANCIAL STATEMENTS'!G17-'FINANCIAL STATEMENTS'!F17)/'FINANCIAL STATEMENTS'!F17 -> -3.1628794
A18: EMPLOYEE BENEFITS EXPENSE | B18: =('FINANCIAL STATEMENTS'!C18-'FINANCIAL STATEMENTS'!B18)/'FINANCIAL STATEMENTS'!B18 -> 0.069019799 | C18: =('FINANCIAL STATEMENTS'!D18-'FINANCIAL STATEMENTS'!C18)/'FINANCIAL STATEMENTS'!C18 -> 0.17646461 | D18: =('FINANCIAL STATEMENTS'!E18-'FINANCIAL STATEMENTS'!D18)/'FINANCIAL STATEMENTS'!D18 -> 0.12740084 | E18: =('FINANCIAL STATEMENTS'!F18-'FINANCIAL STATEMENTS'!E18)/'FINANCIAL STATEMENTS'!E18 -> 0.20050152 | F18: =('FINANCIAL STATEMENTS'!G18-'FINANCIAL STATEMENTS'!F18)/'FINANCIAL STATEMENTS'!F18 -> 0.2321178
A19: OTHER EXPENSE | B19: =('FINANCIAL STATEMENTS'!C19-'FINANCIAL STATEMENTS'!B19)/'FINANCIAL STATEMENTS'!B19 -> -0.10937699 | C19: =('FINANCIAL STATEMENTS'!D19-'FINANCIAL STATEMENTS'!C19)/'FINANCIAL STATEMENTS'!C19 -> 0.23284152 | D19: =('FINANCIAL STATEMENTS'!E19-'FINANCIAL STATEMENTS'!D19)/'FINANCIAL STATEMENTS'!D19 -> 0.2030876 | E19: =('FINANCIAL STATEMENTS'!F19-'FINANCIAL STATEMENTS'!E19)/'FINANCIAL STATEMENTS'!E19 -> 0.25387117 | F19: =('FINANCIAL STATEMENTS'!G19-'FINANCIAL STATEMENTS'!F19)/'FINANCIAL STATEMENTS'!F19 -> 0.099550694
A20: TOTAL EXPENSE BEFORE DEPRECIATION AND AMMORTISATION | B20: =('FINANCIAL STATEMENTS'!C20-'FINANCIAL STATEMENTS'!B20)/'FINANCIAL STATEMENTS'!B20 -> -0.037199192 | C20: =('FINANCIAL STATEMENTS'!D20-'FINANCIAL STATEMENTS'!C20)/'FINANCIAL STATEMENTS'!C20 -> 0.52575584 | D20: =('FINANCIAL STATEMENTS'!E20-'FINANCIAL STATEMENTS'!D20)/'FINANCIAL STATEMENTS'!D20 -> 0.22723852 | E20: =('FINANCIAL STATEMENTS'!F20-'FINANCIAL STATEMENTS'!E20)/'FINANCIAL STATEMENTS'!E20 -> -0.014253211 | F20: =('FINANCIAL STATEMENTS'!G20-'FINANCIAL STATEMENTS'!F20)/'FINANCIAL STATEMENTS'!F20 -> 0.07201568
A22: EBITDA | B22: =('FINANCIAL STATEMENTS'!C22-'FINANCIAL STATEMENTS'!B22)/'FINANCIAL STATEMENTS'!B22 -> -0.008713358 | C22: =('FINANCIAL STATEMENTS'!D22-'FINANCIAL STATEMENTS'!C22)/'FINANCIAL STATEMENTS'!C22 -> 0.11793334 | D22: =('FINANCIAL STATEMENTS'!E22-'FINANCIAL STATEMENTS'!D22)/'FINANCIAL STATEMENTS'!D22 -> 0.058410029 | E22: =('FINANCIAL STATEMENTS'!F22-'FINANCIAL STATEMENTS'!E22)/'FINANCIAL STATEMENTS'!E22 -> 0.41549457 | F22: =('FINANCIAL STATEMENTS'!G22-'FINANCIAL STATEMENTS'!F22)/'FINANCIAL STATEMENTS'!F22 -> 0.15245117
A23: DEPRECIATION, AMORTISATION AND IMPAIRMENT EXPENSE | B23: =('FINANCIAL STATEMENTS'!C23-'FINANCIAL STATEMENTS'!B23)/'FINANCIAL STATEMENTS'!B23 -> 0.16940933 | C23: =('FINANCIAL STATEMENTS'!D23-'FINANCIAL STATEMENTS'!C23)/'FINANCIAL STATEMENTS'!C23 -> 0.321414 | D23: =('FINANCIAL STATEMENTS'!E23-'FINANCIAL STATEMENTS'!D23)/'FINANCIAL STATEMENTS'!D23 -> 0.14193847 | E23: =('FINANCIAL STATEMENTS'!F23-'FINANCIAL STATEMENTS'!E23)/'FINANCIAL STATEMENTS'!E23 -> 0.30247331 | F23: =('FINANCIAL STATEMENTS'!G23-'FINANCIAL STATEMENTS'!F23)/'FINANCIAL STATEMENTS'!F23 -> 0.066756598
A24: EBIT | B24: =('FINANCIAL STATEMENTS'!C24-'FINANCIAL STATEMENTS'!B24)/'FINANCIAL STATEMENTS'!B24 -> -0.023555441 | C24: =('FINANCIAL STATEMENTS'!D24-'FINANCIAL STATEMENTS'!C24)/'FINANCIAL STATEMENTS'!C24 -> 0.097627657 | D24: =('FINANCIAL STATEMENTS'!E24-'FINANCIAL STATEMENTS'!D24)/'FINANCIAL STATEMENTS'!D24 -> 0.048375134 | E24: =('FINANCIAL STATEMENTS'!F24-'FINANCIAL STATEMENTS'!E24)/'FINANCIAL STATEMENTS'!E24 -> 0.43028445 | F24: =('FINANCIAL STATEMENTS'!G24-'FINANCIAL STATEMENTS'!F24)/'FINANCIAL STATEMENTS'!F24 -> 0.16266302
A25: FINANCE COSTS | B25: =('FINANCIAL STATEMENTS'!C25-'FINANCIAL STATEMENTS'!B25)/'FINANCIAL STATEMENTS'!B25 -> 0.26791045 | C25: =('FINANCIAL STATEMENTS'!D25-'FINANCIAL STATEMENTS'!C25)/'FINANCIAL STATEMENTS'!C25 -> 0.60329606 | D25: =('FINANCIAL STATEMENTS'!E25-'FINANCIAL STATEMENTS'!D25)/'FINANCIAL STATEMENTS'!D25 -> 0.047356828 | E25: =('FINANCIAL STATEMENTS'!F25-'FINANCIAL STATEMENTS'!E25)/'FINANCIAL STATEMENTS'!E25 -> 0.032597266 | F25: =('FINANCIAL STATEMENTS'!G25-'FINANCIAL STATEMENTS'!F25)/'FINANCIAL STATEMENTS'!F25 -> 0.17854718
A26: EXCEPTIONAL ITEMS | B26: =('FINANCIAL STATEMENTS'!C26-'FINANCIAL STATEMENTS'!B26)/'FINANCIAL STATEMENTS'!B26 -> -0.99240891 | C26: =('FINANCIAL STATEMENTS'!D26-'FINANCIAL STATEMENTS'!C26)/'FINANCIAL STATEMENTS'!C26 -> -1 | F26: =('FINANCIAL STATEMENTS'!G26-'FINANCIAL STATEMENTS'!F26)/'FINANCIAL STATEMENTS'!F26 -> -3.8195804
A27: PROFIT BEFORE TAX | B27: =('FINANCIAL STATEMENTS'!C27-'FINANCIAL STATEMENTS'!B27)/'FINANCIAL STATEMENTS'!B27 -> 0.013695675 | C27: =('FINANCIAL STATEMENTS'!D27-'FINANCIAL STATEMENTS'!C27)/'FINANCIAL STATEMENTS'!C27 -> 0.092068679 | D27: =('FINANCIAL STATEMENTS'!E27-'FINANCIAL STATEMENTS'!D27)/'FINANCIAL STATEMENTS'!D27 -> 0.048392572 | E27: =('FINANCIAL STATEMENTS'!F27-'FINANCIAL STATEMENTS'!E27)/'FINANCIAL STATEMENTS'!E27 -> 0.44137505 | F27: =('FINANCIAL STATEMENTS'!G27-'FINANCIAL STATEMENTS'!F27)/'FINANCIAL STATEMENTS'!F27 -> 0.15062339
A29: TAX EXPENSE
A31: CURRENT TAX | B31: =('FINANCIAL STATEMENTS'!C31-'FINANCIAL STATEMENTS'!B31)/'FINANCIAL STATEMENTS'!B31 -> 0.01736064 | C31: =('FINANCIAL STATEMENTS'!D31-'FINANCIAL STATEMENTS'!C31)/'FINANCIAL STATEMENTS'!C31 -> 0.059938675 | D31: =('FINANCIAL STATEMENTS'!E31-'FINANCIAL STATEMENTS'!D31)/'FINANCIAL STATEMENTS'!D31 -> 0.064196413 | E31: =('FINANCIAL STATEMENTS'!F31-'FINANCIAL STATEMENTS'!E31)/'FINANCIAL STATEMENTS'!E31 -> 0.42947642 | F31: =('FINANCIAL STATEMENTS'!G31-'FINANCIAL STATEMENTS'!F31)/'FINANCIAL STATEMENTS'!F31 -> 0.11796805
A32: DEFERRED TAX | B32: =('FINANCIAL STATEMENTS'!C32-'FINANCIAL STATEMENTS'!B32)/'FINANCIAL STATEMENTS'!B32 -> -1.0036014 | C32: =('FINANCIAL STATEMENTS'!D32-'FINANCIAL STATEMENTS'!C32)/'FINANCIAL STATEMENTS'!C32 -> 14 | D32: =('FINANCIAL STATEMENTS'!E32-'FINANCIAL STATEMENTS'!D32)/'FINANCIAL STATEMENTS'!D32 -> -7.95 | E32: =('FINANCIAL STATEMENTS'!F32-'FINANCIAL STATEMENTS'!E32)/'FINANCIAL STATEMENTS'!E32 -> -0.96802558 | F32: =('FINANCIAL STATEMENTS'!G32-'FINANCIAL STATEMENTS'!F32)/'FINANCIAL STATEMENTS'!F32 -> -40.925
A33: NET TAX EXPENSE | B33: =('FINANCIAL STATEMENTS'!C33-'FINANCIAL STATEMENTS'!B33)/'FINANCIAL STATEMENTS'!B33 -> 0.11880834 | C33: =('FINANCIAL STATEMENTS'!D33-'FINANCIAL STATEMENTS'!C33)/'FINANCIAL STATEMENTS'!C33 -> 0.064397473 | D33: =('FINANCIAL STATEMENTS'!E33-'FINANCIAL STATEMENTS'!D33)/'FINANCIAL STATEMENTS'!D33 -> 0.028072021 | E33: =('FINANCIAL STATEMENTS'!F33-'FINANCIAL STATEMENTS'!E33)/'FINANCIAL STATEMENTS'!E33 -> 0.47206119 | F33: =('FINANCIAL STATEMENTS'!G33-'FINANCIAL STATEMENTS'!F33)/'FINANCIAL STATEMENTS'!F33 -> 0.14513353
A34: TAX RATE | B34: =('FINANCIAL STATEMENTS'!C34-'FINANCIAL STATEMENTS'!B34)/'FINANCIAL STATEMENTS'!B34 -> 0.10369252 | C34: =('FINANCIAL STATEMENTS'!D34-'FINANCIAL STATEMENTS'!C34)/'FINANCIAL STATEMENTS'!C34 -> -0.025338339 | D34: =('FINANCIAL STATEMENTS'!E34-'FINANCIAL STATEMENTS'!D34)/'FINANCIAL STATEMENTS'!D34 -> -0.019382579 | E34: =('FINANCIAL STATEMENTS'!F34-'FINANCIAL STATEMENTS'!E34)/'FINANCIAL STATEMENTS'!E34 -> 0.021289488 | F34: =('FINANCIAL STATEMENTS'!G34-'FINANCIAL STATEMENTS'!F34)/'FINANCIAL STATEMENTS'!F34 -> -0.0047711974
A36: TOTAL PROFIT FOR THE YEAR ( PROFIT AFTER TAX) | B36: =('FINANCIAL STATEMENTS'!C36-'FINANCIAL STATEMENTS'!B36)/'FINANCIAL STATEMENTS'!B36 -> -0.018300321 | C36: =('FINANCIAL STATEMENTS'!D36-'FINANCIAL STATEMENTS'!C36)/'FINANCIAL STATEMENTS'!C36 -> 0.10166812 | D36: =('FINANCIAL STATEMENTS'!E36-'FINANCIAL STATEMENTS'!D36)/'FINANCIAL STATEMENTS'!D36 -> 0.055203498 | E36: =('FINANCIAL STATEMENTS'!F36-'FINANCIAL STATEMENTS'!E36)/'FINANCIAL STATEMENTS'!E36 -> 0.4313543 | F36: =('FINANCIAL STATEMENTS'!G36-'FINANCIAL STATEMENTS'!F36)/'FINANCIAL STATEMENTS'!F36 -> 0.15246712
A38: OTHER COMPREHENSIVE INCOME
A39: ITEMS THAT WILL NOT BE RECLASSIFIED TO INCOME STATEMENT
A41: REMEASUREMENT OF DEFINED BENEFIT PLAN | B41: =('FINANCIAL STATEMENTS'!C41-'FINANCIAL STATEMENTS'!B41)/'FINANCIAL STATEMENTS'!B41 -> -0.93615591 | C41: =('FINANCIAL STATEMENTS'!D41-'FINANCIAL STATEMENTS'!C41)/'FINANCIAL STATEMENTS'!C41 -> 11.747368 | D41: =('FINANCIAL STATEMENTS'!E41-'FINANCIAL STATEMENTS'!D41)/'FINANCIAL STATEMENTS'!D41 -> -1.1601982 | E41: =('FINANCIAL STATEMENTS'!F41-'FINANCIAL STATEMENTS'!E41)/'FINANCIAL STATEMENTS'!E41 -> -14.804124 | F41: =('FINANCIAL STATEMENTS'!G41-'FINANCIAL STATEMENTS'!F41)/'FINANCIAL STATEMENTS'!F41 -> -0.4309186
A42: INCOME TAX RELATING TO ITEMS THAT WILL NOT RECLASSIFIED TO PROFIT OR LOSS | B42: =('FINANCIAL STATEMENTS'!C42-'FINANCIAL STATEMENTS'!B42)/'FINANCIAL STATEMENTS'!B42 -> -0.92207792 | C42: =('FINANCIAL STATEMENTS'!D42-'FINANCIAL STATEMENTS'!C42)/'FINANCIAL STATEMENTS'!C42 -> 11.708333 | D42: =('FINANCIAL STATEMENTS'!E42-'FINANCIAL STATEMENTS'!D42)/'FINANCIAL STATEMENTS'!D42 -> -1.1606557 | E42: =('FINANCIAL STATEMENTS'!F42-'FINANCIAL STATEMENTS'!E42)/'FINANCIAL STATEMENTS'!E42 -> -14.755102 | F42: =('FINANCIAL STATEMENTS'!G42-'FINANCIAL STATEMENTS'!F42)/'FINANCIAL STATEMENTS'!F42 -> -0.43026706
A43: TOTAL OTHER COMPREHENSIVE LOSS | B43: =('FINANCIAL STATEMENTS'!C43-'FINANCIAL STATEMENTS'!B43)/'FINANCIAL STATEMENTS'!B43 -> -0.93983051 | C43: =('FINANCIAL STATEMENTS'!D43-'FINANCIAL STATEMENTS'!C43)/'FINANCIAL STATEMENTS'!C43 -> 11.760563 | D43: =('FINANCIAL STATEMENTS'!E43-'FINANCIAL STATEMENTS'!D43)/'FINANCIAL STATEMENTS'!D43 -> -1.1600442 | E43: =('FINANCIAL STATEMENTS'!F43-'FINANCIAL STATEMENTS'!E43)/'FINANCIAL STATEMENTS'!E43 -> -14.82069 | F43: =('FINANCIAL STATEMENTS'!G43-'FINANCIAL STATEMENTS'!F43)/'FINANCIAL STATEMENTS'!F43 -> -0.43113772
A45: TOTAL COMPREHENSIVE INCOME FOR THE YEAR | B45: =('FINANCIAL STATEMENTS'!C45-'FINANCIAL STATEMENTS'!B45)/'FINANCIAL STATEMENTS'!B45 -> -0.0083224753 | C45: =('FINANCIAL STATEMENTS'!D45-'FINANCIAL STATEMENTS'!C45)/'FINANCIAL STATEMENTS'!C45 -> 0.09400879 | D45: =('FINANCIAL STATEMENTS'!E45-'FINANCIAL STATEMENTS'!D45)/'FINANCIAL STATEMENTS'!D45 -> 0.064515583 | E45: =('FINANCIAL STATEMENTS'!F45-'FINANCIAL STATEMENTS'!E45)/'FINANCIAL STATEMENTS'!E45 -> 0.41378324 | F45: =('FINANCIAL STATEMENTS'!G45-'FINANCIAL STATEMENTS'!F45)/'FINANCIAL STATEMENTS'!F45 -> 0.15903969
A47: EARNINGS PER EQUITY SHARE
A48: BASIC | B48: =('FINANCIAL STATEMENTS'!C49-'FINANCIAL STATEMENTS'!B49)/'FINANCIAL STATEMENTS'!B49 -> -0.01890272 | C48: =('FINANCIAL STATEMENTS'!D49-'FINANCIAL STATEMENTS'!C49)/'FINANCIAL STATEMENTS'!C49 -> 0.10197368 | D48: =('FINANCIAL STATEMENTS'!E49-'FINANCIAL STATEMENTS'!D49)/'FINANCIAL STATEMENTS'!D49 -> 0.054584222 | E48: =('FINANCIAL STATEMENTS'!F49-'FINANCIAL STATEMENTS'!E49)/'FINANCIAL STATEMENTS'!E49 -> 0.4310554 | F48: =('FINANCIAL STATEMENTS'!G49-'FINANCIAL STATEMENTS'!F49)/'FINANCIAL STATEMENTS'!F49 -> 0.15202034
A49: DILUTED | B49: =('FINANCIAL STATEMENTS'!C50-'FINANCIAL STATEMENTS'!B50)/'FINANCIAL STATEMENTS'!B50 -> -0.018911439 | C49: =('FINANCIAL STATEMENTS'!D50-'FINANCIAL STATEMENTS'!C50)/'FINANCIAL STATEMENTS'!C50 -> 0.10155148 | D49: =('FINANCIAL STATEMENTS'!E50-'FINANCIAL STATEMENTS'!D50)/'FINANCIAL STATEMENTS'!D50 -> 0.055057618 | E49: =('FINANCIAL STATEMENTS'!F50-'FINANCIAL STATEMENTS'!E50)/'FINANCIAL STATEMENTS'!E50 -> 0.43001618 | F49: =('FINANCIAL STATEMENTS'!G50-'FINANCIAL STATEMENTS'!F50)/'FINANCIAL STATEMENTS'!F50 -> 0.15077793
A52: BALANCE SHEET
A54: PARTICULARS(AMOUNT IN CRORES OF INR) | B54: 44286 | C54: 44651 | D54: 45016 | E54: 45382 | F54: 45747
A55: ASSETS
A57: NON CURRENT ASSETS
A58: PROPERTY , PLANT AND EQUIPMENT | B58: =('FINANCIAL STATEMENTS'!C60-'FINANCIAL STATEMENTS'!B60)/'FINANCIAL STATEMENTS'!B60 -> 0.18826343 | C58: =('FINANCIAL STATEMENTS'!D60-'FINANCIAL STATEMENTS'!C60)/'FINANCIAL STATEMENTS'!C60 -> 0.29255018 | D58: =('FINANCIAL STATEMENTS'!E60-'FINANCIAL STATEMENTS'!D60)/'FINANCIAL STATEMENTS'!D60 -> 0.091172313 | E58: =('FINANCIAL STATEMENTS'!F60-'FINANCIAL STATEMENTS'!E60)/'FINANCIAL STATEMENTS'!E60 -> 0.31434074 | F58: =('FINANCIAL STATEMENTS'!G60-'FINANCIAL STATEMENTS'!F60)/'FINANCIAL STATEMENTS'!F60 -> 0.10489278
A59: RIGHT OF USE ASSETS | B59: =('FINANCIAL STATEMENTS'!C61-'FINANCIAL STATEMENTS'!B61)/'FINANCIAL STATEMENTS'!B61 -> 0.087219423 | C59: =('FINANCIAL STATEMENTS'!D61-'FINANCIAL STATEMENTS'!C61)/'FINANCIAL STATEMENTS'!C61 -> 0.44054942 | D59: =('FINANCIAL STATEMENTS'!E61-'FINANCIAL STATEMENTS'!D61)/'FINANCIAL STATEMENTS'!D61 -> 0.59666569 | E59: =('FINANCIAL STATEMENTS'!F61-'FINANCIAL STATEMENTS'!E61)/'FINANCIAL STATEMENTS'!E61 -> 0.14911156 | F59: =('FINANCIAL STATEMENTS'!G61-'FINANCIAL STATEMENTS'!F61)/'FINANCIAL STATEMENTS'!F61 -> 0.26708114
A60: CAPITAL WORK IN PROGRESS | B60: =('FINANCIAL STATEMENTS'!C62-'FINANCIAL STATEMENTS'!B62)/'FINANCIAL STATEMENTS'!B62 -> 0.13673074 | C60: =('FINANCIAL STATEMENTS'!D62-'FINANCIAL STATEMENTS'!C62)/'FINANCIAL STATEMENTS'!C62 -> -0.26344583 | D60: =('FINANCIAL STATEMENTS'!E62-'FINANCIAL STATEMENTS'!D62)/'FINANCIAL STATEMENTS'!D62 -> 0.69287161 | E60: =('FINANCIAL STATEMENTS'!F62-'FINANCIAL STATEMENTS'!E62)/'FINANCIAL STATEMENTS'!E62 -> -0.61407407 | F60: =('FINANCIAL STATEMENTS'!G62-'FINANCIAL STATEMENTS'!F62)/'FINANCIAL STATEMENTS'!F62 -> -0.21880998
A61: GOODWILL | B61: =('FINANCIAL STATEMENTS'!C63-'FINANCIAL STATEMENTS'!B63)/'FINANCIAL STATEMENTS'!B63 -> 0.0026710022 | C61: =('FINANCIAL STATEMENTS'!D63-'FINANCIAL STATEMENTS'!C63)/'FINANCIAL STATEMENTS'!C63 -> 12.723072 | D61: =('FINANCIAL STATEMENTS'!E63-'FINANCIAL STATEMENTS'!D63)/'FINANCIAL STATEMENTS'!D63 -> 0 | E61: =('FINANCIAL STATEMENTS'!F63-'FINANCIAL STATEMENTS'!E63)/'FINANCIAL STATEMENTS'!E63 -> 0 | F61: =('FINANCIAL STATEMENTS'!G63-'FINANCIAL STATEMENTS'!F63)/'FINANCIAL STATEMENTS'!F63 -> 0
A62: OTHER INTANGIBLE ASSETS | B62: =('FINANCIAL STATEMENTS'!C64-'FINANCIAL STATEMENTS'!B64)/'FINANCIAL STATEMENTS'!B64 -> 0.0061143064 | C62: =('FINANCIAL STATEMENTS'!D64-'FINANCIAL STATEMENTS'!C64)/'FINANCIAL STATEMENTS'!C64 -> 7.0181284 | D62: =('FINANCIAL STATEMENTS'!E64-'FINANCIAL STATEMENTS'!D64)/'FINANCIAL STATEMENTS'!D64 -> -0.013257284 | E62: =('FINANCIAL STATEMENTS'!F64-'FINANCIAL STATEMENTS'!E64)/'FINANCIAL STATEMENTS'!E64 -> 0.0018291413 | F62: =('FINANCIAL STATEMENTS'!G64-'FINANCIAL STATEMENTS'!F64)/'FINANCIAL STATEMENTS'!F64 -> -0.010318053
A63: INVESTMENTS | B63: =('FINANCIAL STATEMENTS'!C65-'FINANCIAL STATEMENTS'!B65)/'FINANCIAL STATEMENTS'!B65 -> 1.9884873 | C63: =('FINANCIAL STATEMENTS'!D65-'FINANCIAL STATEMENTS'!C65)/'FINANCIAL STATEMENTS'!C65 -> -0.7239166 | D63: =('FINANCIAL STATEMENTS'!E65-'FINANCIAL STATEMENTS'!D65)/'FINANCIAL STATEMENTS'!D65 -> 0.097817291 | E63: =('FINANCIAL STATEMENTS'!F65-'FINANCIAL STATEMENTS'!E65)/'FINANCIAL STATEMENTS'!E65 -> 0.049745495 | F63: =('FINANCIAL STATEMENTS'!G65-'FINANCIAL STATEMENTS'!F65)/'FINANCIAL STATEMENTS'!F65 -> 0.07804716
A64: LOANS | B64: =('FINANCIAL STATEMENTS'!C66-'FINANCIAL STATEMENTS'!B66)/'FINANCIAL STATEMENTS'!B66 -> 0.19306931 | C64: =('FINANCIAL STATEMENTS'!D66-'FINANCIAL STATEMENTS'!C66)/'FINANCIAL STATEMENTS'!C66 -> 0.047717842 | D64: =('FINANCIAL STATEMENTS'!E66-'FINANCIAL STATEMENTS'!D66)/'FINANCIAL STATEMENTS'!D66 -> 0.22772277 | E64: =('FINANCIAL STATEMENTS'!F66-'FINANCIAL STATEMENTS'!E66)/'FINANCIAL STATEMENTS'!E66 -> 0.25 | F64: =('FINANCIAL STATEMENTS'!G66-'FINANCIAL STATEMENTS'!F66)/'FINANCIAL STATEMENTS'!F66 -> -0.049032258
A65: OTHER FINANCIAL ASSETS | B65: =('FINANCIAL STATEMENTS'!C67-'FINANCIAL STATEMENTS'!B67)/'FINANCIAL STATEMENTS'!B67 -> 0.15472561 | C65: =('FINANCIAL STATEMENTS'!D67-'FINANCIAL STATEMENTS'!C67)/'FINANCIAL STATEMENTS'!C67 -> 0.28382838 | D65: =('FINANCIAL STATEMENTS'!E67-'FINANCIAL STATEMENTS'!D67)/'FINANCIAL STATEMENTS'!D67 -> 0.79691517 | E65: =('FINANCIAL STATEMENTS'!F67-'FINANCIAL STATEMENTS'!E67)/'FINANCIAL STATEMENTS'!E67 -> 0.1304721 | F65: =('FINANCIAL STATEMENTS'!G67-'FINANCIAL STATEMENTS'!F67)/'FINANCIAL STATEMENTS'!F67 -> 0.13996457
A66: INCOME TAX ASSETS (NET) | B66: =('FINANCIAL STATEMENTS'!C68-'FINANCIAL STATEMENTS'!B68)/'FINANCIAL STATEMENTS'!B68 -> -0.1778828 | C66: =('FINANCIAL STATEMENTS'!D68-'FINANCIAL STATEMENTS'!C68)/'FINANCIAL STATEMENTS'!C68 -> 0.49367671 | D66: =('FINANCIAL STATEMENTS'!E68-'FINANCIAL STATEMENTS'!D68)/'FINANCIAL STATEMENTS'!D68 -> 0.056111453 | E66: =('FINANCIAL STATEMENTS'!F68-'FINANCIAL STATEMENTS'!E68)/'FINANCIAL STATEMENTS'!E68 -> -0.055608192 | F66: =('FINANCIAL STATEMENTS'!G68-'FINANCIAL STATEMENTS'!F68)/'FINANCIAL STATEMENTS'!F68 -> 0.21986418
A67: OTHER NON CURRENT ASSETS | B67: =('FINANCIAL STATEMENTS'!C69-'FINANCIAL STATEMENTS'!B69)/'FINANCIAL STATEMENTS'!B69 -> 0.22920861 | C67: =('FINANCIAL STATEMENTS'!D69-'FINANCIAL STATEMENTS'!C69)/'FINANCIAL STATEMENTS'!C69 -> -0.46831296 | D67: =('FINANCIAL STATEMENTS'!E69-'FINANCIAL STATEMENTS'!D69)/'FINANCIAL STATEMENTS'!D69 -> 0.13175355 | E67: =('FINANCIAL STATEMENTS'!F69-'FINANCIAL STATEMENTS'!E69)/'FINANCIAL STATEMENTS'!E69 -> 0.095477387 | F67: =('FINANCIAL STATEMENTS'!G69-'FINANCIAL STATEMENTS'!F69)/'FINANCIAL STATEMENTS'!F69 -> -0.12939602
A68: TOTAL NON CURRENT ASSETS | B68: =('FINANCIAL STATEMENTS'!C71-'FINANCIAL STATEMENTS'!B71)/'FINANCIAL STATEMENTS'!B71 -> 0.86274257 | C68: =('FINANCIAL STATEMENTS'!D71-'FINANCIAL STATEMENTS'!C71)/'FINANCIAL STATEMENTS'!C71 -> 0.067509956 | D68: =('FINANCIAL STATEMENTS'!E71-'FINANCIAL STATEMENTS'!D71)/'FINANCIAL STATEMENTS'!D71 -> 0.083647979 | E68: =('FINANCIAL STATEMENTS'!F71-'FINANCIAL STATEMENTS'!E71)/'FINANCIAL STATEMENTS'!E71 -> 0.055605772 | F68: =('FINANCIAL STATEMENTS'!G71-'FINANCIAL STATEMENTS'!F71)/'FINANCIAL STATEMENTS'!F71 -> 0.054518267
A70: CURRENT ASSETS
A71: INVENTORIES | B71: =('FINANCIAL STATEMENTS'!C75-'FINANCIAL STATEMENTS'!B75)/'FINANCIAL STATEMENTS'!B75 -> 0.33600734 | C71: =('FINANCIAL STATEMENTS'!D75-'FINANCIAL STATEMENTS'!C75)/'FINANCIAL STATEMENTS'!C75 -> 0.47746788 | D71: =('FINANCIAL STATEMENTS'!E75-'FINANCIAL STATEMENTS'!D75)/'FINANCIAL STATEMENTS'!D75 -> 0.082750777 | E71: =('FINANCIAL STATEMENTS'!F75-'FINANCIAL STATEMENTS'!E75)/'FINANCIAL STATEMENTS'!E75 -> -0.19472983 | F71: =('FINANCIAL STATEMENTS'!G75-'FINANCIAL STATEMENTS'!F75)/'FINANCIAL STATEMENTS'!F75 -> 0.18544885
A72: INVESTMENTS | B72: =('FINANCIAL STATEMENTS'!C76-'FINANCIAL STATEMENTS'!B76)/'FINANCIAL STATEMENTS'!B76 -> -0.76320647 | C72: =('FINANCIAL STATEMENTS'!D76-'FINANCIAL STATEMENTS'!C76)/'FINANCIAL STATEMENTS'!C76 -> 0.0056687334 | D72: =('FINANCIAL STATEMENTS'!E76-'FINANCIAL STATEMENTS'!D76)/'FINANCIAL STATEMENTS'!D76 -> 1.5994363 | E72: =('FINANCIAL STATEMENTS'!F76-'FINANCIAL STATEMENTS'!E76)/'FINANCIAL STATEMENTS'!E76 -> 2.9741366 | F72: =('FINANCIAL STATEMENTS'!G76-'FINANCIAL STATEMENTS'!F76)/'FINANCIAL STATEMENTS'!F76 -> 0.72612099
A73: TRADE RECEIVABLES | B73: =('FINANCIAL STATEMENTS'!C77-'FINANCIAL STATEMENTS'!B77)/'FINANCIAL STATEMENTS'!B77 -> 0.23859762 | C73: =('FINANCIAL STATEMENTS'!D77-'FINANCIAL STATEMENTS'!C77)/'FINANCIAL STATEMENTS'!C77 -> 0.21303386 | D73: =('FINANCIAL STATEMENTS'!E77-'FINANCIAL STATEMENTS'!D77)/'FINANCIAL STATEMENTS'!D77 -> 0.07689388 | E73: =('FINANCIAL STATEMENTS'!F77-'FINANCIAL STATEMENTS'!E77)/'FINANCIAL STATEMENTS'!E77 -> 0.076935454 | F73: =('FINANCIAL STATEMENTS'!G77-'FINANCIAL STATEMENTS'!F77)/'FINANCIAL STATEMENTS'!F77 -> 0.10699167
A74: CASH AND CASH EQUIVALENTS | B74: =('FINANCIAL STATEMENTS'!C78-'FINANCIAL STATEMENTS'!B78)/'FINANCIAL STATEMENTS'!B78 -> -0.80536009 | C74: =('FINANCIAL STATEMENTS'!D78-'FINANCIAL STATEMENTS'!C78)/'FINANCIAL STATEMENTS'!C78 -> 0.34505054 | D74: =('FINANCIAL STATEMENTS'!E78-'FINANCIAL STATEMENTS'!D78)/'FINANCIAL STATEMENTS'!D78 -> 0.037914692 | E74: =('FINANCIAL STATEMENTS'!F78-'FINANCIAL STATEMENTS'!E78)/'FINANCIAL STATEMENTS'!E78 -> 1.4779517 | F74: =('FINANCIAL STATEMENTS'!G78-'FINANCIAL STATEMENTS'!F78)/'FINANCIAL STATEMENTS'!F78 -> -0.44175639
A75: BANK BALANCES OTHER THAN CASH AND CASH EQUIVALENTS | B75: =('FINANCIAL STATEMENTS'!C79-'FINANCIAL STATEMENTS'!B79)/'FINANCIAL STATEMENTS'!B79 -> -0.45182013 | C75: =('FINANCIAL STATEMENTS'!D79-'FINANCIAL STATEMENTS'!C79)/'FINANCIAL STATEMENTS'!C79 -> 0.12109375 | D75: =('FINANCIAL STATEMENTS'!E79-'FINANCIAL STATEMENTS'!D79)/'FINANCIAL STATEMENTS'!D79 -> -0.041811847 | E75: =('FINANCIAL STATEMENTS'!F79-'FINANCIAL STATEMENTS'!E79)/'FINANCIAL STATEMENTS'!E79 -> -0.16363636 | F75: =('FINANCIAL STATEMENTS'!G79-'FINANCIAL STATEMENTS'!F79)/'FINANCIAL STATEMENTS'!F79 -> 0.12173913
A76: LOANS | B76: =('FINANCIAL STATEMENTS'!C80-'FINANCIAL STATEMENTS'!B80)/'FINANCIAL STATEMENTS'!B80 -> -0.35973207 | C76: =('FINANCIAL STATEMENTS'!D80-'FINANCIAL STATEMENTS'!C80)/'FINANCIAL STATEMENTS'!C80 -> 0.096 | D76: =('FINANCIAL STATEMENTS'!E80-'FINANCIAL STATEMENTS'!D80)/'FINANCIAL STATEMENTS'!D80 -> 0.34531162 | E76: =('FINANCIAL STATEMENTS'!F80-'FINANCIAL STATEMENTS'!E80)/'FINANCIAL STATEMENTS'!E80 -> 0.23580968 | F76: =('FINANCIAL STATEMENTS'!G80-'FINANCIAL STATEMENTS'!F80)/'FINANCIAL STATEMENTS'!F80 -> -0.23167849
A77: OTHER FINANCIAL ASSETS | B77: =('FINANCIAL STATEMENTS'!C81-'FINANCIAL STATEMENTS'!B81)/'FINANCIAL STATEMENTS'!B81 -> -0.10814095 | C77: =('FINANCIAL STATEMENTS'!D81-'FINANCIAL STATEMENTS'!C81)/'FINANCIAL STATEMENTS'!C81 -> 0.55313351 | D77: =('FINANCIAL STATEMENTS'!E81-'FINANCIAL STATEMENTS'!D81)/'FINANCIAL STATEMENTS'!D81 -> -0.3245614 | E77: =('FINANCIAL STATEMENTS'!F81-'FINANCIAL STATEMENTS'!E81)/'FINANCIAL STATEMENTS'!E81 -> -0.24415584 | F77: =('FINANCIAL STATEMENTS'!G81-'FINANCIAL STATEMENTS'!F81)/'FINANCIAL STATEMENTS'!F81 -> 0.29209622
A78: OTHER CURRENT ASSETS | B78: =('FINANCIAL STATEMENTS'!C82-'FINANCIAL STATEMENTS'!B82)/'FINANCIAL STATEMENTS'!B82 -> -0.18025801 | C78: =('FINANCIAL STATEMENTS'!D82-'FINANCIAL STATEMENTS'!C82)/'FINANCIAL STATEMENTS'!C82 -> 0.28576515 | D78: =('FINANCIAL STATEMENTS'!E82-'FINANCIAL STATEMENTS'!D82)/'FINANCIAL STATEMENTS'!D82 -> -0.08667479 | E78: =('FINANCIAL STATEMENTS'!F82-'FINANCIAL STATEMENTS'!E82)/'FINANCIAL STATEMENTS'!E82 -> 0.058213571 | F78: =('FINANCIAL STATEMENTS'!G82-'FINANCIAL STATEMENTS'!F82)/'FINANCIAL STATEMENTS'!F82 -> 0.39567933
A79: ASSETS HELD FOR SALE
A80: TOTAL CURRENT ASSETS | B80: =('FINANCIAL STATEMENTS'!C85-'FINANCIAL STATEMENTS'!B85)/'FINANCIAL STATEMENTS'!B85 -> -0.20002578 | C80: =('FINANCIAL STATEMENTS'!D85-'FINANCIAL STATEMENTS'!C85)/'FINANCIAL STATEMENTS'!C85 -> 0.31549053 | D80: =('FINANCIAL STATEMENTS'!E85-'FINANCIAL STATEMENTS'!D85)/'FINANCIAL STATEMENTS'!D85 -> 0.1498477 | E80: =('FINANCIAL STATEMENTS'!F85-'FINANCIAL STATEMENTS'!E85)/'FINANCIAL STATEMENTS'!E85 -> 0.37031262 | F80: =('FINANCIAL STATEMENTS'!G85-'FINANCIAL STATEMENTS'!F85)/'FINANCIAL STATEMENTS'!F85 -> 0.30970811
A81: TOTAL ASSETS | B81: =('FINANCIAL STATEMENTS'!C87-'FINANCIAL STATEMENTS'!B87)/'FINANCIAL STATEMENTS'!B87 -> 0.31007585 | C81: =('FINANCIAL STATEMENTS'!D87-'FINANCIAL STATEMENTS'!C87)/'FINANCIAL STATEMENTS'!C87 -> 0.14625476 | D81: =('FINANCIAL STATEMENTS'!E87-'FINANCIAL STATEMENTS'!D87)/'FINANCIAL STATEMENTS'!D87 -> 0.10777296 | E81: =('FINANCIAL STATEMENTS'!F87-'FINANCIAL STATEMENTS'!E87)/'FINANCIAL STATEMENTS'!E87 -> 0.17464951 | F81: =('FINANCIAL STATEMENTS'!G87-'FINANCIAL STATEMENTS'!F87)/'FINANCIAL STATEMENTS'!F87 -> 0.16712779
A83: EQUITIES AND LIABILITES
A85: EQUITY
A86: EQUITY SHARE CAPITAL | B86: =('FINANCIAL STATEMENTS'!C93-'FINANCIAL STATEMENTS'!B93)/'FINANCIAL STATEMENTS'!B93 -> 0.00019681165 | C86: =('FINANCIAL STATEMENTS'!D93-'FINANCIAL STATEMENTS'!C93)/'FINANCIAL STATEMENTS'!C93 -> 0.00019677292 | D86: =('FINANCIAL STATEMENTS'!E93-'FINANCIAL STATEMENTS'!D93)/'FINANCIAL STATEMENTS'!D93 -> 0 | E86: =('FINANCIAL STATEMENTS'!F93-'FINANCIAL STATEMENTS'!E93)/'FINANCIAL STATEMENTS'!E93 -> 0.00059020264 | F86: =('FINANCIAL STATEMENTS'!G93-'FINANCIAL STATEMENTS'!F93)/'FINANCIAL STATEMENTS'!F93 -> 0
A87: EQUITY | B87: =('FINANCIAL STATEMENTS'!C94-'FINANCIAL STATEMENTS'!B94)/'FINANCIAL STATEMENTS'!B94 -> 0.24838865 | C87: =('FINANCIAL STATEMENTS'!D94-'FINANCIAL STATEMENTS'!C94)/'FINANCIAL STATEMENTS'!C94 -> 0.14199877 | D87: =('FINANCIAL STATEMENTS'!E94-'FINANCIAL STATEMENTS'!D94)/'FINANCIAL STATEMENTS'!D94 -> 0.12148034 | E87: =('FINANCIAL STATEMENTS'!F94-'FINANCIAL STATEMENTS'!E94)/'FINANCIAL STATEMENTS'!E94 -> 0.17417352 | F87: =('FINANCIAL STATEMENTS'!G94-'FINANCIAL STATEMENTS'!F94)/'FINANCIAL STATEMENTS'!F94 -> 0.16158875
A88: TOTAL EQUITY | B88: =('FINANCIAL STATEMENTS'!C95-'FINANCIAL STATEMENTS'!B95)/'FINANCIAL STATEMENTS'!B95 -> 0.24556421 | C88: =('FINANCIAL STATEMENTS'!D95-'FINANCIAL STATEMENTS'!C95)/'FINANCIAL STATEMENTS'!C95 -> 0.14070294 | D88: =('FINANCIAL STATEMENTS'!E95-'FINANCIAL STATEMENTS'!D95)/'FINANCIAL STATEMENTS'!D95 -> 0.12050696 | E88: =('FINANCIAL STATEMENTS'!F95-'FINANCIAL STATEMENTS'!E95)/'FINANCIAL STATEMENTS'!E95 -> 0.17293224 | F88: =('FINANCIAL STATEMENTS'!G95-'FINANCIAL STATEMENTS'!F95)/'FINANCIAL STATEMENTS'!F95 -> 0.16060302
A90: LIABILITIES
A91: NON CURRENT LIABILITIES
A92: LEASE LIABILITIES | B92: =('FINANCIAL STATEMENTS'!C101-'FINANCIAL STATEMENTS'!B101)/'FINANCIAL STATEMENTS'!B101 -> -0.048927875 | C92: =('FINANCIAL STATEMENTS'!D101-'FINANCIAL STATEMENTS'!C101)/'FINANCIAL STATEMENTS'!C101 -> 0.37200246 | D92: =('FINANCIAL STATEMENTS'!E101-'FINANCIAL STATEMENTS'!D101)/'FINANCIAL STATEMENTS'!D101 -> 1.1384822 | E92: =('FINANCIAL STATEMENTS'!F101-'FINANCIAL STATEMENTS'!E101)/'FINANCIAL STATEMENTS'!E101 -> 0.13398533 | F92: =('FINANCIAL STATEMENTS'!G101-'FINANCIAL STATEMENTS'!F101)/'FINANCIAL STATEMENTS'!F101 -> 0.31084827
A93: OTHER FINANCIAL LIABILITIES | B93: =('FINANCIAL STATEMENTS'!C102-'FINANCIAL STATEMENTS'!B102)/'FINANCIAL STATEMENTS'!B102 -> 0.87741047 | C93: =('FINANCIAL STATEMENTS'!D102-'FINANCIAL STATEMENTS'!C102)/'FINANCIAL STATEMENTS'!C102 -> 0.46294938 | D93: =('FINANCIAL STATEMENTS'!E102-'FINANCIAL STATEMENTS'!D102)/'FINANCIAL STATEMENTS'!D102 -> -0.27532598 | E93: =('FINANCIAL STATEMENTS'!F102-'FINANCIAL STATEMENTS'!E102)/'FINANCIAL STATEMENTS'!E102 -> -0.69480969 | F93: =('FINANCIAL STATEMENTS'!G102-'FINANCIAL STATEMENTS'!F102)/'FINANCIAL STATEMENTS'!F102 -> -0.12244898
A94: PROVISIONS | B94: =('FINANCIAL STATEMENTS'!C103-'FINANCIAL STATEMENTS'!B103)/'FINANCIAL STATEMENTS'!B103 -> 0.10100269 | C94: =('FINANCIAL STATEMENTS'!D103-'FINANCIAL STATEMENTS'!C103)/'FINANCIAL STATEMENTS'!C103 -> 0.24877832 | D94: =('FINANCIAL STATEMENTS'!E103-'FINANCIAL STATEMENTS'!D103)/'FINANCIAL STATEMENTS'!D103 -> 0.14941302 | E94: =('FINANCIAL STATEMENTS'!F103-'FINANCIAL STATEMENTS'!E103)/'FINANCIAL STATEMENTS'!E103 -> 0.23088827 | F94: =('FINANCIAL STATEMENTS'!G103-'FINANCIAL STATEMENTS'!F103)/'FINANCIAL STATEMENTS'!F103 -> 0.41589138
A95: DEFERRED TAX LIABILITIES(NET) | B95: =('FINANCIAL STATEMENTS'!C104-'FINANCIAL STATEMENTS'!B104)/'FINANCIAL STATEMENTS'!B104 -> -0.00144794 | C95: =('FINANCIAL STATEMENTS'!D104-'FINANCIAL STATEMENTS'!C104)/'FINANCIAL STATEMENTS'!C104 -> 4.1216715 | D95: =('FINANCIAL STATEMENTS'!E104-'FINANCIAL STATEMENTS'!D104)/'FINANCIAL STATEMENTS'!D104 -> -0.030937122 | E95: =('FINANCIAL STATEMENTS'!F104-'FINANCIAL STATEMENTS'!E104)/'FINANCIAL STATEMENTS'!E104 -> -0.0010623888 | F95: =('FINANCIAL STATEMENTS'!G104-'FINANCIAL STATEMENTS'!F104)/'FINANCIAL STATEMENTS'!F104 -> 0.042460982
A96: TOTAL NON CURRENT LIABILITIES | B96: =('FINANCIAL STATEMENTS'!C105-'FINANCIAL STATEMENTS'!B105)/'FINANCIAL STATEMENTS'!B105 -> 0.044920762 | C96: =('FINANCIAL STATEMENTS'!D105-'FINANCIAL STATEMENTS'!C105)/'FINANCIAL STATEMENTS'!C105 -> 1.9003273 | D96: =('FINANCIAL STATEMENTS'!E105-'FINANCIAL STATEMENTS'!D105)/'FINANCIAL STATEMENTS'!D105 -> 0.1262156 | E96: =('FINANCIAL STATEMENTS'!F105-'FINANCIAL STATEMENTS'!E105)/'FINANCIAL STATEMENTS'!E105 -> 0.039516978 | F96: =('FINANCIAL STATEMENTS'!G105-'FINANCIAL STATEMENTS'!F105)/'FINANCIAL STATEMENTS'!F105 -> 0.15901605
A98: CURRENT LIABILITIES
A99: BORROWINGS | C99: =('FINANCIAL STATEMENTS'!D109-'FINANCIAL STATEMENTS'!C109)/'FINANCIAL STATEMENTS'!C109 -> 0.90909091 | D99: =('FINANCIAL STATEMENTS'!E109-'FINANCIAL STATEMENTS'!D109)/'FINANCIAL STATEMENTS'!D109 -> -1
A100: TOTAL OUTSTANDING DUES OF MICRO ENTERPRISES AND SMALL ENTERPRISES | B100: =('FINANCIAL STATEMENTS'!C110-'FINANCIAL STATEMENTS'!B110)/'FINANCIAL STATEMENTS'!B110 -> 6.2086022 | C100: =('FINANCIAL STATEMENTS'!D110-'FINANCIAL STATEMENTS'!C110)/'FINANCIAL STATEMENTS'!C110 -> 0.016557279 | D100: =('FINANCIAL STATEMENTS'!E110-'FINANCIAL STATEMENTS'!D110)/'FINANCIAL STATEMENTS'!D110 -> -0.22494497 | E100: =('FINANCIAL STATEMENTS'!F110-'FINANCIAL STATEMENTS'!E110)/'FINANCIAL STATEMENTS'!E110 -> 0.30537675 | F100: =('FINANCIAL STATEMENTS'!G110-'FINANCIAL STATEMENTS'!F110)/'FINANCIAL STATEMENTS'!F110 -> -0.51007977
A101: TOTAL OUTSTANDING DUES OF CREDITORS OTHER THAN MICRO ENTERPRISES AND SMALL ENTERPRISES | B101: =('FINANCIAL STATEMENTS'!C111-'FINANCIAL STATEMENTS'!B111)/'FINANCIAL STATEMENTS'!B111 -> 0.49694136 | C101: =('FINANCIAL STATEMENTS'!D111-'FINANCIAL STATEMENTS'!C111)/'FINANCIAL STATEMENTS'!C111 -> 0.20764193 | D101: =('FINANCIAL STATEMENTS'!E111-'FINANCIAL STATEMENTS'!D111)/'FINANCIAL STATEMENTS'!D111 -> 0.009627545 | E101: =('FINANCIAL STATEMENTS'!F111-'FINANCIAL STATEMENTS'!E111)/'FINANCIAL STATEMENTS'!E111 -> 0.097749791 | F101: =('FINANCIAL STATEMENTS'!G111-'FINANCIAL STATEMENTS'!F111)/'FINANCIAL STATEMENTS'!F111 -> 0.26976849
A102: LEASE LIABILTIES | B102: =('FINANCIAL STATEMENTS'!C112-'FINANCIAL STATEMENTS'!B112)/'FINANCIAL STATEMENTS'!B112 -> -0.15880218 | C102: =('FINANCIAL STATEMENTS'!D112-'FINANCIAL STATEMENTS'!C112)/'FINANCIAL STATEMENTS'!C112 -> 0.42826321 | D102: =('FINANCIAL STATEMENTS'!E112-'FINANCIAL STATEMENTS'!D112)/'FINANCIAL STATEMENTS'!D112 -> 0.64161631 | E102: =('FINANCIAL STATEMENTS'!F112-'FINANCIAL STATEMENTS'!E112)/'FINANCIAL STATEMENTS'!E112 -> 0.13549574 | F102: =('FINANCIAL STATEMENTS'!G112-'FINANCIAL STATEMENTS'!F112)/'FINANCIAL STATEMENTS'!F112 -> 0.20502431
A103: OTHER FINANCIAL LIABILITIES | B103: =('FINANCIAL STATEMENTS'!C113-'FINANCIAL STATEMENTS'!B113)/'FINANCIAL STATEMENTS'!B113 -> 0.62999167 | C103: =('FINANCIAL STATEMENTS'!D113-'FINANCIAL STATEMENTS'!C113)/'FINANCIAL STATEMENTS'!C113 -> -0.26744703 | D103: =('FINANCIAL STATEMENTS'!E113-'FINANCIAL STATEMENTS'!D113)/'FINANCIAL STATEMENTS'!D113 -> 0.26494042 | E103: =('FINANCIAL STATEMENTS'!F113-'FINANCIAL STATEMENTS'!E113)/'FINANCIAL STATEMENTS'!E113 -> 0.20789089 | F103: =('FINANCIAL STATEMENTS'!G113-'FINANCIAL STATEMENTS'!F113)/'FINANCIAL STATEMENTS'!F113 -> 0.18230076
A104: OTHER CURRENT LIABILITIES | B104: =('FINANCIAL STATEMENTS'!C114-'FINANCIAL STATEMENTS'!B114)/'FINANCIAL STATEMENTS'!B114 -> -0.19293569 | C104: =('FINANCIAL STATEMENTS'!D114-'FINANCIAL STATEMENTS'!C114)/'FINANCIAL STATEMENTS'!C114 -> 0.12992018 | D104: =('FINANCIAL STATEMENTS'!E114-'FINANCIAL STATEMENTS'!D114)/'FINANCIAL STATEMENTS'!D114 -> 0.071132765 | E104: =('FINANCIAL STATEMENTS'!F114-'FINANCIAL STATEMENTS'!E114)/'FINANCIAL STATEMENTS'!E114 -> 0.12167387 | F104: =('FINANCIAL STATEMENTS'!G114-'FINANCIAL STATEMENTS'!F114)/'FINANCIAL STATEMENTS'!F114 -> -0.10158151
A105: PROVISIONS | B105: =('FINANCIAL STATEMENTS'!C115-'FINANCIAL STATEMENTS'!B115)/'FINANCIAL STATEMENTS'!B115 -> 0.39898132 | C105: =('FINANCIAL STATEMENTS'!D115-'FINANCIAL STATEMENTS'!C115)/'FINANCIAL STATEMENTS'!C115 -> 1.1201456 | D105: =('FINANCIAL STATEMENTS'!E115-'FINANCIAL STATEMENTS'!D115)/'FINANCIAL STATEMENTS'!D115 -> -0.13451631 | E105: =('FINANCIAL STATEMENTS'!F115-'FINANCIAL STATEMENTS'!E115)/'FINANCIAL STATEMENTS'!E115 -> 5.2936508 | F105: =('FINANCIAL STATEMENTS'!G115-'FINANCIAL STATEMENTS'!F115)/'FINANCIAL STATEMENTS'!F115 -> 0.28352249
A106: CURRENT TAX LIABILITIES(NET) | B106: =('FINANCIAL STATEMENTS'!C116-'FINANCIAL STATEMENTS'!B116)/'FINANCIAL STATEMENTS'!B116 -> 1.8359173 | C106: =('FINANCIAL STATEMENTS'!D116-'FINANCIAL STATEMENTS'!C116)/'FINANCIAL STATEMENTS'!C116 -> -0.58724374 | D106: =('FINANCIAL STATEMENTS'!E116-'FINANCIAL STATEMENTS'!D116)/'FINANCIAL STATEMENTS'!D116 -> 3.2218543 | E106: =('FINANCIAL STATEMENTS'!F116-'FINANCIAL STATEMENTS'!E116)/'FINANCIAL STATEMENTS'!E116 -> -0.39581699 | F106: =('FINANCIAL STATEMENTS'!G116-'FINANCIAL STATEMENTS'!F116)/'FINANCIAL STATEMENTS'!F116 -> -0.11466897
A107: TOTAL CURRENT LIABILTIES | B107: =('FINANCIAL STATEMENTS'!C117-'FINANCIAL STATEMENTS'!B117)/'FINANCIAL STATEMENTS'!B117 -> 0.59387353 | C107: =('FINANCIAL STATEMENTS'!D117-'FINANCIAL STATEMENTS'!C117)/'FINANCIAL STATEMENTS'!C117 -> -0.0084358318 | D107: =('FINANCIAL STATEMENTS'!E117-'FINANCIAL STATEMENTS'!D117)/'FINANCIAL STATEMENTS'!D117 -> 0.059150636 | E107: =('FINANCIAL STATEMENTS'!F117-'FINANCIAL STATEMENTS'!E117)/'FINANCIAL STATEMENTS'!E117 -> 0.2218382 | F107: =('FINANCIAL STATEMENTS'!G117-'FINANCIAL STATEMENTS'!F117)/'FINANCIAL STATEMENTS'!F117 -> 0.19178508
A108: TOTAL LIABILITIES | B108: =('FINANCIAL STATEMENTS'!C119-'FINANCIAL STATEMENTS'!B119)/'FINANCIAL STATEMENTS'!B119 -> 0.52276554 | C108: =('FINANCIAL STATEMENTS'!D119-'FINANCIAL STATEMENTS'!C119)/'FINANCIAL STATEMENTS'!C119 -> 0.16122666 | D108: =('FINANCIAL STATEMENTS'!E119-'FINANCIAL STATEMENTS'!D119)/'FINANCIAL STATEMENTS'!D119 -> 0.074039429 | E108: =('FINANCIAL STATEMENTS'!F119-'FINANCIAL STATEMENTS'!E119)/'FINANCIAL STATEMENTS'!E119 -> 0.17939556 | F108: =('FINANCIAL STATEMENTS'!G119-'FINANCIAL STATEMENTS'!F119)/'FINANCIAL STATEMENTS'!F119 -> 0.1850615
A109: TOTAL EQUITY AND LIABILITIES | B109: =('FINANCIAL STATEMENTS'!C121-'FINANCIAL STATEMENTS'!B121)/'FINANCIAL STATEMENTS'!B121 -> 0.31007585 | C109: =('FINANCIAL STATEMENTS'!D121-'FINANCIAL STATEMENTS'!C121)/'FINANCIAL STATEMENTS'!C121 -> 0.14625476 | D109: =('FINANCIAL STATEMENTS'!E121-'FINANCIAL STATEMENTS'!D121)/'FINANCIAL STATEMENTS'!D121 -> 0.10777296 | E109: =('FINANCIAL STATEMENTS'!F121-'FINANCIAL STATEMENTS'!E121)/'FINANCIAL STATEMENTS'!E121 -> 0.17464951 | F109: =('FINANCIAL STATEMENTS'!G121-'FINANCIAL STATEMENTS'!F121)/'FINANCIAL STATEMENTS'!F121 -> 0.16712779
