Workbook

Sheet FS & Trend Analysis
A2: Financial Statements of Hero Motor Corporation Ltd. | K2: Trend Analysis
A4: Income Statement | K4: Income Statement
A5: Particulars (Amount in Crores of INR) | B5: 42094 | C5: 42460 | D5: 42825 | E5: 43190 | F5: 43555 | G5: 43921 | H5: 44286 | I5: 44651 | K5: Particulars | L5: 42094 | M5: 42460 | N5: 42825 | O5: 43190 | P5: 43555 | Q5: 43921 | R5: 44286 | S5: 44651
A6: Revenue from Operations | B6: 29255.68 | C6: 30871.94 | D6: 30983.66 | E6: 33100.94 | F6: 33972.23 | G6: 29255.32 | H6: 30959.19 | I6: 29551.28 | K6: Revenue from Operations | L6: =B6/$B6 -> 1 | M6: =C6/$B6 -> 1.055246 | N6: =D6/$B6 -> 1.0590648 | O6: =E6/$B6 -> 1.1314364 | P6: =F6/$B6 -> 1.1612183 | Q6: =G6/$B6 -> 0.99998769 | R6: =H6/$B6 -> 1.0582284 | S6: =I6/$B6 -> 1.010104
A7: Other Income | B7: 492.11 | C7: 389.08 | D7: 521.95 | E7: 523.17 | F7: 686.73 | G7: 730.56 | H7: 557.9 | I7: 555.01 | K7: Other Income | L7: =B7/$B7 -> 1 | M7: =C7/$B7 -> 0.79063624 | N7: =D7/$B7 -> 1.0606368 | O7: =E7/$B7 -> 1.063116 | P7: =F7/$B7 -> 1.3954807 | Q7: =G7/$B7 -> 1.4845461 | R7: =H7/$B7 -> 1.1336896 | S7: =I7/$B7 -> 1.127817
A8: Total Income | B8: =SUM(B6:B7) -> 29747.79 | C8: =SUM(C6:C7) -> 31261.02 | D8: =SUM(D6:D7) -> 31505.61 | E8: =SUM(E6:E7) -> 33624.11 | F8: =SUM(F6:F7) -> 34658.96 | G8: =SUM(G6:G7) -> 29985.88 | H8: =SUM(H6:H7) -> 31517.09 | I8: =SUM(I6:I7) -> 30106.29 | K8: Total Income | L8: =B8/$B8 -> 1 | M8: =C8/$B8 -> 1.0508687 | N8: =D8/$B8 -> 1.0590908 | O8: =E8/$B8 -> 1.1303062 | P8: =F8/$B8 -> 1.1650936 | Q8: =G8/$B8 -> 1.0080036 | R8: =H8/$B8 -> 1.0594767 | S8: =I8/$B8 -> 1.0120513
A10: Expenses | K10: Expenses
A11: Raw Material | B11: 19715.3 | C11: 19313.15 | D11: 19116.08 | E11: 21885.82 | F11: 23444.42 | G11: 19830.95 | H11: 21743.61 | I11: 20920.36 | K11: Raw Material | L11: =B11/$B11 -> 1 | M11: =C11/$B11 -> 0.97960214 | N11: =D11/$B11 -> 0.96960635 | O11: =E11/$B11 -> 1.1100932 | P11: =F11/$B11 -> 1.1891485 | Q11: =G11/$B11 -> 1.005866 | R11: =H11/$B11 -> 1.10288 | S11: =I11/$B11 -> 1.0611231
A12: Excise Duty | B12: 1717.65 | C12: 2258.21 | D12: 2373.23 | E12: 642.57 | F12: 1.41 | G12: 1.35 | H12: 0 | I12: 0 | K12: Excise Duty | L12: =B12/$B12 -> 1 | M12: =C12/$B12 -> 1.3147091 | N12: =D12/$B12 -> 1.3816726 | O12: =E12/$B12 -> 0.37409833 | P12: =F12/$B12 -> 0.00082088901 | Q12: =G12/$B12 -> 0.00078595756 | R12: =H12/$B12 -> 0 | S12: =I12/$B12 -> 0
A13: Employee Costs | B13: 1178.72 | C13: 1343.06 | D13: 1432.49 | E13: 1583.71 | F13: 1778.03 | G13: 1889.32 | H13: 1951.02 | I13: 1995.78 | K13: Employee Costs | L13: =B13/$B13 -> 1 | M13: =C13/$B13 -> 1.1394224 | N13: =D13/$B13 -> 1.2152929 | O13: =E13/$B13 -> 1.3435846 | P13: =F13/$B13 -> 1.5084414 | Q13: =G13/$B13 -> 1.6028573 | R13: =H13/$B13 -> 1.6552023 | S13: =I13/$B13 -> 1.6931756
A14: Other Expenses | B14: 3292.01 | C14: 3575.27 | D14: 3485.89 | E14: 3663.79 | F14: 3729.94 | G14: 3472.78 | H14: 3165.05 | I14: 3190.37 | K14: Other Expenses | L14: =B14/$B14 -> 1 | M14: =C14/$B14 -> 1.0860447 | N14: =D14/$B14 -> 1.0588941 | O14: =E14/$B14 -> 1.112934 | P14: =F14/$B14 -> 1.1330281 | Q14: =G14/$B14 -> 1.0549117 | R14: =H14/$B14 -> 0.9614339 | S14: =I14/$B14 -> 0.96912525
A15: Total Expenses | B15: =SUM(B10:B14) -> 25903.68 | C15: =SUM(C10:C14) -> 26489.69 | D15: =SUM(D10:D14) -> 26407.69 | E15: =SUM(E10:E14) -> 27775.89 | F15: =SUM(F10:F14) -> 28953.8 | G15: =SUM(G10:G14) -> 25194.4 | H15: =SUM(H10:H14) -> 26859.68 | I15: =SUM(I10:I14) -> 26106.51 | K15: Total Expenses | L15: =B15/$B15 -> 1 | M15: =C15/$B15 -> 1.0226227 | N15: =D15/$B15 -> 1.0194571 | O15: =E15/$B15 -> 1.0722758 | P15: =F15/$B15 -> 1.1177485 | Q15: =G15/$B15 -> 0.97261856 | R15: =H15/$B15 -> 1.036906 | S15: =I15/$B15 -> 1.0078302
A17: EBITDA | B17: =B8-B15 -> 3844.11 | C17: =C8-C15 -> 4771.33 | D17: =D8-D15 -> 5097.92 | E17: =E8-E15 -> 5848.22 | F17: =F8-F15 -> 5705.16 | G17: =G8-G15 -> 4791.48 | H17: =H8-H15 -> 4657.41 | I17: =I8-I15 -> 3999.78 | K17: EBITDA | L17: =B17/$B17 -> 1 | M17: =C17/$B17 -> 1.2412054 | N17: =D17/$B17 -> 1.3261639 | O17: =E17/$B17 -> 1.5213456 | P17: =F17/$B17 -> 1.4841303 | Q17: =G17/$B17 -> 1.2464472 | R17: =H17/$B17 -> 1.2115704 | S17: =I17/$B17 -> 1.0404957
A18: Depreciation & Amortization | B18: 540.45 | C18: 447.01 | D18: 502.25 | E18: 574.98 | F18: 624.44 | G18: 845.76 | H18: 715.12 | I18: 689.52 | K18: Depreciation & Amortization | L18: =B18/$B18 -> 1 | M18: =C18/$B18 -> 0.82710704 | N18: =D18/$B18 -> 0.92931816 | O18: =E18/$B18 -> 1.0638912 | P18: =F18/$B18 -> 1.1554075 | Q18: =G18/$B18 -> 1.5649181 | R18: =H18/$B18 -> 1.3231936 | S18: =I18/$B18 -> 1.2758257
A19: EBIT | B19: =B17-B18 -> 3303.66 | C19: =C17-C18 -> 4324.32 | D19: =D17-D18 -> 4595.67 | E19: =E17-E18 -> 5273.24 | F19: =F17-F18 -> 5080.72 | G19: =G17-G18 -> 3945.72 | H19: =H17-H18 -> 3942.29 | I19: =I17-I18 -> 3310.26 | K19: EBIT | L19: =B19/$B19 -> 1 | M19: =C19/$B19 -> 1.3089483 | N19: =D19/$B19 -> 1.3910844 | O19: =E19/$B19 -> 1.5961812 | P19: =F19/$B19 -> 1.5379064 | Q19: =G19/$B19 -> 1.1943481 | R19: =H19/$B19 -> 1.1933098 | S19: =I19/$B19 -> 1.0019978
A20: Finance Expenses | B20: 11.7 | C20: 11.87 | D20: 27.28 | E20: 30.8 | F20: 37.18 | G20: 46.64 | H20: 46.41 | I20: 53.1 | K20: Finance Expenses | L20: =B20/$B20 -> 1 | M20: =C20/$B20 -> 1.0145299 | N20: =D20/$B20 -> 2.3316239 | O20: =E20/$B20 -> 2.6324786 | P20: =F20/$B20 -> 3.1777778 | Q20: =G20/$B20 -> 3.9863248 | R20: =H20/$B20 -> 3.9666667 | S20: =I20/$B20 -> 4.5384615
A21: PBT before profits of JVs | B21: =B19-B20 -> 3291.96 | C21: =C19-C20 -> 4312.45 | D21: =D19-D20 -> 4568.39 | E21: =E19-E20 -> 5242.44 | F21: =F19-F20 -> 5043.54 | G21: =G19-G20 -> 3899.08 | H21: =H19-H20 -> 3895.88 | I21: =I19-I20 -> 3257.16 | K21: PBT before profits of JVs | L21: =B21/$B21 -> 1 | M21: =C21/$B21 -> 1.3099947 | N21: =D21/$B21 -> 1.3877416 | O21: =E21/$B21 -> 1.5924981 | P21: =F21/$B21 -> 1.5320782 | Q21: =G21/$B21 -> 1.1844251 | R21: =H21/$B21 -> 1.183453 | S21: =I21/$B21 -> 0.98942879
A22: Add: Share of Profits of JVs | B22: 15.15 | C22: 39.46 | D22: 279.04 | E22: 51.43 | F22: 60.76 | G22: 34.63 | H22: -46.56 | I22: -199.05 | K22: Add: Share of Profits of JVs | L22: =B22/$B22 -> 1 | M22: =C22/$B22 -> 2.6046205 | N22: =D22/$B22 -> 18.418482 | O22: =E22/$B22 -> 3.3947195 | P22: =F22/$B22 -> 4.0105611 | Q22: =G22/$B22 -> 2.2858086 | R22: =H22/$B22 -> -3.0732673 | S22: =I22/$B22 -> -13.138614
A23: PBT & Exceptional Items | B23: =SUM(B21:B22) -> 3307.11 | C23: =SUM(C21:C22) -> 4351.91 | D23: =SUM(D21:D22) -> 4847.43 | E23: =SUM(E21:E22) -> 5293.87 | F23: =SUM(F21:F22) -> 5104.3 | G23: =SUM(G21:G22) -> 3933.71 | H23: =SUM(H21:H22) -> 3849.32 | I23: =SUM(I21:I22) -> 3058.11 | K23: PBT & Exceptional Items | L23: =B23/$B23 -> 1 | M23: =C23/$B23 -> 1.3159254 | N23: =D23/$B23 -> 1.4657601 | O23: =E23/$B23 -> 1.6007541 | P23: =F23/$B23 -> 1.5434322 | Q23: =G23/$B23 -> 1.1894706 | R23: =H23/$B23 -> 1.1639528 | S23: =I23/$B23 -> 0.92470768
A24: Exceptional Items | G24: 677.37 | K24: Exceptional Items
A25: PBT | B25: =B23+B24 -> 3307.11 | C25: =C23+C24 -> 4351.91 | D25: =D23+D24 -> 4847.43 | E25: =E23+E24 -> 5293.87 | F25: =F23+F24 -> 5104.3 | G25: =G23+G24 -> 4611.08 | H25: =H23+H24 -> 3849.32 | I25: =I23+I24 -> 3058.11 | K25: PBT | L25: =B25/$B25 -> 1 | M25: =C25/$B25 -> 1.3159254 | N25: =D25/$B25 -> 1.4657601 | O25: =E25/$B25 -> 1.6007541 | P25: =F25/$B25 -> 1.5434322 | Q25: =G25/$B25 -> 1.3942929 | R25: =H25/$B25 -> 1.1639528 | S25: =I25/$B25 -> 0.92470768
A26: Tax | B26: 943.45 | C26: 1262.24 | D26: 1339.1 | E26: 1569.93 | F26: 1637.95 | G26: 951.67 | H26: 913.27 | I26: 729.06 | K26: Tax | L26: =B26/$B26 -> 1 | M26: =C26/$B26 -> 1.3378981 | N26: =D26/$B26 -> 1.4193651 | O26: =E26/$B26 -> 1.664031 | P26: =F26/$B26 -> 1.736128 | Q26: =G26/$B26 -> 1.0087127 | R26: =H26/$B26 -> 0.96801102 | S26: =I26/$B26 -> 0.77275955
A27: PAT | B27: =B25-B26 -> 2363.66 | C27: =C25-C26 -> 3089.67 | D27: =D25-D26 -> 3508.33 | E27: =E25-E26 -> 3723.94 | F27: =F25-F26 -> 3466.35 | G27: =G25-G26 -> 3659.41 | H27: =H25-H26 -> 2936.05 | I27: =I25-I26 -> 2329.05 | K27: PAT | L27: =B27/$B27 -> 1 | M27: =C27/$B27 -> 1.307155 | N27: =D27/$B27 -> 1.4842786 | O27: =E27/$B27 -> 1.5754973 | P27: =F27/$B27 -> 1.466518 | Q27: =G27/$B27 -> 1.5481964 | R27: =H27/$B27 -> 1.2421626 | S27: =I27/$B27 -> 0.98535745
A28: Less: Share of Minority Interest | B28: -1.04 | C28: -4.11 | D28: -37.97 | E28: 1.77 | F28: 22.66 | G28: 21.3 | H28: 18.3 | I28: 12.17 | K28: Less: Share of Minority Interest | L28: =B28/$B28 -> 1 | M28: =C28/$B28 -> 3.9519231 | N28: =D28/$B28 -> 36.509615 | O28: =E28/$B28 -> -1.7019231 | P28: =F28/$B28 -> -21.788462 | Q28: =G28/$B28 -> -20.480769 | R28: =H28/$B28 -> -17.596154 | S28: =I28/$B28 -> -11.701923
A29: PAT for Equity Shareholders | B29: =B27-B28 -> 2364.7 | C29: =C27-C28 -> 3093.78 | D29: =D27-D28 -> 3546.3 | E29: =E27-E28 -> 3722.17 | F29: =F27-F28 -> 3443.69 | G29: =G27-G28 -> 3638.11 | H29: =H27-H28 -> 2917.75 | I29: =I27-I28 -> 2316.88 | K29: PAT for Equity Shareholders | L29: =B29/$B29 -> 1 | M29: =C29/$B29 -> 1.3083182 | N29: =D29/$B29 -> 1.4996828 | O29: =E29/$B29 -> 1.5740559 | P29: =F29/$B29 -> 1.4562904 | Q29: =G29/$B29 -> 1.5385081 | R29: =H29/$B29 -> 1.2338774 | S29: =I29/$B29 -> 0.97977756
A30: Dividend | B30: 1198.12 | C30: 1397.81 | D30: 1737.34 | E30: 1697.5 | F30: 1897.35 | G30: 1937 | H30: 1398.46 | I30: =85*I37/2 -> 1698.3 | K30: Dividend | L30: =B30/$B30 -> 1 | M30: =C30/$B30 -> 1.1666694 | N30: =D30/$B30 -> 1.4500551 | O30: =E30/$B30 -> 1.416803 | P30: =F30/$B30 -> 1.583606 | Q30: =G30/$B30 -> 1.6166995 | R30: =H30/$B30 -> 1.167212 | S30: =I30/$B30 -> 1.4174707
A31: Tax Rate (%) | B31: =B26/B25 -> 0.28527929 | C31: =C26/C25 -> 0.29004276 | D31: =D26/D25 -> 0.27624948 | E31: =E26/E25 -> 0.29655621 | F31: =F26/F25 -> 0.32089611 | G31: =G26/G25 -> 0.20638766 | H31: =H26/H25 -> 0.23725489 | I31: =I26/I25 -> 0.23840215
A34: Balance Sheet | K34: Balance Sheet
A35: Particulars | B35: 42094 | C35: 42460 | D35: 42825 | E35: 43190 | F35: 43555 | G35: 43921 | H35: 44286 | I35: 44651 | K35: Particulars | L35: 42094 | M35: 42460 | N35: 42825 | O35: 43190 | P35: 43555 | Q35: 43921 | R35: 44286 | S35: 44651
A36: Equity & Liabilities | K36: Equity & Liabilities
A37: Equity Share Capital | B37: 39.94 | C37: 39.94 | D37: 39.94 | E37: 39.94 | F37: 39.95 | G37: 39.95 | H37: 39.96 | I37: 39.96 | K37: Equity Share Capital | L37: =B37/$B37 -> 1 | M37: =C37/$B37 -> 1 | N37: =D37/$B37 -> 1 | O37: =E37/$B37 -> 1 | P37: =F37/$B37 -> 1.0002504 | Q37: =G37/$B37 -> 1.0002504 | R37: =H37/$B37 -> 1.0005008 | S37: =I37/$B37 -> 1.0005008
A38: Other Equity | B38: 6500.06 | C38: 7912.74 | D38: 10275.57 | E38: 11931.52 | F38: 13080.46 | G38: 14366.33 | H38: 15376.46 | I38: 15806.69 | K38: Other Equity | L38: =B38/$B38 -> 1 | M38: =C38/$B38 -> 1.2173334 | N38: =D38/$B38 -> 1.5808423 | O38: =E38/$B38 -> 1.8356015 | P38: =F38/$B38 -> 2.0123599 | Q38: =G38/$B38 -> 2.2101842 | R38: =H38/$B38 -> 2.3655874 | S38: =I38/$B38 -> 2.431776
A39: Total Equity | B39: =SUM(B37:B38) -> 6540 | C39: =SUM(C37:C38) -> 7952.68 | D39: =SUM(D37:D38) -> 10315.51 | E39: =SUM(E37:E38) -> 11971.46 | F39: =SUM(F37:F38) -> 13120.41 | G39: =SUM(G37:G38) -> 14406.28 | H39: =SUM(H37:H38) -> 15416.42 | I39: =SUM(I37:I38) -> 15846.65 | K39: Total Equity | L39: =B39/$B39 -> 1 | M39: =C39/$B39 -> 1.2160061 | N39: =D39/$B39 -> 1.5772951 | O39: =E39/$B39 -> 1.8304985 | P39: =F39/$B39 -> 2.0061789 | Q39: =G39/$B39 -> 2.2027951 | R39: =H39/$B39 -> 2.3572508 | S39: =I39/$B39 -> 2.4230352
A40: Non-Controlling Interest | B40: 18.54 | C40: 53.62 | D40: 67.38 | E40: 93.21 | F40: 116.11 | G40: 140.6 | H40: 143.19 | I40: 148.05 | K40: Non-Controlling Interest | L40: =B40/$B40 -> 1 | M40: =C40/$B40 -> 2.8921251 | N40: =D40/$B40 -> 3.6343042 | O40: =E40/$B40 -> 5.0275081 | P40: =F40/$B40 -> 6.2626753 | Q40: =G40/$B40 -> 7.583603 | R40: =H40/$B40 -> 7.723301 | S40: =I40/$B40 -> 7.9854369
A42: Non-Current Liabilities | K42: Non-Current Liabilities
A43: Borrowings | B43: 12 | C43: 145.98 | D43: 207.9 | E43: 149.63 | F43: 124.84 | G43: 44.02 | H43: 45.18 | I43: 36.17 | K43: Borrowings | L43: =B43/$B43 -> 1 | M43: =C43/$B43 -> 12.165 | N43: =D43/$B43 -> 17.325 | O43: =E43/$B43 -> 12.469167 | P43: =F43/$B43 -> 10.403333 | Q43: =G43/$B43 -> 3.6683333 | R43: =H43/$B43 -> 3.765 | S43: =I43/$B43 -> 3.0141667
A44: Lease Liabilities | B44: 0 | C44: 0 | D44: 0 | E44: 0 | F44: 0 | G44: 207.62 | H44: 212.42 | I44: 215.51 | K44: Lease Liabilities | L44: =B44/$B44 -> #DIV/0! | M44: =C44/$B44 -> #DIV/0! | N44: =D44/$B44 -> #DIV/0! | O44: =E44/$B44 -> #DIV/0! | P44: =F44/$B44 -> #DIV/0! | Q44: =G44/$B44 -> #DIV/0! | R44: =H44/$B44 -> #DIV/0! | S44: =I44/$B44 -> #DIV/0!
A45: Other financial liabilities | B45: 0 | C45: 0 | D45: 0 | E45: 0 | F45: 0 | G45: 0 | H45: 0 | I45: 155.04 | K45: Other financial liabilities | L45: =B45/$B45 -> #DIV/0! | M45: =C45/$B45 -> #DIV/0! | N45: =D45/$B45 -> #DIV/0! | O45: =E45/$B45 -> #DIV/0! | P45: =F45/$B45 -> #DIV/0! | Q45: =G45/$B45 -> #DIV/0! | R45: =H45/$B45 -> #DIV/0! | S45: =I45/$B45 -> #DIV/0!
A46: Provisions | B46: 0 | C46: 0 | D46: 0 | E46: 0 | F46: 0 | G46: 0 | H46: 0 | I46: 181.13 | K46: Provisions | L46: =B46/$B46 -> #DIV/0! | M46: =C46/$B46 -> #DIV/0! | N46: =D46/$B46 -> #DIV/0! | O46: =E46/$B46 -> #DIV/0! | P46: =F46/$B46 -> #DIV/0! | Q46: =G46/$B46 -> #DIV/0! | R46: =H46/$B46 -> #DIV/0! | S46: =I46/$B46 -> #DIV/0!
A47: Deferred Tax Liabilities | B47: 0 | C47: 227.79 | D47: 468.9 | E47: 581.89 | F47: 612.88 | G47: 472.58 | H47: 452.74 | I47: 378.21 | K47: Deferred Tax Liabilities | L47: =B47/$B47 -> #DIV/0! | M47: =C47/$B47 -> #DIV/0! | N47: =D47/$B47 -> #DIV/0! | O47: =E47/$B47 -> #DIV/0! | P47: =F47/$B47 -> #DIV/0! | Q47: =G47/$B47 -> #DIV/0! | R47: =H47/$B47 -> #DIV/0! | S47: =I47/$B47 -> #DIV/0!
A48: Other Non-Current Liabilities | B48: 97.58 | C48: 119.53 | D48: 75.62 | E48: 119.18 | F48: 120.94 | G48: 123.9 | H48: 321.61 | I48: 0 | K48: Other Non-Current Liabilities | L48: =B48/$B48 -> 1 | M48: =C48/$B48 -> 1.2249436 | N48: =D48/$B48 -> 0.77495388 | O48: =E48/$B48 -> 1.2213568 | P48: =F48/$B48 -> 1.2393933 | Q48: =G48/$B48 -> 1.2697274 | R48: =H48/$B48 -> 3.2958598 | S48: =I48/$B48 -> 0
A49: Total Non-Current Liabilities | B49: =SUM(B43:B48) -> 109.58 | C49: =SUM(C43:C48) -> 493.3 | D49: =SUM(D43:D48) -> 752.42 | E49: =SUM(E43:E48) -> 850.7 | F49: =SUM(F43:F48) -> 858.66 | G49: =SUM(G43:G48) -> 848.12 | H49: =SUM(H43:H48) -> 1031.95 | I49: =SUM(I43:I48) -> 966.06 | K49: Total Non-Current Liabilities | L49: =B49/$B49 -> 1 | M49: =C49/$B49 -> 4.5017339 | N49: =D49/$B49 -> 6.866399 | O49: =E49/$B49 -> 7.763278 | P49: =F49/$B49 -> 7.835919 | Q49: =G49/$B49 -> 7.7397335 | R49: =H49/$B49 -> 9.4173207 | S49: =I49/$B49 -> 8.8160248
A51: Current Liabilities | K51: Current Liabilities
A52: Short Term Borrowings | B52: 88 | C52: 84.06 | D52: 40.08 | E52: 75.37 | F52: 183.68 | G52: 165.88 | H52: 285.16 | I52: 317.31 | K52: Short Term Borrowings | L52: =B52/$B52 -> 1 | M52: =C52/$B52 -> 0.95522727 | N52: =D52/$B52 -> 0.45545455 | O52: =E52/$B52 -> 0.85647727 | P52: =F52/$B52 -> 2.0872727 | Q52: =G52/$B52 -> 1.885 | R52: =H52/$B52 -> 3.2404545 | S52: =I52/$B52 -> 3.6057955
A53: Lease Liabilities | B53: 0 | C53: 0 | D53: 0 | E53: 0 | F53: 0 | G53: 33.46 | H53: 29.57 | I53: 36.18 | K53: Lease Liabilities | L53: =B53/$B53 -> #DIV/0! | M53: =C53/$B53 -> #DIV/0! | N53: =D53/$B53 -> #DIV/0! | O53: =E53/$B53 -> #DIV/0! | P53: =F53/$B53 -> #DIV/0! | Q53: =G53/$B53 -> #DIV/0! | R53: =H53/$B53 -> #DIV/0! | S53: =I53/$B53 -> #DIV/0!
A54: Trade Payables | B54: 2713.09 | C54: 2791.7 | D54: 3266.2 | E54: 3375.26 | F54: 3438.24 | G54: 3127.62 | H54: 5264.18 | I54: 4343.09 | K54: Trade Payables | L54: =B54/$B54 -> 1 | M54: =C54/$B54 -> 1.0289743 | N54: =D54/$B54 -> 1.2038672 | O54: =E54/$B54 -> 1.2440649 | P54: =F54/$B54 -> 1.2672783 | Q54: =G54/$B54 -> 1.1527889 | R54: =H54/$B54 -> 1.9402895 | S54: =I54/$B54 -> 1.600791
A55: Other Financial Liabilities | B55: 0 | C55: 0 | D55: 358.58 | E55: 202.6 | F55: 223.84 | G55: 258.69 | H55: 167.52 | I55: 145.58 | K55: Other Financial Liabilities | L55: =B55/$B55 -> #DIV/0! | M55: =C55/$B55 -> #DIV/0! | N55: =D55/$B55 -> #DIV/0! | O55: =E55/$B55 -> #DIV/0! | P55: =F55/$B55 -> #DIV/0! | Q55: =G55/$B55 -> #DIV/0! | R55: =H55/$B55 -> #DIV/0! | S55: =I55/$B55 -> #DIV/0!
A56: - Current Maturities' of LTB | B56: 0 | C56: 0 | D56: 12.63 | E56: 2.89 | F56: 2.89 | G56: 2.27 | H56: 11.69 | I56: 0 | K56: - Current Maturities' of LTB | L56: =B56/$B56 -> #DIV/0! | M56: =C56/$B56 -> #DIV/0! | N56: =D56/$B56 -> #DIV/0! | O56: =E56/$B56 -> #DIV/0! | P56: =F56/$B56 -> #DIV/0! | Q56: =G56/$B56 -> #DIV/0! | R56: =H56/$B56 -> #DIV/0! | S56: =I56/$B56 -> #DIV/0!
A57: Other Current Liabilities | B57: 1185.14 | C57: 1296.34 | D57: 499.2 | E57: 825.24 | F57: 560.53 | G57: 691.15 | H57: 746.41 | I57: 496.32 | K57: Other Current Liabilities | L57: =B57/$B57 -> 1 | M57: =C57/$B57 -> 1.0938286 | N57: =D57/$B57 -> 0.42121606 | O57: =E57/$B57 -> 0.6963228 | P57: =F57/$B57 -> 0.47296522 | Q57: =G57/$B57 -> 0.58318005 | R57: =H57/$B57 -> 0.62980745 | S57: =I57/$B57 -> 0.41878597
A58: Provisions | B58: 0 | C58: 0 | D58: 0 | E58: 0 | F58: 0 | G58: 0 | H58: 0 | I58: 179.15 | K58: Provisions | L58: =B58/$B58 -> #DIV/0! | M58: =C58/$B58 -> #DIV/0! | N58: =D58/$B58 -> #DIV/0! | O58: =E58/$B58 -> #DIV/0! | P58: =F58/$B58 -> #DIV/0! | Q58: =G58/$B58 -> #DIV/0! | R58: =H58/$B58 -> #DIV/0! | S58: =I58/$B58 -> #DIV/0!
A59: Total Current Liabilities | B59: =SUM(B52:B58) -> 3986.23 | C59: =SUM(C52:C58) -> 4172.1 | D59: =SUM(D52:D58) -> 4176.69 | E59: =SUM(E52:E58) -> 4481.36 | F59: =SUM(F52:F58) -> 4409.18 | G59: =SUM(G52:G58) -> 4279.07 | H59: =SUM(H52:H58) -> 6504.53 | I59: =SUM(I52:I58) -> 5517.63 | K59: Total Current Liabilities | L59: =B59/$B59 -> 1 | M59: =C59/$B59 -> 1.046628 | N59: =D59/$B59 -> 1.0477795 | O59: =E59/$B59 -> 1.1242101 | P59: =F59/$B59 -> 1.1061028 | Q59: =G59/$B59 -> 1.0734629 | R59: =H59/$B59 -> 1.6317498 | S59: =I59/$B59 -> 1.3841725
A60: TOTAL EQUITIES & LIABILITIES | B60: =SUM(B39+B40+B49+B59) -> 10654.35 | C60: =SUM(C39+C40+C49+C59) -> 12671.7 | D60: =SUM(D39+D40+D49+D59) -> 15312 | E60: =SUM(E39+E40+E49+E59) -> 17396.73 | F60: =SUM(F39+F40+F49+F59) -> 18504.36 | G60: =SUM(G39+G40+G49+G59) -> 19674.07 | H60: =SUM(H39+H40+H49+H59) -> 23096.09 | I60: =SUM(I39+I40+I49+I59) -> 22478.39 | K60: TOTAL EQUITIES & LIABILITIES | L60: =B60/$B60 -> 1 | M60: =C60/$B60 -> 1.1893452 | N60: =D60/$B60 -> 1.4371595 | O60: =E60/$B60 -> 1.6328288 | P60: =F60/$B60 -> 1.7367892 | Q60: =G60/$B60 -> 1.8465763 | R60: =H60/$B60 -> 2.1677615 | S60: =I60/$B60 -> 2.1097852
A61: Assets | K61: Assets | L61: =B61/$B61 -> #DIV/0! | M61: =C61/$B61 -> #DIV/0! | N61: =D61/$B61 -> #DIV/0! | O61: =E61/$B61 -> #DIV/0! | P61: =F61/$B61 -> #DIV/0! | Q61: =G61/$B61 -> #DIV/0! | R61: =H61/$B61 -> #DIV/0! | S61: =I61/$B61 -> #DIV/0!
A62: Non-Current Assets | K62: Non-Current Assets | L62: =B62/$B62 -> #DIV/0! | M62: =C62/$B62 -> #DIV/0! | N62: =D62/$B62 -> #DIV/0! | O62: =E62/$B62 -> #DIV/0! | P62: =F62/$B62 -> #DIV/0! | Q62: =G62/$B62 -> #DIV/0! | R62: =H62/$B62 -> #DIV/0! | S62: =I62/$B62 -> #DIV/0!
A63: Property, Plant & Equipment | B63: 2850.86 | C63: 3907.02 | D63: 4495.03 | E63: 4771.39 | F63: 4792.5 | G63: 5786.24 | H63: 5550.67 | I63: 5354.34 | K63: Property, Plant & Equipment | L63: =B63/$B63 -> 1 | M63: =C63/$B63 -> 1.3704707 | N63: =D63/$B63 -> 1.5767277 | O63: =E63/$B63 -> 1.6736669 | P63: =F63/$B63 -> 1.6810717 | Q63: =G63/$B63 -> 2.0296472 | R63: =H63/$B63 -> 1.947016 | S63: =I63/$B63 -> 1.878149
A64: Intangible Assets | B64: 101.42 | C64: 129.07 | D64: 386.5 | E64: 239.02 | F64: 384.85 | G64: 686.69 | H64: 829.72 | I64: 0 | K64: Intangible Assets | L64: =B64/$B64 -> 1 | M64: =C64/$B64 -> 1.2726287 | N64: =D64/$B64 -> 3.8108854 | O64: =E64/$B64 -> 2.3567344 | P64: =F64/$B64 -> 3.7946164 | Q64: =G64/$B64 -> 6.7707553 | R64: =H64/$B64 -> 8.1810294 | S64: =I64/$B64 -> 0
A65: Capital-Work in Progress | B65: 315.12 | C65: 330.78 | D65: 103.82 | E65: 189.57 | F65: 159.86 | G65: 204.64 | H65: 236.4 | I65: 149.13 | K65: Capital-Work in Progress | L65: =B65/$B65 -> 1 | M65: =C65/$B65 -> 1.0496954 | N65: =D65/$B65 -> 0.32946179 | O65: =E65/$B65 -> 0.60158035 | P65: =F65/$B65 -> 0.50729881 | Q65: =G65/$B65 -> 0.6494034 | R65: =H65/$B65 -> 0.7501904 | S65: =I65/$B65 -> 0.47324829
A66: Right of use of assets | B66: 0 | C66: 0 | D66: 0 | E66: 0 | F66: 0 | G66: 0 | H66: 0 | I66: 517.9 | K66: Right of use of assets | L66: =B66/$B66 -> #DIV/0! | M66: =C66/$B66 -> #DIV/0! | N66: =D66/$B66 -> #DIV/0! | O66: =E66/$B66 -> #DIV/0! | P66: =F66/$B66 -> #DIV/0! | Q66: =G66/$B66 -> #DIV/0! | R66: =H66/$B66 -> #DIV/0! | S66: =I66/$B66 -> #DIV/0!
A67: Other Intangible assets | B67: 0 | C67: 0 | D67: 0 | E67: 0 | F67: 0 | G67: 0 | H67: 0 | I67: 321.3 | K67: Other Intangible assets | L67: =B67/$B67 -> #DIV/0! | M67: =C67/$B67 -> #DIV/0! | N67: =D67/$B67 -> #DIV/0! | O67: =E67/$B67 -> #DIV/0! | P67: =F67/$B67 -> #DIV/0! | Q67: =G67/$B67 -> #DIV/0! | R67: =H67/$B67 -> #DIV/0! | S67: =I67/$B67 -> #DIV/0!
A68: Intangible Assets under Development | B68: 404.08 | C68: 322.59 | D68: 194.46 | E68: 116.46 | F68: 187.97 | G68: 186.69 | H68: 258.73 | I68: 368.09 | K68: Intangible Assets under Development | L68: =B68/$B68 -> 1 | M68: =C68/$B68 -> 0.79833201 | N68: =D68/$B68 -> 0.48124134 | O68: =E68/$B68 -> 0.28821026 | P68: =F68/$B68 -> 0.46518016 | Q68: =G68/$B68 -> 0.46201247 | R68: =H68/$B68 -> 0.640294 | S68: =I68/$B68 -> 0.91093348
A69: Equity accounted investments in associates | B69: 0 | C69: 0 | D69: 0 | E69: 0 | F69: 0 | G69: 0 | H69: 0 | I69: 2202.51 | K69: Equity accounted investments in associates | L69: =B69/$B69 -> #DIV/0! | M69: =C69/$B69 -> #DIV/0! | N69: =D69/$B69 -> #DIV/0! | O69: =E69/$B69 -> #DIV/0! | P69: =F69/$B69 -> #DIV/0! | Q69: =G69/$B69 -> #DIV/0! | R69: =H69/$B69 -> #DIV/0! | S69: =I69/$B69 -> #DIV/0!
A70: Investment | B70: 821.15 | C70: 945.26 | D70: 1025.37 | E70: 1159.63 | F70: 1705.89 | G70: 2098.34 | H70: 2407.69 | I70: 2455.05 | K70: Investment | L70: =B70/$B70 -> 1 | M70: =C70/$B70 -> 1.1511417 | N70: =D70/$B70 -> 1.2487 | O70: =E70/$B70 -> 1.4122024 | P70: =F70/$B70 -> 2.0774402 | Q70: =G70/$B70 -> 2.5553675 | R70: =H70/$B70 -> 2.9320952 | S70: =I70/$B70 -> 2.9897704
A71: Financial Assets | B71: 721.81 | C71: 876.39 | D71: 545.46 | E71: 964.34 | F71: 1328 | G71: 1618.86 | H71: 2001.28 | I71: 59.44 | K71: Financial Assets | L71: =B71/$B71 -> 1 | M71: =C71/$B71 -> 1.2141561 | N71: =D71/$B71 -> 0.75568363 | O71: =E71/$B71 -> 1.3360025 | P71: =F71/$B71 -> 1.8398193 | Q71: =G71/$B71 -> 2.2427786 | R71: =H71/$B71 -> 2.7725856 | S71: =I71/$B71 -> 0.08234854
A72: Income tax assets | B72: 0 | C72: 0 | D72: 0 | E72: 0 | F72: 0 | G72: 0 | H72: 0 | I72: 358.07 | K72: Income tax assets | L72: =B72/$B72 -> #DIV/0! | M72: =C72/$B72 -> #DIV/0! | N72: =D72/$B72 -> #DIV/0! | O72: =E72/$B72 -> #DIV/0! | P72: =F72/$B72 -> #DIV/0! | Q72: =G72/$B72 -> #DIV/0! | R72: =H72/$B72 -> #DIV/0! | S72: =I72/$B72 -> #DIV/0!
A73: Other Non-Current Assets | B73: 60.19 | C73: 73.68 | D73: 990.85 | E73: 954.09 | F73: 1532.08 | G73: 443.41 | H73: 441.17 | I73: 120.34 | K73: Other Non-Current Assets | L73: =B73/$B73 -> 1 | M73: =C73/$B73 -> 1.2241236 | N73: =D73/$B73 -> 16.462037 | O73: =E73/$B73 -> 15.851304 | P73: =F73/$B73 -> 25.454062 | Q73: =G73/$B73 -> 7.3668383 | R73: =H73/$B73 -> 7.3296229 | S73: =I73/$B73 -> 1.9993354
A74: Total Non-Current Assets | B74: =SUM(B63:B73) -> 5274.63 | C74: =SUM(C63:C73) -> 6584.79 | D74: =SUM(D63:D73) -> 7741.49 | E74: =SUM(E63:E73) -> 8394.5 | F74: =SUM(F63:F73) -> 10091.15 | G74: =SUM(G63:G73) -> 11024.87 | H74: =SUM(H63:H73) -> 11725.66 | I74: =SUM(I63:I73) -> 11906.17 | K74: Total Non-Current Assets | L74: =B74/$B74 -> 1 | M74: =C74/$B74 -> 1.248389 | N74: =D74/$B74 -> 1.467684 | O74: =E74/$B74 -> 1.591486 | P74: =F74/$B74 -> 1.9131484 | Q74: =G74/$B74 -> 2.0901694 | R74: =H74/$B74 -> 2.2230299 | S74: =I74/$B74 -> 2.2572522
A76: Current Assets | K76: Current Assets
A77: Current Investments | B77: 2297.35 | C77: 3249.15 | D77: 4544.06 | E77: 5591.12 | F77: 3173.88 | G77: 4709.12 | H77: 6225.34 | I77: 5870.31 | K77: Current Investments | L77: =B77/$B77 -> 1 | M77: =C77/$B77 -> 1.4143034 | N77: =D77/$B77 -> 1.9779572 | O77: =E77/$B77 -> 2.4337258 | P77: =F77/$B77 -> 1.3815396 | Q77: =G77/$B77 -> 2.0498052 | R77: =H77/$B77 -> 2.7097917 | S77: =I77/$B77 -> 2.5552528
A78: Inventories | B78: 861.39 | C78: 761.99 | D78: 708.58 | E78: 962.68 | F78: 1249.53 | G78: 1282.32 | H78: 1789.27 | I78: 1472.41 | K78: Inventories | L78: =B78/$B78 -> 1 | M78: =C78/$B78 -> 0.88460511 | N78: =D78/$B78 -> 0.82260068 | O78: =E78/$B78 -> 1.117589 | P78: =F78/$B78 -> 1.4505973 | Q78: =G78/$B78 -> 1.4886637 | R78: =H78/$B78 -> 2.0771892 | S78: =I78/$B78 -> 1.7093419
A79: Trade Receivables | B79: 1371.82 | C79: 1282.08 | D79: 1551.75 | E79: 1426.97 | F79: 2745.11 | G79: 1511.91 | H79: 2274.68 | I79: 2158.49 | K79: Trade Receivables | L79: =B79/$B79 -> 1 | M79: =C79/$B79 -> 0.93458325 | N79: =D79/$B79 -> 1.1311615 | O79: =E79/$B79 -> 1.0402021 | P79: =F79/$B79 -> 2.0010716 | Q79: =G79/$B79 -> 1.1021198 | R79: =H79/$B79 -> 1.6581476 | S79: =I79/$B79 -> 1.5734499
A80: Cash, Bank & Cash Equivalents | B80: 215.78 | C80: 179.09 | D80: 195.39 | E80: 237.57 | F80: 303.88 | G80: 435.43 | H80: 396.24 | I80: 299.74 | K80: Cash, Bank & Cash Equivalents | L80: =B80/$B80 -> 1 | M80: =C80/$B80 -> 0.82996571 | N80: =D80/$B80 -> 0.90550561 | O80: =E80/$B80 -> 1.1009825 | P80: =F80/$B80 -> 1.4082862 | Q80: =G80/$B80 -> 2.0179349 | R80: =H80/$B80 -> 1.8363148 | S80: =I80/$B80 -> 1.3891
A81: Loans | B81: 0 | C81: 0 | D81: 0 | E81: 0 | F81: 0 | G81: 0 | H81: 0 | I81: 22.81 | K81: Loans | L81: =B81/$B81 -> #DIV/0! | M81: =C81/$B81 -> #DIV/0! | N81: =D81/$B81 -> #DIV/0! | O81: =E81/$B81 -> #DIV/0! | P81: =F81/$B81 -> #DIV/0! | Q81: =G81/$B81 -> #DIV/0! | R81: =H81/$B81 -> #DIV/0! | S81: =I81/$B81 -> #DIV/0!
A82: Other Financial Assets | B82: 0 | C82: 0 | D82: 0 | E82: 0 | F82: 0 | G82: 0 | H82: 0 | I82: 475 | K82: Other Financial Assets | L82: =B82/$B82 -> #DIV/0! | M82: =C82/$B82 -> #DIV/0! | N82: =D82/$B82 -> #DIV/0! | O82: =E82/$B82 -> #DIV/0! | P82: =F82/$B82 -> #DIV/0! | Q82: =G82/$B82 -> #DIV/0! | R82: =H82/$B82 -> #DIV/0! | S82: =I82/$B82 -> #DIV/0!
A83: Other Current Assets | B83: 633.38 | C83: 614.6 | D83: 570.73 | E83: 783.89 | F83: 940.79 | G83: 710.44 | H83: 684.95 | I83: 273.46 | K83: Other Current Assets | L83: =B83/$B83 -> 1 | M83: =C83/$B83 -> 0.97034955 | N83: =D83/$B83 -> 0.90108624 | O83: =E83/$B83 -> 1.2376299 | P83: =F83/$B83 -> 1.4853484 | Q83: =G83/$B83 -> 1.1216647 | R83: =H83/$B83 -> 1.0814203 | S83: =I83/$B83 -> 0.43174713
A84: Total Current Assets | B84: =SUM(B77:B83) -> 5379.72 | C84: =SUM(C77:C83) -> 6086.91 | D84: =SUM(D77:D83) -> 7570.51 | E84: =SUM(E77:E83) -> 9002.23 | F84: =SUM(F77:F83) -> 8413.19 | G84: =SUM(G77:G83) -> 8649.22 | H84: =SUM(H77:H83) -> 11370.48 | I84: =SUM(I77:I83) -> 10572.22 | K84: Total Current Assets | L84: =B84/$B84 -> 1 | M84: =C84/$B84 -> 1.1314548 | N84: =D84/$B84 -> 1.4072312 | O84: =E84/$B84 -> 1.673364 | P84: =F84/$B84 -> 1.5638714 | Q84: =G84/$B84 -> 1.6077454 | R84: =H84/$B84 -> 2.1135821 | S84: =I84/$B84 -> 1.9651989
A85: TOTAL ASSETS | B85: =SUM(B74,B84) -> 10654.35 | C85: =SUM(C74,C84) -> 12671.7 | D85: =SUM(D74,D84) -> 15312 | E85: =SUM(E74,E84) -> 17396.73 | F85: =SUM(F74,F84) -> 18504.34 | G85: =SUM(G74,G84) -> 19674.09 | H85: =SUM(H74,H84) -> 23096.14 | I85: =SUM(I74,I84) -> 22478.39 | K85: TOTAL ASSETS | L85: =B85/$B85 -> 1 | M85: =C85/$B85 -> 1.1893452 | N85: =D85/$B85 -> 1.4371595 | O85: =E85/$B85 -> 1.6328288 | P85: =F85/$B85 -> 1.7367873 | Q85: =G85/$B85 -> 1.8465782 | R85: =H85/$B85 -> 2.1677662 | S85: =I85/$B85 -> 2.1097852
E87: =105*20 -> 2100
A89: Avg. receivables | B89: =B79 -> 1371.82 | C89: =(B79+C79)/2 -> 1326.95 | D89: =(C79+D79)/2 -> 1416.915 | E89: =(D79+E79)/2 -> 1489.36 | F89: =(E79+F79)/2 -> 2086.04 | G89: =(F79+G79)/2 -> 2128.51 | H89: =(G79+H79)/2 -> 1893.295 | I89: =(H79+I79)/2 -> 2216.585
A90: Avg. inventory | B90: =B78 -> 861.39 | C90: =(B78+C78)/2 -> 811.69 | D90: =(C78+D78)/2 -> 735.285 | E90: =(D78+E78)/2 -> 835.63 | F90: =(E78+F78)/2 -> 1106.105 | G90: =(F78+G78)/2 -> 1265.925 | H90: =(G78+H78)/2 -> 1535.795 | I90: =(H78+I78)/2 -> 1630.84
A91: Avg. payables | B91: =B54 -> 2713.09 | C91: =(C54+B54)/2 -> 2752.395 | D91: =(D54+C54)/2 -> 3028.95 | E91: =(E54+D54)/2 -> 3320.73 | F91: =(F54+E54)/2 -> 3406.75 | G91: =(G54+F54)/2 -> 3282.93 | H91: =(H54+G54)/2 -> 4195.9 | I91: =(I54+H54)/2 -> 4803.635
A92: Avg. Total assets | B92: =B85 -> 10654.35 | C92: =(B85+C85)/2 -> 11663.025 | D92: =(C85+D85)/2 -> 13991.85 | E92: =(D85+E85)/2 -> 16354.365 | F92: =(E85+F85)/2 -> 17950.535 | G92: =(F85+G85)/2 -> 19089.215 | H92: =(G85+H85)/2 -> 21385.115 | I92: =(H85+I85)/2 -> 22787.265
A93: Working Capital | B93: =B84-B59 -> 1393.49 | C93: =C84-C59 -> 1914.81 | D93: =D84-D59 -> 3393.82 | E93: =E84-E59 -> 4520.87 | F93: =F84-F59 -> 4004.01 | G93: =G84-G59 -> 4370.15 | H93: =H84-H59 -> 4865.95 | I93: =I84-I59 -> 5054.59
A94: Avg. Working Capital | B94: =B93 -> 1393.49 | C94: =(B93+C93)/2 -> 1654.15 | D94: =(C93+D93)/2 -> 2654.315 | E94: =(D93+E93)/2 -> 3957.345 | F94: =(E93+F93)/2 -> 4262.44 | G94: =(F93+G93)/2 -> 4187.08 | H94: =(G93+H93)/2 -> 4618.05 | I94: =(H93+I93)/2 -> 4960.27
A95: Avg. Shareholder's Equity | B95: =B39 -> 6540 | C95: =(B39+C39)/2 -> 7246.34 | D95: =(C39+D39)/2 -> 9134.095 | E95: =(D39+E39)/2 -> 11143.485 | F95: =(E39+F39)/2 -> 12545.935 | G95: =(F39+G39)/2 -> 13763.345 | H95: =(G39+H39)/2 -> 14911.35 | I95: =(H39+I39)/2 -> 15631.535
A97: Ratios
A98: Liquidity Measures | B98: 42094 | C98: 42460 | D98: 42825 | E98: 43190 | F98: 43555 | G98: 43921 | H98: 44286 | I98: 44651
A99: Current Ratio (CA/CL)
A100: Quick Ratio (CA-Invent.-Prepaid Exp/CL)
A101: Cash Ratio (Cash and equivalents/CL)
A103: Leverage Measures | B103: 42094 | C103: 42460 | D103: 42825 | E103: 43190 | F103: 43555 | G103: 43921 | H103: 44286 | I103: 44651
A104: Total Debt to Total Assets [(CL+LTD+OL)/Avg. TA]
A105: Long term Debt to Equity Ratio (LTD+OL)/Avg. SE)
A106: Total Debt to Equity Ratio [(CL+LTD+OL)/Avg. SE]
A108: Interest Coverage Measures | B108: 42094 | C108: 42460 | D108: 42825 | E108: 43190 | F108: 43555 | G108: 43921 | H108: 44286 | I108: 44651
A109: Cash coverage (Cash from Operations/Int. Exp.)
A110: Interest coverage (EBIT/Interest Exp.)
A112: Activity Ratios | B112: 42094 | C112: 42460 | D112: 42825 | E112: 43190 | F112: 43555 | G112: 43921 | H112: 44286 | I112: 44651
A113: Inventory Turnover [COGS (RM+Excise duty)]/Avg. Inventory)
A114: Receivables Turnover (Sales / Avg. Receivables)
A115: Payable Turnover (RM+Excise Duty) / Avg. Ac Payables)
...

Sheet Common Size FS
A2: Common Size statement
A4: Income Statement
A5: Particulars | B5: 42094 | C5: 42460 | D5: 42825 | E5: 43190 | F5: 43555 | G5: 43921 | H5: 44286 | I5: 44651
A6: Revenue from Operations | B6: ='FS & Trend Analysis'!B6/'FS & Trend Analysis'!B$6 -> 1 | C6: ='FS & Trend Analysis'!C6/'FS & Trend Analysis'!C$6 -> 1 | D6: ='FS & Trend Analysis'!D6/'FS & Trend Analysis'!D$6 -> 1 | E6: ='FS & Trend Analysis'!E6/'FS & Trend Analysis'!E$6 -> 1 | F6: ='FS & Trend Analysis'!F6/'FS & Trend Analysis'!F$6 -> 1 | G6: ='FS & Trend Analysis'!G6/'FS & Trend Analysis'!G$6 -> 1 | H6: ='FS & Trend Analysis'!H6/'FS & Trend Analysis'!H$6 -> 1 | I6: ='FS & Trend Analysis'!I6/'FS & Trend Analysis'!I$6 -> 1
A7: Other Income | B7: ='FS & Trend Analysis'!B7/'FS & Trend Analysis'!B$6 -> 0.016821007 | C7: ='FS & Trend Analysis'!C7/'FS & Trend Analysis'!C$6 -> 0.01260303 | D7: ='FS & Trend Analysis'!D7/'FS & Trend Analysis'!D$6 -> 0.016845976 | E7: ='FS & Trend Analysis'!E7/'FS & Trend Analysis'!E$6 -> 0.015805291 | F7: ='FS & Trend Analysis'!F7/'FS & Trend Analysis'!F$6 -> 0.020214452 | G7: ='FS & Trend Analysis'!G7/'FS & Trend Analysis'!G$6 -> 0.024971868 | H7: ='FS & Trend Analysis'!H7/'FS & Trend Analysis'!H$6 -> 0.018020497 | I7: ='FS & Trend Analysis'!I7/'FS & Trend Analysis'!I$6 -> 0.018781251
A8: Total Income | B8: ='FS & Trend Analysis'!B8/'FS & Trend Analysis'!B$6 -> 1.016821 | C8: ='FS & Trend Analysis'!C8/'FS & Trend Analysis'!C$6 -> 1.012603 | D8: ='FS & Trend Analysis'!D8/'FS & Trend Analysis'!D$6 -> 1.016846 | E8: ='FS & Trend Analysis'!E8/'FS & Trend Analysis'!E$6 -> 1.0158053 | F8: ='FS & Trend Analysis'!F8/'FS & Trend Analysis'!F$6 -> 1.0202145 | G8: ='FS & Trend Analysis'!G8/'FS & Trend Analysis'!G$6 -> 1.0249719 | H8: ='FS & Trend Analysis'!H8/'FS & Trend Analysis'!H$6 -> 1.0180205 | I8: ='FS & Trend Analysis'!I8/'FS & Trend Analysis'!I$6 -> 1.0187813
A10: Expenses
A11: Raw Material | B11: ='FS & Trend Analysis'!B11/'FS & Trend Analysis'!B$6 -> 0.67389649 | C11: ='FS & Trend Analysis'!C11/'FS & Trend Analysis'!C$6 -> 0.62558913 | D11: ='FS & Trend Analysis'!D11/'FS & Trend Analysis'!D$6 -> 0.61697295 | E11: ='FS & Trend Analysis'!E11/'FS & Trend Analysis'!E$6 -> 0.66118424 | F11: ='FS & Trend Analysis'!F11/'FS & Trend Analysis'!F$6 -> 0.69010542 | G11: ='FS & Trend Analysis'!G11/'FS & Trend Analysis'!G$6 -> 0.67785791 | H11: ='FS & Trend Analysis'!H11/'FS & Trend Analysis'!H$6 -> 0.70233136 | I11: ='FS & Trend Analysis'!I11/'FS & Trend Analysis'!I$6 -> 0.70793414
A12: Excise Duty | B12: ='FS & Trend Analysis'!B12/'FS & Trend Analysis'!B$6 -> 0.058711676 | C12: ='FS & Trend Analysis'!C12/'FS & Trend Analysis'!C$6 -> 0.073147654 | D12: ='FS & Trend Analysis'!D12/'FS & Trend Analysis'!D$6 -> 0.07659618 | E12: ='FS & Trend Analysis'!E12/'FS & Trend Analysis'!E$6 -> 0.01941244 | F12: ='FS & Trend Analysis'!F12/'FS & Trend Analysis'!F$6 -> 4.1504488e-05 | G12: ='FS & Trend Analysis'!G12/'FS & Trend Analysis'!G$6 -> 4.6145453e-05 | H12: ='FS & Trend Analysis'!H12/'FS & Trend Analysis'!H$6 -> 0 | I12: ='FS & Trend Analysis'!I12/'FS & Trend Analysis'!I$6 -> 0
A13: Employee Costs | B13: ='FS & Trend Analysis'!B13/'FS & Trend Analysis'!B$6 -> 0.040290296 | C13: ='FS & Trend Analysis'!C13/'FS & Trend Analysis'!C$6 -> 0.043504231 | D13: ='FS & Trend Analysis'!D13/'FS & Trend Analysis'!D$6 -> 0.046233724 | E13: ='FS & Trend Analysis'!E13/'FS & Trend Analysis'!E$6 -> 0.047844865 | F13: ='FS & Trend Analysis'!F13/'FS & Trend Analysis'!F$6 -> 0.052337748 | G13: ='FS & Trend Analysis'!G13/'FS & Trend Analysis'!G$6 -> 0.064580391 | H13: ='FS & Trend Analysis'!H13/'FS & Trend Analysis'!H$6 -> 0.063019091 | I13: ='FS & Trend Analysis'!I13/'FS & Trend Analysis'!I$6 -> 0.067536161
A14: Other Expenses | B14: ='FS & Trend Analysis'!B14/'FS & Trend Analysis'!B$6 -> 0.1125255 | C14: ='FS & Trend Analysis'!C14/'FS & Trend Analysis'!C$6 -> 0.1158097 | D14: ='FS & Trend Analysis'!D14/'FS & Trend Analysis'!D$6 -> 0.11250737 | E14: ='FS & Trend Analysis'!E14/'FS & Trend Analysis'!E$6 -> 0.11068538 | F14: ='FS & Trend Analysis'!F14/'FS & Trend Analysis'!F$6 -> 0.10979379 | G14: ='FS & Trend Analysis'!G14/'FS & Trend Analysis'!G$6 -> 0.11870593 | H14: ='FS & Trend Analysis'!H14/'FS & Trend Analysis'!H$6 -> 0.10223297 | I14: ='FS & Trend Analysis'!I14/'FS & Trend Analysis'!I$6 -> 0.10796047
A15: Total Expenses | B15: ='FS & Trend Analysis'!B15/'FS & Trend Analysis'!B$6 -> 0.88542396 | C15: ='FS & Trend Analysis'!C15/'FS & Trend Analysis'!C$6 -> 0.85805071 | D15: ='FS & Trend Analysis'!D15/'FS & Trend Analysis'!D$6 -> 0.85231022 | E15: ='FS & Trend Analysis'!E15/'FS & Trend Analysis'!E$6 -> 0.83912693 | F15: ='FS & Trend Analysis'!F15/'FS & Trend Analysis'!F$6 -> 0.85227846 | G15: ='FS & Trend Analysis'!G15/'FS & Trend Analysis'!G$6 -> 0.86119037 | H15: ='FS & Trend Analysis'!H15/'FS & Trend Analysis'!H$6 -> 0.86758342 | I15: ='FS & Trend Analysis'!I15/'FS & Trend Analysis'!I$6 -> 0.88343077
A17: EBITDA | B17: ='FS & Trend Analysis'!B17/'FS & Trend Analysis'!B$6 -> 0.13139705 | C17: ='FS & Trend Analysis'!C17/'FS & Trend Analysis'!C$6 -> 0.15455232 | D17: ='FS & Trend Analysis'!D17/'FS & Trend Analysis'!D$6 -> 0.16453576 | E17: ='FS & Trend Analysis'!E17/'FS & Trend Analysis'!E$6 -> 0.17667837 | F17: ='FS & Trend Analysis'!F17/'FS & Trend Analysis'!F$6 -> 0.16793599 | G17: ='FS & Trend Analysis'!G17/'FS & Trend Analysis'!G$6 -> 0.16378149 | H17: ='FS & Trend Analysis'!H17/'FS & Trend Analysis'!H$6 -> 0.15043708 | I17: ='FS & Trend Analysis'!I17/'FS & Trend Analysis'!I$6 -> 0.13535048
A18: Depreciation & Amortization | B18: ='FS & Trend Analysis'!B18/'FS & Trend Analysis'!B$6 -> 0.018473336 | C18: ='FS & Trend Analysis'!C18/'FS & Trend Analysis'!C$6 -> 0.014479492 | D18: ='FS & Trend Analysis'!D18/'FS & Trend Analysis'!D$6 -> 0.016210157 | E18: ='FS & Trend Analysis'!E18/'FS & Trend Analysis'!E$6 -> 0.017370504 | F18: ='FS & Trend Analysis'!F18/'FS & Trend Analysis'!F$6 -> 0.018380895 | G18: ='FS & Trend Analysis'!G18/'FS & Trend Analysis'!G$6 -> 0.028909614 | H18: ='FS & Trend Analysis'!H18/'FS & Trend Analysis'!H$6 -> 0.023098796 | I18: ='FS & Trend Analysis'!I18/'FS & Trend Analysis'!I$6 -> 0.023332999
A19: EBIT | B19: ='FS & Trend Analysis'!B19/'FS & Trend Analysis'!B$6 -> 0.11292371 | C19: ='FS & Trend Analysis'!C19/'FS & Trend Analysis'!C$6 -> 0.14007283 | D19: ='FS & Trend Analysis'!D19/'FS & Trend Analysis'!D$6 -> 0.1483256 | E19: ='FS & Trend Analysis'!E19/'FS & Trend Analysis'!E$6 -> 0.15930786 | F19: ='FS & Trend Analysis'!F19/'FS & Trend Analysis'!F$6 -> 0.14955509 | G19: ='FS & Trend Analysis'!G19/'FS & Trend Analysis'!G$6 -> 0.13487188 | H19: ='FS & Trend Analysis'!H19/'FS & Trend Analysis'!H$6 -> 0.12733828 | I19: ='FS & Trend Analysis'!I19/'FS & Trend Analysis'!I$6 -> 0.11201748
A20: Finance Expenses | B20: ='FS & Trend Analysis'!B20/'FS & Trend Analysis'!B$6 -> 0.00039992234 | C20: ='FS & Trend Analysis'!C20/'FS & Trend Analysis'!C$6 -> 0.00038449155 | D20: ='FS & Trend Analysis'!D20/'FS & Trend Analysis'!D$6 -> 0.00088046409 | E20: ='FS & Trend Analysis'!E20/'FS & Trend Analysis'!E$6 -> 0.00093048717 | F20: ='FS & Trend Analysis'!F20/'FS & Trend Analysis'!F$6 -> 0.0010944233 | G20: ='FS & Trend Analysis'!G20/'FS & Trend Analysis'!G$6 -> 0.00159424 | H20: ='FS & Trend Analysis'!H20/'FS & Trend Analysis'!H$6 -> 0.0014990702 | I20: ='FS & Trend Analysis'!I20/'FS & Trend Analysis'!I$6 -> 0.0017968765
A21: PBT before profits of JVs | B21: ='FS & Trend Analysis'!B21/'FS & Trend Analysis'!B$6 -> 0.11252379 | C21: ='FS & Trend Analysis'!C21/'FS & Trend Analysis'!C$6 -> 0.13968834 | D21: ='FS & Trend Analysis'!D21/'FS & Trend Analysis'!D$6 -> 0.14744514 | E21: ='FS & Trend Analysis'!E21/'FS & Trend Analysis'!E$6 -> 0.15837738 | F21: ='FS & Trend Analysis'!F21/'FS & Trend Analysis'!F$6 -> 0.14846067 | G21: ='FS & Trend Analysis'!G21/'FS & Trend Analysis'!G$6 -> 0.13327764 | H21: ='FS & Trend Analysis'!H21/'FS & Trend Analysis'!H$6 -> 0.12583921 | I21: ='FS & Trend Analysis'!I21/'FS & Trend Analysis'!I$6 -> 0.11022061
A22: Add: Share of Profits of JVs | B22: ='FS & Trend Analysis'!B22/'FS & Trend Analysis'!B$6 -> 0.00051784816 | C22: ='FS & Trend Analysis'!C22/'FS & Trend Analysis'!C$6 -> 0.0012781834 | D22: ='FS & Trend Analysis'!D22/'FS & Trend Analysis'!D$6 -> 0.0090060374 | E22: ='FS & Trend Analysis'!E22/'FS & Trend Analysis'!E$6 -> 0.0015537323 | F22: ='FS & Trend Analysis'!F22/'FS & Trend Analysis'!F$6 -> 0.0017885196 | G22: ='FS & Trend Analysis'!G22/'FS & Trend Analysis'!G$6 -> 0.0011837163 | H22: ='FS & Trend Analysis'!H22/'FS & Trend Analysis'!H$6 -> -0.0015039153 | I22: ='FS & Trend Analysis'!I22/'FS & Trend Analysis'!I$6 -> -0.0067357488
A23: PBT & Exceptional Items | B23: ='FS & Trend Analysis'!B23/'FS & Trend Analysis'!B$6 -> 0.11304164 | C23: ='FS & Trend Analysis'!C23/'FS & Trend Analysis'!C$6 -> 0.14096652 | D23: ='FS & Trend Analysis'!D23/'FS & Trend Analysis'!D$6 -> 0.15645117 | E23: ='FS & Trend Analysis'!E23/'FS & Trend Analysis'!E$6 -> 0.15993111 | F23: ='FS & Trend Analysis'!F23/'FS & Trend Analysis'!F$6 -> 0.15024919 | G23: ='FS & Trend Analysis'!G23/'FS & Trend Analysis'!G$6 -> 0.13446136 | H23: ='FS & Trend Analysis'!H23/'FS & Trend Analysis'!H$6 -> 0.12433529 | I23: ='FS & Trend Analysis'!I23/'FS & Trend Analysis'!I$6 -> 0.10348486
... A30: Dividend | B30: ='FS & Trend Analysis'!B30/'FS & Trend Analysis'!B$6 -> 0.040953415 | C30: ='FS & Trend Analysis'!C30/'FS & Trend Analysis'!C$6 -> 0.045277686 | D30: ='FS & Trend Analysis'!D30/'FS & Trend Analysis'!D$6 -> 0.056072782 | E30: ='FS & Trend Analysis'!E30/'FS & Trend Analysis'!E$6 -> 0.051282532 | F30: ='FS & Trend Analysis'!F30/'FS & Trend Analysis'!F$6 -> 0.055850028 | G30: ='FS & Trend Analysis'!G30/'FS & Trend Analysis'!G$6 -> 0.06621018 | H30: ='FS & Trend Analysis'!H30/'FS & Trend Analysis'!H$6 -> 0.045171078 | I30: ='FS & Trend Analysis'!I30/'FS & Trend Analysis'!I$6 -> 0.057469592
A33: Balance Sheet
A34: Particulars | B34: 42094 | C34: 42460 | D34: 42825 | E34: 43190 | F34: 43555 | G34: 43921 | H34: 44286 | I34: 44651
A35: Equity & Liabilities
A36: Equity Share Capital | B36: ='FS & Trend Analysis'!B37/'FS & Trend Analysis'!B$60 -> 0.0037487036 | C36: ='FS & Trend Analysis'!C37/'FS & Trend Analysis'!C$60 -> 0.0031519054 | D36: ='FS & Trend Analysis'!D37/'FS & Trend Analysis'!D$60 -> 0.0026084117 | E36: ='FS & Trend Analysis'!E37/'FS & Trend Analysis'!E$60 -> 0.0022958338 | F36: ='FS & Trend Analysis'!F37/'FS & Trend Analysis'!F$60 -> 0.0021589506 | G36: ='FS & Trend Analysis'!G37/'FS & Trend Analysis'!G$60 -> 0.0020305915 | H36: ='FS & Trend Analysis'!H37/'FS & Trend Analysis'!H$60 -> 0.001730163 | I36: ='FS & Trend Analysis'!I37/'FS & Trend Analysis'!I$60 -> 0.0017777074
A37: Other Equity | B37: ='FS & Trend Analysis'!B38/'FS & Trend Analysis'!B$60 -> 0.61008508 | C37: ='FS & Trend Analysis'!C38/'FS & Trend Analysis'!C$60 -> 0.62444187 | D37: ='FS & Trend Analysis'!D38/'FS & Trend Analysis'!D$60 -> 0.67107955 | E37: ='FS & Trend Analysis'!E38/'FS & Trend Analysis'!E$60 -> 0.68584843 | F37: ='FS & Trend Analysis'!F38/'FS & Trend Analysis'!F$60 -> 0.7068853 | G37: ='FS & Trend Analysis'!G38/'FS & Trend Analysis'!G$60 -> 0.73021647 | H37: ='FS & Trend Analysis'!H38/'FS & Trend Analysis'!H$60 -> 0.66576031 | I37: ='FS & Trend Analysis'!I38/'FS & Trend Analysis'!I$60 -> 0.70319494
A38: Total Equity | B38: ='FS & Trend Analysis'!B39/'FS & Trend Analysis'!B$60 -> 0.61383379 | C38: ='FS & Trend Analysis'!C39/'FS & Trend Analysis'!C$60 -> 0.62759377 | D38: ='FS & Trend Analysis'!D39/'FS & Trend Analysis'!D$60 -> 0.67368796 | E38: ='FS & Trend Analysis'!E39/'FS & Trend Analysis'!E$60 -> 0.68814427 | F38: ='FS & Trend Analysis'!F39/'FS & Trend Analysis'!F$60 -> 0.70904425 | G38: ='FS & Trend Analysis'!G39/'FS & Trend Analysis'!G$60 -> 0.73224706 | H38: ='FS & Trend Analysis'!H39/'FS & Trend Analysis'!H$60 -> 0.66749047 | I38: ='FS & Trend Analysis'!I39/'FS & Trend Analysis'!I$60 -> 0.70497264
A39: Non-Controlling Interest | B39: ='FS & Trend Analysis'!B40/'FS & Trend Analysis'!B$60 -> 0.0017401343 | C39: ='FS & Trend Analysis'!C40/'FS & Trend Analysis'!C$60 -> 0.0042314764 | D39: ='FS & Trend Analysis'!D40/'FS & Trend Analysis'!D$60 -> 0.0044004702 | E39: ='FS & Trend Analysis'!E40/'FS & Trend Analysis'!E$60 -> 0.0053579035 | F39: ='FS & Trend Analysis'!F40/'FS & Trend Analysis'!F$60 -> 0.0062747374 | G39: ='FS & Trend Analysis'!G40/'FS & Trend Analysis'!G$60 -> 0.0071464623 | H39: ='FS & Trend Analysis'!H40/'FS & Trend Analysis'!H$60 -> 0.0061997507 | I39: ='FS & Trend Analysis'!I40/'FS & Trend Analysis'!I$60 -> 0.0065863258
A41: Non-Current Liabilities
A42: Borrowings | B42: ='FS & Trend Analysis'!B43/'FS & Trend Analysis'!B$60 -> 0.0011263005 | C42: ='FS & Trend Analysis'!C43/'FS & Trend Analysis'!C$60 -> 0.011520159 | D42: ='FS & Trend Analysis'!D43/'FS & Trend Analysis'!D$60 -> 0.013577586 | E42: ='FS & Trend Analysis'!E43/'FS & Trend Analysis'!E$60 -> 0.0086010417 | F42: ='FS & Trend Analysis'!F43/'FS & Trend Analysis'!F$60 -> 0.0067465181 | G42: ='FS & Trend Analysis'!G43/'FS & Trend Analysis'!G$60 -> 0.0022374628 | H42: ='FS & Trend Analysis'!H43/'FS & Trend Analysis'!H$60 -> 0.0019561753 | I42: ='FS & Trend Analysis'!I43/'FS & Trend Analysis'!I$60 -> 0.001609101
A43: Lease Liabilities | B43: ='FS & Trend Analysis'!B44/'FS & Trend Analysis'!B$60 -> 0 | C43: ='FS & Trend Analysis'!C44/'FS & Trend Analysis'!C$60 -> 0 | D43: ='FS & Trend Analysis'!D44/'FS & Trend Analysis'!D$60 -> 0 | E43: ='FS & Trend Analysis'!E44/'FS & Trend Analysis'!E$60 -> 0 | F43: ='FS & Trend Analysis'!F44/'FS & Trend Analysis'!F$60 -> 0 | G43: ='FS & Trend Analysis'!G44/'FS & Trend Analysis'!G$60 -> 0.010552977 | H43: ='FS & Trend Analysis'!H44/'FS & Trend Analysis'!H$60 -> 0.0091972278 | I43: ='FS & Trend Analysis'!I44/'FS & Trend Analysis'!I$60 -> 0.0095874304
A44: Other financial liabilities | B44: ='FS & Trend Analysis'!B45/'FS & Trend Analysis'!B$60 -> 0 | C44: ='FS & Trend Analysis'!C45/'FS & Trend Analysis'!C$60 -> 0 | D44: ='FS & Trend Analysis'!D45/'FS & Trend Analysis'!D$60 -> 0 | E44: ='FS & Trend Analysis'!E45/'FS & Trend Analysis'!E$60 -> 0 | F44: ='FS & Trend Analysis'!F45/'FS & Trend Analysis'!F$60 -> 0 | G44: ='FS & Trend Analysis'!G45/'FS & Trend Analysis'!G$60 -> 0 | H44: ='FS & Trend Analysis'!H45/'FS & Trend Analysis'!H$60 -> 0 | I44: ='FS & Trend Analysis'!I45/'FS & Trend Analysis'!I$60 -> 0.0068972911
A45: Provisions | B45: ='FS & Trend Analysis'!B46/'FS & Trend Analysis'!B$60 -> 0 | C45: ='FS & Trend Analysis'!C46/'FS & Trend Analysis'!C$60 -> 0 | D45: ='FS & Trend Analysis'!D46/'FS & Trend Analysis'!D$60 -> 0 | E45: ='FS & Trend Analysis'!E46/'FS & Trend Analysis'!E$60 -> 0 | F45: ='FS & Trend Analysis'!F46/'FS & Trend Analysis'!F$60 -> 0 | G45: ='FS & Trend Analysis'!G46/'FS & Trend Analysis'!G$60 -> 0 | H45: ='FS & Trend Analysis'!H46/'FS & Trend Analysis'!H$60 -> 0 | I45: ='FS & Trend Analysis'!I46/'FS & Trend Analysis'!I$60 -> 0.0080579614
A46: Deferred Tax Liabilities | B46: ='FS & Trend Analysis'!B47/'FS & Trend Analysis'!B$60 -> 0 | C46: ='FS & Trend Analysis'!C47/'FS & Trend Analysis'!C$60 -> 0.017976278 | D46: ='FS & Trend Analysis'!D47/'FS & Trend Analysis'!D$60 -> 0.030623041 | E46: ='FS & Trend Analysis'!E47/'FS & Trend Analysis'!E$60 -> 0.03344824 | F46: ='FS & Trend Analysis'!F47/'FS & Trend Analysis'!F$60 -> 0.033120843 | G46: ='FS & Trend Analysis'!G47/'FS & Trend Analysis'!G$60 -> 0.024020449 | H46: ='FS & Trend Analysis'!H47/'FS & Trend Analysis'!H$60 -> 0.019602452 | I46: ='FS & Trend Analysis'!I47/'FS & Trend Analysis'!I$60 -> 0.016825493
A47: Other Non-Current Liabilities | B47: ='FS & Trend Analysis'!B48/'FS & Trend Analysis'!B$60 -> 0.0091587004 | C47: ='FS & Trend Analysis'!C48/'FS & Trend Analysis'!C$60 -> 0.0094328306 | D47: ='FS & Trend Analysis'!D48/'FS & Trend Analysis'!D$60 -> 0.0049386102 | E47: ='FS & Trend Analysis'!E48/'FS & Trend Analysis'!E$60 -> 0.0068507127 | F47: ='FS & Trend Analysis'!F48/'FS & Trend Analysis'!F$60 -> 0.006535757 | G47: ='FS & Trend Analysis'!G48/'FS & Trend Analysis'!G$60 -> 0.0062976293 | H47: ='FS & Trend Analysis'!H48/'FS & Trend Analysis'!H$60 -> 0.013924868 | I47: ='FS & Trend Analysis'!I48/'FS & Trend Analysis'!I$60 -> 0
A48: Total Non-Current Liabilities | B48: ='FS & Trend Analysis'!B49/'FS & Trend Analysis'!B$60 -> 0.010285001 | C48: ='FS & Trend Analysis'!C49/'FS & Trend Analysis'!C$60 -> 0.038929268 | D48: ='FS & Trend Analysis'!D49/'FS & Trend Analysis'!D$60 -> 0.049139237 | E48: ='FS & Trend Analysis'!E49/'FS & Trend Analysis'!E$60 -> 0.048899994 | F48: ='FS & Trend Analysis'!F49/'FS & Trend Analysis'!F$60 -> 0.046403118 | G48: ='FS & Trend Analysis'!G49/'FS & Trend Analysis'!G$60 -> 0.043108518 | H48: ='FS & Trend Analysis'!H49/'FS & Trend Analysis'!H$60 -> 0.044680723 | I48: ='FS & Trend Analysis'!I49/'FS & Trend Analysis'!I$60 -> 0.042977277
A50: Current Liabilities
A51: Short Term Borrowings | B51: ='FS & Trend Analysis'!B52/'FS & Trend Analysis'!B$60 -> 0.0082595372 | C51: ='FS & Trend Analysis'!C52/'FS & Trend Analysis'!C$60 -> 0.0066336798 | D51: ='FS & Trend Analysis'!D52/'FS & Trend Analysis'!D$60 -> 0.0026175549 | E51: ='FS & Trend Analysis'!E52/'FS & Trend Analysis'!E$60 -> 0.0043324234 | F51: ='FS & Trend Analysis'!F52/'FS & Trend Analysis'!F$60 -> 0.0099263093 | G51: ='FS & Trend Analysis'!G52/'FS & Trend Analysis'!G$60 -> 0.0084314023 | H51: ='FS & Trend Analysis'!H52/'FS & Trend Analysis'!H$60 -> 0.012346679 | I51: ='FS & Trend Analysis'!I52/'FS & Trend Analysis'!I$60 -> 0.014116225
A52: Lease Liabilities | B52: ='FS & Trend Analysis'!B53/'FS & Trend Analysis'!B$60 -> 0 | C52: ='FS & Trend Analysis'!C53/'FS & Trend Analysis'!C$60 -> 0 | D52: ='FS & Trend Analysis'!D53/'FS & Trend Analysis'!D$60 -> 0 | E52: ='FS & Trend Analysis'!E53/'FS & Trend Analysis'!E$60 -> 0 | F52: ='FS & Trend Analysis'!F53/'FS & Trend Analysis'!F$60 -> 0 | G52: ='FS & Trend Analysis'!G53/'FS & Trend Analysis'!G$60 -> 0.0017007157 | H52: ='FS & Trend Analysis'!H53/'FS & Trend Analysis'!H$60 -> 0.0012803033 | I52: ='FS & Trend Analysis'!I53/'FS & Trend Analysis'!I$60 -> 0.0016095459
A53: Trade Payables | B53: ='FS & Trend Analysis'!B54/'FS & Trend Analysis'!B$60 -> 0.25464622 | C53: ='FS & Trend Analysis'!C54/'FS & Trend Analysis'!C$60 -> 0.22030982 | D53: ='FS & Trend Analysis'!D54/'FS & Trend Analysis'!D$60 -> 0.21330982 | E53: ='FS & Trend Analysis'!E54/'FS & Trend Analysis'!E$60 -> 0.19401692 | F53: ='FS & Trend Analysis'!F54/'FS & Trend Analysis'!F$60 -> 0.18580702 | G53: ='FS & Trend Analysis'!G54/'FS & Trend Analysis'!G$60 -> 0.15897168 | H53: ='FS & Trend Analysis'!H54/'FS & Trend Analysis'!H$60 -> 0.22792516 | I53: ='FS & Trend Analysis'!I54/'FS & Trend Analysis'!I$60 -> 0.19321179
A54: Other Financial Liabilities | B54: ='FS & Trend Analysis'!B55/'FS & Trend Analysis'!B$60 -> 0 | C54: ='FS & Trend Analysis'!C55/'FS & Trend Analysis'!C$60 -> 0 | D54: ='FS & Trend Analysis'!D55/'FS & Trend Analysis'!D$60 -> 0.023418234 | E54: ='FS & Trend Analysis'!E55/'FS & Trend Analysis'!E$60 -> 0.011645867 | F54: ='FS & Trend Analysis'!F55/'FS & Trend Analysis'!F$60 -> 0.012096609 | G54: ='FS & Trend Analysis'!G55/'FS & Trend Analysis'!G$60 -> 0.013148779 | H54: ='FS & Trend Analysis'!H55/'FS & Trend Analysis'!H$60 -> 0.0072531758 | I54: ='FS & Trend Analysis'!I55/'FS & Trend Analysis'!I$60 -> 0.0064764425
A55: - Current Maturities' of LTB | B55: ='FS & Trend Analysis'!B56/'FS & Trend Analysis'!B$60 -> 0 | C55: ='FS & Trend Analysis'!C56/'FS & Trend Analysis'!C$60 -> 0 | D55: ='FS & Trend Analysis'!D56/'FS & Trend Analysis'!D$60 -> 0.00082484326 | E55: ='FS & Trend Analysis'!E56/'FS & Trend Analysis'!E$60 -> 0.00016612317 | F55: ='FS & Trend Analysis'!F56/'FS & Trend Analysis'!F$60 -> 0.00015617941 | G55: ='FS & Trend Analysis'!G56/'FS & Trend Analysis'!G$60 -> 0.00011538029 | H55: ='FS & Trend Analysis'!H56/'FS & Trend Analysis'!H$60 -> 0.00050614628 | I55: ='FS & Trend Analysis'!I56/'FS & Trend Analysis'!I$60 -> 0
A56: Other Current Liabilities | B56: ='FS & Trend Analysis'!B57/'FS & Trend Analysis'!B$60 -> 0.11123532 | C56: ='FS & Trend Analysis'!C57/'FS & Trend Analysis'!C$60 -> 0.10230198 | D56: ='FS & Trend Analysis'!D57/'FS & Trend Analysis'!D$60 -> 0.032601881 | E56: ='FS & Trend Analysis'!E57/'FS & Trend Analysis'!E$60 -> 0.047436501 | F56: ='FS & Trend Analysis'!F57/'FS & Trend Analysis'!F$60 -> 0.03029178 | G56: ='FS & Trend Analysis'!G57/'FS & Trend Analysis'!G$60 -> 0.035129996 | H56: ='FS & Trend Analysis'!H57/'FS & Trend Analysis'!H$60 -> 0.032317591 | I56: ='FS & Trend Analysis'!I57/'FS & Trend Analysis'!I$60 -> 0.022079873
A57: Provisions | B57: ='FS & Trend Analysis'!B58/'FS & Trend Analysis'!B$60 -> 0 | C57: ='FS & Trend Analysis'!C58/'FS & Trend Analysis'!C$60 -> 0 | D57: ='FS & Trend Analysis'!D58/'FS & Trend Analysis'!D$60 -> 0 | E57: ='FS & Trend Analysis'!E58/'FS & Trend Analysis'!E$60 -> 0 | F57: ='FS & Trend Analysis'!F58/'FS & Trend Analysis'!F$60 -> 0 | G57: ='FS & Trend Analysis'!G58/'FS & Trend Analysis'!G$60 -> 0 | H57: ='FS & Trend Analysis'!H58/'FS & Trend Analysis'!H$60 -> 0 | I57: ='FS & Trend Analysis'!I58/'FS & Trend Analysis'!I$60 -> 0.0079698768
A58: Total Current Liabilities | B58: ='FS & Trend Analysis'!B59/'FS & Trend Analysis'!B$60 -> 0.37414108 | C58: ='FS & Trend Analysis'!C59/'FS & Trend Analysis'!C$60 -> 0.32924548 | D58: ='FS & Trend Analysis'!D59/'FS & Trend Analysis'!D$60 -> 0.27277234 | E58: ='FS & Trend Analysis'!E59/'FS & Trend Analysis'!E$60 -> 0.25759784 | F58: ='FS & Trend Analysis'!F59/'FS & Trend Analysis'!F$60 -> 0.2382779 | G58: ='FS & Trend Analysis'!G59/'FS & Trend Analysis'!G$60 -> 0.21749796 | H58: ='FS & Trend Analysis'!H59/'FS & Trend Analysis'!H$60 -> 0.28162905 | I58: ='FS & Trend Analysis'!I59/'FS & Trend Analysis'!I$60 -> 0.24546375
A59: TOTAL EQUITIES & LIABILITIES | B59: ='FS & Trend Analysis'!B60/'FS & Trend Analysis'!B$60 -> 1 | C59: ='FS & Trend Analysis'!C60/'FS & Trend Analysis'!C$60 -> 1 | D59: ='FS & Trend Analysis'!D60/'FS & Trend Analysis'!D$60 -> 1 | E59: ='FS & Trend Analysis'!E60/'FS & Trend Analysis'!E$60 -> 1 | F59: ='FS & Trend Analysis'!F60/'FS & Trend Analysis'!F$60 -> 1 | G59: ='FS & Trend Analysis'!G60/'FS & Trend Analysis'!G$60 -> 1 | H59: ='FS & Trend Analysis'!H60/'FS & Trend Analysis'!H$60 -> 1 | I59: ='FS & Trend Analysis'!I60/'FS & Trend Analysis'!I$60 -> 1
A60: Assets
A61: Non-Current Assets
A62: Property, Plant & Equipment | B62: ='FS & Trend Analysis'!B63/'FS & Trend Analysis'!B$85 -> 0.26757709 | C62: ='FS & Trend Analysis'!C63/'FS & Trend Analysis'!C$85 -> 0.30832643 | D62: ='FS & Trend Analysis'!D63/'FS & Trend Analysis'!D$85 -> 0.29356257 | E62: ='FS & Trend Analysis'!E63/'FS & Trend Analysis'!E$85 -> 0.27426936 | F62: ='FS & Trend Analysis'!F63/'FS & Trend Analysis'!F$85 -> 0.2589933 | G62: ='FS & Trend Analysis'!G63/'FS & Trend Analysis'!G$85 -> 0.29410458 | H62: ='FS & Trend Analysis'!H63/'FS & Trend Analysis'!H$85 -> 0.2403289 | I62: ='FS & Trend Analysis'!I63/'FS & Trend Analysis'!I$85 -> 0.23819944
A63: Intangible Assets | B63: ='FS & Trend Analysis'!B64/'FS & Trend Analysis'!B$85 -> 0.0095191166 | C63: ='FS & Trend Analysis'!C64/'FS & Trend Analysis'!C$85 -> 0.010185689 | D63: ='FS & Trend Analysis'!D64/'FS & Trend Analysis'!D$85 -> 0.025241641 | E63: ='FS & Trend Analysis'!E64/'FS & Trend Analysis'!E$85 -> 0.013739364 | F63: ='FS & Trend Analysis'!F64/'FS & Trend Analysis'!F$85 -> 0.020797824 | G63: ='FS & Trend Analysis'!G64/'FS & Trend Analysis'!G$85 -> 0.034903266 | H63: ='FS & Trend Analysis'!H64/'FS & Trend Analysis'!H$85 -> 0.035924618 | I63: ='FS & Trend Analysis'!I64/'FS & Trend Analysis'!I$85 -> 0
A64: Capital-Work in Progress | B64: ='FS & Trend Analysis'!B65/'FS & Trend Analysis'!B$85 -> 0.029576652 | C64: ='FS & Trend Analysis'!C65/'FS & Trend Analysis'!C$85 -> 0.026103838 | D64: ='FS & Trend Analysis'!D65/'FS & Trend Analysis'!D$85 -> 0.006780303 | E64: ='FS & Trend Analysis'!E65/'FS & Trend Analysis'!E$85 -> 0.010896875 | F64: ='FS & Trend Analysis'!F65/'FS & Trend Analysis'!F$85 -> 0.0086390544 | G64: ='FS & Trend Analysis'!G65/'FS & Trend Analysis'!G$85 -> 0.010401498 | H64: ='FS & Trend Analysis'!H65/'FS & Trend Analysis'!H$85 -> 0.010235477 | I64: ='FS & Trend Analysis'!I65/'FS & Trend Analysis'!I$85 -> 0.0066343719
A65: Right of use of assets | B65: ='FS & Trend Analysis'!B66/'FS & Trend Analysis'!B$85 -> 0 | C65: ='FS & Trend Analysis'!C66/'FS & Trend Analysis'!C$85 -> 0 | D65: ='FS & Trend Analysis'!D66/'FS & Trend Analysis'!D$85 -> 0 | E65: ='FS & Trend Analysis'!E66/'FS & Trend Analysis'!E$85 -> 0 | F65: ='FS & Trend Analysis'!F66/'FS & Trend Analysis'!F$85 -> 0 | G65: ='FS & Trend Analysis'!G66/'FS & Trend Analysis'!G$85 -> 0 | H65: ='FS & Trend Analysis'!H66/'FS & Trend Analysis'!H$85 -> 0 | I65: ='FS & Trend Analysis'!I66/'FS & Trend Analysis'!I$85 -> 0.023039906
A66: Other Intangible assets | B66: ='FS & Trend Analysis'!B67/'FS & Trend Analysis'!B$85 -> 0 | C66: ='FS & Trend Analysis'!C67/'FS & Trend Analysis'!C$85 -> 0 | D66: ='FS & Trend Analysis'!D67/'FS & Trend Analysis'!D$85 -> 0 | E66: ='FS & Trend Analysis'!E67/'FS & Trend Analysis'!E$85 -> 0 | F66: ='FS & Trend Analysis'!F67/'FS & Trend Analysis'!F$85 -> 0 | G66: ='FS & Trend Analysis'!G67/'FS & Trend Analysis'!G$85 -> 0 | H66: ='FS & Trend Analysis'!H67/'FS & Trend Analysis'!H$85 -> 0 | I66: ='FS & Trend Analysis'!I67/'FS & Trend Analysis'!I$85 -> 0.014293728
A67: Intangible Assets under Development | B67: ='FS & Trend Analysis'!B68/'FS & Trend Analysis'!B$85 -> 0.037926293 | C67: ='FS & Trend Analysis'!C68/'FS & Trend Analysis'!C$85 -> 0.025457516 | D67: ='FS & Trend Analysis'!D68/'FS & Trend Analysis'!D$85 -> 0.012699843 | E67: ='FS & Trend Analysis'!E68/'FS & Trend Analysis'!E$85 -> 0.0066943615 | F67: ='FS & Trend Analysis'!F68/'FS & Trend Analysis'!F$85 -> 0.010158157 | G67: ='FS & Trend Analysis'!G68/'FS & Trend Analysis'!G$85 -> 0.0094891301 | H67: ='FS & Trend Analysis'!H68/'FS & Trend Analysis'!H$85 -> 0.011202305 | I67: ='FS & Trend Analysis'!I68/'FS & Trend Analysis'!I$85 -> 0.016375283
A68: Equity accounted investments in associates | B68: ='FS & Trend Analysis'!B69/'FS & Trend Analysis'!B$85 -> 0 | C68: ='FS & Trend Analysis'!C69/'FS & Trend Analysis'!C$85 -> 0 | D68: ='FS & Trend Analysis'!D69/'FS & Trend Analysis'!D$85 -> 0 | E68: ='FS & Trend Analysis'!E69/'FS & Trend Analysis'!E$85 -> 0 | F68: ='FS & Trend Analysis'!F69/'FS & Trend Analysis'!F$85 -> 0 | G68: ='FS & Trend Analysis'!G69/'FS & Trend Analysis'!G$85 -> 0 | H68: ='FS & Trend Analysis'!H69/'FS & Trend Analysis'!H$85 -> 0 | I68: ='FS & Trend Analysis'!I69/'FS & Trend Analysis'!I$85 -> 0.097983441
A69: Investment | B69: ='FS & Trend Analysis'!B70/'FS & Trend Analysis'!B$85 -> 0.077071806 | C69: ='FS & Trend Analysis'!C70/'FS & Trend Analysis'!C$85 -> 0.074596147 | D69: ='FS & Trend Analysis'!D70/'FS & Trend Analysis'!D$85 -> 0.066965125 | E69: ='FS & Trend Analysis'!E70/'FS & Trend Analysis'!E$85 -> 0.066657929 | F69: ='FS & Trend Analysis'!F70/'FS & Trend Analysis'!F$85 -> 0.092188643 | G69: ='FS & Trend Analysis'!G70/'FS & Trend Analysis'!G$85 -> 0.106655 | H69: ='FS & Trend Analysis'!H70/'FS & Trend Analysis'!H$85 -> 0.10424642 | I69: ='FS & Trend Analysis'!I70/'FS & Trend Analysis'!I$85 -> 0.10921823
A70: Financial Assets | B70: ='FS & Trend Analysis'!B71/'FS & Trend Analysis'!B$85 -> 0.067747915 | C70: ='FS & Trend Analysis'!C71/'FS & Trend Analysis'!C$85 -> 0.069161202 | D70: ='FS & Trend Analysis'!D71/'FS & Trend Analysis'!D$85 -> 0.035623041 | E70: ='FS & Trend Analysis'!E71/'FS & Trend Analysis'!E$85 -> 0.055432257 | F70: ='FS & Trend Analysis'!F71/'FS & Trend Analysis'!F$85 -> 0.071766948 | G70: ='FS & Trend Analysis'!G71/'FS & Trend Analysis'!G$85 -> 0.082283857 | H70: ='FS & Trend Analysis'!H71/'FS & Trend Analysis'!H$85 -> 0.086649977 | I70: ='FS & Trend Analysis'!I71/'FS & Trend Analysis'!I$85 -> 0.0026443175
A71: Income tax assets | B71: ='FS & Trend Analysis'!B72/'FS & Trend Analysis'!B$85 -> 0 | C71: ='FS & Trend Analysis'!C72/'FS & Trend Analysis'!C$85 -> 0 | D71: ='FS & Trend Analysis'!D72/'FS & Trend Analysis'!D$85 -> 0 | E71: ='FS & Trend Analysis'!E72/'FS & Trend Analysis'!E$85 -> 0 | F71: ='FS & Trend Analysis'!F72/'FS & Trend Analysis'!F$85 -> 0 | G71: ='FS & Trend Analysis'!G72/'FS & Trend Analysis'!G$85 -> 0 | H71: ='FS & Trend Analysis'!H72/'FS & Trend Analysis'!H$85 -> 0 | I71: ='FS & Trend Analysis'!I72/'FS & Trend Analysis'!I$85 -> 0.015929522
A72: Other Non-Current Assets | B72: ='FS & Trend Analysis'!B73/'FS & Trend Analysis'!B$85 -> 0.0056493357 | C72: ='FS & Trend Analysis'!C73/'FS & Trend Analysis'!C$85 -> 0.0058145316 | D72: ='FS & Trend Analysis'!D73/'FS & Trend Analysis'!D$85 -> 0.064710684 | E72: ='FS & Trend Analysis'!E73/'FS & Trend Analysis'!E$85 -> 0.054843065 | F72: ='FS & Trend Analysis'!F73/'FS & Trend Analysis'!F$85 -> 0.082795712 | G72: ='FS & Trend Analysis'!G73/'FS & Trend Analysis'!G$85 -> 0.022537764 | H72: ='FS & Trend Analysis'!H73/'FS & Trend Analysis'!H$85 -> 0.01910146 | I72: ='FS & Trend Analysis'!I73/'FS & Trend Analysis'!I$85 -> 0.0053535863
A73: Total Non-Current Assets | B73: ='FS & Trend Analysis'!B74/'FS & Trend Analysis'!B$85 -> 0.49506821 | C73: ='FS & Trend Analysis'!C74/'FS & Trend Analysis'!C$85 -> 0.51964535 | D73: ='FS & Trend Analysis'!D74/'FS & Trend Analysis'!D$85 -> 0.5055832 | E73: ='FS & Trend Analysis'!E74/'FS & Trend Analysis'!E$85 -> 0.48253321 | F73: ='FS & Trend Analysis'!F74/'FS & Trend Analysis'!F$85 -> 0.54533963 | G73: ='FS & Trend Analysis'!G74/'FS & Trend Analysis'!G$85 -> 0.56037509 | H73: ='FS & Trend Analysis'!H74/'FS & Trend Analysis'!H$85 -> 0.50768916 | I73: ='FS & Trend Analysis'!I74/'FS & Trend Analysis'!I$85 -> 0.52967183
A75: Current Assets
A76: Current Investments | B76: ='FS & Trend Analysis'!B77/'FS & Trend Analysis'!B$85 -> 0.21562554 | C76: ='FS & Trend Analysis'!C77/'FS & Trend Analysis'!C$85 -> 0.25640995 | D76: ='FS & Trend Analysis'!D77/'FS & Trend Analysis'!D$85 -> 0.29676463 | E76: ='FS & Trend Analysis'!E77/'FS & Trend Analysis'!E$85 -> 0.32138913 | F76: ='FS & Trend Analysis'!F77/'FS & Trend Analysis'!F$85 -> 0.17152084 | G76: ='FS & Trend Analysis'!G77/'FS & Trend Analysis'!G$85 -> 0.23935643 | H76: ='FS & Trend Analysis'!H77/'FS & Trend Analysis'!H$85 -> 0.26954028 | I76: ='FS & Trend Analysis'!I77/'FS & Trend Analysis'!I$85 -> 0.26115349
A77: Inventories | B77: ='FS & Trend Analysis'!B78/'FS & Trend Analysis'!B$85 -> 0.080848667 | C77: ='FS & Trend Analysis'!C78/'FS & Trend Analysis'!C$85 -> 0.06013321 | D77: ='FS & Trend Analysis'!D78/'FS & Trend Analysis'!D$85 -> 0.046276123 | E77: ='FS & Trend Analysis'!E78/'FS & Trend Analysis'!E$85 -> 0.055336836 | F77: ='FS & Trend Analysis'!F78/'FS & Trend Analysis'!F$85 -> 0.067526321 | G77: ='FS & Trend Analysis'!G78/'FS & Trend Analysis'!G$85 -> 0.06517811 | H77: ='FS & Trend Analysis'!H78/'FS & Trend Analysis'!H$85 -> 0.077470521 | I77: ='FS & Trend Analysis'!I78/'FS & Trend Analysis'!I$85 -> 0.065503357
A78: Trade Receivables | B78: ='FS & Trend Analysis'!B79/'FS & Trend Analysis'!B$85 -> 0.1287568 | C78: ='FS & Trend Analysis'!C79/'FS & Trend Analysis'!C$85 -> 0.10117664 | D78: ='FS & Trend Analysis'!D79/'FS & Trend Analysis'!D$85 -> 0.10134208 | E78: ='FS & Trend Analysis'!E79/'FS & Trend Analysis'!E$85 -> 0.082025185 | F78: ='FS & Trend Analysis'!F79/'FS & Trend Analysis'!F$85 -> 0.14834952 | G78: ='FS & Trend Analysis'!G79/'FS & Trend Analysis'!G$85 -> 0.076847773 | H78: ='FS & Trend Analysis'!H79/'FS & Trend Analysis'!H$85 -> 0.098487453 | I78: ='FS & Trend Analysis'!I79/'FS & Trend Analysis'!I$85 -> 0.096025116
A79: Cash, Bank & Cash Equivalents | B79: ='FS & Trend Analysis'!B80/'FS & Trend Analysis'!B$85 -> 0.020252761 | C79: ='FS & Trend Analysis'!C80/'FS & Trend Analysis'!C$85 -> 0.014133068 | D79: ='FS & Trend Analysis'!D80/'FS & Trend Analysis'!D$85 -> 0.01276058 | E79: ='FS & Trend Analysis'!E80/'FS & Trend Analysis'!E$85 -> 0.013656015 | F79: ='FS & Trend Analysis'!F80/'FS & Trend Analysis'!F$85 -> 0.016422093 | G79: ='FS & Trend Analysis'!G80/'FS & Trend Analysis'!G$85 -> 0.022132155 | H79: ='FS & Trend Analysis'!H80/'FS & Trend Analysis'!H$85 -> 0.017156114 | I79: ='FS & Trend Analysis'!I80/'FS & Trend Analysis'!I$85 -> 0.013334585
A80: Loans | B80: ='FS & Trend Analysis'!B81/'FS & Trend Analysis'!B$85 -> 0 | C80: ='FS & Trend Analysis'!C81/'FS & Trend Analysis'!C$85 -> 0 | D80: ='FS & Trend Analysis'!D81/'FS & Trend Analysis'!D$85 -> 0 | E80: ='FS & Trend Analysis'!E81/'FS & Trend Analysis'!E$85 -> 0 | F80: ='FS & Trend Analysis'!F81/'FS & Trend Analysis'!F$85 -> 0 | G80: ='FS & Trend Analysis'!G81/'FS & Trend Analysis'!G$85 -> 0 | H80: ='FS & Trend Analysis'!H81/'FS & Trend Analysis'!H$85 -> 0 | I80: ='FS & Trend Analysis'!I81/'FS & Trend Analysis'!I$85 -> 0.0010147524
A81: Other Financial Assets | B81: ='FS & Trend Analysis'!B82/'FS & Trend Analysis'!B$85 -> 0 | C81: ='FS & Trend Analysis'!C82/'FS & Trend Analysis'!C$85 -> 0 | D81: ='FS & Trend Analysis'!D82/'FS & Trend Analysis'!D$85 -> 0 | E81: ='FS & Trend Analysis'!E82/'FS & Trend Analysis'!E$85 -> 0 | F81: ='FS & Trend Analysis'!F82/'FS & Trend Analysis'!F$85 -> 0 | G81: ='FS & Trend Analysis'!G82/'FS & Trend Analysis'!G$85 -> 0 | H81: ='FS & Trend Analysis'!H82/'FS & Trend Analysis'!H$85 -> 0 | I81: ='FS & Trend Analysis'!I82/'FS & Trend Analysis'!I$85 -> 0.021131407
A82: Other Current Assets | B82: ='FS & Trend Analysis'!B83/'FS & Trend Analysis'!B$85 -> 0.059448019 | C82: ='FS & Trend Analysis'!C83/'FS & Trend Analysis'!C$85 -> 0.04850178 | D82: ='FS & Trend Analysis'!D83/'FS & Trend Analysis'!D$85 -> 0.03727338 | E82: ='FS & Trend Analysis'!E83/'FS & Trend Analysis'!E$85 -> 0.045059618 | F82: ='FS & Trend Analysis'!F83/'FS & Trend Analysis'!F$85 -> 0.050841586 | G82: ='FS & Trend Analysis'!G83/'FS & Trend Analysis'!G$85 -> 0.036110438 | H82: ='FS & Trend Analysis'!H83/'FS & Trend Analysis'!H$85 -> 0.029656471 | I82: ='FS & Trend Analysis'!I83/'FS & Trend Analysis'!I$85 -> 0.012165462
A83: Total Current Assets | B83: ='FS & Trend Analysis'!B84/'FS & Trend Analysis'!B$85 -> 0.50493179 | C83: ='FS & Trend Analysis'!C84/'FS & Trend Analysis'!C$85 -> 0.48035465 | D83: ='FS & Trend Analysis'!D84/'FS & Trend Analysis'!D$85 -> 0.4944168 | E83: ='FS & Trend Analysis'!E84/'FS & Trend Analysis'!E$85 -> 0.51746679 | F83: ='FS & Trend Analysis'!F84/'FS & Trend Analysis'!F$85 -> 0.45466037 | G83: ='FS & Trend Analysis'!G84/'FS & Trend Analysis'!G$85 -> 0.43962491 | H83: ='FS & Trend Analysis'!H84/'FS & Trend Analysis'!H$85 -> 0.49231084 | I83: ='FS & Trend Analysis'!I84/'FS & Trend Analysis'!I$85 -> 0.47032817
A84: TOTAL ASSETS | B84: ='FS & Trend Analysis'!B85/'FS & Trend Analysis'!B$85 -> 1 | C84: ='FS & Trend Analysis'!C85/'FS & Trend Analysis'!C$85 -> 1 | D84: ='FS & Trend Analysis'!D85/'FS & Trend Analysis'!D$85 -> 1 | E84: ='FS & Trend Analysis'!E85/'FS & Trend Analysis'!E$85 -> 1 | F84: ='FS & Trend Analysis'!F85/'FS & Trend Analysis'!F$85 -> 1 | G84: ='FS & Trend Analysis'!G85/'FS & Trend Analysis'!G$85 -> 1 | H84: ='FS & Trend Analysis'!H85/'FS & Trend Analysis'!H$85 -> 1 | I84: ='FS & Trend Analysis'!I85/'FS & Trend Analysis'!I$85 -> 1

Sheet Comparative FS
B2: Comparative Financial Statements (YoY)
B4: Comparative Income Statement
B5: Particulars | C5: 42460 | D5: 42825 | E5: 43190 | F5: 43555 | G5: 43921 | H5: 44286 | I5: 44651
B6: Revenue from Operations
B7: Other Income
B8: Total Income
B10: Expenses
B11: Raw Material
B12: Excise Duty
B13: Employee Costs
B14: Other Expenses
B15: Total Expenses
B17: EBITDA
B18: Depreciation & Amortization
B19: EBIT
... B32: Comparative Balance Sheet
B33: Particulars | C33: 42460 | D33: 42825 | E33: 43190 | F33: 43555 | G33: 43921 | H33: 44286 | I33: 44651
B34: Equity & Liabilities
B35: Equity Share Capital
B36: Other Equity
B37: Total Equity
B38: Non-Controlling Interest
B40: Non-Current Liabilities
B41: Borrowings
B42: Lease Liabilities
B43: Other financial liabilities
B44: Provisions
B45: Deferred Tax Liabilities
B46: Other Non-Current Liabilities
... B83: TOTAL ASSETS

Sheet Cash Flow Statement
A1: Cash Flow Statement
A3: Particulars
A4: Cash Flow from Operating Activities | B4: March 31, 2015 | C4: March 31, 2016 | D4: March 31, 2017 | E4: March 31, 2018 | F4: March 31, 2019 | G4: March 31, 2020 | H4: March 31, 2021 | I4: March 31, 2022
A5: Net profit before tax | B5: 3291.96 | C5: 4312.45 | D5: 3546.3 | E5: 3722.17 | F5: 3466.35 | G5: 3659.41 | H5: 2936.05 | I5: 2329.05
A6: Adjustments for:
A7: Add: Depreciation and amortisation | B7: 540.45 | C7: 447.01 | D7: 502.25 | E7: 574.98 | F7: 624.44 | G7: 845.76 | H7: 715.12 | I7: 689.52
A8: Tax expense | D8: 1339.1 | E8: 1569.93 | F8: 1637.95 | G8: 951.67 | H8: 913.27 | I8: 729.06
A9: Loss on fixed assets sold/discarded | B9: 22.84 | C9: 108.99 | D9: 170.82 | E9: 9.28 | F9: 6.47 | G9: 8.66 | H9: 4.67 | I9: 10.23
A10: Loss on sale of non-trade current investments | B10: 0.21 | C10: 0.03
A11: Provision for diminution in value of investment:
A12: Exceptional item: Long term trade investment - non current | B12: 144.73
A13: Long term non trade investment | B13: 0.72 | C13: 0.52
A14: Finance cost | B14: 11.7 | C14: 11.87 | D14: 27.28 | E14: 30.8 | F14: 37.18 | G14: 46.64 | H14: 46.41 | I14: 53.1
A15: Exchange differences | B15: 0.03
A16: Impairment of goodwill on consolidation | B16: 3.94
A17: Expense on employee stock option scheme | C17: 0.93 | D17: 3.42 | E17: 5.35 | F17: 6.55 | G17: 10.15 | H17: 8.86 | I17: 10
A18: Provision for doubtful debts | B18: 0.7 | C18: 3.03
A19: Loss allowance on advances | I19: 52.24
A20: Loss allowance on trade receivables | G20: 53.04 | H20: 46.9 | I20: 0.74
B21: =SUM(B7:B18) -> 725.32 | C21: =SUM(C7:C18) -> 572.38 | D21: =SUM(D7:D18) -> 2042.87 | E21: =SUM(E7:E18) -> 2190.34 | F21: =SUM(F7:F18) -> 2312.59 | G21: =SUM(G7:G20) -> 1915.92 | H21: =SUM(H7:H20) -> 1735.23 | I21: =SUM(I7:I20) -> 1544.89
A22: Less: Interest on long term and current non-trade investments | B22: 50.37 | C22: 41.54 | D22: 159.3 | E22: 157.19 | F22: 288.03 | G22: 277.77 | H22: 100.42 | I22: 189.05
A23: Interest on loans, deposits etc. | B23: 99.64 | C23: 124.24
A24: Profit on sale of fixed assets | B24: 0.68 | C24: 0.51 | D24: 0.76 | E24: 0.54 | F24: 0.66 | G24: 0.37 | H24: 0.89 | I24: 0.62
A25: Profit on sale of investments | D25: 137.85 | E25: 216.09 | F25: 144.61 | G25: 136.07 | H25: 169.07 | I25: 109.11
A26: Gain on investments carried at fair value through profit or loss | D26: 179.6 | E26: 74.59 | F26: 175.11 | G26: 221.78 | H26: 285.77 | I26: 223.82
A27: Share of profit in associates | D27: 317.01 | E27: 49.66 | F27: 60.19 | G27: 34.63 | H27: -46.56 | I27: -199.05
A28: Re-measurement loss on defined benefit plans | D28: 21.58
A29: Foreign currency translation (net) | B29: 3.64 | C29: -1.81 | D29: 2.43 | E29: 11.13 | F29: -9.91 | G29: -19.01 | H29: 6.79 | I29: -7.53
A30: Dividend income: | D30: 37.98 | E30: 70.56 | F30: 71.76 | G30: 48.27 | H30: 1.39 | I30: 1.67
A31: On current Investments - Non-Trade | B31: 1.5 | C31: 7.06
A32: On long-term investments- Non trade | B32: 0.06 | C32: 0.12
A33: Profit on sale of non-trade current investments | B33: 320.75 | C33: 205.18
B34: =SUM(B22:B33) -> 476.64 | C34: =SUM(C22:C33) -> 376.84 | D34: =SUM(D22:D33) -> 856.51 | E34: =SUM(E22:E33) -> 579.76 | F34: =SUM(F22:F33) -> 730.45 | G34: =SUM(G22:G33) -> 699.88 | H34: =SUM(H22:H33) -> 517.77 | I34: =SUM(I22:I33) -> 317.69
A35: Operating profit before working capital changes | B35: =B5+B21-B34 -> 3540.64 | C35: =C5+C21-C34 -> 4507.99 | D35: =D5+D21-D34 -> 4732.66 | E35: =E5+E21-E34 -> 5332.75 | F35: =F5+F21-F34 -> 5048.49 | G35: =G5+G21-G34 -> 4875.45 | H35: =H5+H21-H34 -> 4153.51 | I35: =I5+I21-I34 -> 3556.25
A36: Changes in working capital:
A37: Adjustment for (increase)/decrease in operating assets:
A38: Add: Inventories | B38: -191.84 | C38: 99.4 | D38: 53.41 | E38: -254.1 | F38: -286.86 | G38: -32.79 | H38: -506.95 | I38: 316.86
A39: Trade receivables | B39: -451.97 | C39: 86.71 | D39: -269.68 | E39: 124.78 | F39: -1318.14 | G39: 1180.16 | H39: -809.67 | I39: 115.45
A40: Short-term loans and advances | B40: -243.03 | C40: 38.29 | D40: 1.48 | E40: -3.57 | F40: 3.42 | G40: 1.33 | H40: -16.02 | I40: 0.14
A41: Long-term loans and advances | B41: -23.14 | C41: 44.21 | D41: 3.57 | E41: 2.67 | F41: -14.28 | G41: -7.56 | H41: 15.04 | I41: -0.7
A42: Other financial assets | I42: -66.89
A43: Other financial assets-current | D43: -1.87 | E43: -398.07 | F43: -111.04 | G43: 290.71 | H43: 1.6
A44: Other financial assets-non-current | D44: -2.01
A45: Other current assets | B45: -30.78 | C45: -22.13 | D45: 38.26 | E45: 188.67 | F45: -49.41 | G45: -64.36 | H45: 43.19 | I45: -46.25
A46: Other non-current assets | D46: 68.74 | E46: 70.39 | F46: 46.88 | G46: 42.84 | H46: -3.57 | I46: 3.08
B47: =SUM(B38:B45) -> -940.76 | C47: =SUM(C38:C45) -> 246.48 | D47: =SUM(D38:D46) -> -108.1 | E47: =SUM(E38:E46) -> -269.23 | F47: =SUM(F38:F46) -> -1729.43 | G47: =SUM(G38:G46) -> 1410.33 | H47: =SUM(H38:H46) -> -1276.38 | I47: =SUM(I38:I46) -> 321.69
A48: Adjustment for increase/(decrease) in operating liabilities:
A49: Less: Trade payables | B49: 564.59 | C49: 78.61 | D49: 590.86 | E49: 109.06 | F49: 62.98 | G49: -310.63 | H49: 2136.56 | I49: -921.09
A50: Other financial liabilities-Current | D50: 7.87 | E50: -11.97 | F50: 2.07 | G50: 5.32 | H50: -1.23 | I50: 3.53
A51: Other current liabilities | B51: -5.22 | C51: 28.42 | D51: -49.67 | E51: 308.32 | F51: -264.13 | G51: 30.64 | H51: 39.13 | I51: -74.27
A52: Other long-term liabilities | B52: 6.88 | C52: 3.56
A53: Short-term provisions | B53: 2.99 | C53: 16.61 | D53: 12.77 | E53: 17.72 | F53: -19.01 | G53: 56.84 | H53: -12.03 | I53: -3.89
A54: Long-term provisions | B54: 16.23 | C54: 18.39 | D54: 7.82 | E54: 43.56 | F54: 1.76 | G54: 2.96 | H54: 51.67 | I54: 5.56
B55: =SUM(B49:B54) -> 585.47 | C55: =SUM(C49:C54) -> 145.59 | D55: =SUM(D49:D54) -> 569.65 | E55: =SUM(E49:E54) -> 466.69 | F55: =SUM(F49:F54) -> -216.33 | G55: =SUM(G49:G54) -> -214.87 | H55: =SUM(H49:H54) -> 2214.1 | I55: =SUM(I49:I54) -> -990.16
A56: Cash generated from operations | B56: =B35+B47+B55 -> 3185.35 | C56: =C35+C47+C55 -> 4900.06 | D56: =D35+D47+D55 -> 5194.21 | E56: =E35+E47+E55 -> 5530.21 | F56: =F35+F47+F55 -> 3102.73 | G56: =G35+G47+G55 -> 6070.91 | H56: =H35+H47+H55 -> 5091.23 | I56: =I35+I47+I55 -> 2887.78
A57: Less: Direct taxes paid | B57: 999.84 | C57: 1103.65 | D57: 1187.02 | E57: 1513 | F57: 2070.46 | G57: 552.78 | H57: 980.78 | I57: 784.08
A58: Net cash from operating activities | B58: =B56-B57 -> 2185.51 | C58: =C56-C57 -> 3796.41 | D58: =D56-D57 -> 4007.19 | E58: =E56-E57 -> 4017.21 | F58: =F56-F57 -> 1032.27 | G58: =G56-G57 -> 5518.13 | H58: =H56-H57 -> 4110.45 | I58: =I56-I57 -> 2103.7
A60: Cash Flow from Investing Activities
A61: Capital expenditure on property, plant & equipment and intangible assets | D61: -1238.11 | E61: -824.16 | F61: -979.56 | G61: -1274.5 | H61: -581.02 | I61: -569.66
A62: Proceeds from sale of fixed assets | B62: 2.71 | C62: 6.63 | D62: 1.58 | E62: 2.66 | F62: 4.17 | G62: -13.3 | H62: 7.18 | I62: 10.82
A63: Deposits more than 12 months and other than cash and cash | F63: -22.65 | G63: -4.48 | H63: 0.69 | I63: -9.82
A64: Sale of investments | B64: 1349.29 | C64: 26972.56 | D64: 28334.82 | E64: 33681.58 | F64: 42020.45 | G64: 47232.41 | H64: 47929.45 | I64: 42437.49
A65: (Purchase) of investments | C65: -27521.95 | D65: -29048.77 | E65: -34854.02 | F65: -39456.26 | G65: -49353.1 | H65: -49388.54 | I65: -42105.1
A66: Investment in Associates | B66: -152.4 | C66: -197.19 | D66: -216.92 | E66: -90.09 | F66: -628.3 | G66: 248.37 | H66: -368.37 | I66: -150
A67: Inter corporate deposits received back | B67: 515 | C67: -
A68: Inter corporate deposits paid | B68: -295 | C68: -
A69: Interest received on long term and current non-trade investments | B69: 30.85 | C69: 30.67
A70: Dividend income received from associates | G70: 19.99 | H70: 12.76 | I70: 5.24
A71: Interest received on loans, deposits etc. | B71: 99.64 | C71: 124.24 | D71: 157.47 | E71: 155.26 | F71: 288.03 | G71: 277.2 | H71: 97.14 | I71: 157.39
A72: Dividend income | D72: 37.98 | E72: 70.56 | F72: 71.76 | G72: 48.27 | H72: 1.39 | I72: 1.67
A73: On current Investments - Non-Trade | B73: 1.5 | C73: 7.06
A74: On long-term investments-Trade and Non trade | B74: 0.06 | C74: 0.12
A75: Capital expenditure on fixed assets, including capital advances | B75: -1232.93 | C75: -1708.02
A76: Payment of deferred credits | B76: -287.34
A77: Net cash from / (used) in investing activities | B77: =SUM(B62:B76) -> 31.38 | C77: =SUM(C62:C76) -> -2285.88 | D77: =SUM(D61:D76) -> -1971.95 | E77: =SUM(E61:E76) -> -1858.21 | F77: =SUM(F61:F76) -> 1297.64 | G77: =SUM(G61:G76) -> -2819.14 | H77: =SUM(H61:H76) -> -2289.32 | I77: =SUM(I61:I76) -> -221.97
A79: Cash Flow from Financing Activities
A80: Interest paid | B80: -11.7 | C80: -11.23 | D80: -27.4 | E80: -31.25 | F80: -36.93 | G80: -46.67 | H80: -46.19 | I80: -52.85
A81: Payment of lease liabilities | G81: -114.95 | H81: -29.17 | I81: -30.58
A82: Dividends paid | B82: -1897.03 | C82: -1397.81 | D82: -1737.34 | E82: -1697.5 | F82: -1928.6 | G82: -1957.04 | H82: -1918.3 | I82: -1907.27
A83: Tax on dividend | B83: -322.4 | C83: -284.56 | D83: -353.69 | E83: -345.57 | F83: -390.01 | G83: -401.4 | H83: -2.5 | I83: -1.12
A84: Additions to minority interest | D84: 52.72 | E84: 1.93 | F84: 17.55 | G84: 17.47 | H84: 6.65 | I84: -
A85: Proceeds from issue of equity share capital | B85: - | C85: 0.56 | D85: 1.45 | E85: 2.66 | F85: 1.98 | G85: 0.12 | H85: 7.83 | I85: 5.04
A86: Proceeds from long-term borrowings | B86: 12 | C86: 136.15 | D86: 61.92 | E86: -58.27 | F86: -24.79 | G86: -80.82 | H86: 1.16 | I86: -9.01
A87: Proceeds from other short-term borrowings | B87: 88 | C87: -3.94 | D87: -33.52 | E87: 25.55 | F87: 108.4 | G87: -18.51 | H87: 128.7 | I87: 20.46
A88: Net cash (used) in financing activities | B88: =SUM(B80:B87) -> -2131.13 | C88: =SUM(C80:C87) -> -1560.83 | D88: =SUM(D80:D87) -> -2035.86 | E88: =SUM(E80:E87) -> -2102.45 | F88: =SUM(F80:F87) -> -2252.4 | G88: =SUM(G80:G87) -> -2601.8 | H88: =SUM(H80:H87) -> -1851.82 | I88: =SUM(I80:I87) -> -1975.33
A90: Increase/(Decrease) In Cash and Cash Equivalents | B90: =B58+B77+B88 -> 85.76 | C90: =C58+C77+C88 -> -50.3 | D90: =D58+D77+D88 -> -0.62 | E90: =E58+E77+E88 -> 56.55 | F90: =F58+F77+F88 -> 77.51 | G90: =G58+G77+G88 -> 97.19 | H90: =H58+H77+H88 -> -30.69 | I90: =I58+I77+I88 -> -93.6
A91: Cash and cash equivalents at the beginning of the year | B91: 68.74 | C91: 154.5 | D91: 74.68 | E91: 74.06 | F91: 130.61 | G91: 208.12 | H91: 305.31 | I91: 274.62
A92: Add: on account of amalgamation
A93: Cash and cash equivalents at the end of the year | B93: =SUM(B90:B92) -> 154.5 | C93: =SUM(C90:C92) -> 104.2 | D93: =SUM(D90:D92) -> 74.06 | E93: =SUM(E90:E92) -> 130.61 | F93: =SUM(F90:F92) -> 208.12 | G93: =SUM(G90:G92) -> 305.31 | H93: =SUM(H90:H92) -> 274.62 | I93: =SUM(I90:I92) -> 181.02
A94: Bank balance | D94: 121.33 | E94: 106.96 | F94: 95.78 | G94: 130.1 | H94: 121.62 | I94: 118.72
A95: Cash and Bank balances as per Balance Sheet | B95: 215.78 | C95: 179.09 | D95: 195.39 | E95: 237.57 | F95: 303.88 | G95: 435.43 | H95: 396.24 | I95: 299.74
A96: Less: Unpaid dividend current account with Banks | B96: 61.28 | C96: 74.89
A97: Cash and cash equivalents at the end of the year | B97: =B95-B96 -> 154.5 | C97: =C95-C96 -> 104.2 | D97: =D95-D96 -> 195.39 | E97: =E95-E96 -> 237.57 | F97: =F95-F96 -> 303.88 | G97: =G95-G96 -> 435.43 | H97: =H95-H96 -> 396.24 | I97: =I95-I96 -> 299.74

Sheet Shareholding
A2: Promoter Group | B2: 0.346
A3: Foreign Institutional Investors (FII) | B3: 0.343
A4: Non Resident Indians (NRIs) | B4: 0.004
A5: Indian Public | B5: 0.083
A6: Insurance companies | B6: 0.083
A7: Mutual Funds / UTI | B7: 0.082
A8: Bodies Corporate | B8: 0.014
A9: Financial Institutions / Banks | B9: 0.02
A10: Others | B10: 0.025
