Workbook

Sheet Copyright

Sheet Exhibit 1
A1: Movie | B1: Opening Gross | C1: Total U.S. Gross | D1: Total Non-U.S. Gross | E1: Budget | F1: Opening Theatres | G1: Known Story | H1: Sequel | I1: Origin_United States | J1: Genre | K1: Summer | L1: Holiday | M1: Christmas | N1: MPAA | O1: MPAA_D | P1: Critics´ Opinion | Q1: Oscar Nominations | R1: Oscars Won | S1: COMEDY DUMMY | T1: COMMEDY x CRITICS
A2: 16 Blocks | B2: 11855260 | C2: 36895141 | D2: 65664721 | E2: 45000000 | F2: 2706 | G2: 0 | H2: 0 | I2: 1 | J2: Action | K2: 1 | L2: 0 | M2: 0 | N2: PG-13 | O2: 0 | P2: 63 | Q2: 0 | R2: 0 | S2: =IF(J2="Comedy",1,0) -> 0 | T2: =S2*P2 -> 0
A3: Accepted | B3: 10023835 | C3: 36323505 | D3: 2146261 | E3: 23000000 | F3: 2914 | G3: 0 | H3: 0 | I3: 1 | J3: Comedy | K3: 0 | L3: 0 | M3: 0 | N3: PG-13 | O3: 0 | P3: 47 | Q3: 0 | R3: 0 | S3: =IF(J3="Comedy",1,0) -> 1 | T3: =S3*P3 -> 47
A4: Apocalypto | B4: 15005604 | C4: 50866635 | D4: 69309076 | E4: 40000000 | F4: 2465 | G4: 0 | H4: 0 | I4: 1 | J4: Adventure | K4: 0 | L4: 0 | M4: 0 | N4: R | O4: 1 | P4: 68 | Q4: 3 | R4: 0 | S4: =IF(J4="Comedy",1,0) -> 0 | T4: =S4*P4 -> 0
A5: Arthur and the Invisibles | B5: 4294936 | C5: 15132763 | D5: 97854413 | E5: 86000000 | F5: 2247 | G5: 0 | H5: 0 | I5: 0 | J5: Animation | K5: 1 | L5: 0 | M5: 0 | N5: PG | O5: 0 | P5: 39 | Q5: 0 | R5: 0 | S5: =IF(J5="Comedy",1,0) -> 0 | T5: =S5*P5 -> 0
A6: ATL | B6: 11554404 | C6: 21170563 | D6: 0 | E6: 20000000 | F6: 1602 | G6: 0 | H6: 0 | I6: 1 | J6: Drama | K6: 0 | L6: 0 | M6: 0 | N6: PG-13 | O6: 0 | P6: 63 | Q6: 0 | R6: 0 | S6: =IF(J6="Comedy",1,0) -> 0 | T6: =S6*P6 -> 0
A7: Babel | B7: 5558095 | C7: 34302837 | D7: 101027326 | E7: 20000000 | F7: 1251 | G7: 0 | H7: 0 | I7: 1 | J7: Drama | K7: 0 | L7: 0 | M7: 0 | N7: R | O7: 1 | P7: 69 | Q7: 7 | R7: 1 | S7: =IF(J7="Comedy",1,0) -> 0 | T7: =S7*P7 -> 0
A8: Barnyard: The Original Party Animals | B8: 15820864 | C8: 72637803 | D8: 43272126 | E8: 51000000 | F8: 3311 | G8: 0 | H8: 0 | I8: 1 | J8: Animation | K8: 1 | L8: 0 | M8: 0 | N8: PG | O8: 0 | P8: 42 | Q8: 0 | R8: 0 | S8: =IF(J8="Comedy",1,0) -> 0 | T8: =S8*P8 -> 0
A9: Big Momma's House 2 | B9: 27736056 | C9: 70165972 | D9: 68079671 | E9: 40000000 | F9: 3261 | G9: 0 | H9: 1 | I9: 1 | J9: Comedy | K9: 0 | L9: 1 | M9: 1 | N9: PG-13 | O9: 0 | P9: 34 | Q9: 0 | R9: 0 | S9: =IF(J9="Comedy",1,0) -> 1 | T9: =S9*P9 -> 34
A10: Blood Diamond | B10: 8648324 | C10: 57377916 | D10: 171407179 | E10: 100000000 | F10: 1910 | G10: 0 | H10: 0 | I10: 1 | J10: Drama | K10: 0 | L10: 0 | M10: 1 | N10: R | O10: 1 | P10: 63 | Q10: 5 | R10: 0 | S10: =IF(J10="Comedy",1,0) -> 0 | T10: =S10*P10 -> 0
A11: Charlotte's Web | B11: 11457353 | C11: 82599768 | D11: 61768463 | E11: 85000000 | F11: 3566 | G11: 1 | H11: 0 | I11: 1 | J11: Comedy | K11: 0 | L11: 0 | M11: 0 | N11: G | O11: 0 | P11: 68 | Q11: 0 | R11: 0 | S11: =IF(J11="Comedy",1,0) -> 1 | T11: =S11*P11 -> 68
A12: Children of Men | B12: 10197775 | C12: 35327768 | D12: 33897819 | E12: 76000000 | F12: 1209 | G12: 1 | H12: 0 | I12: 0 | J12: Thriller | K12: 0 | L12: 0 | M12: 0 | N12: R | O12: 1 | P12: 84 | Q12: 3 | R12: 0 | S12: =IF(J12="Comedy",1,0) -> 0 | T12: =S12*P12 -> 0
A13: Click | B13: 40011365 | C13: 137355633 | D13: 100325666 | E13: 82500000 | F13: 3749 | G13: 0 | H13: 0 | I13: 1 | J13: Comedy | K13: 1 | L13: 0 | M13: 0 | N13: PG-13 | O13: 0 | P13: 45 | Q13: 1 | R13: 0 | S13: =IF(J13="Comedy",1,0) -> 1 | T13: =S13*P13 -> 45
... A76: You, Me and Dupree | B76: 21525560 | C76: 75628110 | D76: 54731328 | E76: 54000000 | F76: 3131 | G76: 0 | H76: 0 | I76: 1 | J76: Comedy | K76: 0 | L76: 0 | M76: 0 | N76: PG-13 | O76: 0 | P76: 46 | Q76: 0 | R76: 0 | S76: =IF(J76="Comedy",1,0) -> 1 | T76: =S76*P76 -> 46

Sheet QUESTION 1
C3: MIN | D3: AVERAGE | E3: MAX
B4: OPENING GROSS | C4: =MIN('Exhibit 1'!B$2:B$76) -> 4120497 | D4: =AVERAGE('Exhibit 1'!B$2:B$76) -> 17468466 | E4: =MAX('Exhibit 1'!B$2:B$76) -> 68033544
B5: TOTAL US GROSS | C5: =MIN('Exhibit 1'!C$2:C$76) -> 13090630 | D5: =AVERAGE('Exhibit 1'!C$2:C$76) -> 59620651 | E5: =MAX('Exhibit 1'!C$2:C$76) -> 198000317
B6: TOTAL NON US GROSS | C6: =MIN('Exhibit 1'!D2:D76) -> 0 | D6: =AVERAGE('Exhibit 1'!D2:D76) -> 59560983 | E6: =MAX('Exhibit 1'!D2:D76) -> 456235122
B7: OPENING THEATRES | C7: =MIN('Exhibit 1'!F2:F76) -> 852 | D7: =AVERAGE('Exhibit 1'!F2:F76) -> 2766.28 | E7: =MAX('Exhibit 1'!F2:F76) -> 3964
B13: NUMBER OF COMEDIES | C13: =COUNTIF('Exhibit 1'!J2:J76,"Comedy") -> 23
B14: NUMBER OF R RATED MOVIES | C14: =COUNTIF('Exhibit 1'!O2:O76,1) -> 15

Sheet QUESTION 2
C1: TOTAL US GROSS | D1: BUDGET | E1: ROI
A2: QUESTION 2 A | C2: 36895141 | D2: 45000000 | E2: =(C2-D2)/D2 -> -0.18010798
C3: 36323505 | D3: 23000000 | E3: =(C3-D3)/D3 -> 0.57928283
C4: 50866635 | D4: 40000000 | E4: =(C4-D4)/D4 -> 0.27166588
C5: 15132763 | D5: 86000000 | E5: =(C5-D5)/D5 -> -0.82403764
C6: 21170563 | D6: 20000000 | E6: =(C6-D6)/D6 -> 0.05852815
C7: 34302837 | D7: 20000000 | E7: =(C7-D7)/D7 -> 0.71514185
C8: 72637803 | D8: 51000000 | E8: =(C8-D8)/D8 -> 0.42427065
C9: 70165972 | D9: 40000000 | E9: =(C9-D9)/D9 -> 0.7541493
C10: 57377916 | D10: 100000000 | E10: =(C10-D10)/D10 -> -0.42622084
C11: 82599768 | D11: 85000000 | E11: =(C11-D11)/D11 -> -0.028238024
C12: 35327768 | D12: 76000000 | E12: =(C12-D12)/D12 -> -0.53516095
C13: 137355633 | D13: 82500000 | E13: =(C13-D13)/D13 -> 0.66491676
C14: 58360760 | D14: 50000000 | E14: =(C14-D14)/D14 -> 0.1672152
... C76: 75628110 | D76: 54000000 | E76: =(C76-D76)/D76 -> 0.40052056
A79: QUESTION 2 B | C79: CONFIDENCE LEVEL | D79: 0.95
C80: SIGNIFICANCE LEVEL | D80: 0.05
C82: MEAN ROI | D82: =AVERAGE(E2:E76) -> 0.29293174
C83: SAMPLE STANDARD DEVIATION | D83: =_xlfn.STDEV.S(E2:E76) -> 0.68722811
C84: SAMPLE SIZE | D84: =COUNT(E2:E76) -> 75
C85: STANDARD ERROR | D85: =D83/SQRT(D84) -> 0.079354267
C86: T CRITICAL | D86: =_xlfn.T.INV.2T(D80,D84-1) -> 1.9925435
C88: CI UPPER | D88: =D82+D86*D85 -> 0.45104857
C89: CI LOWER | D89: =D82-D86*D85 -> 0.13481492
A91: QUESTION 2 C
C92: NULL HYPOTHESIS | D92: MEAN ROI <.12
C93: ALTERNATE HYPOTHESIS | D93: MEAN ROI >.12
C95: T-STAT | D95: =(D82-0.12)/D85 -> 2.1792369
C96: ONE-TAILED P-VALUE | D96: =_xlfn.T.DIST.RT(D95,(D84-1)) -> 0.016248627
C98: P-VALUE < SIGNIFICANCE LEVEL | D98: =IF(D96<D80,TRUE,FALSE) -> TRUE
C100: CONCLUSION | D100: REJECT NULL HYPOTHESIS, MEAN ROI SIGNIFICANTLY GREATER THAN 12%

Sheet QUESTION 3
C5: SIGNIFICANCE LEVEL | D5: 0.05
A9: QUESTION 3 A
C10: MEAN TOTAL US GROSS - COMEDY MOVIES | D10: =AVERAGEIF('Exhibit 1'!J2:J76,"Comedy",'Exhibit 1'!C2:C76) -> 68743100
C11: MEAN TOTAL US GROSS - NON COMEDY MOVIES | D11: =AVERAGEIF('Exhibit 1'!J2:J76,"<>Comedy",'Exhibit 1'!C2:C76) -> 55585721
C13: T- TEST P-VALUE | D13: {=_xlfn.T.TEST(_xlfn._xlws.FILTER('Exhibit 1'!C2:C76,'Exhibit 1'!J2:J76="Comedy"),_xlfn._xlws.FILTER('Exhibit 1'!C2:C76,'Exhibit 1'!J2:J76<>"Comedy"),2,3)} -> 0.17632026
C15: NULL HYPOTHESIS | D15: NO SIGNIFICANT STATISTICAL DIFFERENCE BETWEEN US GROSS OF COMEDY AND NON COMEDY MOVIES
C16: ALTERNATE HYPOTHESIS | D16: SIGNIFICANT STATISTICAL DIFFERENCE BETWEEN US GROSS OF COMEDY AND NON COMEDY MOVIES
C18: P-VALUE < SIGNIFICANCE LEVEL | D18: =IF(D13<D5,TRUE,FALSE) -> FALSE
C20: CONCLUSION | D20: NO SIGNIFICANT STATISTICAL DIFFERENCE BETWEEN US GROSS OF COMEDY AND NON COMEDY MOVIES
A23: QUESTION 3B | C23: MEAN ROI - COMEDY MOVIES | D23: {=AVERAGE(_xlfn._xlws.FILTER(('Exhibit 1'!C2:C76-'Exhibit 1'!E2:E76)/'Exhibit 1'!E2:E76,'Exhibit 1'!J2:J76="Comedy"))} -> 0.54017219
C24: MEAN ROI - NON COMEDY MOVIES | D24: {=AVERAGE(_xlfn._xlws.FILTER(('Exhibit 1'!C2:C76-'Exhibit 1'!E2:E76)/'Exhibit 1'!E2:E76,'Exhibit 1'!J2:J76<>"Comedy"))} -> 0.18357539
C26: T - TEST P - VALUE | D26: {=_xlfn.T.TEST( _xlfn._xlws.FILTER(('Exhibit 1'!C2:C76-'Exhibit 1'!E2:E76)/'Exhibit 1'!E2:E76,'Exhibit 1'!J2:J76="Comedy"), _xlfn._xlws.FILTER(('Exhibit 1'!C2:C76-'Exhibit 1'!E2:E76)/'Exhibit 1'!E2:E76,'Exhibit 1'!J2:J76<>"Comedy"), 2,3)} -> 0.047430039
C28: NULL HYPOTHESIS | D28: COMEDY MEAN ROI > NON COMEDY MEAN ROI
C29: ALTERNATE HYPOTHESIS | D29: COMEDY MEAN ROI < NON COMEDY MEAN ROI
C31: P-VALUE < SIGNIFICANCE LEVEL | D31: =IF(D26<D5,TRUE,FALSE) -> TRUE
C33: CONCLUSION | D33: COMEDY MEAN ROI > NON COMEDY MEAN ROI

Sheet QUESTION 4
C1: SIGNIFICANCE LEVEL | D1: 0.05
A2: QUESTION 4A
C3: MEAN TOTAL US GROSS - R RATED MOVIES | D3: =AVERAGEIF('Exhibit 1'!N2:N76,"R",'Exhibit 1'!C2:C76) -> 53330312
C4: MEAN TOTAL US GROSS - NON R RATED MOVIES | D4: =AVERAGEIF('Exhibit 1'!N2:N76,"<>R",'Exhibit 1'!C2:C76) -> 61193236
C6: T- TEST P-VALUE | D6: {=_xlfn.T.TEST( _xlfn._xlws.FILTER('Exhibit 1'!C2:C76,'Exhibit 1'!N2:N76="R"), _xlfn._xlws.FILTER('Exhibit 1'!C2:C76,'Exhibit 1'!N2:N76<>"R"), 2, 3 )} -> 0.39789816
C8: NULL HYPOTHESIS | D8: NO SIGNIFICANT STATISTICAL DIFFERENCE BETWEEN US GROSS OF R AND NON R RATED MOVIES
C9: ALTERNATE HYPOTHESIS | D9: SIGNIFICANT STATISTICAL DIFFERENCE BETWEEN US GROSS OF R AND NON R RATED MOVIES
C11: P-VALUE < SIGNIFICANCE LEVEL | D11: =IF(D6<D1,TRUE,FALSE) -> FALSE
C13: CONCLUSION | D13: NO SIGNIFICANT STATISTICAL DIFFERENCE BETWEEN US GROSS OF R AND NON R RATED MOVIES

Sheet QUESTION 5
A1: Total U.S. Gross | B1: Budget | C1: Sequel | D1: Known Story | E1: COMEDY DUMMY | F1: MPAA_D
A2: 36895141 | B2: 45000000 | C2: 0 | D2: 0 | E2: 0 | F2: 0
A3: 36323505 | B3: 23000000 | C3: 0 | D3: 0 | E3: 1 | F3: 0
A4: 50866635 | B4: 40000000 | C4: 0 | D4: 0 | E4: 0 | F4: 1
A5: 15132763 | B5: 86000000 | C5: 0 | D5: 0 | E5: 0 | F5: 0
A6: 21170563 | B6: 20000000 | C6: 0 | D6: 0 | E6: 0 | F6: 0
A7: 34302837 | B7: 20000000 | C7: 0 | D7: 0 | E7: 0 | F7: 1
A8: 72637803 | B8: 51000000 | C8: 0 | D8: 0 | E8: 0 | F8: 0
A9: 70165972 | B9: 40000000 | C9: 1 | D9: 0 | E9: 1 | F9: 0
A10: 57377916 | B10: 100000000 | C10: 0 | D10: 0 | E10: 0 | F10: 1
A11: 82599768 | B11: 85000000 | C11: 0 | D11: 1 | E11: 1 | F11: 0
A12: 35327768 | B12: 76000000 | C12: 0 | D12: 1 | E12: 0 | F12: 1
A13: 137355633 | B13: 82500000 | C13: 0 | D13: 0 | E13: 1 | F13: 0
... A76: 75628110 | B76: 54000000 | C76: 0 | D76: 0 | E76: 1 | F76: 0
A80: QUESTION 5A
A82: SUMMARY OUTPUT
A84: Regression Statistics
A85: Multiple R | B85: 0.59597218
A86: R Square | B86: 0.35518284
A87: Adjusted R Square | B87: 0.30845696
A88: Standard Error | B88: 33494160
A89: Observations | B89: 75
A91: ANOVA
B92: df | C92: MS | D92: SS | E92: F | F92: Significance F
A93: Regression | B93: 5 | C93: 8.5277143e+15 | D93: 4.2638571e+16 | E93: 7.6014155 | F93: 9.7800571e-06
A94: Residual | B94: 69 | C94: 1.1218587e+15 | D94: 7.7408252e+16
A95: Total | B95: 74 | D95: 1.2004682e+17
B97: Coefficients | C97: t Stat | D97: Standard Error | E97: P-value | F97: Lower 95% | G97: Upper 95% | H97: Lower 90.0% | I97: Upper 90.0%
A98: Intercept | B98: 12225020 | C98: 1.1619871 | D98: 10520788 | E98: 0.24924431 | F98: -8763378.1 | G98: 33213418 | H98: -5315643.6 | I98: 29765683
A99: Budget | B99: 0.89667184 | C99: 5.4235884 | D99: 0.16532815 | E99: 8.1184e-07 | F99: 0.5668512 | G99: 1.2264925 | H99: 0.62103037 | I99: 1.1723133
A100: Known Story | B100: -9977764.1 | C100: -1.2101007 | D100: 8245400 | E100: 0.23036956 | F100: -26426887 | G100: 6471358.8 | H100: -23724813 | I100: 3769284.6
A101: Sequel | B101: 29166707 | C101: 2.2832507 | D101: 12774203 | E101: 0.025499829 | F101: 3682869.8 | G101: 54650544 | H101: 7869063.7 | I101: 50464350
A102: COMEDY DUMMY | B102: 14758022 | C102: 1.6545629 | D102: 8919589.8 | E102: 0.10255549 | F102: -3036072.4 | G102: 32552117 | H102: -113061.63 | I102: 29629106
A103: MPAA_D | B103: -4156466.8 | C103: -0.40314394 | D103: 10310131 | E103: 0.68808883 | F103: -24724615 | G103: 16411682 | H103: -21345914 | I103: 13032981
A106: SIGNIFICANT LEVEL | B106: 0.1
A108: P-VALUE < SIGNIFICANT LEVEL
A110: Budget | B110: =IF($E99<$B$106,TRUE,FALSE) -> TRUE
A111: Known Story | B111: =IF($E100<$B$106,TRUE,FALSE) -> FALSE
A112: Sequel | B112: =IF($E101<$B$106,TRUE,FALSE) -> TRUE
A113: COMEDY DUMMY | B113: =IF($E102<$B$106,TRUE,FALSE) -> FALSE
A114: MPAA_D | B114: =IF($E103<$B$106,TRUE,FALSE) -> FALSE
A118: If p-value < 0.10 → variable is statistically significant at 10% level. If p-value > 0.10 → remove from regression.
A123: Conclusion for model simplification
A125: KEEP | B125: Budget
B126: MPAA_D
A128: REMOVE | B128: Known Story
B129: Sequel
B130: COMEDY DUMMY
A134: QUESTION 5B
A136: At the 10% significance level, only Budget and Sequel have statistically
A137: significant p-values. Therefore, the reduced regression model retains
A138: Budget and Sequel and removes Known Story, Comedy Dummy, and MPAA_D.
A140: Regression Statistics
A141: Multiple R | B141: 0.54917946
A142: R Square | B142: 0.30159808
A143: Adjusted R Square | B143: 0.28219803
A144: Standard Error | B144: 34124147
A145: Observations | B145: 75
A147: ANOVA
B148: df | C148: SS | D148: MS | E148: F | F148: Significance F
A149: Regression | B149: 2 | C149: 3.6205892e+16 | D149: 1.8102946e+16 | E149: 15.54625 | F149: 2.4422788e-06
A150: Residual | B150: 72 | C150: 8.3840932e+16 | D150: 1.1644574e+15
A151: Total | B151: 74 | C151: 1.2004682e+17
B153: Coefficients | C153: Standard Error | D153: t Stat | E153: P-value | F153: Lower 95% | G153: Upper 95% | H153: Lower 90.0% | I153: Upper 90.0%
A154: Intercept | B154: 13446248 | C154: 9348392 | D154: 1.4383487 | E154: 0.15466785 | F154: -5189431.3 | G154: 32081927 | H154: -2130919 | I154: 29023414
A155: Budget | B155: 0.87108823 | C155: 0.16802402 | D155: 5.1843076 | E155: 1.9081933e-06 | F155: 0.53613846 | G155: 1.206038 | H155: 0.59111085 | I155: 1.1510656
A156: Sequel | B156: 30496712 | C156: 12791462 | D156: 2.3841459 | E156: 0.019756182 | F156: 4997398.2 | G156: 55996026 | H156: 9182379.2 | I156: 51811045
A159: QUESTION 5C
A161: Holding all other explanatory variables constant, sequel movies have higher
A162: total U.S. box-office gross than non-sequels, because the coefficient for
A163: Sequel in the regression is positive and statistically significant.

Sheet QUESTION 6
A1: Opening Gross | B1: Budget | C1: Opening Theatres | D1: Sequel | E1: COMEDY DUMMY | F1: Summer | G1: Holiday | H1: Christmas
A2: 11855260 | B2: 45000000 | C2: 2706 | D2: 0 | E2: 0 | F2: 1 | G2: 0 | H2: 0
A3: 10023835 | B3: 23000000 | C3: 2914 | D3: 0 | E3: 1 | F3: 0 | G3: 0 | H3: 0
A4: 15005604 | B4: 40000000 | C4: 2465 | D4: 0 | E4: 0 | F4: 0 | G4: 0 | H4: 0
A5: 4294936 | B5: 86000000 | C5: 2247 | D5: 0 | E5: 0 | F5: 1 | G5: 0 | H5: 0
A6: 11554404 | B6: 20000000 | C6: 1602 | D6: 0 | E6: 0 | F6: 0 | G6: 0 | H6: 0
A7: 5558095 | B7: 20000000 | C7: 1251 | D7: 0 | E7: 0 | F7: 0 | G7: 0 | H7: 0
A8: 15820864 | B8: 51000000 | C8: 3311 | D8: 0 | E8: 0 | F8: 1 | G8: 0 | H8: 0
A9: 27736056 | B9: 40000000 | C9: 3261 | D9: 1 | E9: 1 | F9: 0 | G9: 1 | H9: 1
A10: 8648324 | B10: 100000000 | C10: 1910 | D10: 0 | E10: 0 | F10: 0 | G10: 0 | H10: 1
A11: 11457353 | B11: 85000000 | C11: 3566 | D11: 0 | E11: 1 | F11: 0 | G11: 0 | H11: 0
A12: 10197775 | B12: 76000000 | C12: 1209 | D12: 0 | E12: 0 | F12: 0 | G12: 0 | H12: 0
A13: 40011365 | B13: 82500000 | C13: 3749 | D13: 0 | E13: 1 | F13: 1 | G13: 0 | H13: 0
... A76: 21525560 | B76: 54000000 | C76: 3131 | D76: 0 | E76: 1 | F76: 0 | G76: 0 | H76: 0
A80: QUESTION 6A
B81: SUMMARY OUTPUT
B83: Regression Statistics
B84: Multiple R | C84: 0.71551664
B85: R Square | C85: 0.51196406
B86: Adjusted R Square | C86: 0.46097524
B87: Standard Error | C87: 8136070.5
B88: Observations | C88: 75
B90: ANOVA
C91: df | D91: SS | E91: MS | F91: F | G91: Significance F
B92: Regression | C92: 7 | D92: 4.652559e+15 | E92: 6.6465128e+14 | F92: 10.04071 | G92: 1.6312359e-08
B93: Residual | C93: 67 | D93: 4.4351081e+15 | E93: 6.6195643e+13
B94: Total | C94: 74 | D94: 9.0876671e+15
C96: Coefficients | D96: Standard Error | E96: t Stat | F96: P-value | G96: Lower 95% | H96: Upper 95% | I96: Lower 90.0% | J96: Upper 90.0%
B97: Intercept | C97: -9060367.4 | D97: 4091807.3 | E97: -2.2142703 | F97: 0.030216702 | G97: -17227649 | H97: -893085.85 | I97: -15885159 | J97: -2235576.1
B98: Budget | C98: 0.1328254 | D98: 0.042834755 | E98: 3.1008793 | F98: 0.0028220956 | G98: 0.047326876 | H98: 0.21832393 | I98: 0.061380626 | J98: 0.20427018
B99: Opening Theatres | C99: 7303.9372 | D99: 1527.8588 | E99: 4.7805054 | F99: 9.9505713e-06 | G99: 4254.3183 | H99: 10353.556 | I99: 4755.5969 | J99: 9852.2775
B100: Sequel | C100: 9879577.1 | D100: 3239752.2 | E100: 3.0494854 | F100: 0.0032812535 | G100: 3413004.6 | H100: 16346150 | I100: 4475942.2 | J100: 15283212
B101: Summer | C101: -3874082.6 | D101: 2173467.7 | E101: -1.7824431 | F101: 0.079207586 | G101: -8212342.3 | H101: 464177.15 | I101: -7499244.5 | J101: -248920.75
B102: Holiday | C102: -131146.03 | D102: 3539372.7 | E102: -0.037053468 | F102: 0.97055255 | G102: -7195763.5 | H102: 6933471.4 | I102: -6034522.8 | J102: 5772230.7
B103: Christmas | C103: -3935239.9 | D103: 3479048.6 | E103: -1.1311253 | F103: 0.26203495 | G103: -10879450 | H103: 3008970.1 | I103: -9738001 | J103: 1867521.3
B104: COMEDY DUMMY | C104: 1126880.8 | D104: 2187450.3 | E104: 0.51515722 | F104: 0.60813871 | G104: -3239288.2 | H104: 5493049.8 | I104: -2521602.8 | J104: 4775364.4
A108: QUESTION 6B
B109: SIGNIFICANCE LEVEL | C109: 0.1
B111: VARIABLES | C111: P-VALUE < SIGNIFICANCE LEVEL
B112: Budget | C112: =IF(F99<$C$109,TRUE,FALSE) -> TRUE
B113: Opening Theatres | C113: =IF(F100<$C$109,TRUE,FALSE) -> TRUE
B114: Sequel | C114: =IF(F101<$C$109,TRUE,FALSE) -> TRUE
B115: Summer | C115: =IF(F102<$C$109,TRUE,FALSE) -> FALSE
B116: Holiday | C116: =IF(F103<$C$109,TRUE,FALSE) -> FALSE
B117: Christmas | C117: =IF(F104<$C$109,TRUE,FALSE) -> FALSE | E117: If p-value < 0.10 → variable is statistically significant at 10% level.
B118: COMEDY DUMMY | C118: =IF(F105<$C$109,TRUE,FALSE) -> TRUE | E118: If p-value > 0.10 → remove from regression.
B121: VARIABLES TO BE DROPPED | C121: Holiday
C122: Christmas
C123: Summer
B126: FINAL REGRESSION
B128: SUMMARY OUTPUT
B130: Regression Statistics
B131: Multiple R | C131: 0.69494553
B132: R Square | C132: 0.48294929
B133: Adjusted R Square | C133: 0.45340354
B134: Standard Error | C134: 8193015
B135: Observations | C135: 75
B137: ANOVA
C138: df | D138: SS | E138: MS | F138: F | G138: Significance F
B139: Regression | C139: 4 | D139: 4.3888824e+15 | E139: 1.0972206e+15 | F139: 16.34581 | G139: 1.6849657e-09
B140: Residual | C140: 70 | D140: 4.6987847e+15 | E140: 6.7125496e+13
B141: Total | C141: 74 | D141: 9.0876671e+15
C143: Coefficients | D143: Standard Error | E143: t Stat | F143: P-value | G143: Lower 95% | H143: Upper 95% | I143: Lower 90.0% | J143: Upper 90.0%
B144: Intercept | C144: -10160198 | D144: 4079526.6 | E144: -2.4905336 | F144: 0.015130827 | G144: -18296557 | H144: -2023838.8 | I144: -16960420 | J144: -3359976.1
B145: Budget | C145: 0.11861785 | D145: 0.042332765 | E145: 2.8020341 | F145: 0.0065625093 | G145: 0.034187814 | H145: 0.20304789 | I145: 0.048052753 | J145: 0.18918295
B146: Opening Theatres | C146: 7325.3159 | D146: 1535.8847 | E146: 4.7694439 | F146: 9.7480641e-06 | G146: 4262.0905 | H146: 10388.541 | I146: 4765.1275 | J146: 9885.5044
B147: Sequel | C147: 9448917.4 | D147: 3254533.3 | E147: 2.9033094 | F147: 0.004935364 | G147: 2957955.3 | H147: 15939879 | I147: 4023888.6 | J147: 14873946
B148: COMEDY DUMMY | C148: 1670240.7 | D148: 2156332 | E148: 0.77457493 | F148: 0.44119939 | G148: -2630427.9 | H148: 5970909.3 | I148: -1924180.3 | J148: 5264661.7
A150: QUESTION 6C
B151: Variable | C151: Coefficient | D151: P-value | E151: Interpretation
B152: Intercept | C152: -10160198 | D152: 0.015 | E152: Predicted revenue when all predictors = 0 (not practically meaningful)
B153: Budget | C153: 0.1186 | D153: 0.0066 | E153: For every $1 million increase in Budget, revenue increases by approximately $118,617
B154: Opening Theatres | C154: 7325.32 | D154: 9.7e-06 | E154: Each additional Opening Theatre increases revenue by about $7,325
B155: Sequel (1=yes) | C155: 9448917.4 | D155: 0.0049 | E155: Sequels earn about $9.45 million more than non-sequels
B156: Comedy (1=yes) | C156: 1670240.7 | D156: 0.441 | E156: Comedies earn about $1.67 million more than non-comedies
A158: QUESTION 6D
B160: OPENING THEATRE
B162: Statistic | C162: Value
B163: Coefficient | C163: =C146 -> 7325.3159
B164: Standard Error | C164: =D146 -> 1535.8847
B165: df | C165: =C140 -> 70
B166: 95% CI Lower bound (per theatre) | C166: =G146 -> 4262.0905
B167: 95% CI Upper bound (per theatre) | C167: =H146 -> 10388.541
B169: POINT ESTIMATE | C169: =100*C163 -> 732531.59
B171: 95 % CONFIDENCE INTERVAL
B173: LOWER BOUND | C173: =100*C166 -> 426209.05
B174: UPPER BOUND | C174: =100*C167 -> 1038854.1

Sheet QUESTION 7
A1: Opening Gross | B1: Total U.S. Gross
A2: 11855260 | B2: 36895141
A3: 10023835 | B3: 36323505
A4: 15005604 | B4: 50866635
A5: 4294936 | B5: 15132763
A6: 11554404 | B6: 21170563
A7: 5558095 | B7: 34302837
A8: 15820864 | B8: 72637803
A9: 27736056 | B9: 70165972
A10: 8648324 | B10: 57377916
A11: 11457353 | B11: 82599768
A12: 10197775 | B12: 35327768
A13: 40011365 | B13: 137355633
... A76: 21525560 | B76: 75628110
A80: QUESTION 7A | B80: SUMMARY OUTPUT
B82: Regression Statistics
B83: Multiple R | C83: 0.85860152
B84: R Square | C84: 0.73719658
B85: Adjusted R Square | C85: 0.73359653
B86: Standard Error | C86: 20788800
B87: Observations | C87: 75
B89: ANOVA
C90: df | D90: SS | E90: MS | F90: F | G90: Significance F
B91: Regression | C91: 1 | D91: 8.8498107e+16 | E91: 8.8498107e+16 | F91: 204.77416 | G91: 7.0711641e-23
B92: Residual | C92: 73 | D92: 3.1548716e+16 | E92: 4.321742e+14
B93: Total | C93: 74 | D93: 1.2004682e+17
C95: Coefficients | D95: Standard Error | E95: t Stat | F95: P-value | G95: Lower 95% | H95: Upper 95% | I95: Lower 95.0% | J95: Upper 95.0%
B96: Intercept | C96: 5108220.4 | D96: 4502659.7 | E96: 1.1344896 | F96: 0.26030086 | G96: -3865567.4 | H96: 14082008 | I96: -3865567.4 | J96: 14082008
B97: Opening | C97: 3.1206193 | D97: 0.21807366 | E97: 14.309932 | F97: 7.0711641e-23 | G97: 2.6859991 | H97: 3.5552395 | I97: 2.6859991 | J97: 3.5552395
A103: QUESTION 7B | B103: SLOPE IF 25% RULE WERE TRUE: | C103: =1/0.25 -> 4 | D103: AS TOTAL = 1/0.25 x OPENING
B105: CONCLUSION: | C105: If the age-old wisdom were that 25% of the total gross comes from
C106: the opening weekend, the relationship would be: Opening=0.25xTotal.
C107: So the slope coefficient would have to be 4.
B110: SIGNIFICANCE LEVEL | C110: 0.05
A112: QUESTION 7C | B112: HYPOTHESIZED SLOPE | C112: 4
B113: T-STATISTICS | C113: =(C97-C103)/D97 -> -4.032494
B114: P-VALUE | C114: =_xlfn.T.DIST.2T(ABS(C103),C92) -> 0.00015019156
B115: ACTUAL MULTIPLIER | C115: =1/C97 -> 0.32044922
B117: NULL HYPOTHESIS | C117: H0​:β1​=4
B118: ALTERNATE HYPOTHESIS | C118: H1​:β1​≠4
B120: P-VALUE < SIGNIFICANCE LEVEL | C120: =IF(C114<C110,TRUE,FALSE) -> TRUE
B122: CONCLUSION: | C122: We reject the null hypothesis
A125: QUESTION 7D | B125: INTERCEPT COEFFICIENT | C125: =C96 -> 5108220.4
B126: INTERCEPT P-VALUE | C126: =F96 -> 0.26030086
B128: P-VALUE < SIGNIFICANCE LEVEL | C128: =IF(C126<C110,TRUE,FALSE) -> FALSE
B130: CONCLUSION: | C130: The regression shows a statistically significant intercept. This is logically flawed
C131: because it implies that a movie with an Opening Gross of $0 would still earn some
C132: ammount. While the model fits the data well, the intercept is not logically possible.
A135: QUESTION 7E | B135: INTERCEPT P-VALUE | C135: =F96 -> 0.26030086
B136: SLOPE P-VALUE | C136: =F97 -> 7.0711641e-23
B138: P-VALUE < SIGNIFICANT LEVEL
B140: Intercept | C140: =IF(C135<C110,TRUE,FALSE) -> FALSE
B141: Opening | C141: =IF(C136<C110,TRUE,FALSE) -> TRUE
B143: MODEL EQUATION | C143: ="Total Gross = " & TEXT(C96, "$0,0") & " + " & ROUND(C97, 2) & "(Opening)" -> Total Gross = $5,108,220 + 3.12(Opening)
A146: QUESTION 7F | B146: REGRESSION SLOPE | C146: =C97 -> 3.1206193
B147: IMPLIED SLOPE | C147: =C103 -> 4
B148: ACTUAL SHARE % | C148: =1/C146*100 -> 32.044922
B149: IMPLIED SHARE % | C149: =1/C147*100 -> 25
B150: DIFFERENCE | C150: =C148-C149 -> 7.0449216
B151: VALIDITY | C151: =IF(C150=0,"VALID","INVALID") -> INVALID
B153: CONCLUSION: | C153: The age-old wisdom is invalid for this dataset. The actual multiplier is ~3.12,
C154: meaning Opening Weekend accounts for ~32% of toal gross, not 25%
A157: QUESTION 7G | B157: R SQUARE | C157: =C84 -> 0.73719658
B158: EXPLAINED VARIATION % | C158: =C157*100 -> 73.719658
B160: CONCLUSION: | C160: Approximately 73% of the variation in the Total U.S. Box Office Gross is explained
C161: by the variation in the Opening Weekend Gross.

Sheet QUESTION 8
A1: Total U.S. Gross | B1: Opening Gross | C1: Budget | D1: Critics´ Opinion | E1: COMEDY DUMMY | F1: Opening Theatres | G1: Sequel | H1: MPAA_D
A2: 36895141 | B2: 11855260 | C2: 45000000 | D2: 63 | E2: 0 | F2: 2706 | G2: 0 | H2: 0
A3: 36323505 | B3: 10023835 | C3: 23000000 | D3: 47 | E3: 1 | F3: 2914 | G3: 0 | H3: 0
A4: 50866635 | B4: 15005604 | C4: 40000000 | D4: 68 | E4: 0 | F4: 2465 | G4: 0 | H4: 1
A5: 15132763 | B5: 4294936 | C5: 86000000 | D5: 39 | E5: 0 | F5: 2247 | G5: 0 | H5: 0
A6: 21170563 | B6: 11554404 | C6: 20000000 | D6: 63 | E6: 0 | F6: 1602 | G6: 0 | H6: 0
A7: 34302837 | B7: 5558095 | C7: 20000000 | D7: 69 | E7: 0 | F7: 1251 | G7: 0 | H7: 1
A8: 72637803 | B8: 15820864 | C8: 51000000 | D8: 42 | E8: 0 | F8: 3311 | G8: 0 | H8: 0
A9: 70165972 | B9: 27736056 | C9: 40000000 | D9: 34 | E9: 1 | F9: 3261 | G9: 1 | H9: 0
A10: 57377916 | B10: 8648324 | C10: 100000000 | D10: 63 | E10: 0 | F10: 1910 | G10: 0 | H10: 1
A11: 82599768 | B11: 11457353 | C11: 85000000 | D11: 68 | E11: 1 | F11: 3566 | G11: 0 | H11: 0
A12: 35327768 | B12: 10197775 | C12: 76000000 | D12: 84 | E12: 0 | F12: 1209 | G12: 0 | H12: 1
A13: 137355633 | B13: 40011365 | C13: 82500000 | D13: 45 | E13: 1 | F13: 3749 | G13: 0 | H13: 0
... A76: 75628110 | B76: 21525560 | C76: 54000000 | D76: 46 | E76: 1 | F76: 3131 | G76: 0 | H76: 0
A80: QUESTION 8A | B80: SUMMARY OUTPUT
B82: Regression Statistics
B83: Multiple R | C83: 0.91407422
B84: R Square | C84: 0.83553168
B85: Adjusted R Square | C85: 0.81834842
B86: Standard Error | C86: 17166394
B87: Observations | C87: 75
B89: ANOVA
C90: df | D90: SS | E90: MS | F90: F | G90: Significance F
B91: Regression | C91: 7 | D91: 1.0030292e+17 | E91: 1.4328989e+16 | F91: 48.624754 | G91: 7.8703757e-24
B92: Residual | C92: 67 | D92: 1.97439e+16 | E92: 2.9468507e+14
B93: Total | C93: 74 | D93: 1.2004682e+17
C95: Coefficients | D95: Standard Error | E95: t Stat | F95: P-value | G95: Lower 95% | H95: Upper 95% | I95: Lower 95.0% | J95: Upper 95.0%
B96: Intercept | C96: -34722042 | D96: 12230083 | E96: -2.8390683 | F96: 0.0059840356 | G96: -59133391 | H96: -10310693 | I96: -59133391 | J96: -10310693
B97: Opening Gross | C97: 2.7990926 | D97: 0.25860121 | E97: 10.823973 | F97: 2.3526163e-16 | G97: 2.2829224 | H97: 3.3152627 | I97: 2.2829224 | J97: 3.3152627
B98: Budget | C98: 0.25119634 | D98: 0.098362491 | E98: 2.5537818 | F98: 0.012937204 | G98: 0.054863988 | H98: 0.4475287 | I98: 0.054863988 | J98: 0.4475287
B99: Opening Theaters | C99: 953.80943 | D99: 3890.0361 | E99: 0.24519295 | F99: 0.8070565 | G99: -6810.7351 | H99: 8718.354 | I99: -6810.7351 | J99: 8718.354
B100: Sequel | C100: -4422888 | D100: 7374763.5 | E100: -0.59973286 | F100: 0.55070721 | G100: -19142978 | H100: 10297202 | I100: -19142978 | J100: 10297202
B101: MPAA_D | C101: -8788581.8 | D101: 5452830.9 | E101: -1.6117466 | F101: 0.11171829 | G101: -19672478 | H101: 2095314.3 | I101: -19672478 | J101: 2095314.3
B102: Critics Opinion | C102: 611856.46 | D102: 149133.21 | E102: 4.1027513 | F102: 0.00011293783 | G102: 314185.33 | H102: 909527.58 | I102: 314185.33 | J102: 909527.58
B103: COMMEDY DUMMY | C103: 5572070.8 | D103: 4789103.7 | E103: 1.1634893 | F103: 0.24875792 | G103: -3987020.1 | H103: 15131162 | I103: -3987020.1 | J103: 15131162
B106: SIGNIFICANT LEVEL | C106: 0.1
A108: QUESTION 8B | B108: P-VALUE < SIGNIFICANT LEVEL
B110: Opening Gross | C110: =IF(F97<$C$106,TRUE,FALSE) -> TRUE
B111: Budget | C111: =IF(F98<$C$106,TRUE,FALSE) -> TRUE
B112: Opening Theaters | C112: =IF(F99<$C$106,TRUE,FALSE) -> FALSE
B113: Sequel | C113: =IF(F100<$C$106,TRUE,FALSE) -> FALSE
B114: MPAA_D | C114: =IF(F101<$C$106,TRUE,FALSE) -> FALSE
B115: Critics Opinion | C115: =IF(F102<$C$106,TRUE,FALSE) -> TRUE
B116: COMEDY DUMMY | C116: =IF(F103<$C$106,TRUE,FALSE) -> FALSE
B119: If p-value < 0.10 → variable is statistically significant at 10% level.
B120: If p-value > 0.10 → remove from regression.
B123: REMOVE | C123: Opening Theater
C124: Sequel
C125: MPAA_D
C126: COMMEDY DUMMY
B129: FINAL REGRESSION
B131: SUMMARY OUTPUT
B133: Regression Statistics
B134: Multiple R | C134: 0.90502412
B135: R Square | C135: 0.81906865
B136: Adjusted R Square | C136: 0.81142366
B137: Standard Error | C137: 17490534
B138: Observations | C138: 75
B140: ANOVA
C141: df | D141: SS | E141: MS | F141: F | G141: Significance F
B142: Regression | C142: 3 | D142: 9.8326589e+16 | E142: 3.277553e+16 | F142: 107.13801 | G142: 2.7028599e-26
B143: Residual | C143: 71 | D143: 2.1720234e+16 | E143: 3.0591879e+14
B144: Total | C144: 74 | D144: 1.2004682e+17
C146: Coefficients | D146: Standard Error | E146: t Stat | F146: P-value | G146: Lower 95% | H146: Upper 95% | I146: Lower 90.0% | J146: Upper 90.0%
B147: Intercept | C147: -28791152 | D147: 7294541.1 | E147: -3.9469449 | F147: 0.00018407033 | G147: -43336054 | H147: -14246250 | I147: -40948232 | J147: -16634072
B148: Opening Gross | C148: 2.8492547 | D148: 0.1953452 | E148: 14.585742 | F148: 4.743877e-23 | G148: 2.4597474 | H148: 3.2387619 | I148: 2.5236924 | J148: 3.1748169
B149: Budget | C149: 0.26632357 | D149: 0.097280469 | E149: 2.737688 | F149: 0.0078141927 | G149: 0.072351828 | H149: 0.46029532 | I149: 0.10419598 | J149: 0.42845117
B150: Critics´ Opinion | C150: 504422.36 | D150: 134994.49 | E150: 3.7366143 | F150: 0.00037389087 | G150: 235250.98 | H150: 773593.73 | I150: 279440.58 | J150: 729404.13
A152: QUESTION 8C
B154: MOVIE TITLE | C154: FLAG OF OUR FATHERS
B155: OPENING GROSS | C155: ='Exhibit 1'!B22 -> 10245190
B156: BUDGET | C156: ='Exhibit 1'!E22 -> 90000000
B157: CRITICS SCORE | C157: ='Exhibit 1'!P22 -> 79
B159: POINT ESTIMATE: | C159: =C147+ (C155*C148) + (C156*C149) + (C157*C150) -> 64218491
B161: SIGNIFICANCE INTERVAL | C161: 0.05
B163: FOR 95% PREDICTION INTERVAL
B164: STANDARD ERROR | C164: =C137 -> 17490534
B165: T-VALUE | C165: =_xlfn.T.INV.2T(C161,C164) -> 1.9599641
B166: MARGIN OF ERROR | C166: =C164*C165 -> 34280819
B167: LOWER BOUND | C167: =C159-C166 -> 29937672
B168: UPPER BOUND | C168: =C159+C167 -> 94156163
A171: QUESTION 8D
B172: DESCRIPTION | C172: VALUE
B173: CRITICS COEFFICIENT | C173: =C150 -> 504422.36
B174: INCREASE IN SCORE | C174: 10
B175: INCREASE IN US GROSS | C175: =C150*C174 -> 5044223.6
B176: MAX INVESTMENT | C176: =C175 -> 5044223.6
B178: CONCLUSION | C178: DO NOT SPEND MORE THAN 5.04 MILLION DOLLARS TO INFLUENCE CRITICS SCORE BY 10

Sheet QUESTION 9
A1: Total U.S. Gross | B1: Opening Gross | C1: Opening Theatres | D1: Critics´ Opinion | E1: COMEDY DUMMY | F1: COMMEDY x CRITICS
A2: 36895141 | B2: 11855260 | C2: 2706 | D2: 63 | E2: 0 | F2: 0
A3: 36323505 | B3: 10023835 | C3: 2914 | D3: 47 | E3: 1 | F3: 47
A4: 50866635 | B4: 15005604 | C4: 2465 | D4: 68 | E4: 0 | F4: 0
A5: 15132763 | B5: 4294936 | C5: 2247 | D5: 39 | E5: 0 | F5: 0
A6: 21170563 | B6: 11554404 | C6: 1602 | D6: 63 | E6: 0 | F6: 0
A7: 34302837 | B7: 5558095 | C7: 1251 | D7: 69 | E7: 0 | F7: 0
A8: 72637803 | B8: 15820864 | C8: 3311 | D8: 42 | E8: 0 | F8: 0
A9: 70165972 | B9: 27736056 | C9: 3261 | D9: 34 | E9: 1 | F9: 34
A10: 57377916 | B10: 8648324 | C10: 1910 | D10: 63 | E10: 0 | F10: 0
A11: 82599768 | B11: 11457353 | C11: 3566 | D11: 68 | E11: 1 | F11: 68
A12: 35327768 | B12: 10197775 | C12: 1209 | D12: 84 | E12: 0 | F12: 0
A13: 137355633 | B13: 40011365 | C13: 3749 | D13: 45 | E13: 1 | F13: 45
... A76: 75628110 | B76: 21525560 | C76: 3131 | D76: 46 | E76: 1 | F76: 46
B80: SUMMARY OUTPUT
B82: Regression Statistics
B83: Multiple R | C83: 0.90032224
B84: R Square | C84: 0.81058013
B85: Adjusted R Square | C85: 0.79685405
B86: Standard Error | C86: 18153633
B87: Observations | C87: 75
B89: ANOVA
C90: df | D90: SS | E90: MS | F90: F | G90: Significance F
B91: Regression | C91: 5 | D91: 9.730757e+16 | E91: 1.9461514e+16 | F91: 59.054025 | G91: 1.3960693e-23
B92: Residual | C92: 69 | D92: 2.2739254e+16 | E92: 3.295544e+14
B93: Total | C93: 74 | D93: 1.2004682e+17
C95: Coefficients | D95: Standard Error | E95: t Stat | F95: P-value | G95: Lower 95% | H95: Upper 95% | I95: Lower 95.0% | J95: Upper 95.0%
B96: Intercept | C96: -41015567 | D96: 13736519 | E96: -2.9858778 | F96: 0.0039107068 | G96: -68419173 | H96: -13611961 | I96: -68419173 | J96: -13611961
B97: Opening Gross | C97: 2.8321968 | D97: 0.25201111 | E97: 11.238381 | F97: 3.0428676e-17 | G97: 2.3294484 | H97: 3.3349452 | I97: 2.3294484 | J97: 3.3349452
B98: Opening Theater | C98: 3360.0634 | D98: 4043.4278 | E98: 0.83099378 | F98: 0.40884351 | G98: -4706.3544 | H98: 11426.481 | I98: -4706.3544 | J98: 11426.481
B99: Critics Opinion | C99: 779933.34 | D99: 163449.97 | E99: 4.7716944 | F99: 9.8619971e-06 | G99: 453859.56 | H99: 1106007.1 | I99: 453859.56 | J99: 1106007.1
B100: COMMEDY DUMMY | C100: 18140650 | D100: 15343518 | E100: 1.1823005 | F100: 0.24114477 | G100: -12468831 | H100: 48750132 | I100: -12468831 | J100: 48750132
B101: COMMEDY x CRITICS | C101: -230049.97 | D101: 312209.33 | E101: -0.73684527 | F101: 0.46371454 | G101: -852890.55 | H101: 392790.61 | I101: -852890.55 | J101: 392790.61
A104: QUESTION 9
B105: SIGNIFICANT VALUE | C105: 0.05
B107: NULL HYPOTHESIS | C107: CRITICS SCORE AFFECT COMEDY AND NON COMEDY MOVIES EQUALLY
B108: ALTERNATE HYPOTHESIS | C108: CRITICS SCORE MATTER LESS FOR COMEDIES
B110: P-VALUE OF COMEDY X CRITICS < SIGNIFICANT VALUE | C110: =IF(F101<C105,TRUE,FALSE) -> FALSE

Sheet QUESTION 10
A1: Total U.S. Gross | B1: Opening Gross | C1: Budget | D1: Critics´ Opinion | E1: COMEDY DUMMY | F1: COMMEDY x CRITICS
A2: 36895141 | B2: 11855260 | C2: 45000000 | D2: 63 | E2: 0 | F2: 0
A3: 36323505 | B3: 10023835 | C3: 23000000 | D3: 47 | E3: 1 | F3: 47
A4: 50866635 | B4: 15005604 | C4: 40000000 | D4: 68 | E4: 0 | F4: 0
A5: 15132763 | B5: 4294936 | C5: 86000000 | D5: 39 | E5: 0 | F5: 0
A6: 21170563 | B6: 11554404 | C6: 20000000 | D6: 63 | E6: 0 | F6: 0
A7: 34302837 | B7: 5558095 | C7: 20000000 | D7: 69 | E7: 0 | F7: 0
A8: 72637803 | B8: 15820864 | C8: 51000000 | D8: 42 | E8: 0 | F8: 0
A9: 70165972 | B9: 27736056 | C9: 40000000 | D9: 34 | E9: 1 | F9: 34
A10: 57377916 | B10: 8648324 | C10: 100000000 | D10: 63 | E10: 0 | F10: 0
A11: 82599768 | B11: 11457353 | C11: 85000000 | D11: 68 | E11: 1 | F11: 68
A12: 35327768 | B12: 10197775 | C12: 76000000 | D12: 84 | E12: 0 | F12: 0
A13: 137355633 | B13: 40011365 | C13: 82500000 | D13: 45 | E13: 1 | F13: 45
... A76: 75628110 | B76: 21525560 | C76: 54000000 | D76: 46 | E76: 1 | F76: 46
B80: SUMMARY OUTPUT
B82: Regression Statistics
B83: Multiple R | C83: 0.909983
B84: R Square | C84: 0.82806905
B85: Adjusted R Square | C85: 0.81561029
B86: Standard Error | C86: 17295289
B87: Observations | C87: 75
B89: ANOVA
C90: df | D90: SS | E90: MS | F90: F | G90: Significance F
B91: Regression | C91: 5 | D91: 9.9407059e+16 | E91: 1.9881412e+16 | F91: 66.464782 | G91: 5.0917872e-25
B92: Residual | C92: 69 | D92: 2.0639764e+16 | E92: 299127014886055
B93: Total | C93: 74 | D93: 1.2004682e+17
C95: Coefficients | D95: Standard Error | E95: t Stat | F95: P-value | G95: Lower 95% | H95: Upper 95% | I95: Lower 95.0% | J95: Upper 95.0%
B96: Intercept | C96: -35555909 | D96: 8600826.4 | E96: -4.1340108 | F96: 9.8741268e-05 | G96: -52714088 | H96: -18397730 | I96: -52714088 | J96: -18397730
B97: Opening Gross | C97: 2.7831972 | D97: 0.19692126 | E97: 14.133554 | F97: 4.684296e-22 | G97: 2.3903501 | H97: 3.1760444 | I97: 2.3903501 | J97: 3.1760444
B98: Budget | C98: 0.26915136 | D98: 0.09649843 | E98: 2.7891786 | F98: 0.0068243756 | G98: 0.076642255 | H98: 0.46166046 | I98: 0.076642255 | J98: 0.46166046
B99: Critics Opinion | C99: 605744.69 | D99: 158117.47 | E99: 3.8309789 | F99: 0.00027813902 | G99: 290308.97 | H99: 921180.41 | I99: 290308.97 | J99: 921180.41
B100: COMMEDY DUMMY | C100: 15543606 | D100: 14636456 | E100: 1.0619788 | F100: 0.29194821 | G100: -13655325 | H100: 44742536 | I100: -13655325 | J100: 44742536
B101: COMMEDY x CRITICS | C101: -154302.79 | D101: 297541.09 | E101: -0.5185932 | F101: 0.60570364 | G101: -747881.02 | H101: 439275.45 | I101: -747881.02 | J101: 439275.45
A105: QUESTION 10 | B105: CURRENT STATE: | C105: The regression above shows Budget has a coefficient of 0.27 and is statistically significant (p=0.007). This suggests every $1 of budget adds $0.27 to the gross.
B106: GRIFITH THEORY: | C106: He claims Star Power (missing from data) is the real driver. Star Power is positively correlated with Budget (stars cost money) and positively correlated with Gross (stars attract viewers).
B107: CONCLUSION: | C107: If we could add Star Power to this calculation, the Budget coefficient (currently 0.27) would decrease (likely becoming insignificant). The current 0.27 value is "biased upwards" because it is stealing credit from the missing Star Power variable.
