Workbook

Sheet Documentation
A1: MedIT Conference
A3: Prepared By | B3: Carmen Estrada
A4: Purpose | B4: To estimate revenues and expenses for the upcoming Medical Information Technology regional conference in Boston, Massachuesetts
A6: Topic | B6: Getting Started with Excel
A7: Chapter | B7: 1
A8: Section | B8: Chapter
A9: Filename | B9: NP_EX_1-1.xlsx

Sheet Budget
A1: MedIT Conference Budget
A2: Summary of Projected Revenue and Expenses
A4: Revenue
A5: Account ID | B5: Description | C5: Amount
A6: R1-1010 | B6: Individual | C6: ='Registration Revenue'!E4 -> 211990
A7: R1-1020 | B7: Corporate Sponsors | C7: ='Registration Revenue'!E5 -> 30000
A8: R1-1030 | B8: Vendor Exhibits | C8: ='Registration Revenue'!E6 -> 20000
B9: Total | C9: =SUM(C6:C8) -> 261990
A11: Expenses
A12: Account ID | B12: Description | C12: Amount
A13: E1-1010 | B13: Food | C13: ='Meal Costs'!E15 -> 183573
A14: E1-2010 | B14: Conference Organizer | C14: 15000
A15: E1-2020 | B15: Speakers | C15: 10000
A16: E1-4010 | B16: Rooms | C16: ='Room Costs'!E14+'Room Costs'!F19 -> 26350
A17: E1-5010 | B17: A/V/Network | C17: 6000
A18: E1-7010 | B18: Travel | C18: 10000
A19: E1-9090 | B19: Miscellaneous | C19: 9000
B20: Total | C20: =SUM(C13:C19) -> 259923
B22: Balance | C22: =C9-C20 -> 2067

Sheet Registration Revenue
A1: MedIT Conference Registration Revenue
A3: Account ID | B3: Description | C3: Units | D3: per Unit | E3: Amount
A4: R1-1010 | B4: Individual Registration | C4: =COUNTA('Registration List'!A:A)-2 -> 493 | D4: 430 | E4: =D4*C4 -> 211990
A5: R1-1020 | B5: Sponsorship | C5: 5 | D5: 6000 | E5: =D5*C5 -> 30000
A6: R1-1030 | B6: Vendor Exhibits | C6: 20 | D6: 1000 | E6: =D6*C6 -> 20000
D7: Total | E7: =SUM(E4:E6) -> 261990

Sheet Meal Costs
A1: MedIT Conference Meal Costs
A3: Account ID | B3: Meal Description | C3: Plates | D3: Cost per Plate | E3: Total
A4: E2-1010 | B4: Breakfast Day 1 | C4: ='Registration Revenue'!$C$4+'Room Costs'!$C$17+'Room Costs'!$C$18 -> 523 | D4: 20 | E4: =C4*D4 -> 10460
A5: E2-1020 | B5: Lunch Day 1 | C5: ='Registration Revenue'!$C$4+'Room Costs'!$C$17+'Room Costs'!$C$18 -> 523 | D5: 25 | E5: =C5*D5 -> 13075
A6: E2-1030 | B6: Dinner Day 1 | C6: ='Registration Revenue'!$C$4+'Room Costs'!$C$17+'Room Costs'!$C$18 -> 523 | D6: 50 | E6: =C6*D6 -> 26150
A7: E2-1010 | B7: Breakfast Day 2 | C7: ='Registration Revenue'!$C$4+'Room Costs'!$C$17+'Room Costs'!$C$18 -> 523 | D7: 20 | E7: =C7*D7 -> 10460
A8: E2-1020 | B8: Lunch Day 2 | C8: ='Registration Revenue'!$C$4+'Room Costs'!$C$17+'Room Costs'!$C$18 -> 523 | D8: 25 | E8: =C8*D8 -> 13075
A9: E2-1040 | B9: Bar Day 2 | C9: ='Registration Revenue'!$C$4+'Room Costs'!$C$17+'Room Costs'!$C$18 -> 523 | D9: 20 | E9: =C9*D9 -> 10460
A10: E2-1030 | B10: Dinner Day 2 | C10: ='Registration Revenue'!$C$4+'Room Costs'!$C$17+'Room Costs'!$C$18 -> 523 | D10: 65 | E10: =C10*D10 -> 33995
A11: E2-1010 | B11: Breakfast Day 3 | C11: ='Registration Revenue'!$C$4+'Room Costs'!$C$17+'Room Costs'!$C$18 -> 523 | D11: 20 | E11: =C11*D11 -> 10460
A12: E2-1020 | B12: Lunch Day 3 | C12: ='Registration Revenue'!$C$4+'Room Costs'!$C$17+'Room Costs'!$C$18 -> 523 | D12: 25 | E12: =C12*D12 -> 13075
A13: E2-1030 | B13: Dinner Day 3 | C13: ='Registration Revenue'!$C$4+'Room Costs'!$C$17+'Room Costs'!$C$18 -> 523 | D13: 45 | E13: =C13*D13 -> 23535
A14: E2-1050 | B14: Breaks/Snacks | C14: =3*('Registration Revenue'!$C$4+'Room Costs'!$C$17+'Room Costs'!$C$18) -> 1569 | D14: 12 | E14: =C14*D14 -> 18828
D15: Total | E15: =SUM(E4:E14) -> 183573

Sheet Room Costs
A1: MedIT Conference Room Costs
A3: Conference Rooms
A4: Account ID | B4: Room | C4: Rent/Hr. | D4: Hours | E4: Total
A5: E2-4050 | B5: Banquet Room | C5: 70 | D5: 12 | E5: =C5*D5 -> 840
A6: E2-4010 | B6: Conference Room 1 | C6: 55 | D6: 24 | E6: =C6*D6 -> 1320
A7: E2-4010 | B7: Conference Room 2 | C7: 55 | D7: 24 | E7: =C7*D7 -> 1320
A8: E2-4010 | B8: Conference Room 3 | C8: 40 | D8: 24 | E8: =C8*D8 -> 960
A9: E2-4010 | B9: Conference Room 4 | C9: 40 | D9: 24 | E9: =C9*D9 -> 960
A10: E2-4010 | B10: Conference Room 5 | C10: 40 | D10: 24 | E10: =C10*D10 -> 960
A11: E2-4010 | B11: Conference Room 6 | C11: 40 | D11: 24 | E11: =C11*D11 -> 960
A12: E2-4060 | B12: Exhibit Hall | C12: 50 | D12: 18 | E12: =C12*D12 -> 900
A13: E2-4070 | B13: Gathering Space | C13: 35 | D13: 18 | E13: =C13*D13 -> 630
D14: Total | E14: =SUM(E5:E13) -> 8850
A15: Lodging
A16: Account ID | B16: Room | C16: Guests | D16: per Day | E16: Days | F16: Total
A17: E2-4090 | B17: MedIT Support Staff | C17: 25 | D17: 125 | E17: 5 | F17: =C17*D17*E17 -> 15625
A18: E2-4095 | B18: Keynote Speakers | C18: 5 | D18: 125 | E18: 3 | F18: =C18*D18*E18 -> 1875
E19: Total | F19: =SUM(F17:F18) -> 17500

Sheet Budget History
A1: MedIT Conference History
A3: Year | B3: Attendees | C3: Revenue | D3: Expenses | E3: Balance
A4: 2016 | B4: 388 | C4: 208310 | D4: 215420 | E4: =C4-D4 -> -7110
A5: 2017 | B5: 455 | C5: 237440 | D5: 233920 | E5: =C5-D5 -> 3520
A6: 2018 | B6: 472 | C6: 245120 | D6: 242150 | E6: =C6-D6 -> 2970
A7: 2019 | B7: 412 | C7: 235380 | D7: 257190 | E7: =C7-D7 -> -21810
A8: 2020 | B8: 465 | C8: 241150 | D8: 242890 | E8: =C8-D8 -> -1740
A9: 2021 | B9: ='Registration Revenue'!$C$4 -> 493 | C9: =Budget!C9 -> 261990 | D9: =Budget!C20 -> 259923 | E9: =C9-D9 -> 2067

Sheet Registration List
A1: MedIT Conference Individual Registrations
A3: Registration ID | B3: First Name | C3: Last Name | D3: Street | E3: City | F3: State | G3: Postal Code | H3: Phone
A4: R4012 | B4: Raul | C4: Ada | D4: 693 Mac Dermont Avenue | E4: New Bedford | F4: MA | G4: 02740 | H4: (303) 555-4642
A5: R4053 | B5: Heather | C5: Adelson | D5: 143 Lakely Avenue | E5: Orleans | F5: MA | G5: 02653 | H5: (303) 555-9255
A6: R4169 | B6: Linda | C6: Adler | D6: 496 Columbus Street | E6: Chesterfield | F6: NJ | G6: 08515 | H6: (970) 555-8697
A7: R4321 | B7: Nancy | C7: Aldrich | D7: 923 Monterey Lane | E7: Philadelphia | F7: PA | G7: 19132 | H7: (520) 555-2055
A8: R4431 | B8: Sean | C8: Alger | D8: 74 Ferdinand Lane | E8: Cambridge | F8: MA | G8: 02139 | H8: (702) 555-9852
A9: R4075 | B9: Melissa | C9: Allen | D9: 912 Dean Lane | E9: Pt Pleas Beach | F9: NJ | G9: 08742 | H9: (714) 555-4271
A10: R4109 | B10: Ruby | C10: Allen | D10: 610 East Myrtle Boulevard | E10: VA Hospital | F10: NJ | G10: 07018 | H10: (626) 555-5495
A11: R4008 | B11: Benito | C11: Alvarez | D11: 626 Leonard Street | E11: Meadowview | F11: VA | G11: 24361 | H11: (480) 555-1265
A12: R4377 | B12: Susan | C12: Anderson | D12: 565 Elk Grove Boulevard | E12: Windsor Mill | F12: MD | G12: 21244 | H12: (702) 555-4206
A13: R4493 | B13: Chris | C13: Ang | D13: 645 Larrabee Avenue | E13: Lynn | F13: MA | G13: 01905 | H13: (303) 555-2237
A14: R4036 | B14: Dean | C14: Apple | D14: 185 Neenah Lane | E14: Pittsburgh | F14: PA | G14: 15241 | H14: (801) 555-1663
... A496: R4099 | B496: Pamela | C496: Zoller | D496: 669 Calhoun Way | E496: Athol | F496: MA | G496: 01331 | H496: (714) 555-2764
