Workbook

Sheet Documentation
A1: Holoease
A3: Author
A4: Date
A5: Purpose | B5: To perform a financial analysis for the startup tech company, Holoease

Sheet Startup
A1: Holoease
A2: Start-Up Requirements
A3: Required Expenses
A4: Licensing Fees | B4: 90000
A5: Plant Construction | B5: 345000
A6: Plant Equipment | B6: 200000
A7: Other Required Expenses | B7: 215000
A8: Total Required Expenses | B8: =SUM(B4:B7) -> 850000
A9: Required Assets
A10: Cash | B10: 230000
A11: Property | B11: 120000
A12: Miscellaneous Assets | B12: 100000
A13: Long-Term Assets
A14: Total Required Assets | B14: =SUM(B10:B13) -> 450000
A15: TOTAL REQUIRED EXPENSES AND ASSETS | B15: =B8+B14 -> 1300000
A17: Start-Up Assets
A18: Non-Cash Assets | B18: =SUM($B$11:$B$13) -> 220000
A19: Cash Assets | B19: =B10 -> 230000
A20: Additional Available Cash | B20: =B22-B18-B19 -> -450000
A21: Cash Balance on Starting Date | B21: =SUM(B19:B20) -> -220000
A22: TOTAL START-UP ASSETS | B22: =B39 -> 0
A24: Liabilities and Capital
A25: Start-Up Liabilities
A26: Long-Term Business Loan
A27: Outstanding Debts | B27: 0
A28: Total Liabilities | B28: =SUM(B26:B27) -> 0
A29: Start-Up Capital
A30: Owners | B30: 425000
A31: Investors
A32: Tech Innovations Startup Grant | B32: 425000
A33: Total Available Capital | B33: =SUM(B30:B32) -> 850000
A35: Project Summary
A36: START-UP INVESTMENT | B36: =B33 -> 850000
A37: START-UP EXPENSES | B37: =-B8 -> -850000
A38: INITIAL EQUITY | B38: =B36+B37 -> 0
A39: TOTAL LIABILITIES AND EQUITY | B39: =B28+B38 -> 0
A41: TOTAL FUNDING | B41: =B28+B33 -> 850000

Sheet Income Statement
A1: Holoease
A2: Pro Forma Income Statement
E3: Percent Cost of Sales & Marketing
E4: Percent Cost of Research and Development
E5: Assumed Tax Rate
A7: Income | B7: Year 1 | C7: Year 2 | D7: Year 3 | E7: Year 4 | F7: Year 5
A8: Sales
A9: Cost of Sales & Marketing
A10: Cost of Research and Development
A11: GROSS PROFIT
A13: Expenses | B13: Year 1 | C13: Year 2 | D13: Year 3 | E13: Year 4 | F13: Year 5
A14: Payroll
A15: Utilities
A16: Licensing
A17: Occupancy Costs
A18: Insurance
A19: Miscellaneous Expenses
A20: TOTAL GENERAL EXPENSES
A22: Earnings | B22: Year 1 | C22: Year 2 | D22: Year 3 | E22: Year 4 | F22: Year 5
A23: Initial Earnings
A24: Depreciation
A25: Operating Profit
A27: Interest Expense
A28: Pretax Profit
A30: Taxes Liability
A31: After-Tax Profit
A33: Dividends to Shareholders
A35: Retained Earnings

Sheet Balance Sheet
A1: Holoease
A2: Pro Forma Balance Sheet
A4: Assets | B4: Year 1 | C4: Year 2 | D4: Year 3 | E4: Year 4 | F4: Year 5
A5: Current Assets
A6: Cash | B6: ='Cash Flow'!B23 -> #NAME? | C6: ='Cash Flow'!C23 -> #NAME? | D6: ='Cash Flow'!D23 -> #NAME? | E6: ='Cash Flow'!E23 -> #NAME? | F6: ='Cash Flow'!F23 -> #NAME?
A7: Accounts Receivable | B7: 0 | C7: 0 | D7: 0 | E7: 0 | F7: 0
A8: Inventory | B8: 0 | C8: 0 | D8: 0 | E8: 0 | F8: 0
A9: Total Current Assets | B9: =SUM(B6:B8) -> #NAME? | C9: =SUM(C6:C8) -> #NAME? | D9: =SUM(D6:D8) -> #NAME? | E9: =SUM(E6:E8) -> #NAME? | F9: =SUM(F6:F8) -> #NAME?
A11: Property and Equipment
A12: Property | B12: =Startup!$B$11 -> 120000 | C12: =Startup!$B$11 -> 120000 | D12: =Startup!$B$11 -> 120000 | E12: =Startup!$B$11 -> 120000 | F12: =Startup!$B$11 -> 120000
A13: Miscellaneous Assets | B13: =Startup!$B$12 -> 100000 | C13: =Startup!$B$12 -> 100000 | D13: =Startup!$B$12 -> 100000 | E13: =Startup!$B$12 -> 100000 | F13: =Startup!$B$12 -> 100000
A14: Long-Term Assets | B14: =Startup!$B$13 -> 0 | C14: =Startup!$B$13 -> 0 | D14: =Startup!$B$13 -> 0 | E14: =Startup!$B$13 -> 0 | F14: =Startup!$B$13 -> 0
A15: Less Accumulated Depreciation | B15: =-Depreciation!B17 -> 0 | C15: =-Depreciation!C17 -> 0 | D15: =-Depreciation!D17 -> 0 | E15: =-Depreciation!E17 -> 0 | F15: =-Depreciation!F17 -> 0
A16: Net Property & Equipment | B16: =SUM(B12:B15) -> 220000 | C16: =SUM(C12:C15) -> 220000 | D16: =SUM(D12:D15) -> 220000 | E16: =SUM(E12:E15) -> 220000 | F16: =SUM(F12:F15) -> 220000
A18: TOTAL ASSETS | B18: =B9+B16 -> #NAME? | C18: =C9+C16 -> #NAME? | D18: =D9+D16 -> #NAME? | E18: =E9+E16 -> #NAME? | F18: =F9+F16 -> #NAME?
A20: Liabilities and Equity | B20: Year 1 | C20: Year 2 | D20: Year 3 | E20: Year 4 | F20: Year 5
A21: Current Liabilities
A22: Total Current Liabilities | B22: 0 | C22: 0 | D22: 0 | E22: 0 | F22: 0
A24: Long-Term Liabilities
A25: Total Long-Term Liabilities | B25: ='Loan Schedule'!B38 -> 0 | C25: ='Loan Schedule'!C38 -> 0 | D25: ='Loan Schedule'!D38 -> 0 | E25: ='Loan Schedule'!E38 -> 0 | F25: ='Loan Schedule'!E38 -> 0
A27: Equity
A28: Initial Investment | B28: =Startup!$B$33 -> 850000 | C28: =Startup!$B$33 -> 850000 | D28: =Startup!$B$33 -> 850000 | E28: =Startup!$B$33 -> 850000 | F28: =Startup!$B$33 -> 850000
A29: Less Start-Up Expenses | B29: =-Startup!$B$8 -> -850000 | C29: =-Startup!$B$8 -> -850000 | D29: =-Startup!$B$8 -> -850000 | E29: =-Startup!$B$8 -> -850000 | F29: =-Startup!$B$8 -> -850000
A30: Less Investor Repayment | B30: =-'Cash Flow'!B15 -> 0 | C30: =B30-'Cash Flow'!C15 -> 0 | D30: =C30-'Cash Flow'!D15 -> 0 | E30: =D30-'Cash Flow'!E15 -> 0 | F30: =E30-'Cash Flow'!F15 -> 0
A31: Accumulated Retained Earnings | B31: ='Income Statement'!B35 -> 0 | C31: =B31+'Income Statement'!C35 -> 0 | D31: =C31+'Income Statement'!D35 -> 0 | E31: =D31+'Income Statement'!E35 -> 0 | F31: =E31+'Income Statement'!F35 -> 0
A32: Total Equity | B32: =SUM(B28:B31) -> 0 | C32: =SUM(C28:C31) -> 0 | D32: =SUM(D28:D31) -> 0 | E32: =SUM(E28:E31) -> 0 | F32: =SUM(F28:F31) -> 0
A34: TOTAL LIABILITIES AND EQUITY | B34: =B22+B25+B32 -> 0 | C34: =C22+C25+C32 -> 0 | D34: =D22+D25+D32 -> 0 | E34: =E22+E25+E32 -> 0 | F34: =F22+F25+F32 -> 0
A36: NET WORTH | B36: =B18-B25 -> #NAME? | C36: =C18-C25 -> #NAME? | D36: =D18-D25 -> #NAME? | E36: =E18-E25 -> #NAME? | F36: =F18-F25 -> #NAME?

Sheet Cash Flow
A1: Holoease
A2: Pro Forma Cash Flow
A4: Cash Balance on Starting Date | B4: =Startup!B21 -> -220000
A6: Cash Inflows | B6: Year 1 | C6: Year 2 | D6: Year 3 | E6: Year 4 | F6: Year 5
A7: Operating Profit | B7: ='Income Statement'!B25 -> 0 | C7: ='Income Statement'!C25 -> 0 | D7: ='Income Statement'!D25 -> 0 | E7: ='Income Statement'!E25 -> 0 | F7: ='Income Statement'!F25 -> 0
A8: Depreciation Add-Back | B8: ='Income Statement'!B24 -> 0 | C8: ='Income Statement'!C24 -> 0 | D8: ='Income Statement'!D24 -> 0 | E8: ='Income Statement'!E24 -> 0 | F8: ='Income Statement'!F24 -> 0
A9: Additional Cash Received | B9: 0 | C9: 0 | D9: 0 | E9: 0 | F9: 0
A10: New Borrowing | B10: 0 | C10: 0 | D10: 0 | E10: 0 | F10: 0
A11: Sales of Other Current Assets | B11: 0 | C11: 0 | D11: 0 | E11: 0 | F11: 0
A12: TOTAL CASH INFLOW | B12: =SUM(B7:B11) -> 0 | C12: =SUM(C7:C11) -> 0 | D12: =SUM(D7:D11) -> 0 | E12: =SUM(E7:E11) -> 0 | F12: =SUM(F7:F11) -> 0
A14: Cash Outflows | B14: Year 1 | C14: Year 2 | D14: Year 3 | E14: Year 4 | F14: Year 5
A15: Loan Payment to Investors | B15: ='Investment Analysis'!B12 -> 0 | C15: ='Investment Analysis'!C12 -> 0 | D15: ='Investment Analysis'!D12 -> 0 | E15: ='Investment Analysis'!E12 -> 0 | F15: ='Investment Analysis'!F12 -> 0
A16: Dividends | B16: ='Investment Analysis'!B13 -> 0 | C16: ='Investment Analysis'!C13 -> 0 | D16: ='Investment Analysis'!D13 -> 0 | E16: ='Investment Analysis'!E13 -> 0 | F16: ='Investment Analysis'!F13 -> 0
A17: Estimated Tax | B17: ='Income Statement'!B30 -> 0 | C17: ='Income Statement'!C30 -> 0 | D17: ='Income Statement'!D30 -> 0 | E17: ='Income Statement'!E30 -> 0 | F17: ='Income Statement'!F30 -> 0
A18: Interest Payments | B18: =-'Loan Schedule'!B36 -> 0 | C18: =-'Loan Schedule'!C36 -> 0 | D18: =-'Loan Schedule'!D36 -> 0 | E18: =-'Loan Schedule'!E36 -> 0 | F18: =-'Loan Schedule'!F36 -> 0
A19: Debt Payment | B19: =-'Loan Schedule'!B37 -> 0 | C19: =-'Loan Schedule'!C37 -> 0 | D19: =-'Loan Schedule'!D37 -> 0 | E19: =-'Loan Schedule'!E37 -> 0 | F19: =-'Loan Schedule'!F37 -> 0
A20: TOTAL CASH OUTFLOW | B20: =SUMM(B15:B19) -> #NAME? | C20: =SUM(C15:C19) -> 0 | D20: =SUM(D15:D19) -> 0 | E20: =SUM(E15:E19) -> 0 | F20: =SUM(F15:F19) -> 0
A22: NET CASH FLOW | B22: =B12-B20 -> #NAME? | C22: =C12-C20 -> 0 | D22: =D12-D20 -> 0 | E22: =E12-E20 -> 0 | F22: =F12-F20 -> 0
A23: CASH BALANCE | B23: =B4+'Cash Flow'!B22 -> #NAME? | C23: =B23+C22 -> #NAME? | D23: =C23+D22 -> #NAME? | E23: =D23+E22 -> #NAME? | F23: =E23+F22 -> #NAME?

Sheet Loan Analysis
A1: Holoease
A2: Loan Analysis
A4: Annual Interest Rate
A6: Financial Value | B6: Business Loan (PV) | C6: Future Value (FV) | D6: Years | E6: Payments per Year | F6: Payments (NPER) | G6: Annual Rate | H6: Rate per Period (RATE) | I6: Periodic Payments (PMT)
A7: Quarterly Payment (PMT)
A8: Future Value (FV)
A9: Payments (NPER)
A10: Business Loan (PV)

Sheet Loan Schedule
A1: Holoease
A2: Loan Schedule
A4: Loan (PV) | B4: Annual Rate | C4: Payments per Year | D4: Rate per Period (RATE) | E4: Years | F4: Payments (NPER) | G4: Payment (PMT)
A7: Amortization Schedule
A8: Year | B8: Period | C8: Remaining Principal | D8: Interest Payment | E8: Principal Payment | F8: Total Payment
A9: 1 | B9: 1
A10: 1 | B10: 2
A11: 1 | B11: 3
A12: 1 | B12: 4
A13: 2 | B13: 5
A14: 2 | B14: 6
A15: 2 | B15: 7
A16: 2 | B16: 8
A17: 3 | B17: 9
A18: 3 | B18: 10
A19: 3 | B19: 11
A20: 3 | B20: 12
... A28: 5 | B28: 20
B29: Final Balance
A32: Cumulative Interest and Principal Payments per Year
B33: Year 1 | C33: Year 2 | D33: Year 3 | E33: Year 4 | F33: Year 5
A34: Quarters | B34: 1 | C34: 5 | D34: 9 | E34: 13 | F34: 17
B35: 4 | C35: 8 | D35: 12 | E35: 16 | F35: 20 | G35: Total
A36: Interest
A37: Principal
A38: Principal Remaining

Sheet Depreciation
A1: Holoease
A2: Depreciation
A4: Long-Term Assets (Cost)
A5: Salvage Value (Salvage)
A6: Life of Asset (Life)
B8: Year
A9: Straight-Line (SLN) | B9: 1 | C9: 2 | D9: 3 | E9: 4 | F9: 5
A10: Yearly Depreciation
A11: Cumulative Depreciation
A12: Depreciated Asset Value
B14: Year
A15: Declining Balance (DB) | B15: 1 | C15: 2 | D15: 3 | E15: 4 | F15: 5
A16: Yearly Depreciation
A17: Cumulative Depreciation
A18: Depreciated Asset Value

Sheet Investment Analysis
A1: Holoease
A2: Investment Analysis
A4: Proposed Repayment Schedule to Investors
A6: Investment (PV)
A7: Yearly Payments (PMT)
A8: Payments (NPER)
A9: Interest Rate (RATE)
B11: Year 1 | C11: Year 2 | D11: Year 3 | E11: Year 4 | F11: Year 5
A12: Payments
A13: Dividends
A14: Total
A16: Return on the Investment
B17: Payments | C17: Net Cash Flow
A18: Startup
A19: Year 1
A20: Year 2
A21: Year 3
A22: Year 4
A23: Year 5
A25: Desired Rate of Return
A26: Present Value (NPV)
A27: Net Present Value
A28: Internal Rate of Return (IRR)

Sheet Terms and Defintions
A1: Holoease
A2: Terms and Definitions
A4: Term | B4: Definition | C4: Notes
A5: Cash flow | B5: The direction in which money flows either to or from the user
A6: Negative cash flow | B6: Money that is flowing from the user | C6: Excel returns negative cash flow values for loan payments
A7: Positive cash flow | B7: Money that is flowing towards the user | C7: Excel returns positive cash flow values for investments
A8: Present value | B8: The current value of a loan or investment
A9: Future value | B9: The future value of a loan or investment | C9: Use a future value of 0 for loans that will be completely repaid
A10: Cost of sales | B10: Expenses which are directly related to production
A11: Tangible assets | B11: Noncash assets such as equipment, land, buildings, and vehicles
A12: Gross profit | B12: The difference between the company's sales and the cost of goods sold
A13: Extrapolation | B13: A process by extending a series from a single value or a few values to project future values
A14: Interpolation | B14: A process to fill in a series when given then starting and ending values of the series
A15: Linear trend | B15: A trend by which values change by a constant amount
A16: Growth trend | B16: A trend by which values change by a constant percentage
A17: Depreciation | B17: The process of allocating the original cost of an asset over the lifetime of the asset
A18: Straight-line depreciation | B18: Depreciation in which the asset drops in value by a constant amount | C18: Calculate using the SLN function
A19: Declining balance depreciation | B19: Depreciation in which the asset drops in value by a constant percentage | C19: Calculate using the DB function
A20: Payback period | B20: The length of time before an investment recovers its initial cost
A21: Rate of return | B21: An interest rate that compares of value of current dollars to future dollars from a series of cash flows
A22: Net present value | B22: The difference between the present value of an investment and the initial expenditure on that investment | C22: Calculate by adding the current expenditure to the value returned by the NPV function
A23: Internal rate of return | B23: The return rate for a series of future cash flow that will will result in a net present value of 0 | C23: Calculate using the IRR function
